Workbook
Name __j102: #REF!
Name _j102: #REF!
Name PRINT_AREA_MI: #REF!
Name Tgl: #REF!
Name tgll: #REF!
Name tr: #REF!
Name ﾃﾞｰﾀ海市: #REF!
Name ルピア: #REF!
Name 予算ﾚｰﾄ: #REF!
Name 今: #REF!
Name 印刷領域: #REF!
Name 品種別実績: #REF!
Name 実績レート: #REF!
Name 対象日数: #REF!
Name 技術開発経費181: #REF!
Name 日数: #REF!
Name 期: #REF!
Name 決算期区分: #REF!
Name 為替: #REF!
Name 為替レートEU: #REF!
Name 補助部門比率: #REF!
Name 補助部門費_設計以外181: #REF!
Name 補助部門費_設計以外182: #REF!
Name __j102: #REF!
Name _j102: #REF!
Name aa: #REF!
Name AB: #REF!
Name kissa: #REF!
Name kissakei: #REF!
Name kk: #REF!
Name Print_Area_MI: #REF!
Name PRINT_TITLES_MI: #REF!
Name ry: #REF!
Name Tgl: #REF!
Name tgll: #REF!
Name tr: #REF!
Name ﾃﾞｰﾀ海市: #REF!
Name ルピア: #REF!
Name 予算ﾚｰﾄ: #REF!
Name 今: #REF!
Name 出発: [6]支援計画・０４!$G$4:$G$171
Name 到着: [6]支援計画・０４!$F$4:$F$171
Name 印刷領域: #REF!
Name 品種別実績: #REF!
Name 商品群: [8]テーブル!$B$2:$B$7
Name 実績レート: #REF!
Name 対象日数: #REF!
Name 技術開発経費181: #REF!
Name 担当者: [8]テーブル!$F$2:$F$24
Name 日付: [6]支援計画・０４!$J$4:$CW$4
Name 日数: #REF!
Name 期: #REF!
Name 機能分類リスト: [12]開発計画品番リスト!#REF!
Name 比率: [13]調達計画!#REF!
Name 決算期区分: #REF!
Name 為替: #REF!
Name 為替レートEU: #REF!
Name 生産拠点: [8]テーブル!$C$2:$C$6
Name 立上年: [8]テーブル!$A$2:$A$11
Name 立上月: [8]テーブル!$D$2:$D$13

Sheet Data
A1: BUDGET TYPE | B1: Section Code (From) | C1: Section Name (From/Who Prepare) | D1: Section Code (To) | E1: Section Name (To/Who Use The Cost) | F1: COA-ID | G1: COA NAME | H1: DESCRIPTION | I1: GROUP SECTION | J1: GROUP COST | K1: 2024_10 | L1: 2024_11 | M1: 2024_12 | N1: 2025_01 | O1: 2025_02 | P1: 2025_03 | Q1: 2025_04 | R1: 2025_05 | S1: 2025_06 | T1: 2025_07 | U1: 2025_08 | V1: 2025_09 | W1: 2025_10 | X1: 2025_11 | Y1: 2025_12 | Z1: 2026_01 | AA1: 2026_02 | AB1: 2026_03 | AC1: TOTAL FY125 | AD1: TOTAL FY126 | AE1: TOTAL FY127 | AF1: TOTAL FY128 | AG1: Priority Category | AH1: BUDGET NO.
A2: BEX | B2: B2400 | C2: Information Technology | D2: B2400 | E2: Information Technology | F2: 7515401 | G2: Staff Welfare - Outpatient (Medical) | H2: Outpatient / Medical Expense | I2: ADM | J2: SGA | N2: 750000 | P2: 750000 | R2: 1500000 | T2: 750000 | V2: 750000 | X2: 750000 | Z2: 1500000 | AB2: 750000 | AC2: 1500000 | AD2: 6000000 | AE2: 6000000 | AF2: 6000000 | AG2: A | AH2: BEX26-2400-2400-001
A3: BEX | B3: B2400 | C3: Information Technology | D3: B2400 | E3: Information Technology | F3: 7515402 | G3: Staff Welfare - Hospitalization | H3: Hospitalization Expense | I3: ADM | J3: SGA | Q3: 25000000 | U3: 15000000 | Z3: 15000000 | AD3: 55000000 | AE3: 20000000 | AF3: 20000000 | AG3: A | AH3: BEX26-2400-2400-002
A4: BEX | B4: B2400 | C4: Information Technology | D4: B2400 | E4: Information Technology | F4: 7515404 | G4: Staff Welfare - Dental | H4: Dental Expense | I4: ADM | J4: SGA | N4: 4200000 | Q4: 500000 | S4: 500000 | V4: 1000000 | Y4: 500000 | AB4: 1000000 | AC4: 4200000 | AD4: 3500000 | AE4: 3500000 | AF4: 3500000 | AG4: A | AH4: BEX26-2400-2400-003
A5: BEX | B5: B2400 | C5: Information Technology | D5: B5800 | E5: Quality Assurance | F5: 7671103 | G5: License fee | H5: Google Apps License | I5: IND | J5: MFG | M5: 1941981 | N5: 1941981 | O5: 1941981 | P5: 1941981 | Q5: 2373532 | R5: 2373532 | S5: 2373532 | T5: 2373532 | U5: 2373532 | V5: 2373532 | W5: 2373532 | X5: 2373532 | Y5: 2373532 | Z5: 2373532 | AA5: 2373532 | AB5: 2373532 | AC5: 7767924 | AD5: 28482384 | AE5: 28482382 | AF5: 28482382 | AG5: A | AH5: BEX26-2400-5800-004
A6: BEX | B6: B2400 | C6: Information Technology | D6: B4105 | E6: SP PD- Plating | F6: 7671103 | G6: License fee | H6: Google Apps License | I6: DIR | J6: MFG | M6: 431551 | N6: 431551 | O6: 431551 | P6: 431551 | Q6: 431551 | R6: 431551 | S6: 431551 | T6: 431551 | U6: 431551 | V6: 431551 | W6: 431551 | X6: 431551 | Y6: 431551 | Z6: 431551 | AA6: 431551 | AB6: 431551 | AC6: 1726204 | AD6: 5178612 | AE6: 5178615 | AF6: 5178615 | AG6: A | AH6: BEX26-2400-4105-004
A7: BEX | B7: B2400 | C7: Information Technology | D7: B5130 | E7: Supply Procurement | F7: 7671103 | G7: License fee | H7: Google Apps License | I7: IND | J7: MFG | M7: 2589307 | N7: 2589307 | O7: 2589307 | P7: 2589307 | Q7: 2589307 | R7: 2589307 | S7: 2589307 | T7: 2589307 | U7: 2589307 | V7: 2589307 | W7: 2589307 | X7: 2589307 | Y7: 2589307 | Z7: 2589307 | AA7: 2589307 | AB7: 2589307 | AC7: 10357228 | AD7: 31071684 | AE7: 31071689 | AF7: 31071689 | AG7: A | AH7: BEX26-2400-5130-004
A8: BEX | B8: B2400 | C8: Information Technology | D8: B5500 | E8: Maintenance | F8: 7671103 | G8: License fee | H8: Google Apps License | I8: IND | J8: MFG | M8: 1941981 | N8: 1941981 | O8: 1941981 | P8: 1941981 | Q8: 1941981 | R8: 1941981 | S8: 1941981 | T8: 1941981 | U8: 1941981 | V8: 1941981 | W8: 1941981 | X8: 1941981 | Y8: 1941981 | Z8: 1941981 | AA8: 1941981 | AB8: 1941981 | AC8: 7767924 | AD8: 23303772 | AE8: 23303767 | AF8: 23303767 | AG8: A | AH8: BEX26-2400-5500-004
A9: BEX | B9: B2400 | C9: Information Technology | D9: B3100 | E9: Sales & MKTG Dept.- Automotive | F9: 7671103 | G9: License fee | H9: Google Apps License | I9: ADM | J9: SGA | M9: 431551 | N9: 431551 | O9: 431551 | P9: 431551 | Q9: 431551 | R9: 431551 | S9: 431551 | T9: 431551 | U9: 431551 | V9: 431551 | W9: 431551 | X9: 431551 | Y9: 431551 | Z9: 431551 | AA9: 431551 | AB9: 431551 | AC9: 1726204 | AD9: 5178612 | AE9: 5178615 | AF9: 5178615 | AG9: A | AH9: BEX26-2400-3100-004
A10: BEX | B10: B2400 | C10: Information Technology | D10: B3120 | E10: Sales - OES | F10: 7671103 | G10: License fee | H10: Google Apps License | I10: ADM | J10: SGA | M10: 431551 | N10: 431551 | O10: 431551 | P10: 431551 | Q10: 431551 | R10: 431551 | S10: 431551 | T10: 431551 | U10: 431551 | V10: 431551 | W10: 431551 | X10: 431551 | Y10: 431551 | Z10: 431551 | AA10: 431551 | AB10: 431551 | AC10: 1726204 | AD10: 5178612 | AE10: 5178615 | AF10: 5178615 | AG10: A | AH10: BEX26-2400-3120-004
A11: BEX | B11: B2400 | C11: Information Technology | D11: B3110 | E11: Sales - OEM | F11: 7671103 | G11: License fee | H11: Google Apps License | I11: ADM | J11: SGA | M11: 2589307 | N11: 2589307 | O11: 2589307 | P11: 2589307 | Q11: 2589307 | R11: 2589307 | S11: 2589307 | T11: 2589307 | U11: 2589307 | V11: 2589307 | W11: 2589307 | X11: 2589307 | Y11: 2589307 | Z11: 2589307 | AA11: 2589307 | AB11: 2589307 | AC11: 10357228 | AD11: 31071684 | AE11: 31071689 | AF11: 31071689 | AG11: A | AH11: BEX26-2400-3110-004
A12: BEX | B12: B2400 | C12: Information Technology | D12: B3130 | E12: Sales - IAM | F12: 7671103 | G12: License fee | H12: Google Apps License | I12: ADM | J12: SGA | M12: 3020859 | N12: 3020859 | O12: 3020859 | P12: 3020859 | Q12: 3020859 | R12: 3020859 | S12: 3020859 | T12: 3020859 | U12: 3020859 | V12: 3020859 | W12: 3020859 | X12: 3020859 | Y12: 3020859 | Z12: 3020859 | AA12: 3020859 | AB12: 3020859 | AC12: 12083436 | AD12: 36250308 | AE12: 36250304 | AF12: 36250304 | AG12: A | AH12: BEX26-2400-3130-004
A13: BEX | B13: B2400 | C13: Information Technology | D13: B5007 | E13: Continuous Improvement | F13: 7671103 | G13: License fee | H13: Google Apps License | I13: IND | J13: MFG | M13: 431551 | N13: 431551 | O13: 431551 | P13: 431551 | AC13: 1726204 | AG13: A | AH13: BEX26-2400-5007-004
A14: BEX | B14: B2400 | C14: Information Technology | D14: B5710 | E14: WH Dept.- KD & RM | F14: 7671103 | G14: License fee | H14: Google Apps License | I14: IND | J14: MFG | M14: 863102 | N14: 863102 | O14: 863102 | P14: 863102 | Q14: 863102 | R14: 863102 | S14: 863102 | T14: 863102 | U14: 863102 | V14: 863102 | W14: 863102 | X14: 863102 | Y14: 863102 | Z14: 863102 | AA14: 863102 | AB14: 863102 | AC14: 3452408 | AD14: 10357224 | AE14: 10357230 | AF14: 10357230 | AG14: A | AH14: BEX26-2400-5710-004
A15: BEX | B15: B2400 | C15: Information Technology | D15: B5100 | E15: Production Office | F15: 7671103 | G15: License fee | H15: Google Apps License | I15: IND | J15: MFG | M15: 1726205 | N15: 1726205 | O15: 1726205 | P15: 1726205 | Q15: 1726205 | R15: 1726205 | S15: 1726205 | T15: 1726205 | U15: 1726205 | V15: 1726205 | W15: 1726205 | X15: 1726205 | Y15: 1726205 | Z15: 1726205 | AA15: 1726205 | AB15: 1726205 | AC15: 6904820 | AD15: 20714460 | AE15: 20714460 | AF15: 20714460 | AG15: A | AH15: BEX26-2400-5100-004
A16: BEX | B16: B2400 | C16: Information Technology | D16: B2400 | E16: Information Technology | F16: 7671103 | G16: License fee | H16: Google Apps License | I16: ADM | J16: SGA | M16: 1294654 | N16: 1294654 | O16: 1294654 | P16: 1294654 | Q16: 1294654 | R16: 1294654 | S16: 1294654 | T16: 1294654 | U16: 1294654 | V16: 1294654 | W16: 1294654 | X16: 1294654 | Y16: 1294654 | Z16: 1294654 | AA16: 1294654 | AB16: 1294654 | AC16: 5178616 | AD16: 15535848 | AE16: 15535845 | AF16: 15535845 | AG16: A | AH16: BEX26-2400-2400-004
A17: BEX | B17: B2400 | C17: Information Technology | D17: B2230 | E17: Health, Safety & Environment | F17: 7671103 | G17: License fee | H17: Google Apps License | I17: ADM | J17: SGA | M17: 863102 | N17: 863102 | O17: 863102 | P17: 863102 | Q17: 863102 | R17: 863102 | S17: 863102 | T17: 863102 | U17: 863102 | V17: 863102 | W17: 863102 | X17: 863102 | Y17: 863102 | Z17: 863102 | AA17: 863102 | AB17: 863102 | AC17: 3452408 | AD17: 10357224 | AE17: 10357230 | AF17: 10357230 | AG17: A | AH17: BEX26-2400-2230-004
A18: BEX | B18: B2400 | C18: Information Technology | D18: B5900 | E18: Quality Control | F18: 7671103 | G18: License fee | H18: Google Apps License | I18: IND | J18: MFG | M18: 1078878 | N18: 1078878 | O18: 1078878 | P18: 1078878 | Q18: 1078878 | R18: 1078878 | S18: 1078878 | T18: 1078878 | U18: 1078878 | V18: 1078878 | W18: 1078878 | X18: 1078878 | Y18: 1078878 | Z18: 1078878 | AA18: 1078878 | AB18: 1078878 | AC18: 4315512 | AD18: 12946536 | AE18: 12946537 | AF18: 12946537 | AG18: A | AH18: BEX26-2400-5900-004
A19: BEX | B19: B2400 | C19: Information Technology | D19: B4102 | E19: SP PD- CM | F19: 7671103 | G19: License fee | H19: Google Apps License | I19: DIR | J19: MFG | M19: 647327 | N19: 647327 | O19: 647327 | P19: 647327 | Q19: 647327 | R19: 647327 | S19: 647327 | T19: 647327 | U19: 647327 | V19: 647327 | W19: 647327 | X19: 647327 | Y19: 647327 | Z19: 647327 | AA19: 647327 | AB19: 647327 | AC19: 2589308 | AD19: 7767924 | AE19: 7767922 | AF19: 7767922 | AG19: A | AH19: BEX26-2400-4102-004
A20: BEX | B20: B2400 | C20: Information Technology | D20: B5000 | E20: Plant Operation (Indirect Mfg) | F20: 7671103 | G20: License fee | H20: Google Apps License | I20: IND | J20: MFG | M20: 431551 | N20: 431551 | O20: 431551 | P20: 431551 | Q20: 431551 | R20: 431551 | S20: 431551 | T20: 431551 | U20: 431551 | V20: 431551 | W20: 431551 | X20: 431551 | Y20: 431551 | Z20: 431551 | AA20: 431551 | AB20: 431551 | AC20: 1726204 | AD20: 5178612 | AE20: 5178615 | AF20: 5178615 | AG20: A | AH20: BEX26-2400-5000-004
A21: BEX | B21: B2400 | C21: Information Technology | D21: B4410 | E21: PC PD- Injection | F21: 7671103 | G21: License fee | H21: Google Apps License | I21: DIR | J21: MFG | M21: 215776 | N21: 215776 | O21: 215776 | P21: 215776 | Q21: 215776 | R21: 215776 | S21: 215776 | T21: 215776 | U21: 215776 | V21: 215776 | W21: 215776 | X21: 215776 | Y21: 215776 | AC21: 863104 | AD21: 1941984 | AG21: A | AH21: BEX26-2400-4410-004
A22: BEX | B22: B2400 | C22: Information Technology | D22: B4130 | E22: SP PD- Insulator Sealing | F22: 7671103 | G22: License fee | H22: Google Apps License | I22: DIR | J22: MFG | M22: 215776 | N22: 215776 | O22: 215776 | P22: 215776 | Q22: 215776 | R22: 215776 | S22: 215776 | T22: 215776 | U22: 215776 | V22: 215776 | W22: 215776 | X22: 215776 | Y22: 215776 | Z22: 215776 | AA22: 215776 | AB22: 215776 | AC22: 863104 | AD22: 2589312 | AE22: 2589307 | AF22: 2589307 | AG22: A | AH22: BEX26-2400-4130-004
A23: BEX | B23: B2400 | C23: Information Technology | D23: B4121 | E23: SP PD- QC - OEM | F23: 7671103 | G23: License fee | H23: Google Apps License | I23: DIR | J23: MFG | M23: 215776 | N23: 215776 | O23: 215776 | P23: 215776 | AC23: 863104 | AG23: A | AH23: BEX26-2400-4121-004
A24: BEX | B24: B2400 | C24: Information Technology | D24: B5600 | E24: Production Engineering | F24: 7671103 | G24: License fee | H24: Google Apps License | I24: IND | J24: MFG | M24: 2373532 | N24: 2373532 | O24: 2373532 | P24: 2373532 | Q24: 2373532 | R24: 2373532 | S24: 2373532 | T24: 2373532 | U24: 2373532 | V24: 2373532 | W24: 2373532 | X24: 2373532 | Y24: 2373532 | Z24: 2373532 | AA24: 2373532 | AB24: 2373532 | AC24: 9494128 | AD24: 28482384 | AE24: 28482382 | AF24: 28482382 | AG24: A | AH24: BEX26-2400-5600-004
A25: BEX | B25: B2400 | C25: Information Technology | D25: B4110 | E25: SP PD- Assy | F25: 7671103 | G25: License fee | H25: Google Apps License | I25: DIR | J25: MFG | M25: 647327 | N25: 647327 | O25: 647327 | P25: 647327 | Q25: 647327 | R25: 647327 | S25: 647327 | T25: 647327 | U25: 647327 | V25: 647327 | W25: 647327 | X25: 647327 | Y25: 647327 | Z25: 647327 | AA25: 647327 | AB25: 647327 | AC25: 2589308 | AD25: 7767924 | AE25: 7767922 | AF25: 7767922 | AG25: A | AH25: BEX26-2400-4110-004
A26: BEX | B26: B2400 | C26: Information Technology | D26: B5104 | E26: Production Office (PC) | F26: 7671103 | G26: License fee | H26: Google Apps License | I26: IND | J26: MFG | M26: 431551 | N26: 431551 | O26: 431551 | P26: 431551 | Q26: 431551 | R26: 431551 | S26: 431551 | T26: 431551 | U26: 431551 | V26: 431551 | W26: 431551 | X26: 431551 | Y26: 431551 | Z26: 431551 | AA26: 431551 | AB26: 431551 | AC26: 1726204 | AD26: 5178612 | AE26: 5178615 | AF26: 5178615 | AG26: A | AH26: BEX26-2400-5104-004
A27: BEX | B27: B2400 | C27: Information Technology | D27: B1000 | E27: Top Management | F27: 7671103 | G27: License fee | H27: Google Apps License | I27: ADM | J27: SGA | M27: 431551 | N27: 431551 | O27: 431551 | P27: 431551 | Q27: 431551 | R27: 431551 | S27: 431551 | T27: 431551 | U27: 431551 | V27: 431551 | W27: 431551 | X27: 431551 | Y27: 431551 | Z27: 431551 | AA27: 431551 | AB27: 431551 | AC27: 1726204 | AD27: 5178612 | AE27: 5178615 | AF27: 5178615 | AG27: A | AH27: BEX26-2400-1000-004
A28: BEX | B28: B2400 | C28: Information Technology | D28: B2220 | E28: Human Resource | F28: 7671103 | G28: License fee | H28: Google Apps License | I28: ADM | J28: SGA | M28: 2373532 | N28: 2373532 | O28: 2373532 | P28: 2373532 | Q28: 2373532 | R28: 2373532 | S28: 2373532 | T28: 2373532 | U28: 2373532 | V28: 2373532 | W28: 2373532 | X28: 2373532 | Y28: 2373532 | Z28: 2373532 | AA28: 2373532 | AB28: 2373532 | AC28: 9494128 | AD28: 28482384 | AE28: 28482382 | AF28: 28482382 | AG28: A | AH28: BEX26-2400-2220-004
A29: BEX | B29: B2400 | C29: Information Technology | D29: B2210 | E29: General Affair | F29: 7671103 | G29: License fee | H29: Google Apps License | I29: ADM | J29: SGA | M29: 1510429 | N29: 1510429 | O29: 1510429 | P29: 1510429 | Q29: 1510429 | R29: 1510429 | S29: 1510429 | T29: 1510429 | U29: 1510429 | V29: 1510429 | W29: 1510429 | X29: 1510429 | Y29: 1510429 | Z29: 1510429 | AA29: 1510429 | AB29: 1510429 | AC29: 6041716 | AD29: 18125148 | AE29: 18125152 | AF29: 18125152 | AG29: A | AH29: BEX26-2400-2210-004
A30: BEX | B30: B2400 | C30: Information Technology | D30: B2300 | E30: Accounting & Finance | F30: 7671103 | G30: License fee | H30: Google Apps License | I30: ADM | J30: SGA | M30: 2373532 | N30: 2373532 | O30: 2373532 | P30: 2373532 | Q30: 2373532 | R30: 2373532 | S30: 2373532 | T30: 2373532 | U30: 2373532 | V30: 2373532 | W30: 2373532 | X30: 2373532 | Y30: 2373532 | Z30: 2373532 | AA30: 2373532 | AB30: 2373532 | AC30: 9494128 | AD30: 28482384 | AE30: 28482382 | AF30: 28482382 | AG30: A | AH30: BEX26-2400-2300-004
A31: BEX | B31: B2400 | C31: Information Technology | D31: B5101 | E31: Production Office (SP) | F31: 7671103 | G31: License fee | H31: Google Apps License | I31: IND | J31: MFG | M31: 431551 | N31: 431551 | O31: 431551 | P31: 431551 | Q31: 431551 | R31: 431551 | S31: 431551 | T31: 431551 | U31: 431551 | V31: 431551 | W31: 431551 | X31: 431551 | Y31: 431551 | Z31: 431551 | AA31: 431551 | AB31: 431551 | AC31: 1726204 | AD31: 5178612 | AE31: 5178615 | AF31: 5178615 | AG31: A | AH31: BEX26-2400-5101-004
A32: BEX | B32: B2400 | C32: Information Technology | D32: B3150 | E32: SCM - FG WH | F32: 7671103 | G32: License fee | H32: Google Apps License | I32: ADM | J32: SGA | M32: 1294654 | N32: 1294654 | O32: 1294654 | P32: 1294654 | Q32: 1294654 | R32: 1294654 | S32: 1294654 | T32: 1294654 | U32: 1294654 | V32: 1294654 | W32: 1294654 | X32: 1294654 | Y32: 1294654 | Z32: 1294654 | AA32: 1294654 | AB32: 1294654 | AC32: 5178616 | AD32: 15535848 | AE32: 15535845 | AF32: 15535845 | AG32: A | AH32: BEX26-2400-3150-004
A33: BEX | B33: B2400 | C33: Information Technology | D33: B4120 | E33: SP PD- Final Inspection | F33: 7671103 | G33: License fee | H33: Google Apps License | I33: DIR | J33: MFG | M33: 431551 | N33: 431551 | O33: 431551 | P33: 431551 | Q33: 647327 | R33: 647327 | S33: 647327 | T33: 647327 | U33: 647327 | V33: 647327 | W33: 647327 | X33: 647327 | Y33: 647327 | Z33: 647327 | AA33: 647327 | AB33: 647327 | AC33: 1726204 | AD33: 7767924 | AE33: 7767922 | AF33: 7767922 | AG33: A | AH33: BEX26-2400-4120-004
A34: BEX | B34: B2400 | C34: Information Technology | D34: B3160 | E34: Marketing | F34: 7671103 | G34: License fee | H34: Google Apps License | I34: ADM | J34: SGA | M34: 1510429 | N34: 1510429 | O34: 1510429 | P34: 1510429 | Q34: 1510429 | R34: 1510429 | S34: 1510429 | T34: 1510429 | U34: 1510429 | V34: 1510429 | W34: 1510429 | X34: 1510429 | Y34: 1510429 | Z34: 1510429 | AA34: 1510429 | AB34: 1510429 | AC34: 6041716 | AD34: 18125148 | AE34: 18125152 | AF34: 18125152 | AG34: A | AH34: BEX26-2400-3160-004
A35: BEX | B35: B2400 | C35: Information Technology | D35: B2400 | E35: Information Technology | F35: 7671103 | G35: License fee | H35: New License - 5 Microsoft License Windows 11 | I35: ADM | J35: SGA | Q35: 16000000 | AD35: 16000000 | AE35: 16000000 | AF35: 16000000 | AG35: C | AH35: BEX26-2400-2400-005
A36: BEX | B36: B2400 | C36: Information Technology | D36: B2400 | E36: Information Technology | F36: 7671103 | G36: License fee | H36: New License - Google Developer License Fee | I36: ADM | J36: SGA | Q36: 375000 | AD36: 375000 | AE36: 375000 | AF36: 375000 | AG36: A | AH36: BEX26-2400-2400-006
A37: BEX | B37: B2400 | C37: Information Technology | D37: B2400 | E37: Information Technology | F37: 7671103 | G37: License fee | H37: New License - IOS Developer Membership Fee | I37: ADM | J37: SGA | Q37: 123750 | R37: 123750 | S37: 123750 | T37: 123750 | U37: 123750 | V37: 123750 | W37: 123750 | X37: 123750 | Y37: 123750 | Z37: 123750 | AA37: 123750 | AB37: 123750 | AD37: 1485000 | AE37: 1485000 | AF37: 1485000 | AG37: A | AH37: BEX26-2400-2400-007
A38: BEX | B38: B2400 | C38: Information Technology | D38: B2400 | E38: Information Technology | F38: 7671103 | G38: License fee | H38: New License - Nitro PDF Pro | I38: ADM | J38: SGA | Q38: 350000 | R38: 350000 | S38: 350000 | T38: 350000 | U38: 350000 | V38: 350000 | W38: 350000 | X38: 350000 | Y38: 350000 | Z38: 350000 | AA38: 350000 | AB38: 350000 | AD38: 4200000 | AE38: 4200000 | AF38: 4200000 | AG38: B | AH38: BEX26-2400-2400-008
A39: BEX | B39: B2400 | C39: Information Technology | D39: B3110 | E39: Sales - OEM | F39: 7671103 | G39: License fee | H39: Nrimo Usage License | I39: ADM | J39: SGA | M39: 504217 | N39: 504217 | O39: 504217 | P39: 504217 | Q39: 504217 | R39: 504217 | S39: 504217 | T39: 504217 | U39: 504217 | V39: 504217 | W39: 504217 | X39: 504217 | Y39: 504217 | Z39: 504217 | AA39: 504217 | AB39: 504217 | AC39: 2016868 | AD39: 6050604 | AE39: 6050606 | AF39: 6050606 | AG39: A | AH39: BEX26-2400-3110-009
A40: BEX | B40: B2400 | C40: Information Technology | D40: B3160 | E40: Marketing | F40: 7671103 | G40: License fee | H40: Nrimo Usage License | I40: ADM | J40: SGA | M40: 252109 | N40: 252109 | O40: 252109 | P40: 252109 | Q40: 252109 | R40: 252109 | S40: 252109 | T40: 252109 | U40: 252109 | V40: 252109 | W40: 252109 | X40: 252109 | Y40: 252109 | Z40: 252109 | AA40: 252109 | AB40: 252109 | AC40: 1008436 | AD40: 3025308 | AE40: 3025303 | AF40: 3025303 | AG40: A | AH40: BEX26-2400-3160-009
A41: BEX | B41: B2400 | C41: Information Technology | D41: B5000 | E41: Plant Operation (Indirect Mfg) | F41: 7671103 | G41: License fee | H41: Nrimo Usage License | I41: IND | J41: MFG | M41: 252109 | N41: 252109 | O41: 252109 | P41: 252109 | Q41: 252109 | R41: 252109 | S41: 252109 | T41: 252109 | U41: 252109 | V41: 252109 | W41: 252109 | X41: 252109 | Y41: 252109 | Z41: 252109 | AA41: 252109 | AB41: 252109 | AC41: 1008436 | AD41: 3025308 | AE41: 3025303 | AF41: 3025303 | AG41: A | AH41: BEX26-2400-5000-009
A42: BEX | B42: B2400 | C42: Information Technology | D42: B3150 | E42: SCM - FG WH | F42: 7671103 | G42: License fee | H42: Nrimo Usage License | I42: ADM | J42: SGA | M42: 756326 | N42: 756326 | O42: 756326 | P42: 756326 | Q42: 756326 | R42: 756326 | S42: 756326 | T42: 756326 | U42: 756326 | V42: 756326 | W42: 756326 | X42: 756326 | Y42: 756326 | Z42: 756326 | AA42: 756326 | AB42: 756326 | AC42: 3025304 | AD42: 9075912 | AE42: 9075909 | AF42: 9075909 | AG42: A | AH42: BEX26-2400-3150-009
A43: BEX | B43: B2400 | C43: Information Technology | D43: B5130 | E43: Supply Procurement | F43: 7671103 | G43: License fee | H43: Nrimo Usage License | I43: IND | J43: MFG | M43: 756326 | N43: 756326 | O43: 756326 | P43: 756326 | Q43: 756326 | R43: 756326 | S43: 756326 | T43: 756326 | U43: 756326 | V43: 756326 | W43: 756326 | X43: 756326 | Y43: 756326 | Z43: 756326 | AA43: 756326 | AB43: 756326 | AC43: 3025304 | AD43: 9075912 | AE43: 9075909 | AF43: 9075909 | AG43: A | AH43: BEX26-2400-5130-009
A44: BEX | B44: B2400 | C44: Information Technology | D44: B2300 | E44: Accounting & Finance | F44: 7671103 | G44: License fee | H44: Nrimo Usage License | I44: ADM | J44: SGA | M44: 1260543 | N44: 1260543 | O44: 1260543 | P44: 1260543 | Q44: 1260543 | R44: 1260543 | S44: 1260543 | T44: 1260543 | U44: 1260543 | V44: 1260543 | W44: 1260543 | X44: 1260543 | Y44: 1260543 | Z44: 1260543 | AA44: 1260543 | AB44: 1260543 | AC44: 5042172 | AD44: 15126516 | AE44: 15126515 | AF44: 15126515 | AG44: A | AH44: BEX26-2400-2300-009
A45: BEX | B45: B2400 | C45: Information Technology | D45: B5600 | E45: Production Engineering | F45: 7671103 | G45: License fee | H45: Nrimo Usage License | I45: IND | J45: MFG | M45: 252109 | N45: 252109 | O45: 252109 | P45: 252109 | Q45: 252109 | R45: 252109 | S45: 252109 | T45: 252109 | U45: 252109 | V45: 252109 | W45: 252109 | X45: 252109 | Y45: 252109 | Z45: 252109 | AA45: 252109 | AB45: 252109 | AC45: 1008436 | AD45: 3025308 | AE45: 3025303 | AF45: 3025303 | AG45: A | AH45: BEX26-2400-5600-009
A46: BEX | B46: B2400 | C46: Information Technology | D46: B1000 | E46: Top Management | F46: 7671103 | G46: License fee | H46: Nrimo Usage License | I46: ADM | J46: SGA | M46: 252109 | N46: 252109 | O46: 252109 | P46: 252109 | Q46: 252109 | R46: 252109 | S46: 252109 | T46: 252109 | U46: 252109 | V46: 252109 | W46: 252109 | X46: 252109 | Y46: 252109 | Z46: 252109 | AA46: 252109 | AB46: 252109 | AC46: 1008436 | AD46: 3025308 | AE46: 3025303 | AF46: 3025303 | AG46: A | AH46: BEX26-2400-1000-009
A47: BEX | B47: B2400 | C47: Information Technology | D47: B3130 | E47: Sales - IAM | F47: 7671103 | G47: License fee | H47: Nrimo Usage License | I47: ADM | J47: SGA | M47: 504217 | N47: 504217 | O47: 504217 | P47: 504217 | Q47: 504217 | R47: 504217 | S47: 504217 | T47: 504217 | U47: 504217 | V47: 504217 | W47: 504217 | X47: 504217 | Y47: 504217 | Z47: 504217 | AA47: 504217 | AB47: 504217 | AC47: 2016868 | AD47: 6050604 | AE47: 6050606 | AF47: 6050606 | AG47: A | AH47: BEX26-2400-3130-009
A48: BEX | B48: B2400 | C48: Information Technology | D48: B2400 | E48: Information Technology | F48: 7671103 | G48: License fee | H48: QWORDS - Hosting Website & Domain | I48: ADM | J48: SGA | M48: 319329 | N48: 319329 | O48: 319329 | P48: 319329 | Q48: 319329 | R48: 319329 | S48: 319329 | T48: 319329 | U48: 319329 | V48: 319329 | W48: 319329 | X48: 319329 | Y48: 319329 | Z48: 319329 | AA48: 319329 | AB48: 319329 | AC48: 1277316 | AD48: 3831948 | AE48: 3831945 | AF48: 3831945 | AG48: A | AH48: BEX26-2400-2400-010
A49: BEX | B49: B2400 | C49: Information Technology | D49: B2400 | E49: Information Technology | F49: 7671103 | G49: License fee | H49: Yearly Renewal - Anydesk License | I49: ADM | J49: SGA | M49: 500194 | N49: 500194 | O49: 500194 | P49: 500194 | Q49: 500194 | R49: 500194 | S49: 500194 | T49: 500194 | U49: 500194 | V49: 500194 | W49: 500194 | X49: 500194 | Y49: 500194 | Z49: 500194 | AA49: 500194 | AB49: 500194 | AC49: 2000776 | AD49: 6002328 | AE49: 6002325 | AF49: 6002325 | AG49: A | AH49: BEX26-2400-2400-011
A50: BEX | B50: B2400 | C50: Information Technology | D50: B2400 | E50: Information Technology | F50: 7671103 | G50: License fee | H50: Yearly Renewal - Fortigate Firewall Security | I50: ADM | J50: SGA | M50: 8236250 | N50: 8236250 | O50: 8236250 | P50: 8236250 | Q50: 8236250 | R50: 8236250 | S50: 25983500 | T50: 25983500 | U50: 25983500 | V50: 25983500 | W50: 17500000 | X50: 17500000 | Y50: 17500000 | Z50: 17500000 | AA50: 17500000 | AB50: 17500000 | AC50: 32945000 | AD50: 225406500 | AE50: 210000000 | AF50: 210000000 | AG50: A | AH50: BEX26-2400-2400-012
... A52: BEX | B52: B2400 | C52: Information Technology | D52: B2400 | E52: Information Technology | F52: 7671103 | G52: License fee | H52: Yearly Renewal - JP1 Server Service | I52: ADM | J52: SGA | M52: 3646667 | N52: 3646667 | O52: 3646667 | P52: 3646667 | Q52: 3646667 | R52: 3646667 | S52: 3646667 | T52: 3646667 | U52: 3646667 | V52: 3646667 | W52: 3646667 | X52: 3756167 | Y52: 3756167 | Z52: 3756167 | AA52: 3756167 | AB52: 3756167 | AC52: 14586668 | AD52: 44307504 | AE52: 46000000 | AF52: 46000000 | AG52: B | AH52: BEX26-2400-2400-014
A53: BEX | B53: B2400 | C53: Information Technology | D53: B2400 | E53: Information Technology | F53: 7671103 | G53: License fee | H53: Yearly Renewal - Microsoft Office 70 Licenses | I53: ADM | J53: SGA | Q53: 7625625 | R53: 7625625 | S53: 7625625 | T53: 7625625 | U53: 7625625 | V53: 7625625 | W53: 7625625 | X53: 7625625 | Y53: 7625625 | Z53: 7625625 | AA53: 7625625 | AB53: 7625625 | AD53: 91507500 | AE53: 91507500 | AF53: 91507500 | AG53: B | AH53: BEX26-2400-2400-015
A54: BEX | B54: B2400 | C54: Information Technology | D54: B5800 | E54: Quality Assurance | F54: 7671103 | G54: License fee | H54: Yearly Renewal - Office E1 | I54: IND | J54: MFG | M54: 339500 | N54: 339500 | O54: 339500 | P54: 339500 | Q54: 339500 | R54: 339500 | S54: 339500 | T54: 339500 | U54: 339500 | V54: 339500 | W54: 339500 | X54: 339500 | Y54: 339500 | Z54: 339500 | AA54: 339500 | AB54: 339500 | AC54: 1358000 | AD54: 4074000 | AE54: 4074000 | AF54: 4074000 | AG54: A | AH54: BEX26-2400-5800-016
A55: BEX | B55: B2400 | C55: Information Technology | D55: B2400 | E55: Information Technology | F55: 7671103 | G55: License fee | H55: Yearly Renewal - Oracle Database | I55: ADM | J55: SGA | M55: 16650000 | N55: 16650000 | O55: 16650000 | P55: 16650000 | Q55: 17482500 | R55: 17482500 | S55: 17482500 | T55: 17482500 | U55: 17482500 | V55: 17482500 | W55: 17482500 | X55: 17482500 | Y55: 17482500 | Z55: 17482500 | AA55: 17482500 | AB55: 17482500 | AC55: 66600000 | AD55: 209790000 | AE55: 209790000 | AF55: 209790000 | AG55: A | AH55: BEX26-2400-2400-017
A56: BEX | B56: B2400 | C56: Information Technology | D56: B2400 | E56: Information Technology | F56: 7671103 | G56: License fee | H56: Yearly Renewal - VEEAM License | I56: ADM | J56: SGA | M56: 2154167 | N56: 2154167 | O56: 2154167 | P56: 2154167 | Q56: 2154167 | R56: 2154167 | S56: 2154167 | T56: 2154167 | U56: 2154167 | V56: 2154167 | W56: 2154167 | X56: 2154167 | Y56: 2229167 | Z56: 2229167 | AA56: 2229167 | AB56: 2229167 | AC56: 8616668 | AD56: 26150004 | AE56: 26750000 | AF56: 26750000 | AG56: B | AH56: BEX26-2400-2400-018
A57: BEX | B57: B2400 | C57: Information Technology | D57: B2400 | E57: Information Technology | F57: 7671103 | G57: License fee | H57: Yearly Renewal - VM Ware Server | I57: ADM | J57: SGA | M57: 2995000 | N57: 2995000 | O57: 2995000 | P57: 2995000 | Q57: 2995000 | R57: 2995000 | S57: 2995000 | T57: 2995000 | U57: 2995000 | V57: 2995000 | W57: 2995000 | X57: 3145000 | Y57: 3145000 | Z57: 3145000 | AA57: 3145000 | AB57: 3145000 | AC57: 11980000 | AD57: 36690000 | AE57: 37740000 | AF57: 37740000 | AG57: A | AH57: BEX26-2400-2400-019
A58: BEX | B58: B2400 | C58: Information Technology | D58: B2400 | E58: Information Technology | F58: 7691000 | G58: Office supply & Stationary Expense | H58: IT Stationary | I58: ADM | J58: SGA | M58: 200000 | N58: 200000 | O58: 200000 | P58: 200000 | Q58: 200000 | R58: 200000 | S58: 200000 | T58: 200000 | U58: 200000 | V58: 200000 | W58: 200000 | X58: 200000 | Y58: 200000 | Z58: 200000 | AA58: 200000 | AB58: 200000 | AC58: 800000 | AD58: 2400000 | AE58: 2400000 | AF58: 2400000 | AG58: A | AH58: BEX26-2400-2400-020
A59: BEX | B59: B2400 | C59: Information Technology | D59: B2400 | E59: Information Technology | F59: 7711101 | G59: Communication expenses | H59: 2 Link of Internet Connection (Primary & Backup) | I59: ADM | J59: SGA | M59: 33855000 | N59: 33855000 | O59: 33855000 | P59: 33855000 | Q59: 33855000 | R59: 33855000 | S59: 33855000 | T59: 33855000 | U59: 33855000 | V59: 33855000 | W59: 33855000 | X59: 33855000 | Y59: 33855000 | Z59: 33855000 | AA59: 33855000 | AB59: 33855000 | AC59: 135420000 | AD59: 406260000 | AE59: 406260000 | AF59: 406260000 | AG59: A | AH59: BEX26-2400-2400-021
A60: BEX | B60: B2400 | C60: Information Technology | D60: B2400 | E60: Information Technology | F60: 7711102 | G60: IT Expense | H60: IT Tools / Expenses | I60: ADM | J60: SGA | M60: 1800000 | N60: 800000 | O60: 3000000 | Q60: 1000000 | S60: 1000000 | U60: 2000000 | W60: 3600000 | Y60: 2500000 | AC60: 5600000 | AD60: 10100000 | AE60: 10100000 | AF60: 10100000 | AG60: A | AH60: BEX26-2400-2400-022
A61: BEX | B61: B2400 | C61: Information Technology | D61: B2400 | E61: Information Technology | F61: 7729101 | G61: Consultancy/Professional Fee | H61: Renewal FID Platinum Maintenance Support | I61: ADM | J61: SGA | M61: 2500000 | N61: 2500000 | O61: 2500000 | P61: 2500000 | Q61: 2500000 | R61: 2500000 | S61: 2500000 | T61: 2500000 | U61: 2500000 | V61: 2500000 | W61: 2500000 | X61: 2500000 | Y61: 2500000 | Z61: 2500000 | AA61: 2500000 | AB61: 2500000 | AC61: 10000000 | AD61: 30000000 | AE61: 30000000 | AF61: 30000000 | AG61: A | AH61: BEX26-2400-2400-023
B62: =_xlfn.IFNA(VLOOKUP(C62,Master!$J:$K,2,0),"") | D62: =_xlfn.IFNA(VLOOKUP(E62,Master!$J:$K,2,0),"") | F62: =_xlfn.IFNA(VLOOKUP(G62,Master!B:C,2,0),"") | I62: =_xlfn.IFNA(VLOOKUP(E62,Master!$J:$M,4,0),"") | J62: =_xlfn.IFNA(VLOOKUP($E62,Master!$J:$M,3,0),"") | AC62: =SUM(K62:P62) | AD62: =SUM(Q62:AB62)
B63: =_xlfn.IFNA(VLOOKUP(C63,Master!$J:$K,2,0),"") | D63: =_xlfn.IFNA(VLOOKUP(E63,Master!$J:$K,2,0),"") | F63: =_xlfn.IFNA(VLOOKUP(G63,Master!B:C,2,0),"") | I63: =_xlfn.IFNA(VLOOKUP(E63,Master!$J:$M,4,0),"") | J63: =_xlfn.IFNA(VLOOKUP($E63,Master!$J:$M,3,0),"") | AC63: =SUM(K63:P63) | AD63: =SUM(Q63:AB63)
B64: =_xlfn.IFNA(VLOOKUP(C64,Master!$J:$K,2,0),"") | D64: =_xlfn.IFNA(VLOOKUP(E64,Master!$J:$K,2,0),"") | F64: =_xlfn.IFNA(VLOOKUP(G64,Master!B:C,2,0),"") | I64: =_xlfn.IFNA(VLOOKUP(E64,Master!$J:$M,4,0),"") | J64: =_xlfn.IFNA(VLOOKUP($E64,Master!$J:$M,3,0),"") | AC64: =SUM(K64:P64) | AD64: =SUM(Q64:AB64)
B65: =_xlfn.IFNA(VLOOKUP(C65,Master!$J:$K,2,0),"") | D65: =_xlfn.IFNA(VLOOKUP(E65,Master!$J:$K,2,0),"") | F65: =_xlfn.IFNA(VLOOKUP(G65,Master!B:C,2,0),"") | I65: =_xlfn.IFNA(VLOOKUP(E65,Master!$J:$M,4,0),"") | J65: =_xlfn.IFNA(VLOOKUP($E65,Master!$J:$M,3,0),"") | AC65: =SUM(K65:P65) | AD65: =SUM(Q65:AB65)
B66: =_xlfn.IFNA(VLOOKUP(C66,Master!$J:$K,2,0),"") | D66: =_xlfn.IFNA(VLOOKUP(E66,Master!$J:$K,2,0),"") | F66: =_xlfn.IFNA(VLOOKUP(G66,Master!B:C,2,0),"") | I66: =_xlfn.IFNA(VLOOKUP(E66,Master!$J:$M,4,0),"") | J66: =_xlfn.IFNA(VLOOKUP($E66,Master!$J:$M,3,0),"") | AC66: =SUM(K66:P66) | AD66: =SUM(Q66:AB66)
B67: =_xlfn.IFNA(VLOOKUP(C67,Master!$J:$K,2,0),"") | D67: =_xlfn.IFNA(VLOOKUP(E67,Master!$J:$K,2,0),"") | F67: =_xlfn.IFNA(VLOOKUP(G67,Master!B:C,2,0),"") | I67: =_xlfn.IFNA(VLOOKUP(E67,Master!$J:$M,4,0),"") | J67: =_xlfn.IFNA(VLOOKUP($E67,Master!$J:$M,3,0),"") | AC67: =SUM(K67:P67) | AD67: =SUM(Q67:AB67)
B68: =_xlfn.IFNA(VLOOKUP(C68,Master!$J:$K,2,0),"") | D68: =_xlfn.IFNA(VLOOKUP(E68,Master!$J:$K,2,0),"") | F68: =_xlfn.IFNA(VLOOKUP(G68,Master!B:C,2,0),"") | I68: =_xlfn.IFNA(VLOOKUP(E68,Master!$J:$M,4,0),"") | J68: =_xlfn.IFNA(VLOOKUP($E68,Master!$J:$M,3,0),"") | AC68: =SUM(K68:P68) | AD68: =SUM(Q68:AB68)
B69: =_xlfn.IFNA(VLOOKUP(C69,Master!$J:$K,2,0),"") | D69: =_xlfn.IFNA(VLOOKUP(E69,Master!$J:$K,2,0),"") | F69: =_xlfn.IFNA(VLOOKUP(G69,Master!B:C,2,0),"") | I69: =_xlfn.IFNA(VLOOKUP(E69,Master!$J:$M,4,0),"") | J69: =_xlfn.IFNA(VLOOKUP($E69,Master!$J:$M,3,0),"") | AC69: =SUM(K69:P69) | AD69: =SUM(Q69:AB69)
B70: =_xlfn.IFNA(VLOOKUP(C70,Master!$J:$K,2,0),"") | D70: =_xlfn.IFNA(VLOOKUP(E70,Master!$J:$K,2,0),"") | F70: =_xlfn.IFNA(VLOOKUP(G70,Master!B:C,2,0),"") | I70: =_xlfn.IFNA(VLOOKUP(E70,Master!$J:$M,4,0),"") | J70: =_xlfn.IFNA(VLOOKUP($E70,Master!$J:$M,3,0),"") | AC70: =SUM(K70:P70) | AD70: =SUM(Q70:AB70)
B71: =_xlfn.IFNA(VLOOKUP(C71,Master!$J:$K,2,0),"") | D71: =_xlfn.IFNA(VLOOKUP(E71,Master!$J:$K,2,0),"") | F71: =_xlfn.IFNA(VLOOKUP(G71,Master!B:C,2,0),"") | I71: =_xlfn.IFNA(VLOOKUP(E71,Master!$J:$M,4,0),"") | J71: =_xlfn.IFNA(VLOOKUP($E71,Master!$J:$M,3,0),"") | AC71: =SUM(K71:P71) | AD71: =SUM(Q71:AB71)
B72: =_xlfn.IFNA(VLOOKUP(C72,Master!$J:$K,2,0),"") | D72: =_xlfn.IFNA(VLOOKUP(E72,Master!$J:$K,2,0),"") | F72: =_xlfn.IFNA(VLOOKUP(G72,Master!B:C,2,0),"") | I72: =_xlfn.IFNA(VLOOKUP(E72,Master!$J:$M,4,0),"") | J72: =_xlfn.IFNA(VLOOKUP($E72,Master!$J:$M,3,0),"") | AC72: =SUM(K72:P72) | AD72: =SUM(Q72:AB72)
B73: =_xlfn.IFNA(VLOOKUP(C73,Master!$J:$K,2,0),"") | D73: =_xlfn.IFNA(VLOOKUP(E73,Master!$J:$K,2,0),"") | F73: =_xlfn.IFNA(VLOOKUP(G73,Master!B:C,2,0),"") | I73: =_xlfn.IFNA(VLOOKUP(E73,Master!$J:$M,4,0),"") | J73: =_xlfn.IFNA(VLOOKUP($E73,Master!$J:$M,3,0),"") | AC73: =SUM(K73:P73) | AD73: =SUM(Q73:AB73)
... B450: =_xlfn.IFNA(VLOOKUP(C450,Master!$J:$K,2,0),"") | D450: =_xlfn.IFNA(VLOOKUP(E450,Master!$J:$K,2,0),"") | F450: =_xlfn.IFNA(VLOOKUP(G450,Master!B:C,2,0),"") | I450: =_xlfn.IFNA(VLOOKUP(E450,Master!$J:$M,4,0),"") | J450: =_xlfn.IFNA(VLOOKUP($E450,Master!$J:$M,3,0),"") | AC450: =SUM(K450:P450) | AD450: =SUM(Q450:AB450)
B451: =_xlfn.IFNA(VLOOKUP(C451,Master!$J:$K,2,0),"") | F451: =_xlfn.IFNA(VLOOKUP(G451,Master!B:C,2,0),"") | I451: =_xlfn.IFNA(VLOOKUP(E451,Master!$J:$M,4,0),"") | J451: =_xlfn.IFNA(VLOOKUP($E451,Master!$J:$M,3,0),"") | AC451: =SUM(K451:P451) | AD451: =SUM(Q451:AB451)
B452: =_xlfn.IFNA(VLOOKUP(C452,Master!$J:$K,2,0),"") | F452: =_xlfn.IFNA(VLOOKUP(G452,Master!B:C,2,0),"") | I452: =_xlfn.IFNA(VLOOKUP(E452,Master!$J:$M,4,0),"") | J452: =_xlfn.IFNA(VLOOKUP($E452,Master!$J:$M,3,0),"") | AC452: =SUM(K452:P452) | AD452: =SUM(Q452:AB452)
B453: =_xlfn.IFNA(VLOOKUP(C453,Master!$J:$K,2,0),"") | F453: =_xlfn.IFNA(VLOOKUP(G453,Master!B:C,2,0),"") | I453: =_xlfn.IFNA(VLOOKUP(E453,Master!$J:$M,4,0),"") | J453: =_xlfn.IFNA(VLOOKUP($E453,Master!$J:$M,3,0),"") | AC453: =SUM(K453:P453) | AD453: =SUM(Q453:AB453)
B454: =_xlfn.IFNA(VLOOKUP(C454,Master!$J:$K,2,0),"") | F454: =_xlfn.IFNA(VLOOKUP(G454,Master!B:C,2,0),"") | I454: =_xlfn.IFNA(VLOOKUP(E454,Master!$J:$M,4,0),"") | J454: =_xlfn.IFNA(VLOOKUP($E454,Master!$J:$M,3,0),"") | AC454: =SUM(K454:P454) | AD454: =SUM(Q454:AB454)
B455: =_xlfn.IFNA(VLOOKUP(C455,Master!$J:$K,2,0),"") | F455: =_xlfn.IFNA(VLOOKUP(G455,Master!B:C,2,0),"") | I455: =_xlfn.IFNA(VLOOKUP(E455,Master!$J:$M,4,0),"") | J455: =_xlfn.IFNA(VLOOKUP($E455,Master!$J:$M,3,0),"") | AC455: =SUM(K455:P455) | AD455: =SUM(Q455:AB455)
B456: =_xlfn.IFNA(VLOOKUP(C456,Master!$J:$K,2,0),"") | F456: =_xlfn.IFNA(VLOOKUP(G456,Master!B:C,2,0),"") | I456: =_xlfn.IFNA(VLOOKUP(E456,Master!$J:$M,4,0),"") | J456: =_xlfn.IFNA(VLOOKUP($E456,Master!$J:$M,3,0),"") | AC456: =SUM(K456:P456) | AD456: =SUM(Q456:AB456)
B457: =_xlfn.IFNA(VLOOKUP(C457,Master!$J:$K,2,0),"") | F457: =_xlfn.IFNA(VLOOKUP(G457,Master!B:C,2,0),"") | I457: =_xlfn.IFNA(VLOOKUP(E457,Master!$J:$M,4,0),"") | J457: =_xlfn.IFNA(VLOOKUP($E457,Master!$J:$M,3,0),"") | AC457: =SUM(K457:P457) | AD457: =SUM(Q457:AB457)
B458: =_xlfn.IFNA(VLOOKUP(C458,Master!$J:$K,2,0),"") | F458: =_xlfn.IFNA(VLOOKUP(G458,Master!B:C,2,0),"") | I458: =_xlfn.IFNA(VLOOKUP(E458,Master!$J:$M,4,0),"") | J458: =_xlfn.IFNA(VLOOKUP($E458,Master!$J:$M,3,0),"") | AC458: =SUM(K458:P458) | AD458: =SUM(Q458:AB458)
B459: =_xlfn.IFNA(VLOOKUP(C459,Master!$J:$K,2,0),"") | F459: =_xlfn.IFNA(VLOOKUP(G459,Master!B:C,2,0),"") | I459: =_xlfn.IFNA(VLOOKUP(E459,Master!$J:$M,4,0),"") | J459: =_xlfn.IFNA(VLOOKUP($E459,Master!$J:$M,3,0),"") | AC459: =SUM(K459:P459) | AD459: =SUM(Q459:AB459)
B460: =_xlfn.IFNA(VLOOKUP(C460,Master!$J:$K,2,0),"") | F460: =_xlfn.IFNA(VLOOKUP(G460,Master!B:C,2,0),"") | I460: =_xlfn.IFNA(VLOOKUP(E460,Master!$J:$M,4,0),"") | J460: =_xlfn.IFNA(VLOOKUP($E460,Master!$J:$M,3,0),"") | AC460: =SUM(K460:P460) | AD460: =SUM(Q460:AB460)
B461: =_xlfn.IFNA(VLOOKUP(C461,Master!$J:$K,2,0),"") | F461: =_xlfn.IFNA(VLOOKUP(G461,Master!B:C,2,0),"") | I461: =_xlfn.IFNA(VLOOKUP(E461,Master!$J:$M,4,0),"") | J461: =_xlfn.IFNA(VLOOKUP($E461,Master!$J:$M,3,0),"") | AC461: =SUM(K461:P461) | AD461: =SUM(Q461:AB461)
B462: =_xlfn.IFNA(VLOOKUP(C462,Master!$J:$K,2,0),"") | F462: =_xlfn.IFNA(VLOOKUP(G462,Master!B:C,2,0),"") | I462: =_xlfn.IFNA(VLOOKUP(E462,Master!$J:$M,4,0),"") | J462: =_xlfn.IFNA(VLOOKUP($E462,Master!$J:$M,3,0),"") | AC462: =SUM(K462:P462) | AD462: =SUM(Q462:AB462)
... B512: =_xlfn.IFNA(VLOOKUP(C512,Master!$J:$K,2,0),"") | F512: =_xlfn.IFNA(VLOOKUP(G512,Master!B:C,2,0),"") | I512: =_xlfn.IFNA(VLOOKUP(E512,Master!$J:$M,4,0),"") | J512: =_xlfn.IFNA(VLOOKUP($E512,Master!$J:$M,3,0),"") | AC512: =SUM(K512:P512) | AD512: =SUM(Q512:AB512)
B513: =_xlfn.IFNA(VLOOKUP(C513,Master!$J:$K,2,0),"") | F513: =_xlfn.IFNA(VLOOKUP(G513,Master!B:C,2,0),"") | AC513: =SUM(K513:P513) | AD513: =SUM(Q513:AB513)
B514: =_xlfn.IFNA(VLOOKUP(C514,Master!$J:$K,2,0),"") | F514: =_xlfn.IFNA(VLOOKUP(G514,Master!B:C,2,0),"") | AC514: =SUM(K514:P514) | AD514: =SUM(Q514:AB514)
B515: =_xlfn.IFNA(VLOOKUP(C515,Master!$J:$K,2,0),"") | F515: =_xlfn.IFNA(VLOOKUP(G515,Master!B:C,2,0),"") | AC515: =SUM(K515:P515) | AD515: =SUM(Q515:AB515)
B516: =_xlfn.IFNA(VLOOKUP(C516,Master!$J:$K,2,0),"") | F516: =_xlfn.IFNA(VLOOKUP(G516,Master!B:C,2,0),"") | AC516: =SUM(K516:P516) | AD516: =SUM(Q516:AB516)
B517: =_xlfn.IFNA(VLOOKUP(C517,Master!$J:$K,2,0),"") | F517: =_xlfn.IFNA(VLOOKUP(G517,Master!B:C,2,0),"") | AC517: =SUM(K517:P517) | AD517: =SUM(Q517:AB517)
B518: =_xlfn.IFNA(VLOOKUP(C518,Master!$J:$K,2,0),"") | F518: =_xlfn.IFNA(VLOOKUP(G518,Master!B:C,2,0),"") | AC518: =SUM(K518:P518) | AD518: =SUM(Q518:AB518)
B519: =_xlfn.IFNA(VLOOKUP(C519,Master!$J:$K,2,0),"") | F519: =_xlfn.IFNA(VLOOKUP(G519,Master!B:C,2,0),"") | AC519: =SUM(K519:P519) | AD519: =SUM(Q519:AB519)
B520: =_xlfn.IFNA(VLOOKUP(C520,Master!$J:$K,2,0),"") | F520: =_xlfn.IFNA(VLOOKUP(G520,Master!B:C,2,0),"") | AC520: =SUM(K520:P520) | AD520: =SUM(Q520:AB520)
B521: =_xlfn.IFNA(VLOOKUP(C521,Master!$J:$K,2,0),"") | F521: =_xlfn.IFNA(VLOOKUP(G521,Master!B:C,2,0),"") | AC521: =SUM(K521:P521) | AD521: =SUM(Q521:AB521)
B522: =_xlfn.IFNA(VLOOKUP(C522,Master!$J:$K,2,0),"") | F522: =_xlfn.IFNA(VLOOKUP(G522,Master!B:C,2,0),"") | AC522: =SUM(K522:P522) | AD522: =SUM(Q522:AB522)
B523: =_xlfn.IFNA(VLOOKUP(C523,Master!$J:$K,2,0),"") | F523: =_xlfn.IFNA(VLOOKUP(G523,Master!B:C,2,0),"") | AC523: =SUM(K523:P523) | AD523: =SUM(Q523:AB523)
B524: =_xlfn.IFNA(VLOOKUP(C524,Master!$J:$K,2,0),"") | F524: =_xlfn.IFNA(VLOOKUP(G524,Master!B:C,2,0),"")
B525: =_xlfn.IFNA(VLOOKUP(C525,Master!$J:$K,2,0),"")
B526: =_xlfn.IFNA(VLOOKUP(C526,Master!$J:$K,2,0),"")
...

Sheet V1
A1: This sheet is used for version checking, do not delete

Sheet Master
A1: COA AX | B1: Name COA AX | C1: COA AX | D1: COA AX | E1: Group Cost | F1: UNIQ | G1: COA Budget | H1: Description | J1: Name | K1: BNGK | L1: GROUP COST | M1: GROUP SECTION | N1: Name | P1: Code | Q1: Name | S1: Priority Code | T1: Priority Name | U1: Description
A2: 7511101 | B2: Salary for Commissioner | C2: 7511101 | D2: 7511101 | E2: SGA | F2: SGA-7511101 | G2: A502 | H2: Salary for Commissioner | J2: Top Management | K2: B1000 | L2: SGA | M2: ADM | N2: Top Management | P2: 53450 | Q2: NGK BUSI INDONESIA | S2: A | T2: Must | U2: If this is not done, the company or our team cannot continue its business.
A3: 7511102 | B3: Salary for Director | C3: 7511102 | D3: 7511102 | E3: SGA | F3: SGA-7511102 | G3: A502 | H3: Salary for Director & Expat | J3: Commissioner | K3: B1001 | L3: SGA | M3: ADM | N3: Commissioner | S3: B | T3: Want to | U3: We want to do it as a team this term. we need it.
A4: 7511103 | B4: Staff Labor - Baslc Salary | C4: 7511103 | D4: 7511103 | E4: SGA | F4: SGA-7511103 | G4: A501 | H4: Basic Salary of permanent employee | J4: Admin & HR | K4: B2200 | L4: SGA | M4: ADM | N4: Admin & HR | S4: C | T4: Challenge | U4: We want to do it for this term or the future. But it doesn't matter if it's not this term.
A5: 7511111 | B5: Staff Labor - Allowance | C5: 7511111 | D5: 7511111 | E5: SGA | F5: SGA-7511111 | G5: A501 | H5: Employee allowance | J5: General Affair | K5: B2210 | L5: SGA | M5: ADM | N5: General Affair
A6: 7511112 | B6: Staff Labor - Tax allowance (art.21) | C6: 7511112 | D6: 7511112 | E6: SGA | F6: SGA-7511112 | G6: A501 | H6: Empployee Tax allowance | J6: Human Resource | K6: B2220 | L6: SGA | M6: ADM | N6: Human Resource | P6: BEX
A7: 7511121 | B7: Staff Labor - BPJS JK & JKK (1.19%) | C7: 7511121 | D7: 7511121 | E7: SGA | F7: SGA-7511121 | G7: A501 | H7: BPJS JK & JKK (death warrant, Accident Insurance) | J7: Health, Safety & Environment | K7: B2230 | L7: SGA | M7: ADM | N7: Health, Safety & Environment | P7: BEL
A8: 7511122 | B8: Staff Labor - BPJS Kesehatan (4%) | C8: 7511122 | D8: 7511122 | E8: SGA | F8: SGA-7511122 | G8: A501 | H8: BPJS health insurance | J8: Accounting & Finance | K8: B2300 | L8: SGA | M8: ADM | N8: Accounting & Finance
A9: 7511201 | B9: Staff Overtime | C9: 7511201 | D9: 7511201 | E9: SGA | F9: SGA-7511201 | G9: A503 | H9: Overtime permanent employee | J9: Information Technology | K9: B2400 | L9: SGA | M9: ADM | N9: Information Technology
A10: 7512111 | B10: Staff Welfare - BPJS Dana pensiun (2%) | C10: 7512111 | D10: 7512111 | E10: SGA | F10: SGA-7512111 | G10: A504 | H10: BPJS pension fund | J10: Sales & MKTG Dept.- Automotive | K10: B3100 | L10: SGA | M10: ADM | N10: Sales & MKTG Dept.- Automotive
A11: 7512112 | B11: Staff Welfare - BPJS JHT (3.7%) | C11: 7512112 | D11: 7512112 | E11: SGA | F11: SGA-7512112 | G11: A504 | H11: BPJS Pension plan | J11: Marketing | K11: B3160 | L11: SGA | M11: ADM | N11: Marketing
A12: 7514101 | B12: Staff Bonus / TAT | C12: 7514101 | D12: 7514101 | E12: SGA | F12: SGA-7514101 | G12: A501 | H12: Year-end allowance & Alpha | J12: Sales - OEM | K12: B3110 | L12: SGA | M12: ADM | N12: Sales - OEM
A13: 7514102 | B13: Staff Ramadhan / THR | C13: 7514102 | D13: 7514102 | E13: SGA | F13: SGA-7514102 | G13: A501 | H13: Lebaran bonus | J13: Sales - OES | K13: B3120 | L13: SGA | M13: ADM | N13: Sales - OES
A14: 7515401 | B14: Staff Welfare - Outpatient (Medical) | C14: 7515401 | D14: 7515401 | E14: SGA | F14: SGA-7515401 | G14: A504 | H14: outpatient treatment costs | J14: Sales - IAM | K14: B3130 | L14: SGA | M14: ADM | N14: Sales - IAM
A15: 7515402 | B15: Staff Welfare - Hospitalization | C15: 7515402 | D15: 7515402 | E15: SGA | F15: SGA-7515402 | G15: A504 | H15: hospitalization costs | J15: Sales & MKTG Dept.- DID Chain | K15: B3172 | L15: SGA | M15: ADM | N15: Sales & MKTG Dept.- DID Chain
A16: 7515403 | B16: Staff Welfare - Glasses | C16: 7515403 | D16: 7515403 | E16: SGA | F16: SGA-7515403 | G16: A504 | H16: glasses costs | J16: SP PD- CF | K16: B4101 | L16: MFG | M16: DIR | N16: SP PD- CF
A17: 7515404 | B17: Staff Welfare - Dental | C17: 7515404 | D17: 7515404 | E17: SGA | F17: SGA-7515404 | G17: A504 | H17: dental costs | J17: SP PD- CM | K17: B4102 | L17: MFG | M17: DIR | N17: SP PD- CM
A18: 7515405 | B18: Staff Welfare - Medical Check Up | C18: 7515405 | D18: 7515405 | E18: SGA | F18: SGA-7515405 | G18: A504 | H18: Medical Check Up cost | J18: SP PD- WT | K18: B4103 | L18: MFG | M18: DIR | N18: SP PD- WT
A19: 7515406 | B19: Staff Welfare - Uniform | C19: 7515406 | D19: 7515406 | E19: SGA | F19: SGA-7515406 | G19: A504 | H19: uniform costs | J19: SP PD- Plating | K19: B4105 | L19: MFG | M19: DIR | N19: SP PD- Plating
A20: 7515407 | B20: Staff Welfare - Safety Shoes | C20: 7515407 | D20: 7515407 | E20: SGA | F20: SGA-7515407 | G20: A504 | J20: SP PD- MS Insp. | K20: B4109 | L20: MFG | M20: DIR | N20: SP PD- MS Insp.
A21: 7515408 | B21: Staff Welfare - Family Gathering / Anniversary | C21: 7515408 | D21: 7515408 | E21: SGA | F21: SGA-7515408 | G21: A504 | H21: Family Gathering / Anniversary | J21: SP PD- Insulator Sealing | K21: B4130 | L21: MFG | M21: DIR | N21: SP PD- Insulator Sealing
A22: 7515409 | B22: Staff Welfare - Meals of canteen & other meals | C22: 7515409 | D22: 7515409 | E22: SGA | F22: SGA-7515409 | G22: A504 | H22: Meals of canteen & other meals cost | J22: SP PD- Assy | K22: B4110 | L22: MFG | M22: DIR | N22: SP PD- Assy
A23: 7515410 | B23: Staff Welfare - Kaizen & QCC reward | C23: 7515410 | D23: 7515410 | E23: SGA | F23: SGA-7515410 | G23: A504 | H23: an expense, arising from Kaizen and QCC acitivity | J23: SP-PD-Assy-Auto Assembly | K23: B4115 | L23: MFG | M23: DIR | N23: SP-PD-Assy-Auto Assembly
A24: 7515499 | B24: Staff Welfare - Welfare Others | C24: 7515499 | D24: 7515499 | E24: SGA | F24: SGA-7515499 | G24: A504 | H24: an other welfare expense, arising besides the above welfare expense | J24: SP PD- Bending | K24: B4114 | L24: MFG | M24: DIR | N24: SP PD- Bending
A25: 7516102 | B25: Retirement Allowance | C25: 7516102 | D25: 7516102 | E25: SGA | F25: SGA-7516102 | G25: A505 | H25: employee retirement provission costs | J25: SP PD- Final Inspection | K25: B4120 | L25: MFG | M25: DIR | N25: SP PD- Final Inspection
A26: 7519101 | B26: House Rent Allowance | C26: 7519101 | D26: 7519101 | E26: SGA | F26: SGA-7519101 | G26: A502 | H26: House Rent Allowance for expat | J26: SP PD- QC - OEM | K26: B4121 | L26: MFG | M26: DIR | N26: SP PD- QC - OEM
A27: 7521101 | B27: Casual Staff Labor - Basic Salary | C27: 7521101 | D27: 7521101 | E27: SGA | F27: SGA-7521101 | G27: A501 | H27: All benefit for temporary worker | J27: PC PD- Injection | K27: B4410 | L27: MFG | M27: DIR | N27: PC PD- Injection
A28: 7521102 | B28: Casual Staff Labor - Overtime | C28: 7521102 | D28: 7521102 | E28: SGA | F28: SGA-7521102 | G28: A503 | H28: Overtime temporary worker | J28: PC PD- Assy | K28: B4430 | L28: MFG | M28: DIR | N28: PC PD- Assy
A29: 7571101 | B29: Personnel expense transferred | C29: 7571101 | D29: 7571101 | E29: SGA | F29: SGA-7571101 | G29: A506 | H29: Transfer Labor cost from one section into another section | J29: PC PD- QC | K29: B4440 | L29: MFG | M29: DIR | N29: PC PD- QC
A30: 7611100 | B30: Depreciation-Building | C30: 7611100 | D30: 7611100 | E30: SGA | F30: SGA-7611100 | G30: A601 | H30: the amount of depreciation of tangible assets for building | J30: Plant Operation (Indirect Mfg) | K30: B5000 | L30: MFG | M30: IND | N30: Plant Operation (Indirect Mfg)
A31: 7611300 | B31: Depreciation-Machiney & equipment | C31: 7611300 | D31: 7611300 | E31: SGA | F31: SGA-7611300 | G31: A601 | H31: the amount of depreciation of tangible assets for machinery & factory equipment | J31: Production Office | K31: B5100 | L31: MFG | M31: IND | N31: Production Office
A32: 7611400 | B32: Depreciation-Lease Machinery & equipment | C32: 7611400 | D32: 7611400 | E32: SGA | F32: SGA-7611400 | G32: A601 | H32: the amount of depreciation of tangible assets for machinery & factory equipment (Leases) | J32: Production Office (SP) | K32: B5101 | L32: MFG | M32: IND | N32: Production Office (SP)
... A42: 7641102 | B42: Repair of Equipment | C42: 7641102 | D42: 7641102 | E42: SGA | F42: SGA-7641102 | G42: A1002 | H42: expenses for repair and maintenance tangible assets, intangible assets and other assets beside building | J42: Continuous Improvement | K42: B5007 | L42: MFG | M42: IND | N42: Continuous Improvement
A43: 7641103 | B43: Factory Supply Expense | C43: 7641103 | D43: 7641103 | E43: SGA | F43: SGA-7641103 | G43: A1099 | H43: All cost that arrising to support factory acitivity | J43: All | K43: B0000 | N43: All
A44: 7641104 | B44: Calibration Cost | C44: 7641104 | D44: 7641104 | E44: SGA | F44: SGA-7641104 | G44: A1099 | H44: Cost of calibration for tools and equipment of factory and others
A45: 7651101 | B45: Transportation Fee for employee | C45: 7651101 | D45: 7651101 | E45: SGA | F45: SGA-7651101 | G45: A801 | H45: Gasoline of company cars & expense for Local transportation
A46: 7651102 | B46: Travel Expense-Domestic | C46: 7651102 | D46: 7651102 | E46: SGA | F46: SGA-7651102 | G46: A801 | H46: expenses for business trip, including allowance for business trip to an employee only for domestic travel
A47: 7651103 | B47: Travel Expense-Oversea | C47: 7651103 | D47: 7651103 | E47: SGA | F47: SGA-7651103 | G47: A801 | H47: expenses for business trip, including allowance for business trip to an employee only for overseas travel
A48: 7661101 | B48: Entertainment | C48: 7661101 | D48: 7661101 | E48: SGA | F48: SGA-7661101 | G48: A1001 | H48: the amount of expenses for the act of entertaining the business partner
A49: 7671102 | B49: Amortization of Land & Building tax (PBB) | C49: 7671102 | D49: 7671102 | E49: SGA | F49: SGA-7671102 | G49: A1099 | H49: the amount of depreciation of intangible of Land & Building Tax (PBB)
A50: 7671103 | B50: License fee | C50: 7671103 | D50: 7671103 | E50: SGA | F50: SGA-7671103 | G50: A1099 | H50: The expense related with the documentation process, such as : KIR, Car lisence, company lisence, etc.
A51: 7681101 | B51: Insurance Premium | C51: 7681101 | D51: 7681101 | E51: SGA | F51: SGA-7681101 | G51: A1099 | H51: expenses for risk management with no premium at the end of the term, such as fire insurance for plants and inventories
A52: 7691000 | B52: Office supply & Stationary Expense | C52: 7691000 | D52: 7691000 | E52: SGA | F52: SGA-7691000 | G52: A1099 | H52: the amount of supplies for office, such as stationery. Small office equipment included
A53: 7711101 | B53: Communication expenses | C53: 7711101 | D53: 7711101 | E53: SGA | F53: SGA-7711101 | G53: A1099 | H53: expenses for communication with a people in remote place, such as expense for telephone and postage
A54: 7711102 | B54: IT Expense | C54: 7711102 | D54: 7711102 | E54: SGA | F54: SGA-7711102 | G54: A1005 | H54: the amount of supplies for IT tools
A55: 7711103 | B55: Stamp/Post Fee | C55: 7711103 | D55: 7711103 | E55: SGA | F55: SGA-7711103 | G55: A1099 | H55: The expenses related with stamp duty
... A76: 7461101 | B76: Sample expense | C76: 7461101 | D76: 7461101 | E76: SGA | F76: SGA-7461101 | G76: A499 | H76: Sample expense
A77: 7411105 | B77: Sales - Insurance of Delivery or Shipment | C77: 7411105 | D77: 7411105 | E77: SGA | F77: SGA-7411105 | G77: A299
A78: 7471201 | B78: Sales - Insurance of AR (Credit Insurance) | C78: 7471201 | D78: 7471201 | E78: SGA | F78: SGA-7471201 | G78: A299
A79: 7751101 | B79: Sales - Royalty to NGK Group | C79: 7751101 | D79: 7751101 | E79: SGA | F79: SGA-7751101
A80: 7751102 | B80: Sales - Royalty to Independence Party | C80: 7751102 | D80: 7751102 | E80: SGA | F80: SGA-7751102
A81: 7111211 | B81: Import Duty-purchased FG from NGK group | C81: 7111211 | D81: 7111211 | E81: MFG | F81: MFG-7111211
A82: 7111212 | B82: Import Duty-purchased FG from outside supplier | C82: 7111212 | D82: 7111212 | E82: MFG | F82: MFG-7111212
A83: 7111221 | B83: Import Duty-purchased KD&RM from NGK Japan | C83: 7111221 | D83: 7111221 | E83: MFG | F83: MFG-7111221
A84: 7111222 | B84: Import Duty-purchased KD&RM from NGK Group(Not fromJP) | C84: 7111222 | D84: 7111222 | E84: MFG | F84: MFG-7111222
A85: 7111223 | B85: Import Duty-purchased Comp Parts&RM from outside supplier | C85: 7111223 | D85: 7111223 | E85: MFG | F85: MFG-7111223
A86: 7111311 | B86: Import Expense-purchased FG from NGK group | C86: 7111311 | D86: 7111311 | E86: MFG | F86: MFG-7111311
A87: 7111312 | B87: Import Expense-purchased FG from outside supplier | C87: 7111312 | D87: 7111312 | E87: MFG | F87: MFG-7111312
A88: 7111321 | B88: Import Expense-purchased KD&RM from NGK Japan | C88: 7111321 | D88: 7111321 | E88: MFG | F88: MFG-7111321
A89: 7111322 | B89: Import Expense-purchased KD&RM from NGK Group(Not fromJP) | C89: 7111322 | D89: 7111322 | E89: MFG | F89: MFG-7111322
A90: 7111323 | B90: Import Expense-purchased Comp Parts&RM from outside supplier | C90: 7111323 | D90: 7111323 | E90: MFG | F90: MFG-7111323
... A94: 7211101 | B94: Cost of Factory Supply | C94: 7211101 | D94: 7211101 | E94: MFG | F94: MFG-7211101
A95: 7211102 | B95: Cost of Chemical | C95: 7211102 | D95: 7211102 | E95: MFG | F95: MFG-7211102 | G95: 901 | H95: The expenses of Chemicals consumption
A96: 7211103 | B96: Cost of Packaging | C96: 7211103 | D96: 7211103 | E96: MFG | F96: MFG-7211103
A97: 7211104 | B97: Cost of Oil | C97: 7211104 | D97: 7211104 | E97: MFG | F97: MFG-7211104 | G97: 302
A98: 7221101 | B98: Cost of Tooling | C98: 7221101 | D98: 7221101 | E98: MFG | F98: MFG-7221101 | G98: 302 | H98: The expenses of Tooling consumption
A99: 7221102 | B99: Cost of Machinery parts | C99: 7221102 | D99: 7221102 | E99: MFG | F99: MFG-7221102 | G99: 301 | H99: The expenses of Spare Parts consumption
A100: 7511101 | B100: Salary for Commissioner | C100: 7511101 | D100: 7511101 | E100: MFG | F100: MFG-7511101 | G100: 602 | H100: Salary for Commissioner
A101: 7511102 | B101: Salary for Director | C101: 7511102 | D101: 7511102 | E101: MFG | F101: MFG-7511102 | G101: 602 | H101: Salary for Director & Expat
A102: 7511103 | B102: Staff Labor - Baslc Salary | C102: 7511103 | D102: 7511103 | E102: MFG | F102: MFG-7511103 | G102: 601 | H102: Basic Salary of permanent employee
A103: 7511111 | B103: Staff Labor - Allowance | C103: 7511111 | D103: 7511111 | E103: MFG | F103: MFG-7511111 | G103: 601 | H103: Employee allowance
A104: 7511112 | B104: Staff Labor - Tax allowance (art.21) | C104: 7511112 | D104: 7511112 | E104: MFG | F104: MFG-7511112 | G104: 601 | H104: Empployee Tax allowance
A105: 7511121 | B105: Staff Labor - BPJS JK & JKK (1.19%) | C105: 7511121 | D105: 7511121 | E105: MFG | F105: MFG-7511121 | G105: 601 | H105: BPJS JK & JKK (death warrant, Accident Insurance)
A106: 7511122 | B106: Staff Labor - BPJS Kesehatan (4%) | C106: 7511122 | D106: 7511122 | E106: MFG | F106: MFG-7511122 | G106: 601 | H106: BPJS health insurance
A107: 7511201 | B107: Staff Overtime | C107: 7511201 | D107: 7511201 | E107: MFG | F107: MFG-7511201 | G107: 603 | H107: Overtime permanent employee
A108: 7512111 | B108: Staff Welfare - BPJS Dana pensiun (2%) | C108: 7512111 | D108: 7512111 | E108: MFG | F108: MFG-7512111 | G108: 604 | H108: BPJS pension fund
A109: 7512112 | B109: Staff Welfare - BPJS JHT (3.7%) | C109: 7512112 | D109: 7512112 | E109: MFG | F109: MFG-7512112 | G109: 604 | H109: BPJS Pension plan
... A117: 7515406 | B117: Staff Welfare - Uniform | C117: 7515406 | D117: 7515406 | E117: MFG | F117: MFG-7515406 | G117: 604 | H117: uniform costs
A118: 7515407 | B118: Staff Welfare - Safety Shoes | C118: 7515407 | D118: 7515407 | E118: MFG | F118: MFG-7515407 | G118: 604
A119: 7515408 | B119: Staff Welfare - Family Gathering / Anniversary | C119: 7515408 | D119: 7515408 | E119: MFG | F119: MFG-7515408 | G119: 604 | H119: Family Gathering / Anniversary
A120: 7515409 | B120: Staff Welfare - Meals of canteen & other meals | C120: 7515409 | D120: 7515409 | E120: MFG | F120: MFG-7515409 | G120: 604 | H120: Meals of canteen & other meals cost
A121: 7515410 | B121: Staff Welfare - Kaizen & QCC reward | C121: 7515410 | D121: 7515410 | E121: MFG | F121: MFG-7515410 | G121: 604 | H121: an expense, arising from Kaizen and QCC acitivity
A122: 7515499 | B122: Staff Welfare - Welfare Others | C122: 7515499 | D122: 7515499 | E122: MFG | F122: MFG-7515499 | G122: 604 | H122: an other welfare expense, arising besides the above welfare expense
A123: 7516102 | B123: Retirement Allowance | C123: 7516102 | D123: 7516102 | E123: MFG | F123: MFG-7516102 | G123: 605 | H123: employee retirement provission costs
A124: 7519101 | B124: House Rent Allowance | C124: 7519101 | D124: 7519101 | E124: MFG | F124: MFG-7519101 | G124: 602 | H124: House Rent Allowance for expat
A125: 7521101 | B125: Casual Staff Labor - Basic Salary | C125: 7521101 | D125: 7521101 | E125: MFG | F125: MFG-7521101 | G125: 601 | H125: All benefit for temporary worker
A126: 7521102 | B126: Casual Staff Labor - Overtime | C126: 7521102 | D126: 7521102 | E126: MFG | F126: MFG-7521102 | G126: 603 | H126: Overtime temporary worker
A127: 7571101 | B127: Personnel expense transferred | C127: 7571101 | D127: 7571101 | E127: MFG | F127: MFG-7571101 | G127: 606 | H127: Transfer Labor cost from one section into another section
A128: 7611100 | B128: Depreciation-Building | C128: 7611100 | D128: 7611100 | E128: MFG | F128: MFG-7611100 | G128: 701 | H128: the amount of depreciation of tangible assets for building
A129: 7611300 | B129: Depreciation-Machiney & equipment | C129: 7611300 | D129: 7611300 | E129: MFG | F129: MFG-7611300 | G129: 701 | H129: the amount of depreciation of tangible assets for machinery & factory equipment
A130: 7611400 | B130: Depreciation-Lease Machinery & equipment | C130: 7611400 | D130: 7611400 | E130: MFG | F130: MFG-7611400 | G130: 701 | H130: the amount of depreciation of tangible assets for machinery & factory equipment (Leases)
... A166: 7781113 | B166: Expatriate fee Tax (BADORA) | C166: 7781113 | D166: 7781113 | E166: MFG | F166: MFG-7781113 | G166: 999 | H166: Tax income from expatriete
A167: 8291101 | B167: Others - Miscellaneous Waste | C167: 8291101 | D167: 8291101 | E167: OTH | F167: OTH-8291101
A168: 8291102 | B168: Others - Miscellaneous Tax | C168: 8291102 | D168: 8291102 | E168: OTH | F168: OTH-8291102
A169: 8291201 | B169: Others - Sport Activity | C169: 8291201 | D169: 8291201 | E169: OTH | F169: OTH-8291201
A170: 8291202 | B170: Others - Retribution / Garbage Cost | C170: 8291202 | D170: 8291202 | E170: OTH | F170: OTH-8291202
A171: 8291203 | B171: Others - Miscellaneous Non Operational Expense | C171: 8291203 | D171: 8291203 | E171: OTH | F171: OTH-8291203
A172: 8191101 | B172: Other Income | C172: 8191101 | D172: 8191101 | E172: OTH | F172: OTH-8191101
A173: 8311101 | B173: Interest Income | C173: 8311101 | E173: OTH | F173: OTH-8311101
A174: 8413101 | B174: Interest expenses - Lease | C174: 8413101 | E174: OTH | F174: OTH-8413101

Sheet Priority
A1: Priority Code | B1: Priority Name | C1: Description
A2: A | B2: Must | C2: If this is not done, the company or our team cannot continue its business.
A3: B | B3: Want to | C3: We want to do it as a team this term. we need it.
A4: C | B4: Challenge | C4: We want to do it for this term or the future. But it doesn't matter if it's not this term.

Sheet Password
A1: Password protect sheet = budget
