Workbook
Name __j102: #REF!
Name __j102: #REF!
Name __j102: #REF!
Name _1: #N/A
Name _j102: #REF!
Name _j102: #REF!
Name _j102: #REF!
Name aa: #REF!
Name aa: #REF!
Name AB: #REF!
Name AB: #REF!
Name ai: #REF!
Name as: #REF!
Name assit: #REF!
Name b: #REF!
Name BC: #REF!
Name BI: #REF!
Name BO: #REF!
Name cc: #REF!
Name CH: #REF!
Name CI: #REF!
Name Ck_for: #REF!
Name Ck_in: #REF!
Name Ck_out: #REF!
Name d: #REF!
Name dd: #REF!
Name DF: #REF!
Name e: #REF!
Name edy: #REF!
Name ee: #REF!
Name eXCRATE: #REF!
Name exrate: #REF!
Name F: #REF!
Name fcb: #REF!
Name FG: #REF!
Name g: #REF!
Name gg: #REF!
Name HF: #REF!
Name kissa: #REF!
Name kissa: #REF!
Name kissakei: #REF!
Name kissakei: #REF!
Name kk: #REF!
Name kk: #REF!
Name kkk: #REF!
Name kkkk: #REF!
Name l: #REF!
Name L_01: #REF!
Name LIA: #REF!
Name LILI: #REF!
Name LINA: #REF!
Name m: #REF!
Name Manufacturing: #REF!
Name MR: #REF!
Name nittk: #REF!
Name nittk_ok: #REF!
Name nittoukei: #REF!
Name PRINT_AREA_MI: #REF!
Name Print_Area_MI: #REF!
Name PRINT_AREA_MI: #REF!

Sheet Data
A1: BUDGET TYPE | B1: Section Code (From) | C1: Section Name (From/Who Prepare) | D1: Section Code (To) | E1: Section Name (To/Who Use The Cost) | F1: COA-ID | G1: COA NAME | H1: DESCRIPTION | I1: GROUP SECTION | J1: GROUP COST | K1: 2023_10 | L1: 2023_11 | M1: 2023_12 | N1: 2024_01 | O1: 2024_02 | P1: 2024_03 | Q1: 2024_04 | R1: 2024_05 | S1: 2024_06 | T1: 2024_07 | U1: 2024_08 | V1: 2024_09 | W1: 2024_10 | X1: 2024_11 | Y1: 2024_12 | Z1: 2025_01 | AA1: 2025_02 | AB1: 2025_03 | AC1: TOTAL FY124 | AD1: TOTAL FY125 | AE1: TOTAL FY126 | AF1: TOTAL FY127 | AG1: Priority Category | AH1: BUDGET NO.
A2: BEL | B2: =_xlfn.IFNA(VLOOKUP(C2,Master!$J:$K,2,0),"") -> B2220 | C2: Human Resource | D2: =_xlfn.IFNA(VLOOKUP(E2,Master!$J:$K,2,0),"") -> B2210 | E2: General Affair | F2: =_xlfn.IFNA(VLOOKUP(G2,Master!B:C,2,0),"") -> 7511103 | G2: Staff Labor - Basic Salary | H2: Basic Salary | I2: =_xlfn.IFNA(VLOOKUP(E2,Master!$J:$M,4,0),"") -> ADM | J2: =_xlfn.IFNA(VLOOKUP($E2,Master!$J:$M,3,0),"") -> SGA | M2: 142400300 | N2: 152369000 | O2: 152369000 | P2: 152369000 | Q2: 154027000 | R2: 145699100 | S2: 145699100 | T2: 137465400 | U2: 137465400 | V2: 137465400 | W2: 138323700 | X2: 138323700 | Y2: 129563600 | Z2: 138633100 | AA2: 138633100 | AB2: 138633100 | AC2: =SUM(K2:P2) -> 599507300 | AD2: =SUM(Q2:AB2) -> 1679931700 | AE2: 1832502900 | AF2: 1652242900 | AG2: A
A3: BEL | B3: =_xlfn.IFNA(VLOOKUP(C3,Master!$J:$K,2,0),"") -> B2220 | C3: Human Resource | D3: =_xlfn.IFNA(VLOOKUP(E3,Master!$J:$K,2,0),"") -> B2220 | E3: Human Resource | F3: =_xlfn.IFNA(VLOOKUP(G3,Master!B:C,2,0),"") -> 7511103 | G3: Staff Labor - Basic Salary | H3: Basic Salary | I3: =_xlfn.IFNA(VLOOKUP(E3,Master!$J:$M,4,0),"") -> ADM | J3: =_xlfn.IFNA(VLOOKUP($E3,Master!$J:$M,3,0),"") -> SGA | M3: 57236200 | N3: 61242900 | O3: 82642900 | P3: 82642900 | Q3: 89490900 | R3: 89490900 | S3: 89490900 | T3: 89490900 | U3: 89490900 | V3: 89490900 | W3: 90281500 | X3: 90281500 | Y3: 90281500 | Z3: 96601300 | AA3: 96601300 | AB3: 96601300 | AC3: =SUM(K3:P3) -> 283764900 | AD3: =SUM(Q3:AB3) -> 1097593800 | AE3: 1179501900 | AF3: 1262067300 | AG3: A
A4: BEL | B4: =_xlfn.IFNA(VLOOKUP(C4,Master!$J:$K,2,0),"") -> B2220 | C4: Human Resource | D4: =_xlfn.IFNA(VLOOKUP(E4,Master!$J:$K,2,0),"") -> B2230 | E4: Health, Safety & Environment | F4: =_xlfn.IFNA(VLOOKUP(G4,Master!B:C,2,0),"") -> 7511103 | G4: Staff Labor - Basic Salary | H4: Basic Salary | I4: =_xlfn.IFNA(VLOOKUP(E4,Master!$J:$M,4,0),"") -> ADM | J4: =_xlfn.IFNA(VLOOKUP($E4,Master!$J:$M,3,0),"") -> SGA | M4: 44992000 | N4: 48141600 | O4: 48141600 | P4: 48141600 | Q4: 48141600 | R4: 48141600 | S4: 48141600 | T4: 48141600 | U4: 48141600 | V4: 48141600 | W4: 48141600 | X4: 48141600 | Y4: 48141600 | Z4: 51511500 | AA4: 51511500 | AB4: 51511500 | AC4: =SUM(K4:P4) -> 189416800 | AD4: =SUM(Q4:AB4) -> 587808900 | AE4: 628955400 | AF4: 685208100 | AG4: A
A5: BEL | B5: =_xlfn.IFNA(VLOOKUP(C5,Master!$J:$K,2,0),"") -> B2220 | C5: Human Resource | D5: =_xlfn.IFNA(VLOOKUP(E5,Master!$J:$K,2,0),"") -> B2300 | E5: Accounting & Finance | F5: =_xlfn.IFNA(VLOOKUP(G5,Master!B:C,2,0),"") -> 7511103 | G5: Staff Labor - Basic Salary | H5: Basic Salary | I5: =_xlfn.IFNA(VLOOKUP(E5,Master!$J:$M,4,0),"") -> ADM | J5: =_xlfn.IFNA(VLOOKUP($E5,Master!$J:$M,3,0),"") -> SGA | M5: 111751000 | N5: 119573700 | O5: 119573700 | P5: 119573700 | Q5: 119573700 | R5: 119573700 | S5: 119573700 | T5: 119573700 | U5: 119573700 | V5: 119573700 | W5: 119573700 | X5: 119573700 | Y5: 119573700 | Z5: 127944100 | AA5: 127944100 | AB5: 127944100 | AC5: =SUM(K5:P5) -> 470472100 | AD5: =SUM(Q5:AB5) -> 1459995600 | AE5: 1651664700 | AF5: 1767280800 | AG5: A
A6: BEL | B6: =_xlfn.IFNA(VLOOKUP(C6,Master!$J:$K,2,0),"") -> B2220 | C6: Human Resource | D6: =_xlfn.IFNA(VLOOKUP(E6,Master!$J:$K,2,0),"") -> B2400 | E6: Information Technology | F6: =_xlfn.IFNA(VLOOKUP(G6,Master!B:C,2,0),"") -> 7511103 | G6: Staff Labor - Basic Salary | H6: Basic Salary | I6: =_xlfn.IFNA(VLOOKUP(E6,Master!$J:$M,4,0),"") -> ADM | J6: =_xlfn.IFNA(VLOOKUP($E6,Master!$J:$M,3,0),"") -> SGA | M6: 48100000 | N6: 51467100 | O6: 51467100 | P6: 51467100 | Q6: 51467100 | R6: 51467100 | S6: 51467100 | T6: 51467100 | U6: 51467100 | V6: 51467100 | W6: 51467100 | X6: 51467100 | Y6: 51467100 | Z6: 55070000 | AA6: 55070000 | AB6: 55070000 | AC6: =SUM(K6:P6) -> 202501300 | AD6: =SUM(Q6:AB6) -> 628413900 | AE6: 672404400 | AF6: 719471400 | AG6: A
A7: BEL | B7: =_xlfn.IFNA(VLOOKUP(C7,Master!$J:$K,2,0),"") -> B2220 | C7: Human Resource | D7: =_xlfn.IFNA(VLOOKUP(E7,Master!$J:$K,2,0),"") -> B3110 | E7: Sales - OEM | F7: =_xlfn.IFNA(VLOOKUP(G7,Master!B:C,2,0),"") -> 7511103 | G7: Staff Labor - Basic Salary | H7: Basic Salary | I7: =_xlfn.IFNA(VLOOKUP(E7,Master!$J:$M,4,0),"") -> ADM | J7: =_xlfn.IFNA(VLOOKUP($E7,Master!$J:$M,3,0),"") -> SGA | M7: 72104100 | N7: 77151600 | O7: 77151600 | P7: 77151600 | Q7: 77968800 | R7: 77968800 | S7: 77968800 | T7: 77968800 | U7: 77968800 | V7: 77968800 | W7: 77968800 | X7: 77968800 | Y7: 77968800 | Z7: 83426800 | AA7: 83426800 | AB7: 83426800 | AC7: =SUM(K7:P7) -> 303558900 | AD7: =SUM(Q7:AB7) -> 951999600 | AE7: 1018641000 | AF7: 1089944700 | AG7: A
A8: BEL | B8: =_xlfn.IFNA(VLOOKUP(C8,Master!$J:$K,2,0),"") -> B2220 | C8: Human Resource | D8: =_xlfn.IFNA(VLOOKUP(E8,Master!$J:$K,2,0),"") -> B3120 | E8: Sales - OES | F8: =_xlfn.IFNA(VLOOKUP(G8,Master!B:C,2,0),"") -> 7511103 | G8: Staff Labor - Basic Salary | H8: Basic Salary | I8: =_xlfn.IFNA(VLOOKUP(E8,Master!$J:$M,4,0),"") -> ADM | J8: =_xlfn.IFNA(VLOOKUP($E8,Master!$J:$M,3,0),"") -> SGA | M8: 10789000 | N8: 11544300 | O8: 11544300 | P8: 11544300 | Q8: 11544300 | R8: 11544300 | S8: 11544300 | T8: 11544300 | U8: 11544300 | V8: 11544300 | W8: 11544300 | X8: 11544300 | Y8: 11544300 | Z8: 12352400 | AA8: 12352400 | AB8: 12352400 | AC8: =SUM(K8:P8) -> 45421900 | AD8: =SUM(Q8:AB8) -> 140955900 | AE8: 150822600 | AF8: 161379600 | AG8: A
A9: BEL | B9: =_xlfn.IFNA(VLOOKUP(C9,Master!$J:$K,2,0),"") -> B2220 | C9: Human Resource | D9: =_xlfn.IFNA(VLOOKUP(E9,Master!$J:$K,2,0),"") -> B3130 | E9: Sales - IAM | F9: =_xlfn.IFNA(VLOOKUP(G9,Master!B:C,2,0),"") -> 7511103 | G9: Staff Labor - Basic Salary | H9: Basic Salary | I9: =_xlfn.IFNA(VLOOKUP(E9,Master!$J:$M,4,0),"") -> ADM | J9: =_xlfn.IFNA(VLOOKUP($E9,Master!$J:$M,3,0),"") -> SGA | M9: 137330000 | N9: 146943600 | O9: 160639600 | P9: 160639600 | Q9: 175187900 | R9: 175187900 | S9: 175187900 | T9: 175187900 | U9: 175187900 | V9: 175187900 | W9: 175187900 | X9: 175187900 | Y9: 175187900 | Z9: 187451300 | AA9: 187451300 | AB9: 187451300 | AC9: =SUM(K9:P9) -> 605552800 | AD9: =SUM(Q9:AB9) -> 2139045000 | AE9: 2288779500 | AF9: 2448990900 | AG9: A
A10: BEL | B10: =_xlfn.IFNA(VLOOKUP(C10,Master!$J:$K,2,0),"") -> B2220 | C10: Human Resource | D10: =_xlfn.IFNA(VLOOKUP(E10,Master!$J:$K,2,0),"") -> B3150 | E10: SCM - FG WH | F10: =_xlfn.IFNA(VLOOKUP(G10,Master!B:C,2,0),"") -> 7511103 | G10: Staff Labor - Basic Salary | H10: Basic Salary | I10: =_xlfn.IFNA(VLOOKUP(E10,Master!$J:$M,4,0),"") -> ADM | J10: =_xlfn.IFNA(VLOOKUP($E10,Master!$J:$M,3,0),"") -> SGA | M10: 118432000 | N10: 115895200 | O10: 115895200 | P10: 115895200 | Q10: 117330200 | R10: 117330200 | S10: 117330200 | T10: 117330200 | U10: 117330200 | V10: 117330200 | W10: 118003300 | X10: 118003300 | Y10: 118003300 | Z10: 126263700 | AA10: 126263700 | AB10: 126263700 | AC10: =SUM(K10:P10) -> 466117600 | AD10: =SUM(Q10:AB10) -> 1436782200 | AE10: 1546165500 | AF10: 1659033900 | AG10: A
A11: BEL | B11: =_xlfn.IFNA(VLOOKUP(C11,Master!$J:$K,2,0),"") -> B2220 | C11: Human Resource | D11: =_xlfn.IFNA(VLOOKUP(E11,Master!$J:$K,2,0),"") -> B3160 | E11: Marketing | F11: =_xlfn.IFNA(VLOOKUP(G11,Master!B:C,2,0),"") -> 7511103 | G11: Staff Labor - Basic Salary | H11: Basic Salary | I11: =_xlfn.IFNA(VLOOKUP(E11,Master!$J:$M,4,0),"") -> ADM | J11: =_xlfn.IFNA(VLOOKUP($E11,Master!$J:$M,3,0),"") -> SGA | M11: 71196000 | N11: 76179800 | O11: 76179800 | P11: 76179800 | Q11: 76179800 | R11: 76179800 | S11: 76179800 | T11: 76179800 | U11: 76179800 | V11: 76179800 | W11: 76179800 | X11: 76179800 | Y11: 76179800 | Z11: 81512500 | AA11: 81512500 | AB11: 81512500 | AC11: =SUM(K11:P11) -> 299735400 | AD11: =SUM(Q11:AB11) -> 930155700 | AE11: 995268000 | AF11: 1064937600 | AG11: A
A12: BEL | B12: =_xlfn.IFNA(VLOOKUP(C12,Master!$J:$K,2,0),"") -> B2220 | C12: Human Resource | D12: =_xlfn.IFNA(VLOOKUP(E12,Master!$J:$K,2,0),"") -> B4101 | E12: SP PD- CF | F12: =_xlfn.IFNA(VLOOKUP(G12,Master!B:C,2,0),"") -> 7511103 | G12: Staff Labor - Basic Salary | H12: Basic Salary | I12: =_xlfn.IFNA(VLOOKUP(E12,Master!$J:$M,4,0),"") -> DIR | J12: =_xlfn.IFNA(VLOOKUP($E12,Master!$J:$M,3,0),"") -> MFG | M12: 47547000 | N12: 50875600 | O12: 50875600 | P12: 50875600 | Q12: 50875600 | R12: 50875600 | S12: 50875600 | T12: 50875600 | U12: 50875600 | V12: 50875600 | W12: 50875600 | X12: 50875600 | Y12: 50875600 | Z12: 54436800 | AA12: 54436800 | AB12: 54436800 | AC12: =SUM(K12:P12) -> 200173800 | AD12: =SUM(Q12:AB12) -> 621190800 | AE12: 664673400 | AF12: 622194500 | AG12: A
A13: BEL | B13: =_xlfn.IFNA(VLOOKUP(C13,Master!$J:$K,2,0),"") -> B2220 | C13: Human Resource | D13: =_xlfn.IFNA(VLOOKUP(E13,Master!$J:$K,2,0),"") -> B4102 | E13: SP PD- CM | F13: =_xlfn.IFNA(VLOOKUP(G13,Master!B:C,2,0),"") -> 7511103 | G13: Staff Labor - Basic Salary | H13: Basic Salary | I13: =_xlfn.IFNA(VLOOKUP(E13,Master!$J:$M,4,0),"") -> DIR | J13: =_xlfn.IFNA(VLOOKUP($E13,Master!$J:$M,3,0),"") -> MFG | M13: 117001000 | N13: 125191700 | O13: 125191700 | P13: 125191700 | Q13: 114178100 | R13: 114178100 | S13: 114178100 | T13: 114178100 | U13: 114178100 | V13: 114178100 | W13: 120794000 | X13: 120794000 | Y13: 120794000 | Z13: 129249800 | AA13: 129249800 | AB13: 129249800 | AC13: =SUM(K13:P13) -> 492576100 | AD13: =SUM(Q13:AB13) -> 1435200000 | AE13: 1551677100 | AF13: 1457714700 | AG13: A
... A19: BEL | B19: =_xlfn.IFNA(VLOOKUP(C19,Master!$J:$K,2,0),"") -> B2220 | C19: Human Resource | D19: =_xlfn.IFNA(VLOOKUP(E19,Master!$J:$K,2,0),"") -> B4120 | E19: SP PD- Final Inspection | F19: =_xlfn.IFNA(VLOOKUP(G19,Master!B:C,2,0),"") -> 7511103 | G19: Staff Labor - Basic Salary | H19: Basic Salary | I19: =_xlfn.IFNA(VLOOKUP(E19,Master!$J:$M,4,0),"") -> DIR | J19: =_xlfn.IFNA(VLOOKUP($E19,Master!$J:$M,3,0),"") -> MFG | M19: 234388000 | N19: 250796500 | O19: 239044600 | P19: 239044600 | Q19: 235385400 | R19: 223902100 | S19: 223902100 | T19: 200604900 | U19: 200604900 | V19: 200604900 | W19: 214868100 | X19: 214868100 | Y19: 214868100 | Z19: 229908800 | AA19: 229908800 | AB19: 229908800 | AC19: =SUM(K19:P19) -> 963273700 | AD19: =SUM(Q19:AB19) -> 2619335000 | AE19: 2529357100 | AF19: 2663080200 | AG19: A
A20: BEL | B20: =_xlfn.IFNA(VLOOKUP(C20,Master!$J:$K,2,0),"") -> B2220 | C20: Human Resource | D20: =_xlfn.IFNA(VLOOKUP(E20,Master!$J:$K,2,0),"") -> B4121 | E20: SP PD- QC - OEM | F20: =_xlfn.IFNA(VLOOKUP(G20,Master!B:C,2,0),"") -> 7511103 | G20: Staff Labor - Basic Salary | H20: Basic Salary | I20: =_xlfn.IFNA(VLOOKUP(E20,Master!$J:$M,4,0),"") -> DIR | J20: =_xlfn.IFNA(VLOOKUP($E20,Master!$J:$M,3,0),"") -> MFG | M20: 19971000 | N20: 21369200 | O20: 21369200 | P20: 21369200 | AC20: =SUM(K20:P20) -> 84078600 | AD20: =SUM(Q20:AB20) -> 0 | AG20: A
A21: BEL | B21: =_xlfn.IFNA(VLOOKUP(C21,Master!$J:$K,2,0),"") -> B2220 | C21: Human Resource | D21: =_xlfn.IFNA(VLOOKUP(E21,Master!$J:$K,2,0),"") -> B4130 | E21: SP PD- Insulator Sealing | F21: =_xlfn.IFNA(VLOOKUP(G21,Master!B:C,2,0),"") -> 7511103 | G21: Staff Labor - Basic Salary | H21: Basic Salary | I21: =_xlfn.IFNA(VLOOKUP(E21,Master!$J:$M,4,0),"") -> DIR | J21: =_xlfn.IFNA(VLOOKUP($E21,Master!$J:$M,3,0),"") -> MFG | M21: 49572000 | N21: 53042300 | O21: 53042300 | P21: 53042300 | Q21: 53042300 | R21: 53042300 | S21: 53042300 | T21: 53042300 | U21: 53042300 | V21: 53042300 | W21: 53042300 | X21: 53042300 | Y21: 53042300 | Z21: 56755300 | AA21: 56755300 | AB21: 56755300 | AC21: =SUM(K21:P21) -> 208698900 | AD21: =SUM(Q21:AB21) -> 647646600 | AE21: 616097600 | AF21: 602174100 | AG21: A
A22: BEL | B22: =_xlfn.IFNA(VLOOKUP(C22,Master!$J:$K,2,0),"") -> B2220 | C22: Human Resource | D22: =_xlfn.IFNA(VLOOKUP(E22,Master!$J:$K,2,0),"") -> B4410 | E22: PC PD- Injection | F22: =_xlfn.IFNA(VLOOKUP(G22,Master!B:C,2,0),"") -> 7511103 | G22: Staff Labor - Basic Salary | H22: Basic Salary | I22: =_xlfn.IFNA(VLOOKUP(E22,Master!$J:$M,4,0),"") -> DIR | J22: =_xlfn.IFNA(VLOOKUP($E22,Master!$J:$M,3,0),"") -> MFG | M22: 22297000 | N22: 23857900 | O22: 23857900 | P22: 23857900 | Q22: 23857900 | R22: 23857900 | S22: 23857900 | T22: 23857900 | U22: 23857900 | V22: 23857900 | W22: 23857900 | X22: 23857900 | Y22: 23857900 | AC22: =SUM(K22:P22) -> 93870700 | AD22: =SUM(Q22:AB22) -> 214721100 | AG22: A
A23: BEL | B23: =_xlfn.IFNA(VLOOKUP(C23,Master!$J:$K,2,0),"") -> B2220 | C23: Human Resource | D23: =_xlfn.IFNA(VLOOKUP(E23,Master!$J:$K,2,0),"") -> B4430 | E23: PC PD- Assy | F23: =_xlfn.IFNA(VLOOKUP(G23,Master!B:C,2,0),"") -> 7511103 | G23: Staff Labor - Basic Salary | H23: Basic Salary | I23: =_xlfn.IFNA(VLOOKUP(E23,Master!$J:$M,4,0),"") -> DIR | J23: =_xlfn.IFNA(VLOOKUP($E23,Master!$J:$M,3,0),"") -> MFG | M23: 38090000 | N23: 40756600 | O23: 40756600 | P23: 40756600 | Q23: 40756600 | R23: 40756600 | S23: 40756600 | T23: 40756600 | U23: 40756600 | V23: 40756600 | W23: 40756600 | X23: 40756600 | Y23: 40756600 | AC23: =SUM(K23:P23) -> 160359800 | AD23: =SUM(Q23:AB23) -> 366809400 | AG23: A
A24: BEL | B24: =_xlfn.IFNA(VLOOKUP(C24,Master!$J:$K,2,0),"") -> B2220 | C24: Human Resource | D24: =_xlfn.IFNA(VLOOKUP(E24,Master!$J:$K,2,0),"") -> B4440 | E24: PC PD- QC | F24: =_xlfn.IFNA(VLOOKUP(G24,Master!B:C,2,0),"") -> 7511103 | G24: Staff Labor - Basic Salary | H24: Basic Salary | I24: =_xlfn.IFNA(VLOOKUP(E24,Master!$J:$M,4,0),"") -> DIR | J24: =_xlfn.IFNA(VLOOKUP($E24,Master!$J:$M,3,0),"") -> MFG | M24: 41955000 | N24: 44892100 | O24: 32647000 | P24: 32647000 | Q24: 32647000 | R24: 32647000 | S24: 32647000 | T24: 32647000 | U24: 32647000 | V24: 32647000 | W24: 32647000 | X24: 32647000 | Y24: 21749000 | AC24: =SUM(K24:P24) -> 152141100 | AD24: =SUM(Q24:AB24) -> 282925000 | AG24: A
A25: BEL | B25: =_xlfn.IFNA(VLOOKUP(C25,Master!$J:$K,2,0),"") -> B2220 | C25: Human Resource | D25: =_xlfn.IFNA(VLOOKUP(E25,Master!$J:$K,2,0),"") -> B5100 | E25: Production Office | F25: =_xlfn.IFNA(VLOOKUP(G25,Master!B:C,2,0),"") -> 7511103 | G25: Staff Labor - Basic Salary | H25: Basic Salary | I25: =_xlfn.IFNA(VLOOKUP(E25,Master!$J:$M,4,0),"") -> IND | J25: =_xlfn.IFNA(VLOOKUP($E25,Master!$J:$M,3,0),"") -> MFG | M25: 115903000 | N25: 124016400 | O25: 124016400 | P25: 124016400 | Q25: 124016400 | R25: 124016400 | S25: 124016400 | T25: 124016400 | U25: 124016400 | V25: 124016400 | W25: 124016400 | X25: 124016400 | Y25: 124016400 | Z25: 132697500 | AA25: 132697500 | AB25: 132697500 | AC25: =SUM(K25:P25) -> 487952200 | AD25: =SUM(Q25:AB25) -> 1514240100 | AE25: 1620236700 | AF25: 1733653800 | AG25: A
A26: BEL | B26: =_xlfn.IFNA(VLOOKUP(C26,Master!$J:$K,2,0),"") -> B2220 | C26: Human Resource | D26: =_xlfn.IFNA(VLOOKUP(E26,Master!$J:$K,2,0),"") -> B5101 | E26: Production Office (SP) | F26: =_xlfn.IFNA(VLOOKUP(G26,Master!B:C,2,0),"") -> 7511103 | G26: Staff Labor - Basic Salary | H26: Basic Salary | I26: =_xlfn.IFNA(VLOOKUP(E26,Master!$J:$M,4,0),"") -> IND | J26: =_xlfn.IFNA(VLOOKUP($E26,Master!$J:$M,3,0),"") -> MFG | M26: 57936000 | N26: 61991800 | O26: 61991800 | P26: 61991800 | Q26: 60924900 | R26: 60924900 | S26: 60924900 | T26: 60924900 | U26: 60924900 | V26: 60924900 | W26: 61593400 | X26: 61593400 | Y26: 61593400 | Z26: 65904900 | AA26: 65904900 | AB26: 65904900 | AC26: =SUM(K26:P26) -> 243911400 | AD26: =SUM(Q26:AB26) -> 748044300 | AE26: 858662400 | AF26: 974557500 | AG26: A
A27: BEL | B27: =_xlfn.IFNA(VLOOKUP(C27,Master!$J:$K,2,0),"") -> B2220 | C27: Human Resource | D27: =_xlfn.IFNA(VLOOKUP(E27,Master!$J:$K,2,0),"") -> B5130 | E27: Supply Procurement | F27: =_xlfn.IFNA(VLOOKUP(G27,Master!B:C,2,0),"") -> 7511103 | G27: Staff Labor - Basic Salary | H27: Basic Salary | I27: =_xlfn.IFNA(VLOOKUP(E27,Master!$J:$M,4,0),"") -> IND | J27: =_xlfn.IFNA(VLOOKUP($E27,Master!$J:$M,3,0),"") -> MFG | M27: 128750000 | N27: 137763200 | O27: 137763200 | P27: 137763200 | Q27: 137763200 | R27: 137763200 | S27: 137763200 | T27: 137763200 | U27: 137763200 | V27: 137763200 | W27: 137763200 | X27: 137763200 | Y27: 137763200 | Z27: 136608700 | AA27: 136608700 | AB27: 136608700 | AC27: =SUM(K27:P27) -> 542039600 | AD27: =SUM(Q27:AB27) -> 1649694900 | AE27: 1636794300 | AF27: 1657776000 | AG27: A
A28: BEL | B28: =_xlfn.IFNA(VLOOKUP(C28,Master!$J:$K,2,0),"") -> B2220 | C28: Human Resource | D28: =_xlfn.IFNA(VLOOKUP(E28,Master!$J:$K,2,0),"") -> B5200 | E28: Inventory Control | F28: =_xlfn.IFNA(VLOOKUP(G28,Master!B:C,2,0),"") -> 7511103 | G28: Staff Labor - Basic Salary | H28: Basic Salary | I28: =_xlfn.IFNA(VLOOKUP(E28,Master!$J:$M,4,0),"") -> IND | J28: =_xlfn.IFNA(VLOOKUP($E28,Master!$J:$M,3,0),"") -> MFG | M28: 19722000 | N28: 21102700 | O28: 21102700 | P28: 21102700 | Q28: 21813400 | R28: 21813400 | S28: 21813400 | T28: 21813400 | U28: 21813400 | V28: 21813400 | W28: 21813400 | X28: 21813400 | Y28: 21813400 | Z28: 23340300 | AA28: 23340300 | AB28: 23340300 | AC28: =SUM(K28:P28) -> 83030100 | AD28: =SUM(Q28:AB28) -> 266341500 | AE28: 284985300 | AF28: 304935000 | AG28: A
A29: BEL | B29: =_xlfn.IFNA(VLOOKUP(C29,Master!$J:$K,2,0),"") -> B2220 | C29: Human Resource | D29: =_xlfn.IFNA(VLOOKUP(E29,Master!$J:$K,2,0),"") -> B5500 | E29: Maintenance | F29: =_xlfn.IFNA(VLOOKUP(G29,Master!B:C,2,0),"") -> 7511103 | G29: Staff Labor - Basic Salary | H29: Basic Salary | I29: =_xlfn.IFNA(VLOOKUP(E29,Master!$J:$M,4,0),"") -> IND | J29: =_xlfn.IFNA(VLOOKUP($E29,Master!$J:$M,3,0),"") -> MFG | M29: 79461600 | N29: 90267300 | O29: 90267300 | P29: 90267300 | Q29: 118732000 | R29: 118732000 | S29: 118732000 | T29: 118732000 | U29: 118732000 | V29: 118732000 | W29: 125819700 | X29: 125819700 | Y29: 125819700 | Z29: 134627500 | AA29: 134627500 | AB29: 134627500 | AC29: =SUM(K29:P29) -> 350263500 | AD29: =SUM(Q29:AB29) -> 1493733600 | AE29: 1608081300 | AF29: 1669928400 | AG29: A
A30: BEL | B30: =_xlfn.IFNA(VLOOKUP(C30,Master!$J:$K,2,0),"") -> B2220 | C30: Human Resource | D30: =_xlfn.IFNA(VLOOKUP(E30,Master!$J:$K,2,0),"") -> B5600 | E30: Production Engineering | F30: =_xlfn.IFNA(VLOOKUP(G30,Master!B:C,2,0),"") -> 7511103 | G30: Staff Labor - Basic Salary | H30: Basic Salary | I30: =_xlfn.IFNA(VLOOKUP(E30,Master!$J:$M,4,0),"") -> IND | J30: =_xlfn.IFNA(VLOOKUP($E30,Master!$J:$M,3,0),"") -> MFG | M30: 102763000 | N30: 109957000 | O30: 109957000 | P30: 109957000 | Q30: 111382100 | R30: 111382100 | S30: 111382100 | T30: 111382100 | U30: 111382100 | V30: 111382100 | W30: 111382100 | X30: 111382100 | Y30: 111382100 | Z30: 119178600 | AA30: 119178600 | AB30: 119178600 | AC30: =SUM(K30:P30) -> 432634000 | AD30: =SUM(Q30:AB30) -> 1359974700 | AE30: 1474053000 | AF30: 1600005600 | AG30: A
A31: BEL | B31: =_xlfn.IFNA(VLOOKUP(C31,Master!$J:$K,2,0),"") -> B2220 | C31: Human Resource | D31: =_xlfn.IFNA(VLOOKUP(E31,Master!$J:$K,2,0),"") -> B5710 | E31: WH Dept.- KD & RM | F31: =_xlfn.IFNA(VLOOKUP(G31,Master!B:C,2,0),"") -> 7511103 | G31: Staff Labor - Basic Salary | H31: Basic Salary | I31: =_xlfn.IFNA(VLOOKUP(E31,Master!$J:$M,4,0),"") -> IND | J31: =_xlfn.IFNA(VLOOKUP($E31,Master!$J:$M,3,0),"") -> MFG | M31: 49886000 | N31: 53378300 | O31: 53378300 | P31: 53378300 | Q31: 53378300 | R31: 53378300 | S31: 53378300 | T31: 53378300 | U31: 53378300 | V31: 53378300 | W31: 53378300 | X31: 53378300 | Y31: 53378300 | Z31: 67912400 | AA31: 67912400 | AB31: 67912400 | AC31: =SUM(K31:P31) -> 210020900 | AD31: =SUM(Q31:AB31) -> 684141900 | AE31: 726411300 | AF31: 741431400 | AG31: A
A32: BEL | B32: =_xlfn.IFNA(VLOOKUP(C32,Master!$J:$K,2,0),"") -> B2220 | C32: Human Resource | D32: =_xlfn.IFNA(VLOOKUP(E32,Master!$J:$K,2,0),"") -> B5800 | E32: Quality Assurance | F32: =_xlfn.IFNA(VLOOKUP(G32,Master!B:C,2,0),"") -> 7511103 | G32: Staff Labor - Basic Salary | H32: Basic Salary | I32: =_xlfn.IFNA(VLOOKUP(E32,Master!$J:$M,4,0),"") -> IND | J32: =_xlfn.IFNA(VLOOKUP($E32,Master!$J:$M,3,0),"") -> MFG | M32: 105115000 | N32: 112473300 | O32: 112473300 | P32: 112473300 | Q32: 113186800 | R32: 113186800 | S32: 113186800 | T32: 113186800 | U32: 113186800 | V32: 113186800 | W32: 113186800 | X32: 113186800 | Y32: 113186800 | Z32: 121110100 | AA32: 121110100 | AB32: 121110100 | AC32: =SUM(K32:P32) -> 442534900 | AD32: =SUM(Q32:AB32) -> 1382011500 | AE32: 1478754300 | AF32: 1461641600 | AG32: A
A33: BEL | B33: =_xlfn.IFNA(VLOOKUP(C33,Master!$J:$K,2,0),"") -> B2220 | C33: Human Resource | D33: =_xlfn.IFNA(VLOOKUP(E33,Master!$J:$K,2,0),"") -> B5900 | E33: Quality Control | F33: =_xlfn.IFNA(VLOOKUP(G33,Master!B:C,2,0),"") -> 7511103 | G33: Staff Labor - Basic Salary | H33: Basic Salary | I33: =_xlfn.IFNA(VLOOKUP(E33,Master!$J:$M,4,0),"") -> IND | J33: =_xlfn.IFNA(VLOOKUP($E33,Master!$J:$M,3,0),"") -> MFG | M33: 97042000 | N33: 103835500 | O33: 103835500 | P33: 103835500 | Q33: 103835500 | R33: 103835500 | S33: 103835500 | T33: 103835500 | U33: 103835500 | V33: 103835500 | W33: 103835500 | X33: 103835500 | Y33: 103835500 | Z33: 111104000 | AA33: 111104000 | AB33: 111104000 | AC33: =SUM(K33:P33) -> 408548500 | AD33: =SUM(Q33:AB33) -> 1267831500 | AE33: 1370765700 | AF33: 1343855100 | AG33: A
A34: BEL | B34: =_xlfn.IFNA(VLOOKUP(C34,Master!$J:$K,2,0),"") -> B2220 | C34: Human Resource | D34: =_xlfn.IFNA(VLOOKUP(E34,Master!$J:$K,2,0),"") -> B2210 | E34: General Affair | F34: =_xlfn.IFNA(VLOOKUP(G34,Master!B:C,2,0),"") -> 7511111 | G34: Staff Labor - Allowance | H34: ATM Allowance | I34: =_xlfn.IFNA(VLOOKUP(E34,Master!$J:$M,4,0),"") -> ADM | J34: =_xlfn.IFNA(VLOOKUP($E34,Master!$J:$M,3,0),"") -> SGA | M34: 76500 | N34: 76500 | O34: 76500 | P34: 76500 | Q34: 76500 | R34: 72000 | S34: 72000 | T34: 67500 | U34: 67500 | V34: 67500 | W34: 67500 | X34: 67500 | Y34: 63000 | Z34: 63000 | AA34: 63000 | AB34: 63000 | AC34: =SUM(K34:P34) -> 306000 | AD34: =SUM(Q34:AB34) -> 810000 | AE34: 810000 | AF34: 697500 | AG34: A
A35: BEL | B35: =_xlfn.IFNA(VLOOKUP(C35,Master!$J:$K,2,0),"") -> B2220 | C35: Human Resource | D35: =_xlfn.IFNA(VLOOKUP(E35,Master!$J:$K,2,0),"") -> B2210 | E35: General Affair | F35: =_xlfn.IFNA(VLOOKUP(G35,Master!B:C,2,0),"") -> 7511111 | G35: Staff Labor - Allowance | H35: Daily Transportation Allowance | I35: =_xlfn.IFNA(VLOOKUP(E35,Master!$J:$M,4,0),"") -> ADM | J35: =_xlfn.IFNA(VLOOKUP($E35,Master!$J:$M,3,0),"") -> SGA | M35: 7875200 | N35: 9162400 | O35: 8457600 | P35: 7400400 | Q35: 6343200 | R35: 7337000 | S35: 7003500 | T35: 7865000 | U35: 7550400 | V35: 6921200 | W35: 7865000 | X35: 7235800 | Y35: 6505400 | Z35: 7437600 | AA35: 6817800 | AB35: 5888100 | AC35: =SUM(K35:P35) -> 32895600 | AD35: =SUM(Q35:AB35) -> 84770000 | AE35: 85818400 | AF35: 74372100 | AG35: A
A36: BEL | B36: =_xlfn.IFNA(VLOOKUP(C36,Master!$J:$K,2,0),"") -> B2220 | C36: Human Resource | D36: =_xlfn.IFNA(VLOOKUP(E36,Master!$J:$K,2,0),"") -> B2210 | E36: General Affair | F36: =_xlfn.IFNA(VLOOKUP(G36,Master!B:C,2,0),"") -> 7511111 | G36: Staff Labor - Allowance | H36: Job Allowance | I36: =_xlfn.IFNA(VLOOKUP(E36,Master!$J:$M,4,0),"") -> ADM | J36: =_xlfn.IFNA(VLOOKUP($E36,Master!$J:$M,3,0),"") -> SGA | M36: 1550000 | N36: 1550000 | O36: 1550000 | P36: 1550000 | Q36: 1550000 | R36: 1550000 | S36: 1550000 | T36: 1550000 | U36: 1550000 | V36: 1550000 | W36: 1550000 | X36: 1550000 | Y36: 1550000 | Z36: 2950000 | AA36: 2950000 | AB36: 2950000 | AC36: =SUM(K36:P36) -> 6200000 | AD36: =SUM(Q36:AB36) -> 22800000 | AE36: 41400000 | AF36: 33900000 | AG36: A
A37: BEL | B37: =_xlfn.IFNA(VLOOKUP(C37,Master!$J:$K,2,0),"") -> B2220 | C37: Human Resource | D37: =_xlfn.IFNA(VLOOKUP(E37,Master!$J:$K,2,0),"") -> B2210 | E37: General Affair | F37: =_xlfn.IFNA(VLOOKUP(G37,Master!B:C,2,0),"") -> 7511111 | G37: Staff Labor - Allowance | H37: Meals Allowance | I37: =_xlfn.IFNA(VLOOKUP(E37,Master!$J:$M,4,0),"") -> ADM | J37: =_xlfn.IFNA(VLOOKUP($E37,Master!$J:$M,3,0),"") -> SGA | P37: 3128000 | Q37: 1564000 | AB37: 4032000 | AC37: =SUM(K37:P37) -> 3128000 | AD37: =SUM(Q37:AB37) -> 5596000 | AE37: 4500000 | AF37: 3432000 | AG37: A
A38: BEL | B38: =_xlfn.IFNA(VLOOKUP(C38,Master!$J:$K,2,0),"") -> B2220 | C38: Human Resource | D38: =_xlfn.IFNA(VLOOKUP(E38,Master!$J:$K,2,0),"") -> B2210 | E38: General Affair | F38: =_xlfn.IFNA(VLOOKUP(G38,Master!B:C,2,0),"") -> 7511111 | G38: Staff Labor - Allowance | H38: Medical Allowance | I38: =_xlfn.IFNA(VLOOKUP(E38,Master!$J:$M,4,0),"") -> ADM | J38: =_xlfn.IFNA(VLOOKUP($E38,Master!$J:$M,3,0),"") -> SGA | M38: 1000000 | N38: 1000000 | O38: 1000000 | P38: 1000000 | Q38: 1000000 | R38: 940000 | S38: 940000 | T38: 880000 | U38: 880000 | V38: 880000 | W38: 880000 | X38: 880000 | Y38: 820000 | Z38: 820000 | AA38: 820000 | AB38: 820000 | AC38: =SUM(K38:P38) -> 4000000 | AD38: =SUM(Q38:AB38) -> 10560000 | AE38: 10560000 | AF38: 9060000 | AG38: A
A39: BEL | B39: =_xlfn.IFNA(VLOOKUP(C39,Master!$J:$K,2,0),"") -> B2220 | C39: Human Resource | D39: =_xlfn.IFNA(VLOOKUP(E39,Master!$J:$K,2,0),"") -> B2210 | E39: General Affair | F39: =_xlfn.IFNA(VLOOKUP(G39,Master!B:C,2,0),"") -> 7511111 | G39: Staff Labor - Allowance | H39: Transportation (fixed) Allowance | I39: =_xlfn.IFNA(VLOOKUP(E39,Master!$J:$M,4,0),"") -> ADM | J39: =_xlfn.IFNA(VLOOKUP($E39,Master!$J:$M,3,0),"") -> SGA | M39: 5100000 | N39: 5100000 | O39: 5100000 | P39: 5100000 | Q39: 5100000 | R39: 4800000 | S39: 4800000 | T39: 4500000 | U39: 4500000 | V39: 4500000 | W39: 4500000 | X39: 4500000 | Y39: 4200000 | Z39: 4200000 | AA39: 4200000 | AB39: 4200000 | AC39: =SUM(K39:P39) -> 20400000 | AD39: =SUM(Q39:AB39) -> 54000000 | AE39: 54000000 | AF39: 46500000 | AG39: A
A40: BEL | B40: =_xlfn.IFNA(VLOOKUP(C40,Master!$J:$K,2,0),"") -> B2220 | C40: Human Resource | D40: =_xlfn.IFNA(VLOOKUP(E40,Master!$J:$K,2,0),"") -> B2220 | E40: Human Resource | F40: =_xlfn.IFNA(VLOOKUP(G40,Master!B:C,2,0),"") -> 7511111 | G40: Staff Labor - Allowance | H40: ATM Allowance | I40: =_xlfn.IFNA(VLOOKUP(E40,Master!$J:$M,4,0),"") -> ADM | J40: =_xlfn.IFNA(VLOOKUP($E40,Master!$J:$M,3,0),"") -> SGA | M40: 22500 | N40: 22500 | O40: 27000 | P40: 27000 | Q40: 31500 | R40: 31500 | S40: 31500 | T40: 31500 | U40: 31500 | V40: 31500 | W40: 31500 | X40: 31500 | Y40: 31500 | Z40: 31500 | AA40: 31500 | AB40: 31500 | AC40: =SUM(K40:P40) -> 99000 | AD40: =SUM(Q40:AB40) -> 378000 | AE40: 378000 | AF40: 378000 | AG40: A
A41: BEL | B41: =_xlfn.IFNA(VLOOKUP(C41,Master!$J:$K,2,0),"") -> B2220 | C41: Human Resource | D41: =_xlfn.IFNA(VLOOKUP(E41,Master!$J:$K,2,0),"") -> B2220 | E41: Human Resource | F41: =_xlfn.IFNA(VLOOKUP(G41,Master!B:C,2,0),"") -> 7511111 | G41: Staff Labor - Allowance | H41: Daily Transportation Allowance | I41: =_xlfn.IFNA(VLOOKUP(E41,Master!$J:$M,4,0),"") -> ADM | J41: =_xlfn.IFNA(VLOOKUP($E41,Master!$J:$M,3,0),"") -> SGA | M41: 12720650 | N41: 13010300 | O41: 16317200 | P41: 16027550 | Q41: 18696000 | R41: 19184000 | S41: 19062000 | T41: 19550000 | U41: 19428000 | V41: 19184000 | W41: 19550000 | X41: 19306000 | Y41: 19184000 | Z41: 19428000 | AA41: 19184000 | AB41: 18818000 | AC41: =SUM(K41:P41) -> 58075700 | AD41: =SUM(Q41:AB41) -> 230574000 | AE41: 231153000 | AF41: 233700000 | AG41: A
A42: BEL | B42: =_xlfn.IFNA(VLOOKUP(C42,Master!$J:$K,2,0),"") -> B2220 | C42: Human Resource | D42: =_xlfn.IFNA(VLOOKUP(E42,Master!$J:$K,2,0),"") -> B2220 | E42: Human Resource | F42: =_xlfn.IFNA(VLOOKUP(G42,Master!B:C,2,0),"") -> 7511111 | G42: Staff Labor - Allowance | H42: Job Allowance | I42: =_xlfn.IFNA(VLOOKUP(E42,Master!$J:$M,4,0),"") -> ADM | J42: =_xlfn.IFNA(VLOOKUP($E42,Master!$J:$M,3,0),"") -> SGA | M42: 4250000 | N42: 4250000 | O42: 5750000 | P42: 5750000 | Q42: 5750000 | R42: 5750000 | S42: 5750000 | T42: 5750000 | U42: 5750000 | V42: 5750000 | W42: 5750000 | X42: 5750000 | Y42: 5750000 | Z42: 7600000 | AA42: 7600000 | AB42: 7600000 | AC42: =SUM(K42:P42) -> 20000000 | AD42: =SUM(Q42:AB42) -> 74550000 | AE42: 91200000 | AF42: 91200000 | AG42: A
A43: BEL | B43: =_xlfn.IFNA(VLOOKUP(C43,Master!$J:$K,2,0),"") -> B2220 | C43: Human Resource | D43: =_xlfn.IFNA(VLOOKUP(E43,Master!$J:$K,2,0),"") -> B2220 | E43: Human Resource | F43: =_xlfn.IFNA(VLOOKUP(G43,Master!B:C,2,0),"") -> 7511111 | G43: Staff Labor - Allowance | H43: Meals Allowance | I43: =_xlfn.IFNA(VLOOKUP(E43,Master!$J:$M,4,0),"") -> ADM | J43: =_xlfn.IFNA(VLOOKUP($E43,Master!$J:$M,3,0),"") -> SGA | P43: 1104000 | Q43: 644000 | AB43: 2016000 | AC43: =SUM(K43:P43) -> 1104000 | AD43: =SUM(Q43:AB43) -> 2660000 | AE43: 2100000 | AF43: 2184000 | AG43: A
A44: BEL | B44: =_xlfn.IFNA(VLOOKUP(C44,Master!$J:$K,2,0),"") -> B2220 | C44: Human Resource | D44: =_xlfn.IFNA(VLOOKUP(E44,Master!$J:$K,2,0),"") -> B2220 | E44: Human Resource | F44: =_xlfn.IFNA(VLOOKUP(G44,Master!B:C,2,0),"") -> 7511111 | G44: Staff Labor - Allowance | H44: Medical Allowance | I44: =_xlfn.IFNA(VLOOKUP(E44,Master!$J:$M,4,0),"") -> ADM | J44: =_xlfn.IFNA(VLOOKUP($E44,Master!$J:$M,3,0),"") -> SGA | M44: 160000 | N44: 160000 | O44: 160000 | P44: 160000 | Q44: 220000 | R44: 220000 | S44: 220000 | T44: 220000 | U44: 220000 | V44: 220000 | W44: 220000 | X44: 220000 | Y44: 220000 | Z44: 220000 | AA44: 220000 | AB44: 220000 | AC44: =SUM(K44:P44) -> 640000 | AD44: =SUM(Q44:AB44) -> 2640000 | AE44: 2640000 | AF44: 2640000 | AG44: A
A45: BEL | B45: =_xlfn.IFNA(VLOOKUP(C45,Master!$J:$K,2,0),"") -> B2220 | C45: Human Resource | D45: =_xlfn.IFNA(VLOOKUP(E45,Master!$J:$K,2,0),"") -> B2220 | E45: Human Resource | F45: =_xlfn.IFNA(VLOOKUP(G45,Master!B:C,2,0),"") -> 7511111 | G45: Staff Labor - Allowance | H45: Transportation (fixed) Allowance | I45: =_xlfn.IFNA(VLOOKUP(E45,Master!$J:$M,4,0),"") -> ADM | J45: =_xlfn.IFNA(VLOOKUP($E45,Master!$J:$M,3,0),"") -> SGA | M45: 1200000 | N45: 1200000 | O45: 3200000 | P45: 3200000 | Q45: 3500000 | R45: 3500000 | S45: 3500000 | T45: 3500000 | U45: 3500000 | V45: 3500000 | W45: 3500000 | X45: 3500000 | Y45: 3500000 | Z45: 3500000 | AA45: 3500000 | AB45: 3500000 | AC45: =SUM(K45:P45) -> 8800000 | AD45: =SUM(Q45:AB45) -> 42000000 | AE45: 42000000 | AF45: 42000000 | AG45: A
A46: BEL | B46: =_xlfn.IFNA(VLOOKUP(C46,Master!$J:$K,2,0),"") -> B2220 | C46: Human Resource | D46: =_xlfn.IFNA(VLOOKUP(E46,Master!$J:$K,2,0),"") -> B2230 | E46: Health, Safety & Environment | F46: =_xlfn.IFNA(VLOOKUP(G46,Master!B:C,2,0),"") -> 7511111 | G46: Staff Labor - Allowance | H46: ATM Allowance | I46: =_xlfn.IFNA(VLOOKUP(E46,Master!$J:$M,4,0),"") -> ADM | J46: =_xlfn.IFNA(VLOOKUP($E46,Master!$J:$M,3,0),"") -> SGA | M46: 18000 | N46: 18000 | O46: 18000 | P46: 18000 | Q46: 18000 | R46: 18000 | S46: 18000 | T46: 18000 | U46: 18000 | V46: 18000 | W46: 18000 | X46: 18000 | Y46: 18000 | Z46: 18000 | AA46: 18000 | AB46: 18000 | AC46: =SUM(K46:P46) -> 72000 | AD46: =SUM(Q46:AB46) -> 216000 | AE46: 216000 | AF46: 216000 | AG46: A
A47: BEL | B47: =_xlfn.IFNA(VLOOKUP(C47,Master!$J:$K,2,0),"") -> B2220 | C47: Human Resource | D47: =_xlfn.IFNA(VLOOKUP(E47,Master!$J:$K,2,0),"") -> B2230 | E47: Health, Safety & Environment | F47: =_xlfn.IFNA(VLOOKUP(G47,Master!B:C,2,0),"") -> 7511111 | G47: Staff Labor - Allowance | H47: Daily Transportation Allowance | I47: =_xlfn.IFNA(VLOOKUP(E47,Master!$J:$M,4,0),"") -> ADM | J47: =_xlfn.IFNA(VLOOKUP($E47,Master!$J:$M,3,0),"") -> SGA | M47: 4800650 | N47: 4970300 | O47: 4857200 | P47: 4687550 | Q47: 7080000 | R47: 7320000 | S47: 7260000 | T47: 7500000 | U47: 7440000 | V47: 7320000 | W47: 7500000 | X47: 7380000 | Y47: 7320000 | Z47: 7440000 | AA47: 7320000 | AB47: 7140000 | AC47: =SUM(K47:P47) -> 19315700 | AD47: =SUM(Q47:AB47) -> 88020000 | AE47: 88191000 | AF47: 89595000 | AG47: A
A48: BEL | B48: =_xlfn.IFNA(VLOOKUP(C48,Master!$J:$K,2,0),"") -> B2220 | C48: Human Resource | D48: =_xlfn.IFNA(VLOOKUP(E48,Master!$J:$K,2,0),"") -> B2230 | E48: Health, Safety & Environment | F48: =_xlfn.IFNA(VLOOKUP(G48,Master!B:C,2,0),"") -> 7511111 | G48: Staff Labor - Allowance | H48: Job Allowance | I48: =_xlfn.IFNA(VLOOKUP(E48,Master!$J:$M,4,0),"") -> ADM | J48: =_xlfn.IFNA(VLOOKUP($E48,Master!$J:$M,3,0),"") -> SGA | M48: 1800000 | N48: 1800000 | O48: 1800000 | P48: 1800000 | Q48: 1800000 | R48: 1800000 | S48: 1800000 | T48: 1800000 | U48: 1800000 | V48: 1800000 | W48: 1800000 | X48: 1800000 | Y48: 1800000 | Z48: 3150000 | AA48: 3150000 | AB48: 3150000 | AC48: =SUM(K48:P48) -> 7200000 | AD48: =SUM(Q48:AB48) -> 25650000 | AE48: 37800000 | AF48: 39000000 | AG48: A
A49: BEL | B49: =_xlfn.IFNA(VLOOKUP(C49,Master!$J:$K,2,0),"") -> B2220 | C49: Human Resource | D49: =_xlfn.IFNA(VLOOKUP(E49,Master!$J:$K,2,0),"") -> B2230 | E49: Health, Safety & Environment | F49: =_xlfn.IFNA(VLOOKUP(G49,Master!B:C,2,0),"") -> 7511111 | G49: Staff Labor - Allowance | H49: Meals Allowance | I49: =_xlfn.IFNA(VLOOKUP(E49,Master!$J:$M,4,0),"") -> ADM | J49: =_xlfn.IFNA(VLOOKUP($E49,Master!$J:$M,3,0),"") -> SGA | P49: 736000 | Q49: 368000 | AB49: 1152000 | AC49: =SUM(K49:P49) -> 736000 | AD49: =SUM(Q49:AB49) -> 1520000 | AE49: 1200000 | AF49: 1248000 | AG49: A
A50: BEL | B50: =_xlfn.IFNA(VLOOKUP(C50,Master!$J:$K,2,0),"") -> B2220 | C50: Human Resource | D50: =_xlfn.IFNA(VLOOKUP(E50,Master!$J:$K,2,0),"") -> B2230 | E50: Health, Safety & Environment | F50: =_xlfn.IFNA(VLOOKUP(G50,Master!B:C,2,0),"") -> 7511111 | G50: Staff Labor - Allowance | H50: Medical Allowance | I50: =_xlfn.IFNA(VLOOKUP(E50,Master!$J:$M,4,0),"") -> ADM | J50: =_xlfn.IFNA(VLOOKUP($E50,Master!$J:$M,3,0),"") -> SGA | M50: 160000 | N50: 160000 | O50: 160000 | P50: 160000 | Q50: 160000 | R50: 160000 | S50: 160000 | T50: 160000 | U50: 160000 | V50: 160000 | W50: 160000 | X50: 160000 | Y50: 160000 | Z50: 160000 | AA50: 160000 | AB50: 160000 | AC50: =SUM(K50:P50) -> 640000 | AD50: =SUM(Q50:AB50) -> 1920000 | AE50: 1920000 | AF50: 1920000 | AG50: A
A51: BEL | B51: =_xlfn.IFNA(VLOOKUP(C51,Master!$J:$K,2,0),"") -> B2220 | C51: Human Resource | D51: =_xlfn.IFNA(VLOOKUP(E51,Master!$J:$K,2,0),"") -> B2230 | E51: Health, Safety & Environment | F51: =_xlfn.IFNA(VLOOKUP(G51,Master!B:C,2,0),"") -> 7511111 | G51: Staff Labor - Allowance | H51: Transportation (fixed) Allowance | I51: =_xlfn.IFNA(VLOOKUP(E51,Master!$J:$M,4,0),"") -> ADM | J51: =_xlfn.IFNA(VLOOKUP($E51,Master!$J:$M,3,0),"") -> SGA | M51: 900000 | N51: 900000 | O51: 900000 | P51: 900000 | Q51: 900000 | R51: 900000 | S51: 900000 | T51: 900000 | U51: 900000 | V51: 900000 | W51: 900000 | X51: 900000 | Y51: 900000 | Z51: 900000 | AA51: 900000 | AB51: 900000 | AC51: =SUM(K51:P51) -> 3600000 | AD51: =SUM(Q51:AB51) -> 10800000 | AE51: 10800000 | AF51: 10800000 | AG51: A
A52: BEL | B52: =_xlfn.IFNA(VLOOKUP(C52,Master!$J:$K,2,0),"") -> B2220 | C52: Human Resource | D52: =_xlfn.IFNA(VLOOKUP(E52,Master!$J:$K,2,0),"") -> B2300 | E52: Accounting & Finance | F52: =_xlfn.IFNA(VLOOKUP(G52,Master!B:C,2,0),"") -> 7511111 | G52: Staff Labor - Allowance | H52: ATM Allowance | I52: =_xlfn.IFNA(VLOOKUP(E52,Master!$J:$M,4,0),"") -> ADM | J52: =_xlfn.IFNA(VLOOKUP($E52,Master!$J:$M,3,0),"") -> SGA | M52: 36000 | N52: 36000 | O52: 36000 | P52: 36000 | Q52: 36000 | R52: 36000 | S52: 36000 | T52: 36000 | U52: 36000 | V52: 36000 | W52: 36000 | X52: 36000 | Y52: 36000 | Z52: 36000 | AA52: 36000 | AB52: 36000 | AC52: =SUM(K52:P52) -> 144000 | AD52: =SUM(Q52:AB52) -> 432000 | AE52: 486000 | AF52: 486000 | AG52: A
A53: BEL | B53: =_xlfn.IFNA(VLOOKUP(C53,Master!$J:$K,2,0),"") -> B2220 | C53: Human Resource | D53: =_xlfn.IFNA(VLOOKUP(E53,Master!$J:$K,2,0),"") -> B2300 | E53: Accounting & Finance | F53: =_xlfn.IFNA(VLOOKUP(G53,Master!B:C,2,0),"") -> 7511111 | G53: Staff Labor - Allowance | H53: Daily Transportation Allowance | I53: =_xlfn.IFNA(VLOOKUP(E53,Master!$J:$M,4,0),"") -> ADM | J53: =_xlfn.IFNA(VLOOKUP($E53,Master!$J:$M,3,0),"") -> SGA | M53: 15507750 | N53: 16030500 | O53: 15682000 | P53: 15159250 | Q53: 15312000 | R53: 16048000 | S53: 15864000 | T53: 16600000 | U53: 16416000 | V53: 16048000 | W53: 16600000 | X53: 16232000 | Y53: 16048000 | Z53: 16416000 | AA53: 16048000 | AB53: 15496000 | AC53: =SUM(K53:P53) -> 62379500 | AD53: =SUM(Q53:AB53) -> 193128000 | AE53: 199512000 | AF53: 203670000 | AG53: A
A54: BEL | B54: =_xlfn.IFNA(VLOOKUP(C54,Master!$J:$K,2,0),"") -> B2220 | C54: Human Resource | D54: =_xlfn.IFNA(VLOOKUP(E54,Master!$J:$K,2,0),"") -> B2300 | E54: Accounting & Finance | F54: =_xlfn.IFNA(VLOOKUP(G54,Master!B:C,2,0),"") -> 7511111 | G54: Staff Labor - Allowance | H54: Job Allowance | I54: =_xlfn.IFNA(VLOOKUP(E54,Master!$J:$M,4,0),"") -> ADM | J54: =_xlfn.IFNA(VLOOKUP($E54,Master!$J:$M,3,0),"") -> SGA | M54: 8400000 | N54: 8400000 | O54: 8400000 | P54: 8400000 | Q54: 8400000 | R54: 8400000 | S54: 8400000 | T54: 8400000 | U54: 8400000 | V54: 8400000 | W54: 8400000 | X54: 8400000 | Y54: 8400000 | Z54: 10450000 | AA54: 10450000 | AB54: 10450000 | AC54: =SUM(K54:P54) -> 33600000 | AD54: =SUM(Q54:AB54) -> 106950000 | AE54: 128400000 | AF54: 128400000 | AG54: A
A55: BEL | B55: =_xlfn.IFNA(VLOOKUP(C55,Master!$J:$K,2,0),"") -> B2220 | C55: Human Resource | D55: =_xlfn.IFNA(VLOOKUP(E55,Master!$J:$K,2,0),"") -> B2300 | E55: Accounting & Finance | F55: =_xlfn.IFNA(VLOOKUP(G55,Master!B:C,2,0),"") -> 7511111 | G55: Staff Labor - Allowance | H55: Meals Allowance | I55: =_xlfn.IFNA(VLOOKUP(E55,Master!$J:$M,4,0),"") -> ADM | J55: =_xlfn.IFNA(VLOOKUP($E55,Master!$J:$M,3,0),"") -> SGA | P55: 1472000 | Q55: 736000 | AB55: 2304000 | AC55: =SUM(K55:P55) -> 1472000 | AD55: =SUM(Q55:AB55) -> 3040000 | AE55: 2700000 | AF55: 2808000 | AG55: A
A56: BEL | B56: =_xlfn.IFNA(VLOOKUP(C56,Master!$J:$K,2,0),"") -> B2220 | C56: Human Resource | D56: =_xlfn.IFNA(VLOOKUP(E56,Master!$J:$K,2,0),"") -> B2300 | E56: Accounting & Finance | F56: =_xlfn.IFNA(VLOOKUP(G56,Master!B:C,2,0),"") -> 7511111 | G56: Staff Labor - Allowance | H56: Medical Allowance | I56: =_xlfn.IFNA(VLOOKUP(E56,Master!$J:$M,4,0),"") -> ADM | J56: =_xlfn.IFNA(VLOOKUP($E56,Master!$J:$M,3,0),"") -> SGA | M56: 340000 | N56: 340000 | O56: 340000 | P56: 340000 | Q56: 340000 | R56: 340000 | S56: 340000 | T56: 340000 | U56: 340000 | V56: 340000 | W56: 340000 | X56: 340000 | Y56: 340000 | Z56: 340000 | AA56: 340000 | AB56: 340000 | AC56: =SUM(K56:P56) -> 1360000 | AD56: =SUM(Q56:AB56) -> 4080000 | AE56: 4800000 | AF56: 4800000 | AG56: A
A57: BEL | B57: =_xlfn.IFNA(VLOOKUP(C57,Master!$J:$K,2,0),"") -> B2220 | C57: Human Resource | D57: =_xlfn.IFNA(VLOOKUP(E57,Master!$J:$K,2,0),"") -> B2300 | E57: Accounting & Finance | F57: =_xlfn.IFNA(VLOOKUP(G57,Master!B:C,2,0),"") -> 7511111 | G57: Staff Labor - Allowance | H57: Skill Allowance | I57: =_xlfn.IFNA(VLOOKUP(E57,Master!$J:$M,4,0),"") -> ADM | J57: =_xlfn.IFNA(VLOOKUP($E57,Master!$J:$M,3,0),"") -> SGA | M57: 4500000 | N57: 4500000 | O57: 4500000 | P57: 4500000 | Q57: 4500000 | R57: 4500000 | S57: 4500000 | T57: 4500000 | U57: 4500000 | V57: 4500000 | W57: 4500000 | X57: 4500000 | Y57: 4500000 | Z57: 4500000 | AA57: 4500000 | AB57: 4500000 | AC57: =SUM(K57:P57) -> 18000000 | AD57: =SUM(Q57:AB57) -> 54000000 | AE57: 54000000 | AF57: 54000000 | AG57: A
A58: BEL | B58: =_xlfn.IFNA(VLOOKUP(C58,Master!$J:$K,2,0),"") -> B2220 | C58: Human Resource | D58: =_xlfn.IFNA(VLOOKUP(E58,Master!$J:$K,2,0),"") -> B2300 | E58: Accounting & Finance | F58: =_xlfn.IFNA(VLOOKUP(G58,Master!B:C,2,0),"") -> 7511111 | G58: Staff Labor - Allowance | H58: Transportation (fixed) Allowance | I58: =_xlfn.IFNA(VLOOKUP(E58,Master!$J:$M,4,0),"") -> ADM | J58: =_xlfn.IFNA(VLOOKUP($E58,Master!$J:$M,3,0),"") -> SGA | M58: 2100000 | N58: 2100000 | O58: 2100000 | P58: 2100000 | Q58: 2100000 | R58: 2100000 | S58: 2100000 | T58: 2100000 | U58: 2100000 | V58: 2100000 | W58: 2100000 | X58: 2100000 | Y58: 2100000 | Z58: 2100000 | AA58: 2100000 | AB58: 2100000 | AC58: =SUM(K58:P58) -> 8400000 | AD58: =SUM(Q58:AB58) -> 25200000 | AE58: 28800000 | AF58: 28800000 | AG58: A
A59: BEL | B59: =_xlfn.IFNA(VLOOKUP(C59,Master!$J:$K,2,0),"") -> B2220 | C59: Human Resource | D59: =_xlfn.IFNA(VLOOKUP(E59,Master!$J:$K,2,0),"") -> B2400 | E59: Information Technology | F59: =_xlfn.IFNA(VLOOKUP(G59,Master!B:C,2,0),"") -> 7511111 | G59: Staff Labor - Allowance | H59: ATM Allowance | I59: =_xlfn.IFNA(VLOOKUP(E59,Master!$J:$M,4,0),"") -> ADM | J59: =_xlfn.IFNA(VLOOKUP($E59,Master!$J:$M,3,0),"") -> SGA | M59: 18000 | N59: 18000 | O59: 18000 | P59: 18000 | Q59: 18000 | R59: 18000 | S59: 18000 | T59: 18000 | U59: 18000 | V59: 18000 | W59: 18000 | X59: 18000 | Y59: 18000 | Z59: 18000 | AA59: 18000 | AB59: 18000 | AC59: =SUM(K59:P59) -> 72000 | AD59: =SUM(Q59:AB59) -> 216000 | AE59: 216000 | AF59: 216000 | AG59: A
A60: BEL | B60: =_xlfn.IFNA(VLOOKUP(C60,Master!$J:$K,2,0),"") -> B2220 | C60: Human Resource | D60: =_xlfn.IFNA(VLOOKUP(E60,Master!$J:$K,2,0),"") -> B2400 | E60: Information Technology | F60: =_xlfn.IFNA(VLOOKUP(G60,Master!B:C,2,0),"") -> 7511111 | G60: Staff Labor - Allowance | H60: Daily Transportation Allowance | I60: =_xlfn.IFNA(VLOOKUP(E60,Master!$J:$M,4,0),"") -> ADM | J60: =_xlfn.IFNA(VLOOKUP($E60,Master!$J:$M,3,0),"") -> SGA | M60: 5287100 | N60: 5520200 | O60: 5364800 | P60: 5131700 | Q60: 7476000 | R60: 7804000 | S60: 7722000 | T60: 8050000 | U60: 7968000 | V60: 7804000 | W60: 8050000 | X60: 7886000 | Y60: 7804000 | Z60: 7968000 | AA60: 7804000 | AB60: 7558000 | AC60: =SUM(K60:P60) -> 21303800 | AD60: =SUM(Q60:AB60) -> 93894000 | AE60: 94359000 | AF60: 95970000 | AG60: A
A61: BEL | B61: =_xlfn.IFNA(VLOOKUP(C61,Master!$J:$K,2,0),"") -> B2220 | C61: Human Resource | D61: =_xlfn.IFNA(VLOOKUP(E61,Master!$J:$K,2,0),"") -> B2400 | E61: Information Technology | F61: =_xlfn.IFNA(VLOOKUP(G61,Master!B:C,2,0),"") -> 7511111 | G61: Staff Labor - Allowance | H61: Job Allowance | I61: =_xlfn.IFNA(VLOOKUP(E61,Master!$J:$M,4,0),"") -> ADM | J61: =_xlfn.IFNA(VLOOKUP($E61,Master!$J:$M,3,0),"") -> SGA | M61: 3050000 | N61: 3050000 | O61: 3050000 | P61: 3050000 | Q61: 3050000 | R61: 3050000 | S61: 3050000 | T61: 3050000 | U61: 3050000 | V61: 3050000 | W61: 3050000 | X61: 3050000 | Y61: 3050000 | Z61: 4400000 | AA61: 4400000 | AB61: 4400000 | AC61: =SUM(K61:P61) -> 12200000 | AD61: =SUM(Q61:AB61) -> 40650000 | AE61: 52800000 | AF61: 52800000 | AG61: A
A62: BEL | B62: =_xlfn.IFNA(VLOOKUP(C62,Master!$J:$K,2,0),"") -> B2220 | C62: Human Resource | D62: =_xlfn.IFNA(VLOOKUP(E62,Master!$J:$K,2,0),"") -> B2400 | E62: Information Technology | F62: =_xlfn.IFNA(VLOOKUP(G62,Master!B:C,2,0),"") -> 7511111 | G62: Staff Labor - Allowance | H62: Meals Allowance | I62: =_xlfn.IFNA(VLOOKUP(E62,Master!$J:$M,4,0),"") -> ADM | J62: =_xlfn.IFNA(VLOOKUP($E62,Master!$J:$M,3,0),"") -> SGA | P62: 736000 | Q62: 368000 | AB62: 1152000 | AC62: =SUM(K62:P62) -> 736000 | AD62: =SUM(Q62:AB62) -> 1520000 | AE62: 1200000 | AF62: 1248000 | AG62: A
A63: BEL | B63: =_xlfn.IFNA(VLOOKUP(C63,Master!$J:$K,2,0),"") -> B2220 | C63: Human Resource | D63: =_xlfn.IFNA(VLOOKUP(E63,Master!$J:$K,2,0),"") -> B2400 | E63: Information Technology | F63: =_xlfn.IFNA(VLOOKUP(G63,Master!B:C,2,0),"") -> 7511111 | G63: Staff Labor - Allowance | H63: Medical Allowance | I63: =_xlfn.IFNA(VLOOKUP(E63,Master!$J:$M,4,0),"") -> ADM | J63: =_xlfn.IFNA(VLOOKUP($E63,Master!$J:$M,3,0),"") -> SGA | M63: 180000 | N63: 180000 | O63: 180000 | P63: 180000 | Q63: 180000 | R63: 180000 | S63: 180000 | T63: 180000 | U63: 180000 | V63: 180000 | W63: 180000 | X63: 180000 | Y63: 180000 | Z63: 180000 | AA63: 180000 | AB63: 180000 | AC63: =SUM(K63:P63) -> 720000 | AD63: =SUM(Q63:AB63) -> 2160000 | AE63: 2160000 | AF63: 2160000 | AG63: A
A64: BEL | B64: =_xlfn.IFNA(VLOOKUP(C64,Master!$J:$K,2,0),"") -> B2220 | C64: Human Resource | D64: =_xlfn.IFNA(VLOOKUP(E64,Master!$J:$K,2,0),"") -> B2400 | E64: Information Technology | F64: =_xlfn.IFNA(VLOOKUP(G64,Master!B:C,2,0),"") -> 7511111 | G64: Staff Labor - Allowance | H64: Transportation (fixed) Allowance | I64: =_xlfn.IFNA(VLOOKUP(E64,Master!$J:$M,4,0),"") -> ADM | J64: =_xlfn.IFNA(VLOOKUP($E64,Master!$J:$M,3,0),"") -> SGA | M64: 900000 | N64: 900000 | O64: 900000 | P64: 900000 | Q64: 900000 | R64: 900000 | S64: 900000 | T64: 900000 | U64: 900000 | V64: 900000 | W64: 900000 | X64: 900000 | Y64: 900000 | Z64: 900000 | AA64: 900000 | AB64: 900000 | AC64: =SUM(K64:P64) -> 3600000 | AD64: =SUM(Q64:AB64) -> 10800000 | AE64: 10800000 | AF64: 10800000 | AG64: A
A65: BEL | B65: =_xlfn.IFNA(VLOOKUP(C65,Master!$J:$K,2,0),"") -> B2220 | C65: Human Resource | D65: =_xlfn.IFNA(VLOOKUP(E65,Master!$J:$K,2,0),"") -> B3110 | E65: Sales - OEM | F65: =_xlfn.IFNA(VLOOKUP(G65,Master!B:C,2,0),"") -> 7511111 | G65: Staff Labor - Allowance | H65: ATM Allowance | I65: =_xlfn.IFNA(VLOOKUP(E65,Master!$J:$M,4,0),"") -> ADM | J65: =_xlfn.IFNA(VLOOKUP($E65,Master!$J:$M,3,0),"") -> SGA | M65: 31500 | N65: 31500 | O65: 31500 | P65: 31500 | Q65: 31500 | R65: 31500 | S65: 31500 | T65: 31500 | U65: 31500 | V65: 31500 | W65: 31500 | X65: 31500 | Y65: 31500 | Z65: 31500 | AA65: 31500 | AB65: 31500 | AC65: =SUM(K65:P65) -> 126000 | AD65: =SUM(Q65:AB65) -> 378000 | AE65: 378000 | AF65: 378000 | AG65: A
A66: BEL | B66: =_xlfn.IFNA(VLOOKUP(C66,Master!$J:$K,2,0),"") -> B2220 | C66: Human Resource | D66: =_xlfn.IFNA(VLOOKUP(E66,Master!$J:$K,2,0),"") -> B3110 | E66: Sales - OEM | F66: =_xlfn.IFNA(VLOOKUP(G66,Master!B:C,2,0),"") -> 7511111 | G66: Staff Labor - Allowance | H66: Daily Transportation Allowance | I66: =_xlfn.IFNA(VLOOKUP(E66,Master!$J:$M,4,0),"") -> ADM | J66: =_xlfn.IFNA(VLOOKUP($E66,Master!$J:$M,3,0),"") -> SGA | M66: 6587750 | N66: 6990500 | O66: 6722000 | P66: 6319250 | Q66: 8556000 | R66: 9124000 | S66: 8982000 | T66: 9550000 | U66: 9408000 | V66: 9124000 | W66: 9550000 | X66: 9266000 | Y66: 9124000 | Z66: 9408000 | AA66: 9124000 | AB66: 8698000 | AC66: =SUM(K66:P66) -> 26619500 | AD66: =SUM(Q66:AB66) -> 109914000 | AE66: 110550000 | AF66: 113565000 | AG66: A
A67: BEL | B67: =_xlfn.IFNA(VLOOKUP(C67,Master!$J:$K,2,0),"") -> B2220 | C67: Human Resource | D67: =_xlfn.IFNA(VLOOKUP(E67,Master!$J:$K,2,0),"") -> B3110 | E67: Sales - OEM | F67: =_xlfn.IFNA(VLOOKUP(G67,Master!B:C,2,0),"") -> 7511111 | G67: Staff Labor - Allowance | H67: Job Allowance | I67: =_xlfn.IFNA(VLOOKUP(E67,Master!$J:$M,4,0),"") -> ADM | J67: =_xlfn.IFNA(VLOOKUP($E67,Master!$J:$M,3,0),"") -> SGA | M67: 3000000 | N67: 3000000 | O67: 3000000 | P67: 3000000 | Q67: 3000000 | R67: 3000000 | S67: 3000000 | T67: 3000000 | U67: 3000000 | V67: 3000000 | W67: 3000000 | X67: 3000000 | Y67: 3000000 | Z67: 5300000 | AA67: 5300000 | AB67: 5300000 | AC67: =SUM(K67:P67) -> 12000000 | AD67: =SUM(Q67:AB67) -> 42900000 | AE67: 63600000 | AF67: 63600000 | AG67: A
A68: BEL | B68: =_xlfn.IFNA(VLOOKUP(C68,Master!$J:$K,2,0),"") -> B2220 | C68: Human Resource | D68: =_xlfn.IFNA(VLOOKUP(E68,Master!$J:$K,2,0),"") -> B3110 | E68: Sales - OEM | F68: =_xlfn.IFNA(VLOOKUP(G68,Master!B:C,2,0),"") -> 7511111 | G68: Staff Labor - Allowance | H68: Meals Allowance | I68: =_xlfn.IFNA(VLOOKUP(E68,Master!$J:$M,4,0),"") -> ADM | J68: =_xlfn.IFNA(VLOOKUP($E68,Master!$J:$M,3,0),"") -> SGA | P68: 1288000 | Q68: 644000 | AB68: 2016000 | AC68: =SUM(K68:P68) -> 1288000 | AD68: =SUM(Q68:AB68) -> 2660000 | AE68: 2100000 | AF68: 2184000 | AG68: A
A69: BEL | B69: =_xlfn.IFNA(VLOOKUP(C69,Master!$J:$K,2,0),"") -> B2220 | C69: Human Resource | D69: =_xlfn.IFNA(VLOOKUP(E69,Master!$J:$K,2,0),"") -> B3110 | E69: Sales - OEM | F69: =_xlfn.IFNA(VLOOKUP(G69,Master!B:C,2,0),"") -> 7511111 | G69: Staff Labor - Allowance | H69: Medical Allowance | I69: =_xlfn.IFNA(VLOOKUP(E69,Master!$J:$M,4,0),"") -> ADM | J69: =_xlfn.IFNA(VLOOKUP($E69,Master!$J:$M,3,0),"") -> SGA | M69: 280000 | N69: 280000 | O69: 280000 | P69: 280000 | Q69: 280000 | R69: 280000 | S69: 280000 | T69: 280000 | U69: 280000 | V69: 280000 | W69: 280000 | X69: 280000 | Y69: 280000 | Z69: 280000 | AA69: 280000 | AB69: 280000 | AC69: =SUM(K69:P69) -> 1120000 | AD69: =SUM(Q69:AB69) -> 3360000 | AE69: 3360000 | AF69: 3360000 | AG69: A
A70: BEL | B70: =_xlfn.IFNA(VLOOKUP(C70,Master!$J:$K,2,0),"") -> B2220 | C70: Human Resource | D70: =_xlfn.IFNA(VLOOKUP(E70,Master!$J:$K,2,0),"") -> B3110 | E70: Sales - OEM | F70: =_xlfn.IFNA(VLOOKUP(G70,Master!B:C,2,0),"") -> 7511111 | G70: Staff Labor - Allowance | H70: Transportation (fixed) Allowance | I70: =_xlfn.IFNA(VLOOKUP(E70,Master!$J:$M,4,0),"") -> ADM | J70: =_xlfn.IFNA(VLOOKUP($E70,Master!$J:$M,3,0),"") -> SGA | M70: 1800000 | N70: 1800000 | O70: 1800000 | P70: 1800000 | Q70: 1800000 | R70: 1800000 | S70: 1800000 | T70: 1800000 | U70: 1800000 | V70: 1800000 | W70: 1800000 | X70: 1800000 | Y70: 1800000 | Z70: 1800000 | AA70: 1800000 | AB70: 1800000 | AC70: =SUM(K70:P70) -> 7200000 | AD70: =SUM(Q70:AB70) -> 21600000 | AE70: 21600000 | AF70: 21600000 | AG70: A
A71: BEL | B71: =_xlfn.IFNA(VLOOKUP(C71,Master!$J:$K,2,0),"") -> B2220 | C71: Human Resource | D71: =_xlfn.IFNA(VLOOKUP(E71,Master!$J:$K,2,0),"") -> B3120 | E71: Sales - OES | F71: =_xlfn.IFNA(VLOOKUP(G71,Master!B:C,2,0),"") -> 7511111 | G71: Staff Labor - Allowance | H71: ATM Allowance | I71: =_xlfn.IFNA(VLOOKUP(E71,Master!$J:$M,4,0),"") -> ADM | J71: =_xlfn.IFNA(VLOOKUP($E71,Master!$J:$M,3,0),"") -> SGA | M71: 4500 | N71: 4500 | O71: 4500 | P71: 4500 | Q71: 4500 | R71: 4500 | S71: 4500 | T71: 4500 | U71: 4500 | V71: 4500 | W71: 4500 | X71: 4500 | Y71: 4500 | Z71: 4500 | AA71: 4500 | AB71: 4500 | AC71: =SUM(K71:P71) -> 18000 | AD71: =SUM(Q71:AB71) -> 54000 | AE71: 54000 | AF71: 54000 | AG71: A
A72: BEL | B72: =_xlfn.IFNA(VLOOKUP(C72,Master!$J:$K,2,0),"") -> B2220 | C72: Human Resource | D72: =_xlfn.IFNA(VLOOKUP(E72,Master!$J:$K,2,0),"") -> B3120 | E72: Sales - OES | F72: =_xlfn.IFNA(VLOOKUP(G72,Master!B:C,2,0),"") -> 7511111 | G72: Staff Labor - Allowance | H72: Daily Transportation Allowance | I72: =_xlfn.IFNA(VLOOKUP(E72,Master!$J:$M,4,0),"") -> ADM | J72: =_xlfn.IFNA(VLOOKUP($E72,Master!$J:$M,3,0),"") -> SGA | M72: 434700 | N72: 491400 | O72: 453600 | P72: 396900 | Q72: 340200 | R72: 415800 | S72: 396900 | T72: 472500 | U72: 453600 | V72: 415800 | W72: 472500 | X72: 434700 | Y72: 415800 | Z72: 475200 | AA72: 435600 | AB72: 376200 | AC72: =SUM(K72:P72) -> 1776600 | AD72: =SUM(Q72:AB72) -> 5104800 | AE72: 5153600 | AF72: 5373300 | AG72: A
A73: BEL | B73: =_xlfn.IFNA(VLOOKUP(C73,Master!$J:$K,2,0),"") -> B2220 | C73: Human Resource | D73: =_xlfn.IFNA(VLOOKUP(E73,Master!$J:$K,2,0),"") -> B3120 | E73: Sales - OES | F73: =_xlfn.IFNA(VLOOKUP(G73,Master!B:C,2,0),"") -> 7511111 | G73: Staff Labor - Allowance | H73: Job Allowance | I73: =_xlfn.IFNA(VLOOKUP(E73,Master!$J:$M,4,0),"") -> ADM | J73: =_xlfn.IFNA(VLOOKUP($E73,Master!$J:$M,3,0),"") -> SGA | M73: 150000 | N73: 150000 | O73: 150000 | P73: 150000 | Q73: 150000 | R73: 150000 | S73: 150000 | T73: 150000 | U73: 150000 | V73: 150000 | W73: 150000 | X73: 150000 | Y73: 150000 | Z73: 500000 | AA73: 500000 | AB73: 500000 | AC73: =SUM(K73:P73) -> 600000 | AD73: =SUM(Q73:AB73) -> 2850000 | AE73: 6000000 | AF73: 6000000 | AG73: A
A74: BEL | B74: =_xlfn.IFNA(VLOOKUP(C74,Master!$J:$K,2,0),"") -> B2220 | C74: Human Resource | D74: =_xlfn.IFNA(VLOOKUP(E74,Master!$J:$K,2,0),"") -> B3120 | E74: Sales - OES | F74: =_xlfn.IFNA(VLOOKUP(G74,Master!B:C,2,0),"") -> 7511111 | G74: Staff Labor - Allowance | H74: Meals Allowance | I74: =_xlfn.IFNA(VLOOKUP(E74,Master!$J:$M,4,0),"") -> ADM | J74: =_xlfn.IFNA(VLOOKUP($E74,Master!$J:$M,3,0),"") -> SGA | P74: 184000 | Q74: 92000 | AB74: 288000 | AC74: =SUM(K74:P74) -> 184000 | AD74: =SUM(Q74:AB74) -> 380000 | AE74: 300000 | AF74: 312000 | AG74: A
A75: BEL | B75: =_xlfn.IFNA(VLOOKUP(C75,Master!$J:$K,2,0),"") -> B2220 | C75: Human Resource | D75: =_xlfn.IFNA(VLOOKUP(E75,Master!$J:$K,2,0),"") -> B3120 | E75: Sales - OES | F75: =_xlfn.IFNA(VLOOKUP(G75,Master!B:C,2,0),"") -> 7511111 | G75: Staff Labor - Allowance | H75: Medical Allowance | I75: =_xlfn.IFNA(VLOOKUP(E75,Master!$J:$M,4,0),"") -> ADM | J75: =_xlfn.IFNA(VLOOKUP($E75,Master!$J:$M,3,0),"") -> SGA | M75: 60000 | N75: 60000 | O75: 60000 | P75: 60000 | Q75: 60000 | R75: 60000 | S75: 60000 | T75: 60000 | U75: 60000 | V75: 60000 | W75: 60000 | X75: 60000 | Y75: 60000 | Z75: 60000 | AA75: 60000 | AB75: 60000 | AC75: =SUM(K75:P75) -> 240000 | AD75: =SUM(Q75:AB75) -> 720000 | AE75: 720000 | AF75: 720000 | AG75: A
A76: BEL | B76: =_xlfn.IFNA(VLOOKUP(C76,Master!$J:$K,2,0),"") -> B2220 | C76: Human Resource | D76: =_xlfn.IFNA(VLOOKUP(E76,Master!$J:$K,2,0),"") -> B3120 | E76: Sales - OES | F76: =_xlfn.IFNA(VLOOKUP(G76,Master!B:C,2,0),"") -> 7511111 | G76: Staff Labor - Allowance | H76: Transportation (fixed) Allowance | I76: =_xlfn.IFNA(VLOOKUP(E76,Master!$J:$M,4,0),"") -> ADM | J76: =_xlfn.IFNA(VLOOKUP($E76,Master!$J:$M,3,0),"") -> SGA | M76: 300000 | N76: 300000 | O76: 300000 | P76: 300000 | Q76: 300000 | R76: 300000 | S76: 300000 | T76: 300000 | U76: 300000 | V76: 300000 | W76: 300000 | X76: 300000 | Y76: 300000 | Z76: 300000 | AA76: 300000 | AB76: 300000 | AC76: =SUM(K76:P76) -> 1200000 | AD76: =SUM(Q76:AB76) -> 3600000 | AE76: 3600000 | AF76: 3600000 | AG76: A
A77: BEL | B77: =_xlfn.IFNA(VLOOKUP(C77,Master!$J:$K,2,0),"") -> B2220 | C77: Human Resource | D77: =_xlfn.IFNA(VLOOKUP(E77,Master!$J:$K,2,0),"") -> B3130 | E77: Sales - IAM | F77: =_xlfn.IFNA(VLOOKUP(G77,Master!B:C,2,0),"") -> 7511111 | G77: Staff Labor - Allowance | H77: ATM Allowance | I77: =_xlfn.IFNA(VLOOKUP(E77,Master!$J:$M,4,0),"") -> ADM | J77: =_xlfn.IFNA(VLOOKUP($E77,Master!$J:$M,3,0),"") -> SGA | M77: 45000 | N77: 45000 | O77: 54000 | P77: 54000 | Q77: 63000 | R77: 63000 | S77: 63000 | T77: 63000 | U77: 63000 | V77: 63000 | W77: 63000 | X77: 63000 | Y77: 63000 | Z77: 63000 | AA77: 63000 | AB77: 63000 | AC77: =SUM(K77:P77) -> 198000 | AD77: =SUM(Q77:AB77) -> 756000 | AE77: 756000 | AF77: 756000 | AG77: A
A78: BEL | B78: =_xlfn.IFNA(VLOOKUP(C78,Master!$J:$K,2,0),"") -> B2220 | C78: Human Resource | D78: =_xlfn.IFNA(VLOOKUP(E78,Master!$J:$K,2,0),"") -> B3130 | E78: Sales - IAM | F78: =_xlfn.IFNA(VLOOKUP(G78,Master!B:C,2,0),"") -> 7511111 | G78: Staff Labor - Allowance | H78: Daily Transportation Allowance | I78: =_xlfn.IFNA(VLOOKUP(E78,Master!$J:$M,4,0),"") -> ADM | J78: =_xlfn.IFNA(VLOOKUP($E78,Master!$J:$M,3,0),"") -> SGA | M78: 18441300 | N78: 19020600 | O78: 19539200 | P78: 18846800 | Q78: 21612000 | R78: 22748000 | S78: 22464000 | T78: 23600000 | U78: 23316000 | V78: 22748000 | W78: 23600000 | X78: 23032000 | Y78: 22748000 | Z78: 23316000 | AA78: 22748000 | AB78: 21896000 | AC78: =SUM(K78:P78) -> 75847900 | AD78: =SUM(Q78:AB78) -> 273828000 | AE78: 275100000 | AF78: 281130000 | AG78: A
A79: BEL | B79: =_xlfn.IFNA(VLOOKUP(C79,Master!$J:$K,2,0),"") -> B2220 | C79: Human Resource | D79: =_xlfn.IFNA(VLOOKUP(E79,Master!$J:$K,2,0),"") -> B3130 | E79: Sales - IAM | F79: =_xlfn.IFNA(VLOOKUP(G79,Master!B:C,2,0),"") -> 7511111 | G79: Staff Labor - Allowance | H79: Job Allowance | I79: =_xlfn.IFNA(VLOOKUP(E79,Master!$J:$M,4,0),"") -> ADM | J79: =_xlfn.IFNA(VLOOKUP($E79,Master!$J:$M,3,0),"") -> SGA | M79: 8200000 | N79: 8200000 | O79: 8200000 | P79: 8200000 | Q79: 8200000 | R79: 8200000 | S79: 8200000 | T79: 8200000 | U79: 8200000 | V79: 8200000 | W79: 8200000 | X79: 8200000 | Y79: 8200000 | Z79: 12100000 | AA79: 12100000 | AB79: 12100000 | AC79: =SUM(K79:P79) -> 32800000 | AD79: =SUM(Q79:AB79) -> 110100000 | AE79: 145200000 | AF79: 145200000 | AG79: A
A80: BEL | B80: =_xlfn.IFNA(VLOOKUP(C80,Master!$J:$K,2,0),"") -> B2220 | C80: Human Resource | D80: =_xlfn.IFNA(VLOOKUP(E80,Master!$J:$K,2,0),"") -> B3130 | E80: Sales - IAM | F80: =_xlfn.IFNA(VLOOKUP(G80,Master!B:C,2,0),"") -> 7511111 | G80: Staff Labor - Allowance | H80: Meals Allowance | I80: =_xlfn.IFNA(VLOOKUP(E80,Master!$J:$M,4,0),"") -> ADM | J80: =_xlfn.IFNA(VLOOKUP($E80,Master!$J:$M,3,0),"") -> SGA | P80: 2208000 | Q80: 1288000 | AB80: 4032000 | AC80: =SUM(K80:P80) -> 2208000 | AD80: =SUM(Q80:AB80) -> 5320000 | AE80: 4200000 | AF80: 4368000 | AG80: A
A81: BEL | B81: =_xlfn.IFNA(VLOOKUP(C81,Master!$J:$K,2,0),"") -> B2220 | C81: Human Resource | D81: =_xlfn.IFNA(VLOOKUP(E81,Master!$J:$K,2,0),"") -> B3130 | E81: Sales - IAM | F81: =_xlfn.IFNA(VLOOKUP(G81,Master!B:C,2,0),"") -> 7511111 | G81: Staff Labor - Allowance | H81: Medical Allowance | I81: =_xlfn.IFNA(VLOOKUP(E81,Master!$J:$M,4,0),"") -> ADM | J81: =_xlfn.IFNA(VLOOKUP($E81,Master!$J:$M,3,0),"") -> SGA | M81: 440000 | N81: 440000 | O81: 560000 | P81: 560000 | Q81: 680000 | R81: 680000 | S81: 680000 | T81: 680000 | U81: 680000 | V81: 680000 | W81: 680000 | X81: 680000 | Y81: 680000 | Z81: 680000 | AA81: 680000 | AB81: 680000 | AC81: =SUM(K81:P81) -> 2000000 | AD81: =SUM(Q81:AB81) -> 8160000 | AE81: 8160000 | AF81: 8160000 | AG81: A
A82: BEL | B82: =_xlfn.IFNA(VLOOKUP(C82,Master!$J:$K,2,0),"") -> B2220 | C82: Human Resource | D82: =_xlfn.IFNA(VLOOKUP(E82,Master!$J:$K,2,0),"") -> B3130 | E82: Sales - IAM | F82: =_xlfn.IFNA(VLOOKUP(G82,Master!B:C,2,0),"") -> 7511111 | G82: Staff Labor - Allowance | H82: Transportation (fixed) Allowance | I82: =_xlfn.IFNA(VLOOKUP(E82,Master!$J:$M,4,0),"") -> ADM | J82: =_xlfn.IFNA(VLOOKUP($E82,Master!$J:$M,3,0),"") -> SGA | M82: 2400000 | N82: 2400000 | O82: 3000000 | P82: 3000000 | Q82: 3600000 | R82: 3600000 | S82: 3600000 | T82: 3600000 | U82: 3600000 | V82: 3600000 | W82: 3600000 | X82: 3600000 | Y82: 3600000 | Z82: 3600000 | AA82: 3600000 | AB82: 3600000 | AC82: =SUM(K82:P82) -> 10800000 | AD82: =SUM(Q82:AB82) -> 43200000 | AE82: 43200000 | AF82: 43200000 | AG82: A
A83: BEL | B83: =_xlfn.IFNA(VLOOKUP(C83,Master!$J:$K,2,0),"") -> B2220 | C83: Human Resource | D83: =_xlfn.IFNA(VLOOKUP(E83,Master!$J:$K,2,0),"") -> B3150 | E83: SCM - FG WH | F83: =_xlfn.IFNA(VLOOKUP(G83,Master!B:C,2,0),"") -> 7511111 | G83: Staff Labor - Allowance | H83: ATM Allowance | I83: =_xlfn.IFNA(VLOOKUP(E83,Master!$J:$M,4,0),"") -> ADM | J83: =_xlfn.IFNA(VLOOKUP($E83,Master!$J:$M,3,0),"") -> SGA | M83: 54000 | N83: 49500 | O83: 49500 | P83: 49500 | Q83: 49500 | R83: 49500 | S83: 49500 | T83: 49500 | U83: 49500 | V83: 49500 | W83: 49500 | X83: 49500 | Y83: 49500 | Z83: 49500 | AA83: 49500 | AB83: 49500 | AC83: =SUM(K83:P83) -> 202500 | AD83: =SUM(Q83:AB83) -> 594000 | AE83: 594000 | AF83: 594000 | AG83: A
A84: BEL | B84: =_xlfn.IFNA(VLOOKUP(C84,Master!$J:$K,2,0),"") -> B2220 | C84: Human Resource | D84: =_xlfn.IFNA(VLOOKUP(E84,Master!$J:$K,2,0),"") -> B3150 | E84: SCM - FG WH | F84: =_xlfn.IFNA(VLOOKUP(G84,Master!B:C,2,0),"") -> 7511111 | G84: Staff Labor - Allowance | H84: Daily Transportation Allowance | I84: =_xlfn.IFNA(VLOOKUP(E84,Master!$J:$M,4,0),"") -> ADM | J84: =_xlfn.IFNA(VLOOKUP($E84,Master!$J:$M,3,0),"") -> SGA | M84: 8755500 | N84: 8950900 | O84: 8531600 | P84: 7902650 | Q84: 9996000 | R84: 10884000 | S84: 10662000 | T84: 11550000 | U84: 11328000 | V84: 10884000 | W84: 11550000 | X84: 11106000 | Y84: 10884000 | Z84: 11328000 | AA84: 10884000 | AB84: 10218000 | AC84: =SUM(K84:P84) -> 34140650 | AD84: =SUM(Q84:AB84) -> 131274000 | AE84: 132138000 | AF84: 137025000 | AG84: A
A85: BEL | B85: =_xlfn.IFNA(VLOOKUP(C85,Master!$J:$K,2,0),"") -> B2220 | C85: Human Resource | D85: =_xlfn.IFNA(VLOOKUP(E85,Master!$J:$K,2,0),"") -> B3150 | E85: SCM - FG WH | F85: =_xlfn.IFNA(VLOOKUP(G85,Master!B:C,2,0),"") -> 7511111 | G85: Staff Labor - Allowance | H85: Job Allowance | I85: =_xlfn.IFNA(VLOOKUP(E85,Master!$J:$M,4,0),"") -> ADM | J85: =_xlfn.IFNA(VLOOKUP($E85,Master!$J:$M,3,0),"") -> SGA | M85: 3200000 | N85: 3200000 | O85: 3200000 | P85: 3200000 | Q85: 3200000 | R85: 3200000 | S85: 3200000 | T85: 3200000 | U85: 3200000 | V85: 3200000 | W85: 3200000 | X85: 3200000 | Y85: 3200000 | Z85: 4900000 | AA85: 4900000 | AB85: 4900000 | AC85: =SUM(K85:P85) -> 12800000 | AD85: =SUM(Q85:AB85) -> 43500000 | AE85: 60300000 | AF85: 61800000 | AG85: A
A86: BEL | B86: =_xlfn.IFNA(VLOOKUP(C86,Master!$J:$K,2,0),"") -> B2220 | C86: Human Resource | D86: =_xlfn.IFNA(VLOOKUP(E86,Master!$J:$K,2,0),"") -> B3150 | E86: SCM - FG WH | F86: =_xlfn.IFNA(VLOOKUP(G86,Master!B:C,2,0),"") -> 7511111 | G86: Staff Labor - Allowance | H86: Meals Allowance | I86: =_xlfn.IFNA(VLOOKUP(E86,Master!$J:$M,4,0),"") -> ADM | J86: =_xlfn.IFNA(VLOOKUP($E86,Master!$J:$M,3,0),"") -> SGA | P86: 2024000 | Q86: 1012000 | AB86: 3168000 | AC86: =SUM(K86:P86) -> 2024000 | AD86: =SUM(Q86:AB86) -> 4180000 | AE86: 3300000 | AF86: 3432000 | AG86: A
A87: BEL | B87: =_xlfn.IFNA(VLOOKUP(C87,Master!$J:$K,2,0),"") -> B2220 | C87: Human Resource | D87: =_xlfn.IFNA(VLOOKUP(E87,Master!$J:$K,2,0),"") -> B3150 | E87: SCM - FG WH | F87: =_xlfn.IFNA(VLOOKUP(G87,Master!B:C,2,0),"") -> 7511111 | G87: Staff Labor - Allowance | H87: Medical Allowance | I87: =_xlfn.IFNA(VLOOKUP(E87,Master!$J:$M,4,0),"") -> ADM | J87: =_xlfn.IFNA(VLOOKUP($E87,Master!$J:$M,3,0),"") -> SGA | M87: 620000 | N87: 560000 | O87: 560000 | P87: 560000 | Q87: 560000 | R87: 560000 | S87: 560000 | T87: 560000 | U87: 560000 | V87: 560000 | W87: 560000 | X87: 560000 | Y87: 560000 | Z87: 560000 | AA87: 560000 | AB87: 560000 | AC87: =SUM(K87:P87) -> 2300000 | AD87: =SUM(Q87:AB87) -> 6720000 | AE87: 6720000 | AF87: 6720000 | AG87: A
A88: BEL | B88: =_xlfn.IFNA(VLOOKUP(C88,Master!$J:$K,2,0),"") -> B2220 | C88: Human Resource | D88: =_xlfn.IFNA(VLOOKUP(E88,Master!$J:$K,2,0),"") -> B3150 | E88: SCM - FG WH | F88: =_xlfn.IFNA(VLOOKUP(G88,Master!B:C,2,0),"") -> 7511111 | G88: Staff Labor - Allowance | H88: Transportation (fixed) Allowance | I88: =_xlfn.IFNA(VLOOKUP(E88,Master!$J:$M,4,0),"") -> ADM | J88: =_xlfn.IFNA(VLOOKUP($E88,Master!$J:$M,3,0),"") -> SGA | M88: 3300000 | N88: 3000000 | O88: 3000000 | P88: 3000000 | Q88: 3000000 | R88: 3000000 | S88: 3000000 | T88: 3000000 | U88: 3000000 | V88: 3000000 | W88: 3000000 | X88: 3000000 | Y88: 3000000 | Z88: 3000000 | AA88: 3000000 | AB88: 3000000 | AC88: =SUM(K88:P88) -> 12300000 | AD88: =SUM(Q88:AB88) -> 36000000 | AE88: 36000000 | AF88: 36000000 | AG88: A
A89: BEL | B89: =_xlfn.IFNA(VLOOKUP(C89,Master!$J:$K,2,0),"") -> B2220 | C89: Human Resource | D89: =_xlfn.IFNA(VLOOKUP(E89,Master!$J:$K,2,0),"") -> B3160 | E89: Marketing | F89: =_xlfn.IFNA(VLOOKUP(G89,Master!B:C,2,0),"") -> 7511111 | G89: Staff Labor - Allowance | H89: ATM Allowance | I89: =_xlfn.IFNA(VLOOKUP(E89,Master!$J:$M,4,0),"") -> ADM | J89: =_xlfn.IFNA(VLOOKUP($E89,Master!$J:$M,3,0),"") -> SGA | M89: 31500 | N89: 31500 | O89: 31500 | P89: 31500 | Q89: 31500 | R89: 31500 | S89: 31500 | T89: 31500 | U89: 31500 | V89: 31500 | W89: 31500 | X89: 31500 | Y89: 31500 | Z89: 31500 | AA89: 31500 | AB89: 31500 | AC89: =SUM(K89:P89) -> 126000 | AD89: =SUM(Q89:AB89) -> 378000 | AE89: 378000 | AF89: 378000 | AG89: A
A90: BEL | B90: =_xlfn.IFNA(VLOOKUP(C90,Master!$J:$K,2,0),"") -> B2220 | C90: Human Resource | D90: =_xlfn.IFNA(VLOOKUP(E90,Master!$J:$K,2,0),"") -> B3160 | E90: Marketing | F90: =_xlfn.IFNA(VLOOKUP(G90,Master!B:C,2,0),"") -> 7511111 | G90: Staff Labor - Allowance | H90: Daily Transportation Allowance | I90: =_xlfn.IFNA(VLOOKUP(E90,Master!$J:$M,4,0),"") -> ADM | J90: =_xlfn.IFNA(VLOOKUP($E90,Master!$J:$M,3,0),"") -> SGA | M90: 6587750 | N90: 6990500 | O90: 6722000 | P90: 6319250 | Q90: 8556000 | R90: 9124000 | S90: 8982000 | T90: 9550000 | U90: 9408000 | V90: 9124000 | W90: 9550000 | X90: 9266000 | Y90: 9124000 | Z90: 9408000 | AA90: 9124000 | AB90: 8698000 | AC90: =SUM(K90:P90) -> 26619500 | AD90: =SUM(Q90:AB90) -> 109914000 | AE90: 110550000 | AF90: 113565000 | AG90: A
A91: BEL | B91: =_xlfn.IFNA(VLOOKUP(C91,Master!$J:$K,2,0),"") -> B2220 | C91: Human Resource | D91: =_xlfn.IFNA(VLOOKUP(E91,Master!$J:$K,2,0),"") -> B3160 | E91: Marketing | F91: =_xlfn.IFNA(VLOOKUP(G91,Master!B:C,2,0),"") -> 7511111 | G91: Staff Labor - Allowance | H91: Job Allowance | I91: =_xlfn.IFNA(VLOOKUP(E91,Master!$J:$M,4,0),"") -> ADM | J91: =_xlfn.IFNA(VLOOKUP($E91,Master!$J:$M,3,0),"") -> SGA | M91: 3500000 | N91: 3500000 | O91: 3500000 | P91: 3500000 | Q91: 3500000 | R91: 3500000 | S91: 3500000 | T91: 3500000 | U91: 3500000 | V91: 3500000 | W91: 3500000 | X91: 3500000 | Y91: 3500000 | Z91: 5800000 | AA91: 5800000 | AB91: 5800000 | AC91: =SUM(K91:P91) -> 14000000 | AD91: =SUM(Q91:AB91) -> 48900000 | AE91: 69600000 | AF91: 69600000 | AG91: A
A92: BEL | B92: =_xlfn.IFNA(VLOOKUP(C92,Master!$J:$K,2,0),"") -> B2220 | C92: Human Resource | D92: =_xlfn.IFNA(VLOOKUP(E92,Master!$J:$K,2,0),"") -> B3160 | E92: Marketing | F92: =_xlfn.IFNA(VLOOKUP(G92,Master!B:C,2,0),"") -> 7511111 | G92: Staff Labor - Allowance | H92: Meals Allowance | I92: =_xlfn.IFNA(VLOOKUP(E92,Master!$J:$M,4,0),"") -> ADM | J92: =_xlfn.IFNA(VLOOKUP($E92,Master!$J:$M,3,0),"") -> SGA | P92: 1288000 | Q92: 644000 | AB92: 2016000 | AC92: =SUM(K92:P92) -> 1288000 | AD92: =SUM(Q92:AB92) -> 2660000 | AE92: 2100000 | AF92: 2184000 | AG92: A
A93: BEL | B93: =_xlfn.IFNA(VLOOKUP(C93,Master!$J:$K,2,0),"") -> B2220 | C93: Human Resource | D93: =_xlfn.IFNA(VLOOKUP(E93,Master!$J:$K,2,0),"") -> B3160 | E93: Marketing | F93: =_xlfn.IFNA(VLOOKUP(G93,Master!B:C,2,0),"") -> 7511111 | G93: Staff Labor - Allowance | H93: Medical Allowance | I93: =_xlfn.IFNA(VLOOKUP(E93,Master!$J:$M,4,0),"") -> ADM | J93: =_xlfn.IFNA(VLOOKUP($E93,Master!$J:$M,3,0),"") -> SGA | M93: 400000 | N93: 400000 | O93: 400000 | P93: 400000 | Q93: 400000 | R93: 400000 | S93: 400000 | T93: 400000 | U93: 400000 | V93: 400000 | W93: 400000 | X93: 400000 | Y93: 400000 | Z93: 400000 | AA93: 400000 | AB93: 400000 | AC93: =SUM(K93:P93) -> 1600000 | AD93: =SUM(Q93:AB93) -> 4800000 | AE93: 4800000 | AF93: 4800000 | AG93: A
A94: BEL | B94: =_xlfn.IFNA(VLOOKUP(C94,Master!$J:$K,2,0),"") -> B2220 | C94: Human Resource | D94: =_xlfn.IFNA(VLOOKUP(E94,Master!$J:$K,2,0),"") -> B3160 | E94: Marketing | F94: =_xlfn.IFNA(VLOOKUP(G94,Master!B:C,2,0),"") -> 7511111 | G94: Staff Labor - Allowance | H94: Skill Allowance | I94: =_xlfn.IFNA(VLOOKUP(E94,Master!$J:$M,4,0),"") -> ADM | J94: =_xlfn.IFNA(VLOOKUP($E94,Master!$J:$M,3,0),"") -> SGA | M94: 500000 | N94: 500000 | O94: 500000 | P94: 500000 | Q94: 500000 | R94: 500000 | S94: 500000 | T94: 500000 | U94: 500000 | V94: 500000 | W94: 500000 | X94: 500000 | Y94: 500000 | Z94: 500000 | AA94: 500000 | AB94: 500000 | AC94: =SUM(K94:P94) -> 2000000 | AD94: =SUM(Q94:AB94) -> 6000000 | AE94: 6000000 | AF94: 6000000 | AG94: A
A95: BEL | B95: =_xlfn.IFNA(VLOOKUP(C95,Master!$J:$K,2,0),"") -> B2220 | C95: Human Resource | D95: =_xlfn.IFNA(VLOOKUP(E95,Master!$J:$K,2,0),"") -> B3160 | E95: Marketing | F95: =_xlfn.IFNA(VLOOKUP(G95,Master!B:C,2,0),"") -> 7511111 | G95: Staff Labor - Allowance | H95: Transportation (fixed) Allowance | I95: =_xlfn.IFNA(VLOOKUP(E95,Master!$J:$M,4,0),"") -> ADM | J95: =_xlfn.IFNA(VLOOKUP($E95,Master!$J:$M,3,0),"") -> SGA | M95: 2100000 | N95: 2100000 | O95: 2100000 | P95: 2100000 | Q95: 2100000 | R95: 2100000 | S95: 2100000 | T95: 2100000 | U95: 2100000 | V95: 2100000 | W95: 2100000 | X95: 2100000 | Y95: 2100000 | Z95: 2100000 | AA95: 2100000 | AB95: 2100000 | AC95: =SUM(K95:P95) -> 8400000 | AD95: =SUM(Q95:AB95) -> 25200000 | AE95: 25200000 | AF95: 25200000 | AG95: A
A96: BEL | B96: =_xlfn.IFNA(VLOOKUP(C96,Master!$J:$K,2,0),"") -> B2220 | C96: Human Resource | D96: =_xlfn.IFNA(VLOOKUP(E96,Master!$J:$K,2,0),"") -> B4101 | E96: SP PD- CF | F96: =_xlfn.IFNA(VLOOKUP(G96,Master!B:C,2,0),"") -> 7511111 | G96: Staff Labor - Allowance | H96: ATM Allowance | I96: =_xlfn.IFNA(VLOOKUP(E96,Master!$J:$M,4,0),"") -> DIR | J96: =_xlfn.IFNA(VLOOKUP($E96,Master!$J:$M,3,0),"") -> MFG | M96: 27000 | N96: 27000 | O96: 27000 | P96: 27000 | Q96: 27000 | R96: 27000 | S96: 27000 | T96: 27000 | U96: 27000 | V96: 27000 | W96: 27000 | X96: 27000 | Y96: 27000 | Z96: 27000 | AA96: 27000 | AB96: 27000 | AC96: =SUM(K96:P96) -> 108000 | AD96: =SUM(Q96:AB96) -> 324000 | AE96: 324000 | AF96: 292500 | AG96: A
A97: BEL | B97: =_xlfn.IFNA(VLOOKUP(C97,Master!$J:$K,2,0),"") -> B2220 | C97: Human Resource | D97: =_xlfn.IFNA(VLOOKUP(E97,Master!$J:$K,2,0),"") -> B4101 | E97: SP PD- CF | F97: =_xlfn.IFNA(VLOOKUP(G97,Master!B:C,2,0),"") -> 7511111 | G97: Staff Labor - Allowance | H97: Daily Transportation Allowance | I97: =_xlfn.IFNA(VLOOKUP(E97,Master!$J:$M,4,0),"") -> DIR | J97: =_xlfn.IFNA(VLOOKUP($E97,Master!$J:$M,3,0),"") -> MFG | M97: 2608200 | N97: 2948400 | O97: 2721600 | P97: 2381400 | Q97: 2041200 | R97: 2494800 | S97: 2381400 | T97: 2835000 | U97: 2721600 | V97: 2494800 | W97: 2835000 | X97: 2608200 | Y97: 2494800 | Z97: 2851200 | AA97: 2613600 | AB97: 2257200 | AC97: =SUM(K97:P97) -> 10659600 | AD97: =SUM(Q97:AB97) -> 30628800 | AE97: 30921600 | AF97: 29029700 | AG97: A
A98: BEL | B98: =_xlfn.IFNA(VLOOKUP(C98,Master!$J:$K,2,0),"") -> B2220 | C98: Human Resource | D98: =_xlfn.IFNA(VLOOKUP(E98,Master!$J:$K,2,0),"") -> B4101 | E98: SP PD- CF | F98: =_xlfn.IFNA(VLOOKUP(G98,Master!B:C,2,0),"") -> 7511111 | G98: Staff Labor - Allowance | H98: Job Allowance | I98: =_xlfn.IFNA(VLOOKUP(E98,Master!$J:$M,4,0),"") -> DIR | J98: =_xlfn.IFNA(VLOOKUP($E98,Master!$J:$M,3,0),"") -> MFG | M98: 600000 | N98: 600000 | O98: 600000 | P98: 600000 | Q98: 600000 | R98: 600000 | S98: 600000 | T98: 600000 | U98: 600000 | V98: 600000 | W98: 600000 | X98: 600000 | Y98: 600000 | Z98: 1000000 | AA98: 1000000 | AB98: 1000000 | AC98: =SUM(K98:P98) -> 2400000 | AD98: =SUM(Q98:AB98) -> 8400000 | AE98: 12000000 | AF98: 12000000 | AG98: A
A99: BEL | B99: =_xlfn.IFNA(VLOOKUP(C99,Master!$J:$K,2,0),"") -> B2220 | C99: Human Resource | D99: =_xlfn.IFNA(VLOOKUP(E99,Master!$J:$K,2,0),"") -> B4101 | E99: SP PD- CF | F99: =_xlfn.IFNA(VLOOKUP(G99,Master!B:C,2,0),"") -> 7511111 | G99: Staff Labor - Allowance | H99: Meals Allowance | I99: =_xlfn.IFNA(VLOOKUP(E99,Master!$J:$M,4,0),"") -> DIR | J99: =_xlfn.IFNA(VLOOKUP($E99,Master!$J:$M,3,0),"") -> MFG | P99: 1104000 | Q99: 552000 | AB99: 1728000 | AC99: =SUM(K99:P99) -> 1104000 | AD99: =SUM(Q99:AB99) -> 2280000 | AE99: 1800000 | AF99: 1560000 | AG99: A
A100: BEL | B100: =_xlfn.IFNA(VLOOKUP(C100,Master!$J:$K,2,0),"") -> B2220 | C100: Human Resource | D100: =_xlfn.IFNA(VLOOKUP(E100,Master!$J:$K,2,0),"") -> B4101 | E100: SP PD- CF | F100: =_xlfn.IFNA(VLOOKUP(G100,Master!B:C,2,0),"") -> 7511111 | G100: Staff Labor - Allowance | H100: Medical Allowance | I100: =_xlfn.IFNA(VLOOKUP(E100,Master!$J:$M,4,0),"") -> DIR | J100: =_xlfn.IFNA(VLOOKUP($E100,Master!$J:$M,3,0),"") -> MFG | M100: 360000 | N100: 360000 | O100: 360000 | P100: 360000 | Q100: 360000 | R100: 360000 | S100: 360000 | T100: 360000 | U100: 360000 | V100: 360000 | W100: 360000 | X100: 360000 | Y100: 360000 | Z100: 360000 | AA100: 360000 | AB100: 360000 | AC100: =SUM(K100:P100) -> 1440000 | AD100: =SUM(Q100:AB100) -> 4320000 | AE100: 4320000 | AF100: 3900000 | AG100: A
A101: BEL | B101: =_xlfn.IFNA(VLOOKUP(C101,Master!$J:$K,2,0),"") -> B2220 | C101: Human Resource | D101: =_xlfn.IFNA(VLOOKUP(E101,Master!$J:$K,2,0),"") -> B4101 | E101: SP PD- CF | F101: =_xlfn.IFNA(VLOOKUP(G101,Master!B:C,2,0),"") -> 7511111 | G101: Staff Labor - Allowance | H101: Shift Allowance | I101: =_xlfn.IFNA(VLOOKUP(E101,Master!$J:$M,4,0),"") -> DIR | J101: =_xlfn.IFNA(VLOOKUP($E101,Master!$J:$M,3,0),"") -> MFG | M101: 690000 | N101: 780000 | O101: 720000 | P101: 630000 | Q101: 540000 | R101: 660000 | S101: 630000 | T101: 750000 | U101: 720000 | V101: 660000 | W101: 750000 | X101: 690000 | Y101: 660000 | Z101: 720000 | AA101: 660000 | AB101: 570000 | AC101: =SUM(K101:P101) -> 2820000 | AD101: =SUM(Q101:AB101) -> 8010000 | AE101: 7710000 | AF101: 6895000 | AG101: A
A102: BEL | B102: =_xlfn.IFNA(VLOOKUP(C102,Master!$J:$K,2,0),"") -> B2220 | C102: Human Resource | D102: =_xlfn.IFNA(VLOOKUP(E102,Master!$J:$K,2,0),"") -> B4101 | E102: SP PD- CF | F102: =_xlfn.IFNA(VLOOKUP(G102,Master!B:C,2,0),"") -> 7511111 | G102: Staff Labor - Allowance | H102: Transportation (fixed) Allowance | I102: =_xlfn.IFNA(VLOOKUP(E102,Master!$J:$M,4,0),"") -> DIR | J102: =_xlfn.IFNA(VLOOKUP($E102,Master!$J:$M,3,0),"") -> MFG | M102: 1800000 | N102: 1800000 | O102: 1800000 | P102: 1800000 | Q102: 1800000 | R102: 1800000 | S102: 1800000 | T102: 1800000 | U102: 1800000 | V102: 1800000 | W102: 1800000 | X102: 1800000 | Y102: 1800000 | Z102: 1800000 | AA102: 1800000 | AB102: 1800000 | AC102: =SUM(K102:P102) -> 7200000 | AD102: =SUM(Q102:AB102) -> 21600000 | AE102: 21600000 | AF102: 19500000 | AG102: A
A103: BEL | B103: =_xlfn.IFNA(VLOOKUP(C103,Master!$J:$K,2,0),"") -> B2220 | C103: Human Resource | D103: =_xlfn.IFNA(VLOOKUP(E103,Master!$J:$K,2,0),"") -> B4102 | E103: SP PD- CM | F103: =_xlfn.IFNA(VLOOKUP(G103,Master!B:C,2,0),"") -> 7511111 | G103: Staff Labor - Allowance | H103: ATM Allowance | I103: =_xlfn.IFNA(VLOOKUP(E103,Master!$J:$M,4,0),"") -> DIR | J103: =_xlfn.IFNA(VLOOKUP($E103,Master!$J:$M,3,0),"") -> MFG | M103: 72000 | N103: 72000 | O103: 72000 | P103: 72000 | Q103: 67500 | R103: 67500 | S103: 67500 | T103: 67500 | U103: 67500 | V103: 67500 | W103: 72000 | X103: 72000 | Y103: 72000 | Z103: 72000 | AA103: 72000 | AB103: 72000 | AC103: =SUM(K103:P103) -> 288000 | AD103: =SUM(Q103:AB103) -> 837000 | AE103: 850500 | AF103: 760500 | AG103: A
A104: BEL | B104: =_xlfn.IFNA(VLOOKUP(C104,Master!$J:$K,2,0),"") -> B2220 | C104: Human Resource | D104: =_xlfn.IFNA(VLOOKUP(E104,Master!$J:$K,2,0),"") -> B4102 | E104: SP PD- CM | F104: =_xlfn.IFNA(VLOOKUP(G104,Master!B:C,2,0),"") -> 7511111 | G104: Staff Labor - Allowance | H104: Daily Transportation Allowance | I104: =_xlfn.IFNA(VLOOKUP(E104,Master!$J:$M,4,0),"") -> DIR | J104: =_xlfn.IFNA(VLOOKUP($E104,Master!$J:$M,3,0),"") -> MFG | M104: 6955200 | N104: 7862400 | O104: 7257600 | P104: 6350400 | Q104: 5103000 | R104: 6237000 | S104: 5953500 | T104: 7087500 | U104: 6804000 | V104: 6237000 | W104: 7560000 | X104: 6955200 | Y104: 6652800 | Z104: 7603200 | AA104: 6969600 | AB104: 6019200 | AC104: =SUM(K104:P104) -> 28425600 | AD104: =SUM(Q104:AB104) -> 79182000 | AE104: 81105600 | AF104: 75600600 | AG104: A
A105: BEL | B105: =_xlfn.IFNA(VLOOKUP(C105,Master!$J:$K,2,0),"") -> B2220 | C105: Human Resource | D105: =_xlfn.IFNA(VLOOKUP(E105,Master!$J:$K,2,0),"") -> B4102 | E105: SP PD- CM | F105: =_xlfn.IFNA(VLOOKUP(G105,Master!B:C,2,0),"") -> 7511111 | G105: Staff Labor - Allowance | H105: Job Allowance | I105: =_xlfn.IFNA(VLOOKUP(E105,Master!$J:$M,4,0),"") -> DIR | J105: =_xlfn.IFNA(VLOOKUP($E105,Master!$J:$M,3,0),"") -> MFG | M105: 1450000 | N105: 1450000 | O105: 1450000 | P105: 1450000 | Q105: 1400000 | R105: 1400000 | S105: 1400000 | T105: 1400000 | U105: 1400000 | V105: 1400000 | W105: 1400000 | X105: 1400000 | Y105: 1400000 | Z105: 2650000 | AA105: 2650000 | AB105: 2650000 | AC105: =SUM(K105:P105) -> 5800000 | AD105: =SUM(Q105:AB105) -> 20550000 | AE105: 31950000 | AF105: 28100000 | AG105: A
...

Sheet Master
A1: COA AX | B1: Name COA AX | C1: COA AX | D1: COA AX | E1: Group Cost | F1: UNIQ | G1: COA Budget | H1: Description | J1: Name | K1: BNGK | L1: GROUP COST | M1: GROUP SECTION | N1: Name | P1: Code | Q1: Name | S1: Priority Code | T1: Priority Name | U1: Description
A2: 7511101 | B2: Salary for Commissioner | C2: 7511101 | D2: 7511101 | E2: SGA | F2: SGA-7511101 | G2: A502 | H2: Salary for Commissioner | J2: Top Management | K2: B1000 | L2: SGA | M2: ADM | N2: Top Management | P2: 53450 | Q2: NGK BUSI INDONESIA | S2: A | T2: Must | U2: If this is not done, the company or our team cannot continue its business.
A3: 7511102 | B3: Salary for Director | C3: 7511102 | D3: 7511102 | E3: SGA | F3: SGA-7511102 | G3: A502 | H3: Salary for Director & Expat | J3: Commissioner | K3: B1001 | L3: SGA | M3: ADM | N3: Commissioner | S3: B | T3: Want to | U3: We want to do it as a team this term. we need it.
A4: 7511103 | B4: Staff Labor - Baslc Salary | C4: 7511103 | D4: 7511103 | E4: SGA | F4: SGA-7511103 | G4: A501 | H4: Basic Salary of permanent employee | J4: Admin & HR | K4: B2200 | L4: SGA | M4: ADM | N4: Admin & HR | S4: C | T4: Challenge | U4: We want to do it for this term or the future. But it doesn't matter if it's not this term.
A5: 7511111 | B5: Staff Labor - Allowance | C5: 7511111 | D5: 7511111 | E5: SGA | F5: SGA-7511111 | G5: A501 | H5: Employee allowance | J5: General Affair | K5: B2210 | L5: SGA | M5: ADM | N5: General Affair
A6: 7511112 | B6: Staff Labor - Tax allowance (art.21) | C6: 7511112 | D6: 7511112 | E6: SGA | F6: SGA-7511112 | G6: A501 | H6: Empployee Tax allowance | J6: Human Resource | K6: B2220 | L6: SGA | M6: ADM | N6: Human Resource | P6: BEX
A7: 7511121 | B7: Staff Labor - BPJS JK & JKK (1.19%) | C7: 7511121 | D7: 7511121 | E7: SGA | F7: SGA-7511121 | G7: A501 | H7: BPJS JK & JKK (death warrant, Accident Insurance) | J7: Health, Safety & Environment | K7: B2230 | L7: SGA | M7: ADM | N7: Health, Safety & Environment | P7: BEL
A8: 7511122 | B8: Staff Labor - BPJS Kesehatan (4%) | C8: 7511122 | D8: 7511122 | E8: SGA | F8: SGA-7511122 | G8: A501 | H8: BPJS health insurance | J8: Accounting & Finance | K8: B2300 | L8: SGA | M8: ADM | N8: Accounting & Finance
A9: 7511201 | B9: Staff Overtime | C9: 7511201 | D9: 7511201 | E9: SGA | F9: SGA-7511201 | G9: A503 | H9: Overtime permanent employee | J9: Information Technology | K9: B2400 | L9: SGA | M9: ADM | N9: Information Technology
A10: 7512111 | B10: Staff Welfare - BPJS Dana pensiun (2%) | C10: 7512111 | D10: 7512111 | E10: SGA | F10: SGA-7512111 | G10: A504 | H10: BPJS pension fund | J10: Sales & MKTG Dept.- Automotive | K10: B3100 | L10: SGA | M10: ADM | N10: Sales & MKTG Dept.- Automotive
A11: 7512112 | B11: Staff Welfare - BPJS JHT (3.7%) | C11: 7512112 | D11: 7512112 | E11: SGA | F11: SGA-7512112 | G11: A504 | H11: BPJS Pension plan | J11: Marketing | K11: B3160 | L11: SGA | M11: ADM | N11: Marketing
A12: 7514101 | B12: Staff Bonus / TAT | C12: 7514101 | D12: 7514101 | E12: SGA | F12: SGA-7514101 | G12: A501 | H12: Year-end allowance & Alpha | J12: Sales - OEM | K12: B3110 | L12: SGA | M12: ADM | N12: Sales - OEM
A13: 7514102 | B13: Staff Ramadhan / THR | C13: 7514102 | D13: 7514102 | E13: SGA | F13: SGA-7514102 | G13: A501 | H13: Lebaran bonus | J13: Sales - OES | K13: B3120 | L13: SGA | M13: ADM | N13: Sales - OES
A14: 7515401 | B14: Staff Welfare - Outpatient (Medical) | C14: 7515401 | D14: 7515401 | E14: SGA | F14: SGA-7515401 | G14: A504 | H14: outpatient treatment costs | J14: Sales - IAM | K14: B3130 | L14: SGA | M14: ADM | N14: Sales - IAM
A15: 7515402 | B15: Staff Welfare - Hospitalization | C15: 7515402 | D15: 7515402 | E15: SGA | F15: SGA-7515402 | G15: A504 | H15: hospitalization costs | J15: Sales & MKTG Dept.- DID Chain | K15: B3172 | L15: SGA | M15: ADM | N15: Sales & MKTG Dept.- DID Chain
A16: 7515403 | B16: Staff Welfare - Glasses | C16: 7515403 | D16: 7515403 | E16: SGA | F16: SGA-7515403 | G16: A504 | H16: glasses costs | J16: SP PD- CF | K16: B4101 | L16: MFG | M16: DIR | N16: SP PD- CF
A17: 7515404 | B17: Staff Welfare - Dental | C17: 7515404 | D17: 7515404 | E17: SGA | F17: SGA-7515404 | G17: A504 | H17: dental costs | J17: SP PD- CM | K17: B4102 | L17: MFG | M17: DIR | N17: SP PD- CM
A18: 7515405 | B18: Staff Welfare - Medical Check Up | C18: 7515405 | D18: 7515405 | E18: SGA | F18: SGA-7515405 | G18: A504 | H18: Medical Check Up cost | J18: SP PD- WT | K18: B4103 | L18: MFG | M18: DIR | N18: SP PD- WT
A19: 7515406 | B19: Staff Welfare - Uniform | C19: 7515406 | D19: 7515406 | E19: SGA | F19: SGA-7515406 | G19: A504 | H19: uniform costs | J19: SP PD- Plating | K19: B4105 | L19: MFG | M19: DIR | N19: SP PD- Plating
A20: 7515407 | B20: Staff Welfare - Safety Shoes | C20: 7515407 | D20: 7515407 | E20: SGA | F20: SGA-7515407 | G20: A504 | J20: SP PD- MS Insp. | K20: B4109 | L20: MFG | M20: DIR | N20: SP PD- MS Insp.
A21: 7515408 | B21: Staff Welfare - Family Gathering / Anniversary | C21: 7515408 | D21: 7515408 | E21: SGA | F21: SGA-7515408 | G21: A504 | H21: Family Gathering / Anniversary | J21: SP PD- Insulator Sealing | K21: B4130 | L21: MFG | M21: DIR | N21: SP PD- Insulator Sealing
A22: 7515409 | B22: Staff Welfare - Meals of canteen & other meals | C22: 7515409 | D22: 7515409 | E22: SGA | F22: SGA-7515409 | G22: A504 | H22: Meals of canteen & other meals cost | J22: SP PD- Assy | K22: B4110 | L22: MFG | M22: DIR | N22: SP PD- Assy
A23: 7515410 | B23: Staff Welfare - Kaizen & QCC reward | C23: 7515410 | D23: 7515410 | E23: SGA | F23: SGA-7515410 | G23: A504 | H23: an expense, arising from Kaizen and QCC acitivity | J23: SP-PD-Assy-Auto Assembly | K23: B4115 | L23: MFG | M23: DIR | N23: SP-PD-Assy-Auto Assembly
A24: 7515499 | B24: Staff Welfare - Welfare Others | C24: 7515499 | D24: 7515499 | E24: SGA | F24: SGA-7515499 | G24: A504 | H24: an other welfare expense, arising besides the above welfare expense | J24: SP PD- Bending | K24: B4114 | L24: MFG | M24: DIR | N24: SP PD- Bending
A25: 7516102 | B25: Retirement Allowance | C25: 7516102 | D25: 7516102 | E25: SGA | F25: SGA-7516102 | G25: A505 | H25: employee retirement provission costs | J25: SP PD- Final Inspection | K25: B4120 | L25: MFG | M25: DIR | N25: SP PD- Final Inspection
A26: 7519101 | B26: House Rent Allowance | C26: 7519101 | D26: 7519101 | E26: SGA | F26: SGA-7519101 | G26: A502 | H26: House Rent Allowance for expat | J26: SP PD- QC - OEM | K26: B4121 | L26: MFG | M26: DIR | N26: SP PD- QC - OEM
A27: 7521101 | B27: Casual Staff Labor - Basic Salary | C27: 7521101 | D27: 7521101 | E27: SGA | F27: SGA-7521101 | G27: A501 | H27: All benefit for temporary worker | J27: PC PD- Injection | K27: B4410 | L27: MFG | M27: DIR | N27: PC PD- Injection
A28: 7521102 | B28: Casual Staff Labor - Overtime | C28: 7521102 | D28: 7521102 | E28: SGA | F28: SGA-7521102 | G28: A503 | H28: Overtime temporary worker | J28: PC PD- Assy | K28: B4430 | L28: MFG | M28: DIR | N28: PC PD- Assy
A29: 7571101 | B29: Personnel expense transferred | C29: 7571101 | D29: 7571101 | E29: SGA | F29: SGA-7571101 | G29: A506 | H29: Transfer Labor cost from one section into another section | J29: PC PD- QC | K29: B4440 | L29: MFG | M29: DIR | N29: PC PD- QC
A30: 7611100 | B30: Depreciation-Building | C30: 7611100 | D30: 7611100 | E30: SGA | F30: SGA-7611100 | G30: A601 | H30: the amount of depreciation of tangible assets for building | J30: Plant Operation (Indirect Mfg) | K30: B5000 | L30: MFG | M30: IND | N30: Plant Operation (Indirect Mfg)
A31: 7611300 | B31: Depreciation-Machiney & equipment | C31: 7611300 | D31: 7611300 | E31: SGA | F31: SGA-7611300 | G31: A601 | H31: the amount of depreciation of tangible assets for machinery & factory equipment | J31: Production Office | K31: B5100 | L31: MFG | M31: IND | N31: Production Office
A32: 7611400 | B32: Depreciation-Lease Machinery & equipment | C32: 7611400 | D32: 7611400 | E32: SGA | F32: SGA-7611400 | G32: A601 | H32: the amount of depreciation of tangible assets for machinery & factory equipment (Leases) | J32: Production Office (SP) | K32: B5101 | L32: MFG | M32: IND | N32: Production Office (SP)
... A42: 7641102 | B42: Repair of Equipment | C42: 7641102 | D42: 7641102 | E42: SGA | F42: SGA-7641102 | G42: A1002 | H42: expenses for repair and maintenance tangible assets, intangible assets and other assets beside building | J42: Continuous Improvement | K42: B5007 | L42: MFG | M42: IND | N42: Continuous Improvement
A43: 7641103 | B43: Factory Supply Expense | C43: 7641103 | D43: 7641103 | E43: SGA | F43: SGA-7641103 | G43: A1099 | H43: All cost that arrising to support factory acitivity | J43: All | K43: B0000 | N43: All
A44: 7641104 | B44: Calibration Cost | C44: 7641104 | D44: 7641104 | E44: SGA | F44: SGA-7641104 | G44: A1099 | H44: Cost of calibration for tools and equipment of factory and others
A45: 7651101 | B45: Transportation Fee for employee | C45: 7651101 | D45: 7651101 | E45: SGA | F45: SGA-7651101 | G45: A801 | H45: Gasoline of company cars & expense for Local transportation
A46: 7651102 | B46: Travel Expense-Domestic | C46: 7651102 | D46: 7651102 | E46: SGA | F46: SGA-7651102 | G46: A801 | H46: expenses for business trip, including allowance for business trip to an employee only for domestic travel
A47: 7651103 | B47: Travel Expense-Oversea | C47: 7651103 | D47: 7651103 | E47: SGA | F47: SGA-7651103 | G47: A801 | H47: expenses for business trip, including allowance for business trip to an employee only for overseas travel
A48: 7661101 | B48: Entertainment | C48: 7661101 | D48: 7661101 | E48: SGA | F48: SGA-7661101 | G48: A1001 | H48: the amount of expenses for the act of entertaining the business partner
A49: 7671102 | B49: Amortization of Land & Building tax (PBB) | C49: 7671102 | D49: 7671102 | E49: SGA | F49: SGA-7671102 | G49: A1099 | H49: the amount of depreciation of intangible of Land & Building Tax (PBB)
A50: 7671103 | B50: License fee | C50: 7671103 | D50: 7671103 | E50: SGA | F50: SGA-7671103 | G50: A1099 | H50: The expense related with the documentation process, such as : KIR, Car lisence, company lisence, etc.
A51: 7681101 | B51: Insurance Premium | C51: 7681101 | D51: 7681101 | E51: SGA | F51: SGA-7681101 | G51: A1099 | H51: expenses for risk management with no premium at the end of the term, such as fire insurance for plants and inventories
A52: 7691000 | B52: Office supply & Stationary Expense | C52: 7691000 | D52: 7691000 | E52: SGA | F52: SGA-7691000 | G52: A1099 | H52: the amount of supplies for office, such as stationery. Small office equipment included
A53: 7711101 | B53: Communication expenses | C53: 7711101 | D53: 7711101 | E53: SGA | F53: SGA-7711101 | G53: A1099 | H53: expenses for communication with a people in remote place, such as expense for telephone and postage
A54: 7711102 | B54: IT Expense | C54: 7711102 | D54: 7711102 | E54: SGA | F54: SGA-7711102 | G54: A1005 | H54: the amount of supplies for IT tools
A55: 7711103 | B55: Stamp/Post Fee | C55: 7711103 | D55: 7711103 | E55: SGA | F55: SGA-7711103 | G55: A1099 | H55: The expenses related with stamp duty
... A76: 7461101 | B76: Sample expense | C76: 7461101 | D76: 7461101 | E76: SGA | F76: SGA-7461101 | G76: A499 | H76: Sample expense
A77: 7411105 | B77: Sales - Insurance of Delivery or Shipment | C77: 7411105 | D77: 7411105 | E77: SGA | F77: SGA-7411105 | G77: A299
A78: 7471201 | B78: Sales - Insurance of AR (Credit Insurance) | C78: 7471201 | D78: 7471201 | E78: SGA | F78: SGA-7471201 | G78: A299
A79: 7751101 | B79: Sales - Royalty to NGK Group | C79: 7751101 | D79: 7751101 | E79: SGA | F79: SGA-7751101
A80: 7751102 | B80: Sales - Royalty to Independence Party | C80: 7751102 | D80: 7751102 | E80: SGA | F80: SGA-7751102
A81: 7111211 | B81: Import Duty-purchased FG from NGK group | C81: 7111211 | D81: 7111211 | E81: MFG | F81: MFG-7111211
A82: 7111212 | B82: Import Duty-purchased FG from outside supplier | C82: 7111212 | D82: 7111212 | E82: MFG | F82: MFG-7111212
A83: 7111221 | B83: Import Duty-purchased KD&RM from NGK Japan | C83: 7111221 | D83: 7111221 | E83: MFG | F83: MFG-7111221
A84: 7111222 | B84: Import Duty-purchased KD&RM from NGK Group(Not fromJP) | C84: 7111222 | D84: 7111222 | E84: MFG | F84: MFG-7111222
A85: 7111223 | B85: Import Duty-purchased Comp Parts&RM from outside supplier | C85: 7111223 | D85: 7111223 | E85: MFG | F85: MFG-7111223
A86: 7111311 | B86: Import Expense-purchased FG from NGK group | C86: 7111311 | D86: 7111311 | E86: MFG | F86: MFG-7111311
A87: 7111312 | B87: Import Expense-purchased FG from outside supplier | C87: 7111312 | D87: 7111312 | E87: MFG | F87: MFG-7111312
A88: 7111321 | B88: Import Expense-purchased KD&RM from NGK Japan | C88: 7111321 | D88: 7111321 | E88: MFG | F88: MFG-7111321
A89: 7111322 | B89: Import Expense-purchased KD&RM from NGK Group(Not fromJP) | C89: 7111322 | D89: 7111322 | E89: MFG | F89: MFG-7111322
A90: 7111323 | B90: Import Expense-purchased Comp Parts&RM from outside supplier | C90: 7111323 | D90: 7111323 | E90: MFG | F90: MFG-7111323
... A94: 7211101 | B94: Cost of Factory Supply | C94: 7211101 | D94: 7211101 | E94: MFG | F94: MFG-7211101
A95: 7211102 | B95: Cost of Chemical | C95: 7211102 | D95: 7211102 | E95: MFG | F95: MFG-7211102 | G95: 901 | H95: The expenses of Chemicals consumption
A96: 7211103 | B96: Cost of Packaging | C96: 7211103 | D96: 7211103 | E96: MFG | F96: MFG-7211103
A97: 7211104 | B97: Cost of Oil | C97: 7211104 | D97: 7211104 | E97: MFG | F97: MFG-7211104 | G97: 302
A98: 7221101 | B98: Cost of Tooling | C98: 7221101 | D98: 7221101 | E98: MFG | F98: MFG-7221101 | G98: 302 | H98: The expenses of Tooling consumption
A99: 7221102 | B99: Cost of Machinery parts | C99: 7221102 | D99: 7221102 | E99: MFG | F99: MFG-7221102 | G99: 301 | H99: The expenses of Spare Parts consumption
A100: 7511101 | B100: Salary for Commissioner | C100: 7511101 | D100: 7511101 | E100: MFG | F100: MFG-7511101 | G100: 602 | H100: Salary for Commissioner
A101: 7511102 | B101: Salary for Director | C101: 7511102 | D101: 7511102 | E101: MFG | F101: MFG-7511102 | G101: 602 | H101: Salary for Director & Expat
A102: 7511103 | B102: Staff Labor - Basic Salary | C102: 7511103 | D102: 7511103 | E102: MFG | F102: MFG-7511103 | G102: 601 | H102: Basic Salary of permanent employee
A103: 7511111 | B103: Staff Labor - Allowance | C103: 7511111 | D103: 7511111 | E103: MFG | F103: MFG-7511111 | G103: 601 | H103: Employee allowance
A104: 7511112 | B104: Staff Labor - Tax allowance (art.21) | C104: 7511112 | D104: 7511112 | E104: MFG | F104: MFG-7511112 | G104: 601 | H104: Empployee Tax allowance
A105: 7511121 | B105: Staff Labor - BPJS JK & JKK (1.19%) | C105: 7511121 | D105: 7511121 | E105: MFG | F105: MFG-7511121 | G105: 601 | H105: BPJS JK & JKK (death warrant, Accident Insurance)
A106: 7511122 | B106: Staff Labor - BPJS Kesehatan (4%) | C106: 7511122 | D106: 7511122 | E106: MFG | F106: MFG-7511122 | G106: 601 | H106: BPJS health insurance
A107: 7511201 | B107: Staff Overtime | C107: 7511201 | D107: 7511201 | E107: MFG | F107: MFG-7511201 | G107: 603 | H107: Overtime permanent employee
A108: 7512111 | B108: Staff Welfare - BPJS Dana pensiun (2%) | C108: 7512111 | D108: 7512111 | E108: MFG | F108: MFG-7512111 | G108: 604 | H108: BPJS pension fund
A109: 7512112 | B109: Staff Welfare - BPJS JHT (3.7%) | C109: 7512112 | D109: 7512112 | E109: MFG | F109: MFG-7512112 | G109: 604 | H109: BPJS Pension plan
... A117: 7515406 | B117: Staff Welfare - Uniform | C117: 7515406 | D117: 7515406 | E117: MFG | F117: MFG-7515406 | G117: 604 | H117: uniform costs
A118: 7515407 | B118: Staff Welfare - Safety Shoes | C118: 7515407 | D118: 7515407 | E118: MFG | F118: MFG-7515407 | G118: 604
A119: 7515408 | B119: Staff Welfare - Family Gathering / Anniversary | C119: 7515408 | D119: 7515408 | E119: MFG | F119: MFG-7515408 | G119: 604 | H119: Family Gathering / Anniversary
A120: 7515409 | B120: Staff Welfare - Meals of canteen & other meals | C120: 7515409 | D120: 7515409 | E120: MFG | F120: MFG-7515409 | G120: 604 | H120: Meals of canteen & other meals cost
A121: 7515410 | B121: Staff Welfare - Kaizen & QCC reward | C121: 7515410 | D121: 7515410 | E121: MFG | F121: MFG-7515410 | G121: 604 | H121: an expense, arising from Kaizen and QCC acitivity
A122: 7515499 | B122: Staff Welfare - Welfare Others | C122: 7515499 | D122: 7515499 | E122: MFG | F122: MFG-7515499 | G122: 604 | H122: an other welfare expense, arising besides the above welfare expense
A123: 7516102 | B123: Retirement Allowance | C123: 7516102 | D123: 7516102 | E123: MFG | F123: MFG-7516102 | G123: 605 | H123: employee retirement provission costs
A124: 7519101 | B124: House Rent Allowance | C124: 7519101 | D124: 7519101 | E124: MFG | F124: MFG-7519101 | G124: 602 | H124: House Rent Allowance for expat
A125: 7521101 | B125: Casual Staff Labor - Basic Salary | C125: 7521101 | D125: 7521101 | E125: MFG | F125: MFG-7521101 | G125: 601 | H125: All benefit for temporary worker
A126: 7521102 | B126: Casual Staff Labor - Overtime | C126: 7521102 | D126: 7521102 | E126: MFG | F126: MFG-7521102 | G126: 603 | H126: Overtime temporary worker
A127: 7571101 | B127: Personnel expense transferred | C127: 7571101 | D127: 7571101 | E127: MFG | F127: MFG-7571101 | G127: 606 | H127: Transfer Labor cost from one section into another section
A128: 7611100 | B128: Depreciation-Building | C128: 7611100 | D128: 7611100 | E128: MFG | F128: MFG-7611100 | G128: 701 | H128: the amount of depreciation of tangible assets for building
A129: 7611300 | B129: Depreciation-Machiney & equipment | C129: 7611300 | D129: 7611300 | E129: MFG | F129: MFG-7611300 | G129: 701 | H129: the amount of depreciation of tangible assets for machinery & factory equipment
A130: 7611400 | B130: Depreciation-Lease Machinery & equipment | C130: 7611400 | D130: 7611400 | E130: MFG | F130: MFG-7611400 | G130: 701 | H130: the amount of depreciation of tangible assets for machinery & factory equipment (Leases)
... A166: 7781113 | B166: Expatriate fee Tax (BADORA) | C166: 7781113 | D166: 7781113 | E166: MFG | F166: MFG-7781113 | G166: 999 | H166: Tax income from expatriete
A167: 8291101 | B167: Others - Miscellaneous Waste | C167: 8291101 | D167: 8291101 | E167: OTH | F167: OTH-8291101
A168: 8291102 | B168: Others - Miscellaneous Tax | C168: 8291102 | D168: 8291102 | E168: OTH | F168: OTH-8291102
A169: 8291201 | B169: Others - Sport Activity | C169: 8291201 | D169: 8291201 | E169: OTH | F169: OTH-8291201
A170: 8291202 | B170: Others - Retribution / Garbage Cost | C170: 8291202 | D170: 8291202 | E170: OTH | F170: OTH-8291202
A171: 8291203 | B171: Others - Miscellaneous Non Operational Expense | C171: 8291203 | D171: 8291203 | E171: OTH | F171: OTH-8291203
A172: 8191101 | B172: Other Income | C172: 8191101 | D172: 8191101 | E172: OTH | F172: OTH-8191101
A173: 8413101 | B173: Interest expenses - Lease | C173: 8413101 | E173: OTH | F173: OTH-8413101

Sheet Priority
A1: Priority Code | B1: Priority Name | C1: Description
A2: A | B2: Must | C2: If this is not done, the company or our team cannot continue its business.
A3: B | B3: Want to | C3: We want to do it as a team this term. we need it.
A4: C | B4: Challenge | C4: We want to do it for this term or the future. But it doesn't matter if it's not this term.

Sheet Password
A1: Password protect sheet = budget
