Workbook
Name __j102: #REF!
Name __j102: #REF!
Name _1: #N/A
Name _j102: #REF!
Name _j102: #REF!
Name aa: #REF!
Name AB: #REF!
Name ai: #REF!
Name as: #REF!
Name assit: #REF!
Name b: #REF!
Name BC: #REF!
Name BI: #REF!
Name BO: #REF!
Name cc: #REF!
Name CH: #REF!
Name CI: #REF!
Name Ck_for: #REF!
Name Ck_in: #REF!
Name Ck_out: #REF!
Name d: #REF!
Name dd: #REF!
Name DF: #REF!
Name e: #REF!
Name ee: #REF!
Name eXCRATE: #REF!
Name exrate: #REF!
Name F: #REF!
Name fcb: #REF!
Name FG: #REF!
Name g: #REF!
Name gg: #REF!
Name HF: #REF!
Name kissa: #REF!
Name kissakei: #REF!
Name kk: #REF!
Name kkk: #REF!
Name kkkk: #REF!
Name l: #REF!
Name L_01: #REF!
Name LIA: #REF!
Name LILI: #REF!
Name LINA: #REF!
Name m: #REF!
Name Manufacturing: #REF!
Name MR: #REF!
Name nittk: #REF!
Name nittk_ok: #REF!
Name nittoukei: #REF!
Name PRINT_AREA_MI: #REF!
Name PRINT_AREA_MI: #REF!
Name PRINT_TITLES_MI: #REF!
Name ry: #REF!
Name ryohikei: #REF!
Name S: #REF!
Name sais: #REF!
Name saisyuu: #REF!
Name se: #REF!
Name sett: #REF!
Name setta: #REF!

Sheet Upload
A1: BUDGET TYPE | B1: Section Code (From) | C1: Section Name (From/Who Prepare) | D1: Section Code (To) | E1: Section Name (To/Who Use The Cost) | F1: COA-ID | G1: COA NAME | H1: DESCRIPTION | I1: GROUP SECTION | J1: GROUP COST | K1: =$AI$1 & "_" & "10" -> 2021_10 | L1: =$AI$1 & "_" & "11" -> 2021_11 | M1: =$AI$1 & "_" & "12" -> 2021_12 | N1: =$AI$1 + 1 & "_" & "01" -> 2022_01 | O1: =$AI$1 + 1 & "_" & "02" -> 2022_02 | P1: =$AI$1 + 1 & "_" & "03" -> 2022_03 | Q1: =$AI$1 + 1 & "_" & "04" -> 2022_04 | R1: =$AI$1 + 1 & "_" & "05" -> 2022_05 | S1: =$AI$1 + 1 & "_" & "06" -> 2022_06 | T1: =$AI$1 + 1 & "_" & "07" -> 2022_07 | U1: =$AI$1 + 1 & "_" & "08" -> 2022_08 | V1: =$AI$1 + 1 & "_" & "09" -> 2022_09 | W1: =$AI$1 + 1 & "_" & "10" -> 2022_10 | X1: =$AI$1 + 1 & "_" & "11" -> 2022_11 | Y1: =$AI$1 + 1 & "_" & "12" -> 2022_12 | Z1: =$AI$1 + 2 & "_" & "01" -> 2023_01 | AA1: =$AI$1 + 2& "_" & "02" -> 2023_02 | AB1: =$AI$1 + 2 & "_" & "03" -> 2023_03 | AC1: ="TOTAL FY1" & RIGHT(AI1 + 1,2) -> TOTAL FY122 | AD1: ="TOTAL FY1" & RIGHT(AI1 + 2,2) -> TOTAL FY123 | AE1: ="TOTAL FY1" & RIGHT(AI1 + 3,2) -> TOTAL FY124 | AF1: ="TOTAL FY1" & RIGHT(AI1 + 4,2) -> TOTAL FY125 | AG1: Priority Category | AH1: BUDGET NO. | AI1: 2021
A2: BEX | B2: =_xlfn.IFNA(VLOOKUP(C2,Master!$J:$K,2,0),"") -> B1000 | C2: Top Management | D2: =_xlfn.IFNA(VLOOKUP(E2,Master!$J:$K,2,0),"") -> B1000 | E2: Top Management | F2: =_xlfn.IFNA(VLOOKUP(G2,Master!B:C,2,0),"") -> 7781112 | G2: Expatriate expenses exclude labor cost | H2: School fee Aoki san's family | I2: =_xlfn.IFNA(VLOOKUP(E2,Master!$J:$M,4,0),"") -> ADM | J2: =_xlfn.IFNA(VLOOKUP($E2,Master!$J:$M,3,0),"") -> SGA | R2: 57600000 | AC2: =SUM(K2:P2) -> 0 | AD2: =SUM(Q2:AB2) -> 57600000 | AE2: 57600000 | AF2: 57600000 | AG2: A
A3: BEX | B3: =_xlfn.IFNA(VLOOKUP(C3,Master!$J:$K,2,0),"") -> B1000 | C3: Top Management | D3: =_xlfn.IFNA(VLOOKUP(E3,Master!$J:$K,2,0),"") -> B1000 | E3: Top Management | F3: =_xlfn.IFNA(VLOOKUP(G3,Master!B:C,2,0),"") -> 7781112 | G3: Expatriate expenses exclude labor cost | H3: School bus fee Aoki san's family | I3: =_xlfn.IFNA(VLOOKUP(E3,Master!$J:$M,4,0),"") -> ADM | J3: =_xlfn.IFNA(VLOOKUP($E3,Master!$J:$M,3,0),"") -> SGA | R3: 45000000 | AC3: =SUM(K3:P3) -> 0 | AD3: =SUM(Q3:AB3) -> 45000000 | AE3: 45000000 | AF3: 45000000 | AG3: A
A4: BEX | B4: =_xlfn.IFNA(VLOOKUP(C4,Master!$J:$K,2,0),"") -> B1000 | C4: Top Management | D4: =_xlfn.IFNA(VLOOKUP(E4,Master!$J:$K,2,0),"") -> B1000 | E4: Top Management | F4: =_xlfn.IFNA(VLOOKUP(G4,Master!B:C,2,0),"") -> 7651103 | G4: Travel Expense-Oversea | H4: Thaiand for budget fright [2N3D]_Aoki | I4: =_xlfn.IFNA(VLOOKUP(E4,Master!$J:$M,4,0),"") -> ADM | J4: =_xlfn.IFNA(VLOOKUP($E4,Master!$J:$M,3,0),"") -> SGA | Z4: 7100000 | AC4: =SUM(K4:P4) -> 0 | AD4: =SUM(Q4:AB4) -> 7100000 | AE4: 7100000 | AF4: 7100000 | AG4: A
A5: BEX | B5: =_xlfn.IFNA(VLOOKUP(C5,Master!$J:$K,2,0),"") -> B1000 | C5: Top Management | D5: =_xlfn.IFNA(VLOOKUP(E5,Master!$J:$K,2,0),"") -> B1000 | E5: Top Management | F5: =_xlfn.IFNA(VLOOKUP(G5,Master!B:C,2,0),"") -> 7651103 | G5: Travel Expense-Oversea | H5: Thaiand for budget hotel [2N3D]_Aoki | I5: =_xlfn.IFNA(VLOOKUP(E5,Master!$J:$M,4,0),"") -> ADM | J5: =_xlfn.IFNA(VLOOKUP($E5,Master!$J:$M,3,0),"") -> SGA | Z5: =1060000*2 -> 2120000 | AC5: =SUM(K5:P5) -> 0 | AD5: =SUM(Q5:AB5) -> 2120000 | AE5: 2120000 | AF5: 2120000 | AG5: A
A6: BEX | B6: =_xlfn.IFNA(VLOOKUP(C6,Master!$J:$K,2,0),"") -> B1000 | C6: Top Management | D6: =_xlfn.IFNA(VLOOKUP(E6,Master!$J:$K,2,0),"") -> B1000 | E6: Top Management | F6: =_xlfn.IFNA(VLOOKUP(G6,Master!B:C,2,0),"") -> 7651103 | G6: Travel Expense-Oversea | H6: Thaiand for budget daily fee [2N3D]_Aoki | I6: =_xlfn.IFNA(VLOOKUP(E6,Master!$J:$M,4,0),"") -> ADM | J6: =_xlfn.IFNA(VLOOKUP($E6,Master!$J:$M,3,0),"") -> SGA | Z6: =496202*3+170126*3 -> 1998984 | AC6: =SUM(K6:P6) -> 0 | AD6: =SUM(Q6:AB6) -> 1998984 | AE6: 1998984 | AF6: 1998984 | AG6: A
A7: BEX | B7: =_xlfn.IFNA(VLOOKUP(C7,Master!$J:$K,2,0),"") -> B1000 | C7: Top Management | D7: =_xlfn.IFNA(VLOOKUP(E7,Master!$J:$K,2,0),"") -> B1000 | E7: Top Management | F7: =_xlfn.IFNA(VLOOKUP(G7,Master!B:C,2,0),"") -> 7651103 | G7: Travel Expense-Oversea | H7: Thailand for manager meeting fright [3N4D]_Aoki | I7: =_xlfn.IFNA(VLOOKUP(E7,Master!$J:$M,4,0),"") -> ADM | J7: =_xlfn.IFNA(VLOOKUP($E7,Master!$J:$M,3,0),"") -> SGA | AB7: 7100000 | AC7: =SUM(K7:P7) -> 0 | AD7: =SUM(Q7:AB7) -> 7100000 | AE7: 7100000 | AF7: 7100000 | AG7: A
A8: BEX | B8: =_xlfn.IFNA(VLOOKUP(C8,Master!$J:$K,2,0),"") -> B1000 | C8: Top Management | D8: =_xlfn.IFNA(VLOOKUP(E8,Master!$J:$K,2,0),"") -> B1000 | E8: Top Management | F8: =_xlfn.IFNA(VLOOKUP(G8,Master!B:C,2,0),"") -> 7651103 | G8: Travel Expense-Oversea | H8: Thaiand for manager meeting hotel [3N4D]_Aoki | I8: =_xlfn.IFNA(VLOOKUP(E8,Master!$J:$M,4,0),"") -> ADM | J8: =_xlfn.IFNA(VLOOKUP($E8,Master!$J:$M,3,0),"") -> SGA | AB8: =1060000*3 -> 3180000 | AC8: =SUM(K8:P8) -> 0 | AD8: =SUM(Q8:AB8) -> 3180000 | AE8: 3180000 | AF8: 3180000 | AG8: A
A9: BEX | B9: =_xlfn.IFNA(VLOOKUP(C9,Master!$J:$K,2,0),"") -> B1000 | C9: Top Management | D9: =_xlfn.IFNA(VLOOKUP(E9,Master!$J:$K,2,0),"") -> B1000 | E9: Top Management | F9: =_xlfn.IFNA(VLOOKUP(G9,Master!B:C,2,0),"") -> 7651103 | G9: Travel Expense-Oversea | H9: Thaiand for manager meeting daily fee [3N4D]_Aoki | I9: =_xlfn.IFNA(VLOOKUP(E9,Master!$J:$M,4,0),"") -> ADM | J9: =_xlfn.IFNA(VLOOKUP($E9,Master!$J:$M,3,0),"") -> SGA | AB9: =496202*4+170126*4 -> 2665312 | AC9: =SUM(K9:P9) -> 0 | AD9: =SUM(Q9:AB9) -> 2665312 | AE9: 2665312 | AF9: 2665312 | AG9: A
A10: BEX | B10: =_xlfn.IFNA(VLOOKUP(C10,Master!$J:$K,2,0),"") -> B1000 | C10: Top Management | D10: =_xlfn.IFNA(VLOOKUP(E10,Master!$J:$K,2,0),"") -> B1000 | E10: Top Management | F10: =_xlfn.IFNA(VLOOKUP(G10,Master!B:C,2,0),"") -> 7651103 | G10: Travel Expense-Oversea | H10: Thailand for sales meeting fright [3N4D]_Aoki | I10: =_xlfn.IFNA(VLOOKUP(E10,Master!$J:$M,4,0),"") -> ADM | J10: =_xlfn.IFNA(VLOOKUP($E10,Master!$J:$M,3,0),"") -> SGA | R10: 7100000 | W10: 7100000 | AC10: =SUM(K10:P10) -> 0 | AD10: =SUM(Q10:AB10) -> 14200000 | AE10: 14200000 | AF10: 14200000 | AG10: A
A11: BEX | B11: =_xlfn.IFNA(VLOOKUP(C11,Master!$J:$K,2,0),"") -> B1000 | C11: Top Management | D11: =_xlfn.IFNA(VLOOKUP(E11,Master!$J:$K,2,0),"") -> B1000 | E11: Top Management | F11: =_xlfn.IFNA(VLOOKUP(G11,Master!B:C,2,0),"") -> 7651103 | G11: Travel Expense-Oversea | H11: Thaiand for sales meeting hotel [3N4D]_Aoki | I11: =_xlfn.IFNA(VLOOKUP(E11,Master!$J:$M,4,0),"") -> ADM | J11: =_xlfn.IFNA(VLOOKUP($E11,Master!$J:$M,3,0),"") -> SGA | R11: =1060000*3 -> 3180000 | W11: =1060000*3 -> 3180000 | AC11: =SUM(K11:P11) -> 0 | AD11: =SUM(Q11:AB11) -> 6360000 | AE11: 6360000 | AF11: 6360000 | AG11: A
A12: BEX | B12: =_xlfn.IFNA(VLOOKUP(C12,Master!$J:$K,2,0),"") -> B1000 | C12: Top Management | D12: =_xlfn.IFNA(VLOOKUP(E12,Master!$J:$K,2,0),"") -> B1000 | E12: Top Management | F12: =_xlfn.IFNA(VLOOKUP(G12,Master!B:C,2,0),"") -> 7651103 | G12: Travel Expense-Oversea | H12: Thaiand for sales meeting daily fee [3N4D]_Aoki | I12: =_xlfn.IFNA(VLOOKUP(E12,Master!$J:$M,4,0),"") -> ADM | J12: =_xlfn.IFNA(VLOOKUP($E12,Master!$J:$M,3,0),"") -> SGA | R12: =496202*4+170126*4 -> 2665312 | W12: =496202*4+170126*4 -> 2665312 | AC12: =SUM(K12:P12) -> 0 | AD12: =SUM(Q12:AB12) -> 5330624 | AE12: 5330624 | AF12: 5330624 | AG12: A
A13: BEX | B13: =_xlfn.IFNA(VLOOKUP(C13,Master!$J:$K,2,0),"") -> B1000 | C13: Top Management | D13: =_xlfn.IFNA(VLOOKUP(E13,Master!$J:$K,2,0),"") -> B1000 | E13: Top Management | F13: =_xlfn.IFNA(VLOOKUP(G13,Master!B:C,2,0),"") -> 7651103 | G13: Travel Expense-Oversea | H13: Thailand for SVB fright [3N4D]_Aoki | I13: =_xlfn.IFNA(VLOOKUP(E13,Master!$J:$M,4,0),"") -> ADM | J13: =_xlfn.IFNA(VLOOKUP($E13,Master!$J:$M,3,0),"") -> SGA | Y13: 7100000 | AC13: =SUM(K13:P13) -> 0 | AD13: =SUM(Q13:AB13) -> 7100000 | AE13: 7100000 | AF13: 7100000 | AG13: A
A14: BEX | B14: =_xlfn.IFNA(VLOOKUP(C14,Master!$J:$K,2,0),"") -> B1000 | C14: Top Management | D14: =_xlfn.IFNA(VLOOKUP(E14,Master!$J:$K,2,0),"") -> B1000 | E14: Top Management | F14: =_xlfn.IFNA(VLOOKUP(G14,Master!B:C,2,0),"") -> 7651103 | G14: Travel Expense-Oversea | H14: Thaiand for SVB hotel [3N4D]_Aoki | I14: =_xlfn.IFNA(VLOOKUP(E14,Master!$J:$M,4,0),"") -> ADM | J14: =_xlfn.IFNA(VLOOKUP($E14,Master!$J:$M,3,0),"") -> SGA | Y14: =1060000*3 -> 3180000 | AC14: =SUM(K14:P14) -> 0 | AD14: =SUM(Q14:AB14) -> 3180000 | AE14: 3180000 | AF14: 3180000 | AG14: A
A15: BEX | B15: =_xlfn.IFNA(VLOOKUP(C15,Master!$J:$K,2,0),"") -> B1000 | C15: Top Management | D15: =_xlfn.IFNA(VLOOKUP(E15,Master!$J:$K,2,0),"") -> B1000 | E15: Top Management | F15: =_xlfn.IFNA(VLOOKUP(G15,Master!B:C,2,0),"") -> 7651103 | G15: Travel Expense-Oversea | H15: Thaiand for SVB daily fee [3N4D]_Aoki | I15: =_xlfn.IFNA(VLOOKUP(E15,Master!$J:$M,4,0),"") -> ADM | J15: =_xlfn.IFNA(VLOOKUP($E15,Master!$J:$M,3,0),"") -> SGA | Y15: =496202*4+170126*4 -> 2665312 | AC15: =SUM(K15:P15) -> 0 | AD15: =SUM(Q15:AB15) -> 2665312 | AE15: 2665312 | AF15: 2665312 | AG15: A
A16: BEX | B16: =_xlfn.IFNA(VLOOKUP(C16,Master!$J:$K,2,0),"") -> B1000 | C16: Top Management | D16: =_xlfn.IFNA(VLOOKUP(E16,Master!$J:$K,2,0),"") -> B1000 | E16: Top Management | F16: =_xlfn.IFNA(VLOOKUP(G16,Master!B:C,2,0),"") -> 7651102 | G16: Travel Expense-Domestic | H16: Solo fright [1N2D]_Aoki | I16: =_xlfn.IFNA(VLOOKUP(E16,Master!$J:$M,4,0),"") -> ADM | J16: =_xlfn.IFNA(VLOOKUP($E16,Master!$J:$M,3,0),"") -> SGA | R16: 823000 | W16: 823000 | AC16: =SUM(K16:P16) -> 0 | AD16: =SUM(Q16:AB16) -> 1646000 | AE16: 823000 | AF16: 823000 | AG16: A
A17: BEX | B17: =_xlfn.IFNA(VLOOKUP(C17,Master!$J:$K,2,0),"") -> B1000 | C17: Top Management | D17: =_xlfn.IFNA(VLOOKUP(E17,Master!$J:$K,2,0),"") -> B1000 | E17: Top Management | F17: =_xlfn.IFNA(VLOOKUP(G17,Master!B:C,2,0),"") -> 7651102 | G17: Travel Expense-Domestic | H17: Solo hotel [1N2D]_Aoki | I17: =_xlfn.IFNA(VLOOKUP(E17,Master!$J:$M,4,0),"") -> ADM | J17: =_xlfn.IFNA(VLOOKUP($E17,Master!$J:$M,3,0),"") -> SGA | R17: 900000 | W17: 900000 | AC17: =SUM(K17:P17) -> 0 | AD17: =SUM(Q17:AB17) -> 1800000 | AE17: 900000 | AF17: 900000 | AG17: A
A18: BEX | B18: =_xlfn.IFNA(VLOOKUP(C18,Master!$J:$K,2,0),"") -> B1000 | C18: Top Management | D18: =_xlfn.IFNA(VLOOKUP(E18,Master!$J:$K,2,0),"") -> B1000 | E18: Top Management | F18: =_xlfn.IFNA(VLOOKUP(G18,Master!B:C,2,0),"") -> 7651102 | G18: Travel Expense-Domestic | H18: Solo daily fee [1N2D]_Aoki | I18: =_xlfn.IFNA(VLOOKUP(E18,Master!$J:$M,4,0),"") -> ADM | J18: =_xlfn.IFNA(VLOOKUP($E18,Master!$J:$M,3,0),"") -> SGA | R18: 700000 | W18: 700000 | AC18: =SUM(K18:P18) -> 0 | AD18: =SUM(Q18:AB18) -> 1400000 | AE18: 700000 | AF18: 700000 | AG18: A
A19: BEX | B19: =_xlfn.IFNA(VLOOKUP(C19,Master!$J:$K,2,0),"") -> B1000 | C19: Top Management | D19: =_xlfn.IFNA(VLOOKUP(E19,Master!$J:$K,2,0),"") -> B1000 | E19: Top Management | F19: =_xlfn.IFNA(VLOOKUP(G19,Master!B:C,2,0),"") -> 7651102 | G19: Travel Expense-Domestic | H19: Medan fright [1N2D]_Aoki | I19: =_xlfn.IFNA(VLOOKUP(E19,Master!$J:$M,4,0),"") -> ADM | J19: =_xlfn.IFNA(VLOOKUP($E19,Master!$J:$M,3,0),"") -> SGA | S19: 1185000 | X19: 1185000 | AC19: =SUM(K19:P19) -> 0 | AD19: =SUM(Q19:AB19) -> 2370000 | AE19: 1185000 | AF19: 1185000 | AG19: A
A20: BEX | B20: =_xlfn.IFNA(VLOOKUP(C20,Master!$J:$K,2,0),"") -> B1000 | C20: Top Management | D20: =_xlfn.IFNA(VLOOKUP(E20,Master!$J:$K,2,0),"") -> B1000 | E20: Top Management | F20: =_xlfn.IFNA(VLOOKUP(G20,Master!B:C,2,0),"") -> 7651102 | G20: Travel Expense-Domestic | H20: Medan hotel [1N2D]_Aoki | I20: =_xlfn.IFNA(VLOOKUP(E20,Master!$J:$M,4,0),"") -> ADM | J20: =_xlfn.IFNA(VLOOKUP($E20,Master!$J:$M,3,0),"") -> SGA | S20: 900000 | X20: 900000 | AC20: =SUM(K20:P20) -> 0 | AD20: =SUM(Q20:AB20) -> 1800000 | AE20: 900000 | AF20: 900000 | AG20: A
A21: BEX | B21: =_xlfn.IFNA(VLOOKUP(C21,Master!$J:$K,2,0),"") -> B1000 | C21: Top Management | D21: =_xlfn.IFNA(VLOOKUP(E21,Master!$J:$K,2,0),"") -> B1000 | E21: Top Management | F21: =_xlfn.IFNA(VLOOKUP(G21,Master!B:C,2,0),"") -> 7651102 | G21: Travel Expense-Domestic | H21: Medan daily fee [1N2D]_Aoki | I21: =_xlfn.IFNA(VLOOKUP(E21,Master!$J:$M,4,0),"") -> ADM | J21: =_xlfn.IFNA(VLOOKUP($E21,Master!$J:$M,3,0),"") -> SGA | S21: 700000 | X21: 700000 | AC21: =SUM(K21:P21) -> 0 | AD21: =SUM(Q21:AB21) -> 1400000 | AE21: 700000 | AF21: 700000 | AG21: A
A22: BEX | B22: =_xlfn.IFNA(VLOOKUP(C22,Master!$J:$K,2,0),"") -> B1000 | C22: Top Management | D22: =_xlfn.IFNA(VLOOKUP(E22,Master!$J:$K,2,0),"") -> B1000 | E22: Top Management | F22: =_xlfn.IFNA(VLOOKUP(G22,Master!B:C,2,0),"") -> 7651102 | G22: Travel Expense-Domestic | H22: Parenbang fright [1N2D]_Aoki | I22: =_xlfn.IFNA(VLOOKUP(E22,Master!$J:$M,4,0),"") -> ADM | J22: =_xlfn.IFNA(VLOOKUP($E22,Master!$J:$M,3,0),"") -> SGA | T22: 838000 | Y22: 838000 | AC22: =SUM(K22:P22) -> 0 | AD22: =SUM(Q22:AB22) -> 1676000 | AE22: 838000 | AF22: 838000 | AG22: A
A23: BEX | B23: =_xlfn.IFNA(VLOOKUP(C23,Master!$J:$K,2,0),"") -> B1000 | C23: Top Management | D23: =_xlfn.IFNA(VLOOKUP(E23,Master!$J:$K,2,0),"") -> B1000 | E23: Top Management | F23: =_xlfn.IFNA(VLOOKUP(G23,Master!B:C,2,0),"") -> 7651102 | G23: Travel Expense-Domestic | H23: Parenbang hotel [1N2D]_Aoki | I23: =_xlfn.IFNA(VLOOKUP(E23,Master!$J:$M,4,0),"") -> ADM | J23: =_xlfn.IFNA(VLOOKUP($E23,Master!$J:$M,3,0),"") -> SGA | T23: 900000 | Y23: 900000 | AC23: =SUM(K23:P23) -> 0 | AD23: =SUM(Q23:AB23) -> 1800000 | AE23: 900000 | AF23: 900000 | AG23: A
A24: BEX | B24: =_xlfn.IFNA(VLOOKUP(C24,Master!$J:$K,2,0),"") -> B1000 | C24: Top Management | D24: =_xlfn.IFNA(VLOOKUP(E24,Master!$J:$K,2,0),"") -> B1000 | E24: Top Management | F24: =_xlfn.IFNA(VLOOKUP(G24,Master!B:C,2,0),"") -> 7651102 | G24: Travel Expense-Domestic | H24: Parenbang daily fee [1N2D]_Aoki | I24: =_xlfn.IFNA(VLOOKUP(E24,Master!$J:$M,4,0),"") -> ADM | J24: =_xlfn.IFNA(VLOOKUP($E24,Master!$J:$M,3,0),"") -> SGA | T24: 700000 | Y24: 700000 | AC24: =SUM(K24:P24) -> 0 | AD24: =SUM(Q24:AB24) -> 1400000 | AE24: 700000 | AF24: 700000 | AG24: A
A25: BEX | B25: =_xlfn.IFNA(VLOOKUP(C25,Master!$J:$K,2,0),"") -> B1000 | C25: Top Management | D25: =_xlfn.IFNA(VLOOKUP(E25,Master!$J:$K,2,0),"") -> B1000 | E25: Top Management | F25: =_xlfn.IFNA(VLOOKUP(G25,Master!B:C,2,0),"") -> 7651102 | G25: Travel Expense-Domestic | H25: Karimantan fright [1N2D]_Aoki | I25: =_xlfn.IFNA(VLOOKUP(E25,Master!$J:$M,4,0),"") -> ADM | J25: =_xlfn.IFNA(VLOOKUP($E25,Master!$J:$M,3,0),"") -> SGA | U25: 1092000 | AA25: 1092000 | AC25: =SUM(K25:P25) -> 0 | AD25: =SUM(Q25:AB25) -> 2184000 | AE25: 1092000 | AF25: 1092000 | AG25: A
A26: BEX | B26: =_xlfn.IFNA(VLOOKUP(C26,Master!$J:$K,2,0),"") -> B1000 | C26: Top Management | D26: =_xlfn.IFNA(VLOOKUP(E26,Master!$J:$K,2,0),"") -> B1000 | E26: Top Management | F26: =_xlfn.IFNA(VLOOKUP(G26,Master!B:C,2,0),"") -> 7651102 | G26: Travel Expense-Domestic | H26: Karimantan hotel [1N2D]_Aoki | I26: =_xlfn.IFNA(VLOOKUP(E26,Master!$J:$M,4,0),"") -> ADM | J26: =_xlfn.IFNA(VLOOKUP($E26,Master!$J:$M,3,0),"") -> SGA | U26: 900000 | AA26: 900000 | AC26: =SUM(K26:P26) -> 0 | AD26: =SUM(Q26:AB26) -> 1800000 | AE26: 900000 | AF26: 900000 | AG26: A
A27: BEX | B27: =_xlfn.IFNA(VLOOKUP(C27,Master!$J:$K,2,0),"") -> B1000 | C27: Top Management | D27: =_xlfn.IFNA(VLOOKUP(E27,Master!$J:$K,2,0),"") -> B1000 | E27: Top Management | F27: =_xlfn.IFNA(VLOOKUP(G27,Master!B:C,2,0),"") -> 7651102 | G27: Travel Expense-Domestic | H27: Karimantan daily fee [1N2D]_Aoki | I27: =_xlfn.IFNA(VLOOKUP(E27,Master!$J:$M,4,0),"") -> ADM | J27: =_xlfn.IFNA(VLOOKUP($E27,Master!$J:$M,3,0),"") -> SGA | U27: 700000 | AA27: 700000 | AC27: =SUM(K27:P27) -> 0 | AD27: =SUM(Q27:AB27) -> 1400000 | AE27: 700000 | AF27: 700000 | AG27: A
A28: BEX | B28: =_xlfn.IFNA(VLOOKUP(C28,Master!$J:$K,2,0),"") -> B1000 | C28: Top Management | D28: =_xlfn.IFNA(VLOOKUP(E28,Master!$J:$K,2,0),"") -> B1000 | E28: Top Management | F28: =_xlfn.IFNA(VLOOKUP(G28,Master!B:C,2,0),"") -> 7651102 | G28: Travel Expense-Domestic | H28: Bundun hotel [1N2D]_Aoki | I28: =_xlfn.IFNA(VLOOKUP(E28,Master!$J:$M,4,0),"") -> ADM | J28: =_xlfn.IFNA(VLOOKUP($E28,Master!$J:$M,3,0),"") -> SGA | V28: 900000 | AB28: 900000 | AC28: =SUM(K28:P28) -> 0 | AD28: =SUM(Q28:AB28) -> 1800000 | AE28: 900000 | AF28: 900000 | AG28: A
A29: BEX | B29: =_xlfn.IFNA(VLOOKUP(C29,Master!$J:$K,2,0),"") -> B1000 | C29: Top Management | D29: =_xlfn.IFNA(VLOOKUP(E29,Master!$J:$K,2,0),"") -> B1000 | E29: Top Management | F29: =_xlfn.IFNA(VLOOKUP(G29,Master!B:C,2,0),"") -> 7651102 | G29: Travel Expense-Domestic | H29: Bundun daily fee [1N2D]_Aoki | I29: =_xlfn.IFNA(VLOOKUP(E29,Master!$J:$M,4,0),"") -> ADM | J29: =_xlfn.IFNA(VLOOKUP($E29,Master!$J:$M,3,0),"") -> SGA | V29: =300000*2+50000*2 -> 700000 | AB29: =300000*2+50000*2 -> 700000 | AC29: =SUM(K29:P29) -> 0 | AD29: =SUM(Q29:AB29) -> 1400000 | AE29: 700000 | AF29: 700000 | AG29: A
A30: BEX | B30: =_xlfn.IFNA(VLOOKUP(C30,Master!$J:$K,2,0),"") -> B1000 | C30: Top Management | D30: =_xlfn.IFNA(VLOOKUP(E30,Master!$J:$K,2,0),"") -> B1000 | E30: Top Management | F30: =_xlfn.IFNA(VLOOKUP(G30,Master!B:C,2,0),"") -> 7651101 | G30: Transportation Fee for employee | H30: Toll&Parking_Aoki | I30: =_xlfn.IFNA(VLOOKUP(E30,Master!$J:$M,4,0),"") -> ADM | J30: =_xlfn.IFNA(VLOOKUP($E30,Master!$J:$M,3,0),"") -> SGA | K30: 2000000 | L30: 2000000 | M30: 2000000 | N30: 2000000 | O30: 2000000 | P30: 2000000 | Q30: 2000000 | R30: 2000000 | S30: 2000000 | T30: 2000000 | U30: 2000000 | V30: 2000000 | W30: 2000000 | X30: 2000000 | Y30: 2000000 | Z30: 2000000 | AA30: 2000000 | AB30: 2000000 | AC30: =SUM(K30:P30) -> 12000000 | AD30: =SUM(Q30:AB30) -> 24000000 | AE30: 24000000 | AF30: 24000000 | AG30: A
A31: BEX | B31: =_xlfn.IFNA(VLOOKUP(C31,Master!$J:$K,2,0),"") -> B1000 | C31: Top Management | D31: =_xlfn.IFNA(VLOOKUP(E31,Master!$J:$K,2,0),"") -> B1000 | E31: Top Management | F31: =_xlfn.IFNA(VLOOKUP(G31,Master!B:C,2,0),"") -> 7651101 | G31: Transportation Fee for employee | H31: Gasoline_Aoki | I31: =_xlfn.IFNA(VLOOKUP(E31,Master!$J:$M,4,0),"") -> ADM | J31: =_xlfn.IFNA(VLOOKUP($E31,Master!$J:$M,3,0),"") -> SGA | K31: 2000000 | L31: 2000000 | M31: 2000000 | N31: 2000000 | O31: 2000000 | P31: 2000000 | Q31: 2000000 | R31: 2000000 | S31: 2000000 | T31: 2000000 | U31: 2000000 | V31: 2000000 | W31: 2000000 | X31: 2000000 | Y31: 2000000 | Z31: 2000000 | AA31: 2000000 | AB31: 2000000 | AC31: =SUM(K31:P31) -> 12000000 | AD31: =SUM(Q31:AB31) -> 24000000 | AE31: 24000000 | AF31: 24000000 | AG31: A
A32: BEX | B32: =_xlfn.IFNA(VLOOKUP(C32,Master!$J:$K,2,0),"") -> B1000 | C32: Top Management | D32: =_xlfn.IFNA(VLOOKUP(E32,Master!$J:$K,2,0),"") -> B1000 | E32: Top Management | F32: =_xlfn.IFNA(VLOOKUP(G32,Master!B:C,2,0),"") -> 7781103 | G32: Publishing Expense | H32: NNA Daily for BOD | I32: =_xlfn.IFNA(VLOOKUP(E32,Master!$J:$M,4,0),"") -> ADM | J32: =_xlfn.IFNA(VLOOKUP($E32,Master!$J:$M,3,0),"") -> SGA | K32: 2160000 | L32: 2160000 | M32: 2160000 | N32: 2160000 | O32: 2160000 | P32: 2160000 | Q32: 2160000 | R32: 2160000 | S32: 2160000 | T32: 2160000 | U32: 2160000 | V32: 2160000 | W32: 2160000 | X32: 2160000 | Y32: 2160000 | Z32: 2160000 | AA32: 2160000 | AB32: 2160000 | AC32: =SUM(K32:P32) -> 12960000 | AD32: =SUM(Q32:AB32) -> 25920000 | AE32: 25920000 | AF32: 25920000 | AG32: A
A33: BEX | B33: =_xlfn.IFNA(VLOOKUP(C33,Master!$J:$K,2,0),"") -> B1000 | C33: Top Management | D33: =_xlfn.IFNA(VLOOKUP(E33,Master!$J:$K,2,0),"") -> B1000 | E33: Top Management | F33: =_xlfn.IFNA(VLOOKUP(G33,Master!B:C,2,0),"") -> 7781103 | G33: Publishing Expense | H33: The Daily Jakarta Shimbun | I33: =_xlfn.IFNA(VLOOKUP(E33,Master!$J:$M,4,0),"") -> ADM | J33: =_xlfn.IFNA(VLOOKUP($E33,Master!$J:$M,3,0),"") -> SGA | K33: 300000 | L33: 300000 | M33: 300000 | N33: 300000 | O33: 300000 | P33: 300000 | Q33: 300000 | R33: 300000 | S33: 300000 | T33: 300000 | U33: 300000 | V33: 300000 | W33: 300000 | X33: 300000 | Y33: 300000 | Z33: 300000 | AA33: 300000 | AB33: 300000 | AC33: =SUM(K33:P33) -> 1800000 | AD33: =SUM(Q33:AB33) -> 3600000 | AE33: 3600000 | AF33: 3600000 | AG33: A
A34: BEX | B34: =_xlfn.IFNA(VLOOKUP(C34,Master!$J:$K,2,0),"") -> B1000 | C34: Top Management | D34: =_xlfn.IFNA(VLOOKUP(E34,Master!$J:$K,2,0),"") -> B1000 | E34: Top Management | F34: =_xlfn.IFNA(VLOOKUP(G34,Master!B:C,2,0),"") -> 7781103 | G34: Publishing Expense | H34: Annual corporate member fee JJC | I34: =_xlfn.IFNA(VLOOKUP(E34,Master!$J:$M,4,0),"") -> ADM | J34: =_xlfn.IFNA(VLOOKUP($E34,Master!$J:$M,3,0),"") -> SGA | K34: 4000000 | L34: 4000000 | M34: 4000000 | N34: 4000000 | O34: 4000000 | P34: 4000000 | Q34: 4000000 | R34: 4000000 | S34: 4000000 | T34: 4000000 | U34: 4000000 | V34: 4000000 | W34: 4000000 | X34: 4000000 | Y34: 4000000 | Z34: 4000000 | AA34: 4000000 | AB34: 4000000 | AC34: =SUM(K34:P34) -> 24000000 | AD34: =SUM(Q34:AB34) -> 48000000 | AE34: 48000000 | AF34: 48000000 | AG34: A
A35: BEX | B35: =_xlfn.IFNA(VLOOKUP(C35,Master!$J:$K,2,0),"") -> B1000 | C35: Top Management | D35: =_xlfn.IFNA(VLOOKUP(E35,Master!$J:$K,2,0),"") -> B1000 | E35: Top Management | F35: =_xlfn.IFNA(VLOOKUP(G35,Master!B:C,2,0),"") -> 7781103 | G35: Publishing Expense | H35: Annual fee for The Japanese School | I35: =_xlfn.IFNA(VLOOKUP(E35,Master!$J:$M,4,0),"") -> ADM | J35: =_xlfn.IFNA(VLOOKUP($E35,Master!$J:$M,3,0),"") -> SGA | K35: 330000 | L35: 330000 | M35: 330000 | N35: 330000 | O35: 330000 | P35: 330000 | Q35: 330000 | R35: 330000 | S35: 330000 | T35: 330000 | U35: 330000 | V35: 330000 | W35: 330000 | X35: 330000 | Y35: 330000 | Z35: 330000 | AA35: 330000 | AB35: 330000 | AC35: =SUM(K35:P35) -> 1980000 | AD35: =SUM(Q35:AB35) -> 3960000 | AE35: 3960000 | AF35: 3960000 | AG35: A
A36: BEX | B36: =_xlfn.IFNA(VLOOKUP(C36,Master!$J:$K,2,0),"") -> B1000 | C36: Top Management | D36: =_xlfn.IFNA(VLOOKUP(E36,Master!$J:$K,2,0),"") -> B1000 | E36: Top Management | F36: =_xlfn.IFNA(VLOOKUP(G36,Master!B:C,2,0),"") -> 7781103 | G36: Publishing Expense | H36: Membership Bogor Raya Golf_Aoki | I36: =_xlfn.IFNA(VLOOKUP(E36,Master!$J:$M,4,0),"") -> ADM | J36: =_xlfn.IFNA(VLOOKUP($E36,Master!$J:$M,3,0),"") -> SGA | K36: 2100000 | L36: 2100000 | M36: 2100000 | N36: 2100000 | O36: 2100000 | P36: 2100000 | Q36: 2100000 | R36: 2100000 | S36: 2100000 | T36: 2100000 | U36: 2100000 | V36: 2100000 | W36: 2100000 | X36: 2100000 | Y36: 2100000 | Z36: 2100000 | AA36: 2100000 | AB36: 2100000 | AC36: =SUM(K36:P36) -> 12600000 | AD36: =SUM(Q36:AB36) -> 25200000 | AE36: 25200000 | AF36: 25200000 | AG36: A
A37: BEX | B37: =_xlfn.IFNA(VLOOKUP(C37,Master!$J:$K,2,0),"") -> B1000 | C37: Top Management | D37: =_xlfn.IFNA(VLOOKUP(E37,Master!$J:$K,2,0),"") -> B1000 | E37: Top Management | F37: =_xlfn.IFNA(VLOOKUP(G37,Master!B:C,2,0),"") -> 7781103 | G37: Publishing Expense | H37: ADM supplier club 2022 | I37: =_xlfn.IFNA(VLOOKUP(E37,Master!$J:$M,4,0),"") -> ADM | J37: =_xlfn.IFNA(VLOOKUP($E37,Master!$J:$M,3,0),"") -> SGA | Q37: 1500000 | AC37: =SUM(K37:P37) -> 0 | AD37: =SUM(Q37:AB37) -> 1500000 | AE37: 1500000 | AF37: 1500000 | AG37: A
A38: BEX | B38: =_xlfn.IFNA(VLOOKUP(C38,Master!$J:$K,2,0),"") -> B1000 | C38: Top Management | D38: =_xlfn.IFNA(VLOOKUP(E38,Master!$J:$K,2,0),"") -> B1000 | E38: Top Management | F38: =_xlfn.IFNA(VLOOKUP(G38,Master!B:C,2,0),"") -> 7781112 | G38: Expatriate expenses exclude labor cost | H38: KITAS renewal exppense_Aoki | I38: =_xlfn.IFNA(VLOOKUP(E38,Master!$J:$M,4,0),"") -> ADM | J38: =_xlfn.IFNA(VLOOKUP($E38,Master!$J:$M,3,0),"") -> SGA | AB38: =9400000*3 -> 28200000 | AC38: =SUM(K38:P38) -> 0 | AD38: =SUM(Q38:AB38) -> 28200000 | AE38: 28200000 | AF38: 28200000 | AG38: A
A39: BEX | B39: =_xlfn.IFNA(VLOOKUP(C39,Master!$J:$K,2,0),"") -> B1000 | C39: Top Management | D39: =_xlfn.IFNA(VLOOKUP(E39,Master!$J:$K,2,0),"") -> B1000 | E39: Top Management | F39: =_xlfn.IFNA(VLOOKUP(G39,Master!B:C,2,0),"") -> 7781112 | G39: Expatriate expenses exclude labor cost | H39: DPKK_Aoki | I39: =_xlfn.IFNA(VLOOKUP(E39,Master!$J:$M,4,0),"") -> ADM | J39: =_xlfn.IFNA(VLOOKUP($E39,Master!$J:$M,3,0),"") -> SGA | K39: 1417720 | L39: 1417720 | M39: 1417720 | N39: 1417720 | O39: 1417720 | P39: 1417720 | Q39: 1417720 | R39: 1417720 | S39: 1417720 | T39: 1417720 | U39: 1417720 | V39: 1417720 | W39: 1417720 | X39: 1417720 | Y39: 1417720 | Z39: 1417720 | AA39: 1417720 | AB39: 1417720 | AC39: =SUM(K39:P39) -> 8506320 | AD39: =SUM(Q39:AB39) -> 17012640 | AE39: 17012640 | AF39: 17012640 | AG39: A
A40: BEX | B40: =_xlfn.IFNA(VLOOKUP(C40,Master!$J:$K,2,0),"") -> B1000 | C40: Top Management | D40: =_xlfn.IFNA(VLOOKUP(E40,Master!$J:$K,2,0),"") -> B1000 | E40: Top Management | F40: =_xlfn.IFNA(VLOOKUP(G40,Master!B:C,2,0),"") -> 7781103 | G40: Publishing Expense | H40: Cooperate card annual fee_BNI_Aoki | I40: =_xlfn.IFNA(VLOOKUP(E40,Master!$J:$M,4,0),"") -> ADM | J40: =_xlfn.IFNA(VLOOKUP($E40,Master!$J:$M,3,0),"") -> SGA | Q40: 600000 | AC40: =SUM(K40:P40) -> 0 | AD40: =SUM(Q40:AB40) -> 600000 | AE40: 600000 | AF40: 600000 | AG40: A
A41: BEX | B41: =_xlfn.IFNA(VLOOKUP(C41,Master!$J:$K,2,0),"") -> B1000 | C41: Top Management | D41: =_xlfn.IFNA(VLOOKUP(E41,Master!$J:$K,2,0),"") -> B1000 | E41: Top Management | F41: =_xlfn.IFNA(VLOOKUP(G41,Master!B:C,2,0),"") -> 7711101 | G41: Communication expenses | H41: Handphone bill & Document shipment_Aoki | I41: =_xlfn.IFNA(VLOOKUP(E41,Master!$J:$M,4,0),"") -> ADM | J41: =_xlfn.IFNA(VLOOKUP($E41,Master!$J:$M,3,0),"") -> SGA | K41: 1000000 | L41: 1000000 | M41: 1000000 | N41: 1000000 | O41: 1000000 | P41: 1000000 | Q41: 1000000 | R41: 1000000 | S41: 1000000 | T41: 1000000 | U41: 1000000 | V41: 1000000 | W41: 1000000 | X41: 1000000 | Y41: 1000000 | Z41: 1000000 | AA41: 1000000 | AB41: 1000000 | AC41: =SUM(K41:P41) -> 6000000 | AD41: =SUM(Q41:AB41) -> 12000000 | AE41: 12000000 | AF41: 12000000 | AG41: A
A42: BEX | B42: =_xlfn.IFNA(VLOOKUP(C42,Master!$J:$K,2,0),"") -> B1000 | C42: Top Management | D42: =_xlfn.IFNA(VLOOKUP(E42,Master!$J:$K,2,0),"") -> B1000 | E42: Top Management | F42: =_xlfn.IFNA(VLOOKUP(G42,Master!B:C,2,0),"") -> 7781107 | G42: Training Expense | H42: Indonesia language_Aoki | I42: =_xlfn.IFNA(VLOOKUP(E42,Master!$J:$M,4,0),"") -> ADM | J42: =_xlfn.IFNA(VLOOKUP($E42,Master!$J:$M,3,0),"") -> SGA | K42: 1500000 | L42: 1500000 | M42: 1500000 | N42: 1500000 | O42: 1500000 | P42: 1500000 | Q42: 1500000 | R42: 1500000 | S42: 1500000 | T42: 1500000 | U42: 1500000 | V42: 1500000 | W42: 1500000 | X42: 1500000 | Y42: 1500000 | Z42: 1500000 | AA42: 1500000 | AB42: 1500000 | AC42: =SUM(K42:P42) -> 9000000 | AD42: =SUM(Q42:AB42) -> 18000000 | AE42: 18000000 | AF42: 18000000 | AG42: A
A43: BEX | B43: =_xlfn.IFNA(VLOOKUP(C43,Master!$J:$K,2,0),"") -> B1000 | C43: Top Management | D43: =_xlfn.IFNA(VLOOKUP(E43,Master!$J:$K,2,0),"") -> B1000 | E43: Top Management | F43: =_xlfn.IFNA(VLOOKUP(G43,Master!B:C,2,0),"") -> 7781107 | G43: Training Expense | H43: Indonesia language_Aoki’s family | I43: =_xlfn.IFNA(VLOOKUP(E43,Master!$J:$M,4,0),"") -> ADM | J43: =_xlfn.IFNA(VLOOKUP($E43,Master!$J:$M,3,0),"") -> SGA | Q43: 1500000 | R43: 1500000 | S43: 1500000 | T43: 1500000 | U43: 1500000 | V43: 1500000 | W43: 1500000 | X43: 1500000 | Y43: 1500000 | Z43: 1500000 | AA43: 1500000 | AB43: 1500000 | AC43: =SUM(K43:P43) -> 0 | AD43: =SUM(Q43:AB43) -> 18000000 | AE43: 18000000 | AF43: 18000000 | AG43: A
A44: BEX | B44: =_xlfn.IFNA(VLOOKUP(C44,Master!$J:$K,2,0),"") -> B1000 | C44: Top Management | D44: =_xlfn.IFNA(VLOOKUP(E44,Master!$J:$K,2,0),"") -> B1000 | E44: Top Management | F44: =_xlfn.IFNA(VLOOKUP(G44,Master!B:C,2,0),"") -> 7641102 | G44: Repair of Equipment | H44: Maintenance_Operational car | I44: =_xlfn.IFNA(VLOOKUP(E44,Master!$J:$M,4,0),"") -> ADM | J44: =_xlfn.IFNA(VLOOKUP($E44,Master!$J:$M,3,0),"") -> SGA | Q44: 1500000 | R44: 1500000 | S44: 1500000 | T44: 1500000 | U44: 1500000 | V44: 1500000 | W44: 1500000 | X44: 1500000 | Y44: 1500000 | Z44: 1500000 | AA44: 1500000 | AB44: 1500000 | AC44: =SUM(K44:P44) -> 0 | AD44: =SUM(Q44:AB44) -> 18000000 | AE44: 18000000 | AF44: 18000000 | AG44: A
A45: BEX | B45: =_xlfn.IFNA(VLOOKUP(C45,Master!$J:$K,2,0),"") -> B1000 | C45: Top Management | D45: =_xlfn.IFNA(VLOOKUP(E45,Master!$J:$K,2,0),"") -> B1000 | E45: Top Management | F45: =_xlfn.IFNA(VLOOKUP(G45,Master!B:C,2,0),"") -> 7661101 | G45: Entertainment | H45: Annual fee_YAMAHA KAI_2022 | I45: =_xlfn.IFNA(VLOOKUP(E45,Master!$J:$M,4,0),"") -> ADM | J45: =_xlfn.IFNA(VLOOKUP($E45,Master!$J:$M,3,0),"") -> SGA | Q45: 4500000 | AC45: =SUM(K45:P45) -> 0 | AD45: =SUM(Q45:AB45) -> 4500000 | AE45: 4500000 | AF45: 4500000 | AG45: A
A46: BEX | B46: =_xlfn.IFNA(VLOOKUP(C46,Master!$J:$K,2,0),"") -> B1000 | C46: Top Management | D46: =_xlfn.IFNA(VLOOKUP(E46,Master!$J:$K,2,0),"") -> B1000 | E46: Top Management | F46: =_xlfn.IFNA(VLOOKUP(G46,Master!B:C,2,0),"") -> 7661101 | G46: Entertainment | H46: entertaiment golf | I46: =_xlfn.IFNA(VLOOKUP(E46,Master!$J:$M,4,0),"") -> ADM | J46: =_xlfn.IFNA(VLOOKUP($E46,Master!$J:$M,3,0),"") -> SGA | N46: 2650000 | O46: 2650000 | P46: 2650000 | Q46: 10000000 | R46: 10000000 | S46: 10000000 | T46: 10000000 | U46: 10000000 | V46: 10000000 | W46: 10000000 | X46: 10000000 | Y46: 10000000 | Z46: 10000000 | AA46: 10000000 | AB46: 10000000 | AC46: =SUM(K46:P46) -> 7950000 | AD46: =SUM(Q46:AB46) -> 120000000 | AE46: 120000000 | AF46: 120000000 | AG46: A
A47: BEX | B47: =_xlfn.IFNA(VLOOKUP(C47,Master!$J:$K,2,0),"") -> B1000 | C47: Top Management | D47: =_xlfn.IFNA(VLOOKUP(E47,Master!$J:$K,2,0),"") -> B1000 | E47: Top Management | F47: =_xlfn.IFNA(VLOOKUP(G47,Master!B:C,2,0),"") -> 7661101 | G47: Entertainment | H47: entertaiment beverage for customer and NGK-G | I47: =_xlfn.IFNA(VLOOKUP(E47,Master!$J:$M,4,0),"") -> ADM | J47: =_xlfn.IFNA(VLOOKUP($E47,Master!$J:$M,3,0),"") -> SGA | N47: =63000000/12 -> 5250000 | O47: =63000000/12 -> 5250000 | P47: =63000000/12 -> 5250000 | Q47: 12000000 | R47: 12000000 | S47: 12000000 | T47: 12000000 | U47: 12000000 | V47: 12000000 | W47: 12000000 | X47: 12000000 | Y47: 12000000 | Z47: 12000000 | AA47: 12000000 | AB47: 12000000 | AC47: =SUM(K47:P47) -> 15750000 | AD47: =SUM(Q47:AB47) -> 144000000 | AE47: 144000000 | AF47: 144000000 | AG47: A
A48: BEX | B48: =_xlfn.IFNA(VLOOKUP(C48,Master!$J:$K,2,0),"") -> B1000 | C48: Top Management | D48: =_xlfn.IFNA(VLOOKUP(E48,Master!$J:$K,2,0),"") -> B2300 | E48: Accounting & Finance | F48: =_xlfn.IFNA(VLOOKUP(G48,Master!B:C,2,0),"") -> 7651103 | G48: Travel Expense-Oversea | H48: Thaiand for budget fright [2N3D]_ISEKI | I48: =_xlfn.IFNA(VLOOKUP(E48,Master!$J:$M,4,0),"") -> ADM | J48: =_xlfn.IFNA(VLOOKUP($E48,Master!$J:$M,3,0),"") -> SGA | Z48: 7100000 | AC48: =SUM(K48:P48) -> 0 | AD48: =SUM(Q48:AB48) -> 7100000 | AE48: 7100000 | AF48: 7100000 | AG48: A
A49: BEX | B49: =_xlfn.IFNA(VLOOKUP(C49,Master!$J:$K,2,0),"") -> B1000 | C49: Top Management | D49: =_xlfn.IFNA(VLOOKUP(E49,Master!$J:$K,2,0),"") -> B2300 | E49: Accounting & Finance | F49: =_xlfn.IFNA(VLOOKUP(G49,Master!B:C,2,0),"") -> 7651103 | G49: Travel Expense-Oversea | H49: Thaiand for budget hotel [2N3D]_ISEKI | I49: =_xlfn.IFNA(VLOOKUP(E49,Master!$J:$M,4,0),"") -> ADM | J49: =_xlfn.IFNA(VLOOKUP($E49,Master!$J:$M,3,0),"") -> SGA | Z49: 2120000 | AC49: =SUM(K49:P49) -> 0 | AD49: =SUM(Q49:AB49) -> 2120000 | AE49: 2120000 | AF49: 2120000 | AG49: A
A50: BEX | B50: =_xlfn.IFNA(VLOOKUP(C50,Master!$J:$K,2,0),"") -> B1000 | C50: Top Management | D50: =_xlfn.IFNA(VLOOKUP(E50,Master!$J:$K,2,0),"") -> B2300 | E50: Accounting & Finance | F50: =_xlfn.IFNA(VLOOKUP(G50,Master!B:C,2,0),"") -> 7651103 | G50: Travel Expense-Oversea | H50: Thaiand for budget daily fee [2N3D]_ISEKI | I50: =_xlfn.IFNA(VLOOKUP(E50,Master!$J:$M,4,0),"") -> ADM | J50: =_xlfn.IFNA(VLOOKUP($E50,Master!$J:$M,3,0),"") -> SGA | Z50: 1998985.2 | AC50: =SUM(K50:P50) -> 0 | AD50: =SUM(Q50:AB50) -> 1998985.2 | AE50: 2013162.4 | AF50: 2013162.4 | AG50: A
A51: BEX | B51: =_xlfn.IFNA(VLOOKUP(C51,Master!$J:$K,2,0),"") -> B1000 | C51: Top Management | D51: =_xlfn.IFNA(VLOOKUP(E51,Master!$J:$K,2,0),"") -> B2300 | E51: Accounting & Finance | F51: =_xlfn.IFNA(VLOOKUP(G51,Master!B:C,2,0),"") -> 7651103 | G51: Travel Expense-Oversea | H51: Thaiand for meeting fright [2N3D]_ISEKI | I51: =_xlfn.IFNA(VLOOKUP(E51,Master!$J:$M,4,0),"") -> ADM | J51: =_xlfn.IFNA(VLOOKUP($E51,Master!$J:$M,3,0),"") -> SGA | W51: 7100000 | AC51: =SUM(K51:P51) -> 0 | AD51: =SUM(Q51:AB51) -> 7100000 | AE51: 7100000 | AF51: 7100000 | AG51: A
A52: BEX | B52: =_xlfn.IFNA(VLOOKUP(C52,Master!$J:$K,2,0),"") -> B1000 | C52: Top Management | D52: =_xlfn.IFNA(VLOOKUP(E52,Master!$J:$K,2,0),"") -> B2300 | E52: Accounting & Finance | F52: =_xlfn.IFNA(VLOOKUP(G52,Master!B:C,2,0),"") -> 7651103 | G52: Travel Expense-Oversea | H52: Thaiand for meeting hotel [2N3D]_ISEKI | I52: =_xlfn.IFNA(VLOOKUP(E52,Master!$J:$M,4,0),"") -> ADM | J52: =_xlfn.IFNA(VLOOKUP($E52,Master!$J:$M,3,0),"") -> SGA | W52: 2120000 | AC52: =SUM(K52:P52) -> 0 | AD52: =SUM(Q52:AB52) -> 2120000 | AE52: 2120000 | AF52: 2120000 | AG52: A
A53: BEX | B53: =_xlfn.IFNA(VLOOKUP(C53,Master!$J:$K,2,0),"") -> B1000 | C53: Top Management | D53: =_xlfn.IFNA(VLOOKUP(E53,Master!$J:$K,2,0),"") -> B2300 | E53: Accounting & Finance | F53: =_xlfn.IFNA(VLOOKUP(G53,Master!B:C,2,0),"") -> 7651103 | G53: Travel Expense-Oversea | H53: Thaiand for meeting daily fee [2N3D]_ISEKI | I53: =_xlfn.IFNA(VLOOKUP(E53,Master!$J:$M,4,0),"") -> ADM | J53: =_xlfn.IFNA(VLOOKUP($E53,Master!$J:$M,3,0),"") -> SGA | W53: 2509364.4 | AC53: =SUM(K53:P53) -> 0 | AD53: =SUM(Q53:AB53) -> 2509364.4 | AE53: 2013162.4 | AF53: 2013162.4 | AG53: A
A54: BEX | B54: =_xlfn.IFNA(VLOOKUP(C54,Master!$J:$K,2,0),"") -> B1000 | C54: Top Management | D54: =_xlfn.IFNA(VLOOKUP(E54,Master!$J:$K,2,0),"") -> B2300 | E54: Accounting & Finance | F54: =_xlfn.IFNA(VLOOKUP(G54,Master!B:C,2,0),"") -> 7651101 | G54: Transportation Fee for employee | H54: Toll&Parking_ISEKI | I54: =_xlfn.IFNA(VLOOKUP(E54,Master!$J:$M,4,0),"") -> ADM | J54: =_xlfn.IFNA(VLOOKUP($E54,Master!$J:$M,3,0),"") -> SGA | K54: 2000000 | L54: 2000000 | M54: 2000000 | N54: 2000000 | O54: 2000000 | P54: 2000000 | Q54: 2000000 | R54: 2000000 | S54: 2000000 | T54: 2000000 | U54: 2000000 | V54: 2000000 | W54: 2000000 | X54: 2000000 | Y54: 2000000 | Z54: 2000000 | AA54: 2000000 | AB54: 2000000 | AC54: =SUM(K54:P54) -> 12000000 | AD54: =SUM(Q54:AB54) -> 24000000 | AE54: 24000000 | AF54: 24000000 | AG54: A
A55: BEX | B55: =_xlfn.IFNA(VLOOKUP(C55,Master!$J:$K,2,0),"") -> B1000 | C55: Top Management | D55: =_xlfn.IFNA(VLOOKUP(E55,Master!$J:$K,2,0),"") -> B2300 | E55: Accounting & Finance | F55: =_xlfn.IFNA(VLOOKUP(G55,Master!B:C,2,0),"") -> 7651101 | G55: Transportation Fee for employee | H55: Gasoline_ISEKI | I55: =_xlfn.IFNA(VLOOKUP(E55,Master!$J:$M,4,0),"") -> ADM | J55: =_xlfn.IFNA(VLOOKUP($E55,Master!$J:$M,3,0),"") -> SGA | K55: 2000000 | L55: 2000000 | M55: 2000000 | N55: 2000000 | O55: 2000000 | P55: 2000000 | Q55: 2000000 | R55: 2000000 | S55: 2000000 | T55: 2000000 | U55: 2000000 | V55: 2000000 | W55: 2000000 | X55: 2000000 | Y55: 2000000 | Z55: 2000000 | AA55: 2000000 | AB55: 2000000 | AC55: =SUM(K55:P55) -> 12000000 | AD55: =SUM(Q55:AB55) -> 24000000 | AE55: 24000000 | AF55: 24000000 | AG55: A
A56: BEX | B56: =_xlfn.IFNA(VLOOKUP(C56,Master!$J:$K,2,0),"") -> B1000 | C56: Top Management | D56: =_xlfn.IFNA(VLOOKUP(E56,Master!$J:$K,2,0),"") -> B2300 | E56: Accounting & Finance | F56: =_xlfn.IFNA(VLOOKUP(G56,Master!B:C,2,0),"") -> 7781103 | G56: Publishing Expense | H56: Cooperate card annual fee_ISEKI | I56: =_xlfn.IFNA(VLOOKUP(E56,Master!$J:$M,4,0),"") -> ADM | J56: =_xlfn.IFNA(VLOOKUP($E56,Master!$J:$M,3,0),"") -> SGA | K56: 600000 | W56: 600000 | AC56: =SUM(K56:P56) -> 600000 | AD56: =SUM(Q56:AB56) -> 600000 | AE56: 600000 | AF56: 600000 | AG56: A
A57: BEX | B57: =_xlfn.IFNA(VLOOKUP(C57,Master!$J:$K,2,0),"") -> B1000 | C57: Top Management | D57: =_xlfn.IFNA(VLOOKUP(E57,Master!$J:$K,2,0),"") -> B2300 | E57: Accounting & Finance | F57: =_xlfn.IFNA(VLOOKUP(G57,Master!B:C,2,0),"") -> 7711101 | G57: Communication expenses | H57: Handphone bill & Document shipment_ISEKI | I57: =_xlfn.IFNA(VLOOKUP(E57,Master!$J:$M,4,0),"") -> ADM | J57: =_xlfn.IFNA(VLOOKUP($E57,Master!$J:$M,3,0),"") -> SGA | K57: 1000000 | L57: 1000000 | M57: 1000000 | N57: 1000000 | O57: 1000000 | P57: 1000000 | Q57: 1000000 | R57: 1000000 | S57: 1000000 | T57: 1000000 | U57: 1000000 | V57: 1000000 | W57: 1000000 | X57: 1000000 | Y57: 1000000 | Z57: 1000000 | AA57: 1000000 | AB57: 1000000 | AC57: =SUM(K57:P57) -> 6000000 | AD57: =SUM(Q57:AB57) -> 12000000 | AE57: 12000000 | AF57: 12000000 | AG57: A
A58: BEX | B58: =_xlfn.IFNA(VLOOKUP(C58,Master!$J:$K,2,0),"") -> B1000 | C58: Top Management | D58: =_xlfn.IFNA(VLOOKUP(E58,Master!$J:$K,2,0),"") -> B2300 | E58: Accounting & Finance | F58: =_xlfn.IFNA(VLOOKUP(G58,Master!B:C,2,0),"") -> 7781112 | G58: Expatriate expenses exclude labor cost | H58: KITAS renewal exppense_ISEKI | I58: =_xlfn.IFNA(VLOOKUP(E58,Master!$J:$M,4,0),"") -> ADM | J58: =_xlfn.IFNA(VLOOKUP($E58,Master!$J:$M,3,0),"") -> SGA | K58: 18800000 | W58: 18800000 | AC58: =SUM(K58:P58) -> 18800000 | AD58: =SUM(Q58:AB58) -> 18800000 | AE58: 18800000 | AF58: 18800000 | AG58: A
A59: BEX | B59: =_xlfn.IFNA(VLOOKUP(C59,Master!$J:$K,2,0),"") -> B1000 | C59: Top Management | D59: =_xlfn.IFNA(VLOOKUP(E59,Master!$J:$K,2,0),"") -> B2300 | E59: Accounting & Finance | F59: =_xlfn.IFNA(VLOOKUP(G59,Master!B:C,2,0),"") -> 7781112 | G59: Expatriate expenses exclude labor cost | H59: DPKK_ISEKI | I59: =_xlfn.IFNA(VLOOKUP(E59,Master!$J:$M,4,0),"") -> ADM | J59: =_xlfn.IFNA(VLOOKUP($E59,Master!$J:$M,3,0),"") -> SGA | K59: 1417720 | L59: 1417720 | M59: 1417720 | N59: 1417720 | O59: 1417720 | P59: 1417720 | Q59: 1417720 | R59: 1417720 | S59: 1417720 | T59: 1417720 | U59: 1417720 | V59: 1417720 | W59: 1417720 | X59: 1417720 | Y59: 1417720 | Z59: 1417720 | AA59: 1417720 | AB59: 1417720 | AC59: =SUM(K59:P59) -> 8506320 | AD59: =SUM(Q59:AB59) -> 17012640 | AE59: 17012640 | AF59: 17012640 | AG59: A
A60: BEX | B60: =_xlfn.IFNA(VLOOKUP(C60,Master!$J:$K,2,0),"") -> B1000 | C60: Top Management | D60: =_xlfn.IFNA(VLOOKUP(E60,Master!$J:$K,2,0),"") -> B2300 | E60: Accounting & Finance | F60: =_xlfn.IFNA(VLOOKUP(G60,Master!B:C,2,0),"") -> 7661101 | G60: Entertainment | H60: Entertaiment fee for cutomer_ISEKI | I60: =_xlfn.IFNA(VLOOKUP(E60,Master!$J:$M,4,0),"") -> ADM | J60: =_xlfn.IFNA(VLOOKUP($E60,Master!$J:$M,3,0),"") -> SGA | K60: 1700000 | L60: 950000 | M60: 1700000 | N60: 950000 | O60: 1700000 | P60: 950000 | Q60: 1700000 | R60: 950000 | S60: 1700000 | T60: 950000 | U60: 1700000 | V60: 950000 | W60: 1700000 | X60: 950000 | Y60: 1700000 | Z60: 950000 | AA60: 1700000 | AB60: 950000 | AC60: =SUM(K60:P60) -> 7950000 | AD60: =SUM(Q60:AB60) -> 15900000 | AE60: 15900000 | AF60: 15900000 | AG60: A
A61: BEX | B61: =_xlfn.IFNA(VLOOKUP(C61,Master!$J:$K,2,0),"") -> B1000 | C61: Top Management | D61: =_xlfn.IFNA(VLOOKUP(E61,Master!$J:$K,2,0),"") -> B2300 | E61: Accounting & Finance | F61: =_xlfn.IFNA(VLOOKUP(G61,Master!B:C,2,0),"") -> 7711102 | G61: IT expense | H61: Repair laptop_ISEKI | I61: =_xlfn.IFNA(VLOOKUP(E61,Master!$J:$M,4,0),"") -> ADM | J61: =_xlfn.IFNA(VLOOKUP($E61,Master!$J:$M,3,0),"") -> SGA | Q61: 5000000 | AC61: =SUM(K61:P61) -> 0 | AD61: =SUM(Q61:AB61) -> 5000000 | AE61: 5000000 | AF61: 5000000 | AG61: A
B62: =_xlfn.IFNA(VLOOKUP(C62,Master!$J:$K,2,0),"") | D62: =_xlfn.IFNA(VLOOKUP(E62,Master!$J:$K,2,0),"") | F62: =_xlfn.IFNA(VLOOKUP(G62,Master!B:C,2,0),"") | I62: =_xlfn.IFNA(VLOOKUP(E62,Master!$J:$M,4,0),"") | J62: =_xlfn.IFNA(VLOOKUP($E62,Master!$J:$M,3,0),"") | AC62: =SUM(K62:P62) -> 0 | AD62: =SUM(Q62:AB62) -> 0
B63: =_xlfn.IFNA(VLOOKUP(C63,Master!$J:$K,2,0),"") | D63: =_xlfn.IFNA(VLOOKUP(E63,Master!$J:$K,2,0),"") | F63: =_xlfn.IFNA(VLOOKUP(G63,Master!B:C,2,0),"") | I63: =_xlfn.IFNA(VLOOKUP(E63,Master!$J:$M,4,0),"") | J63: =_xlfn.IFNA(VLOOKUP($E63,Master!$J:$M,3,0),"") | AC63: =SUM(K63:P63) -> 0 | AD63: =SUM(Q63:AB63) -> 0
B64: =_xlfn.IFNA(VLOOKUP(C64,Master!$J:$K,2,0),"") | D64: =_xlfn.IFNA(VLOOKUP(E64,Master!$J:$K,2,0),"") | F64: =_xlfn.IFNA(VLOOKUP(G64,Master!B:C,2,0),"") | I64: =_xlfn.IFNA(VLOOKUP(E64,Master!$J:$M,4,0),"") | J64: =_xlfn.IFNA(VLOOKUP($E64,Master!$J:$M,3,0),"") | AC64: =SUM(K64:P64) -> 0 | AD64: =SUM(Q64:AB64) -> 0
B65: =_xlfn.IFNA(VLOOKUP(C65,Master!$J:$K,2,0),"") | D65: =_xlfn.IFNA(VLOOKUP(E65,Master!$J:$K,2,0),"") | F65: =_xlfn.IFNA(VLOOKUP(G65,Master!B:C,2,0),"") | I65: =_xlfn.IFNA(VLOOKUP(E65,Master!$J:$M,4,0),"") | J65: =_xlfn.IFNA(VLOOKUP($E65,Master!$J:$M,3,0),"") | AC65: =SUM(K65:P65) -> 0 | AD65: =SUM(Q65:AB65) -> 0
B66: =_xlfn.IFNA(VLOOKUP(C66,Master!$J:$K,2,0),"") | D66: =_xlfn.IFNA(VLOOKUP(E66,Master!$J:$K,2,0),"") | F66: =_xlfn.IFNA(VLOOKUP(G66,Master!B:C,2,0),"") | I66: =_xlfn.IFNA(VLOOKUP(E66,Master!$J:$M,4,0),"") | J66: =_xlfn.IFNA(VLOOKUP($E66,Master!$J:$M,3,0),"") | AC66: =SUM(K66:P66) -> 0 | AD66: =SUM(Q66:AB66) -> 0
B67: =_xlfn.IFNA(VLOOKUP(C67,Master!$J:$K,2,0),"") | D67: =_xlfn.IFNA(VLOOKUP(E67,Master!$J:$K,2,0),"") | F67: =_xlfn.IFNA(VLOOKUP(G67,Master!B:C,2,0),"") | I67: =_xlfn.IFNA(VLOOKUP(E67,Master!$J:$M,4,0),"") | J67: =_xlfn.IFNA(VLOOKUP($E67,Master!$J:$M,3,0),"") | AC67: =SUM(K67:P67) -> 0 | AD67: =SUM(Q67:AB67) -> 0
B68: =_xlfn.IFNA(VLOOKUP(C68,Master!$J:$K,2,0),"") | D68: =_xlfn.IFNA(VLOOKUP(E68,Master!$J:$K,2,0),"") | F68: =_xlfn.IFNA(VLOOKUP(G68,Master!B:C,2,0),"") | I68: =_xlfn.IFNA(VLOOKUP(E68,Master!$J:$M,4,0),"") | J68: =_xlfn.IFNA(VLOOKUP($E68,Master!$J:$M,3,0),"") | AC68: =SUM(K68:P68) -> 0 | AD68: =SUM(Q68:AB68) -> 0
B69: =_xlfn.IFNA(VLOOKUP(C69,Master!$J:$K,2,0),"") | D69: =_xlfn.IFNA(VLOOKUP(E69,Master!$J:$K,2,0),"") | F69: =_xlfn.IFNA(VLOOKUP(G69,Master!B:C,2,0),"") | I69: =_xlfn.IFNA(VLOOKUP(E69,Master!$J:$M,4,0),"") | J69: =_xlfn.IFNA(VLOOKUP($E69,Master!$J:$M,3,0),"") | AC69: =SUM(K69:P69) -> 0 | AD69: =SUM(Q69:AB69) -> 0
B70: =_xlfn.IFNA(VLOOKUP(C70,Master!$J:$K,2,0),"") | D70: =_xlfn.IFNA(VLOOKUP(E70,Master!$J:$K,2,0),"") | F70: =_xlfn.IFNA(VLOOKUP(G70,Master!B:C,2,0),"") | I70: =_xlfn.IFNA(VLOOKUP(E70,Master!$J:$M,4,0),"") | J70: =_xlfn.IFNA(VLOOKUP($E70,Master!$J:$M,3,0),"") | AC70: =SUM(K70:P70) -> 0 | AD70: =SUM(Q70:AB70) -> 0
B71: =_xlfn.IFNA(VLOOKUP(C71,Master!$J:$K,2,0),"") | D71: =_xlfn.IFNA(VLOOKUP(E71,Master!$J:$K,2,0),"") | F71: =_xlfn.IFNA(VLOOKUP(G71,Master!B:C,2,0),"") | I71: =_xlfn.IFNA(VLOOKUP(E71,Master!$J:$M,4,0),"") | J71: =_xlfn.IFNA(VLOOKUP($E71,Master!$J:$M,3,0),"") | AC71: =SUM(K71:P71) -> 0 | AD71: =SUM(Q71:AB71) -> 0
B72: =_xlfn.IFNA(VLOOKUP(C72,Master!$J:$K,2,0),"") | D72: =_xlfn.IFNA(VLOOKUP(E72,Master!$J:$K,2,0),"") | F72: =_xlfn.IFNA(VLOOKUP(G72,Master!B:C,2,0),"") | I72: =_xlfn.IFNA(VLOOKUP(E72,Master!$J:$M,4,0),"") | J72: =_xlfn.IFNA(VLOOKUP($E72,Master!$J:$M,3,0),"") | AC72: =SUM(K72:P72) -> 0 | AD72: =SUM(Q72:AB72) -> 0
B73: =_xlfn.IFNA(VLOOKUP(C73,Master!$J:$K,2,0),"") | D73: =_xlfn.IFNA(VLOOKUP(E73,Master!$J:$K,2,0),"") | F73: =_xlfn.IFNA(VLOOKUP(G73,Master!B:C,2,0),"") | I73: =_xlfn.IFNA(VLOOKUP(E73,Master!$J:$M,4,0),"") | J73: =_xlfn.IFNA(VLOOKUP($E73,Master!$J:$M,3,0),"") | AC73: =SUM(K73:P73) -> 0 | AD73: =SUM(Q73:AB73) -> 0
... B450: =_xlfn.IFNA(VLOOKUP(C450,Master!$J:$K,2,0),"") | D450: =_xlfn.IFNA(VLOOKUP(E450,Master!$J:$K,2,0),"") | F450: =_xlfn.IFNA(VLOOKUP(G450,Master!B:C,2,0),"") | I450: =_xlfn.IFNA(VLOOKUP(E450,Master!$J:$M,4,0),"") | J450: =_xlfn.IFNA(VLOOKUP($E450,Master!$J:$M,3,0),"") | AC450: =SUM(K450:P450) -> 0 | AD450: =SUM(Q450:AB450) -> 0
B451: =_xlfn.IFNA(VLOOKUP(C451,Master!$J:$K,2,0),"") | F451: =_xlfn.IFNA(VLOOKUP(G451,Master!B:C,2,0),"") | I451: =_xlfn.IFNA(VLOOKUP(E451,Master!$J:$M,4,0),"") | J451: =_xlfn.IFNA(VLOOKUP($E451,Master!$J:$M,3,0),"") | AC451: =SUM(K451:P451) -> 0 | AD451: =SUM(Q451:AB451) -> 0
B452: =_xlfn.IFNA(VLOOKUP(C452,Master!$J:$K,2,0),"") | F452: =_xlfn.IFNA(VLOOKUP(G452,Master!B:C,2,0),"") | I452: =_xlfn.IFNA(VLOOKUP(E452,Master!$J:$M,4,0),"") | J452: =_xlfn.IFNA(VLOOKUP($E452,Master!$J:$M,3,0),"") | AC452: =SUM(K452:P452) -> 0 | AD452: =SUM(Q452:AB452) -> 0
B453: =_xlfn.IFNA(VLOOKUP(C453,Master!$J:$K,2,0),"") | F453: =_xlfn.IFNA(VLOOKUP(G453,Master!B:C,2,0),"") | I453: =_xlfn.IFNA(VLOOKUP(E453,Master!$J:$M,4,0),"") | J453: =_xlfn.IFNA(VLOOKUP($E453,Master!$J:$M,3,0),"") | AC453: =SUM(K453:P453) -> 0 | AD453: =SUM(Q453:AB453) -> 0
B454: =_xlfn.IFNA(VLOOKUP(C454,Master!$J:$K,2,0),"") | F454: =_xlfn.IFNA(VLOOKUP(G454,Master!B:C,2,0),"") | I454: =_xlfn.IFNA(VLOOKUP(E454,Master!$J:$M,4,0),"") | J454: =_xlfn.IFNA(VLOOKUP($E454,Master!$J:$M,3,0),"") | AC454: =SUM(K454:P454) -> 0 | AD454: =SUM(Q454:AB454) -> 0
B455: =_xlfn.IFNA(VLOOKUP(C455,Master!$J:$K,2,0),"") | F455: =_xlfn.IFNA(VLOOKUP(G455,Master!B:C,2,0),"") | I455: =_xlfn.IFNA(VLOOKUP(E455,Master!$J:$M,4,0),"") | J455: =_xlfn.IFNA(VLOOKUP($E455,Master!$J:$M,3,0),"") | AC455: =SUM(K455:P455) -> 0 | AD455: =SUM(Q455:AB455) -> 0
B456: =_xlfn.IFNA(VLOOKUP(C456,Master!$J:$K,2,0),"") | F456: =_xlfn.IFNA(VLOOKUP(G456,Master!B:C,2,0),"") | I456: =_xlfn.IFNA(VLOOKUP(E456,Master!$J:$M,4,0),"") | J456: =_xlfn.IFNA(VLOOKUP($E456,Master!$J:$M,3,0),"") | AC456: =SUM(K456:P456) -> 0 | AD456: =SUM(Q456:AB456) -> 0
B457: =_xlfn.IFNA(VLOOKUP(C457,Master!$J:$K,2,0),"") | F457: =_xlfn.IFNA(VLOOKUP(G457,Master!B:C,2,0),"") | I457: =_xlfn.IFNA(VLOOKUP(E457,Master!$J:$M,4,0),"") | J457: =_xlfn.IFNA(VLOOKUP($E457,Master!$J:$M,3,0),"") | AC457: =SUM(K457:P457) -> 0 | AD457: =SUM(Q457:AB457) -> 0
B458: =_xlfn.IFNA(VLOOKUP(C458,Master!$J:$K,2,0),"") | F458: =_xlfn.IFNA(VLOOKUP(G458,Master!B:C,2,0),"") | I458: =_xlfn.IFNA(VLOOKUP(E458,Master!$J:$M,4,0),"") | J458: =_xlfn.IFNA(VLOOKUP($E458,Master!$J:$M,3,0),"") | AC458: =SUM(K458:P458) -> 0 | AD458: =SUM(Q458:AB458) -> 0
B459: =_xlfn.IFNA(VLOOKUP(C459,Master!$J:$K,2,0),"") | F459: =_xlfn.IFNA(VLOOKUP(G459,Master!B:C,2,0),"") | I459: =_xlfn.IFNA(VLOOKUP(E459,Master!$J:$M,4,0),"") | J459: =_xlfn.IFNA(VLOOKUP($E459,Master!$J:$M,3,0),"") | AC459: =SUM(K459:P459) -> 0 | AD459: =SUM(Q459:AB459) -> 0
B460: =_xlfn.IFNA(VLOOKUP(C460,Master!$J:$K,2,0),"") | F460: =_xlfn.IFNA(VLOOKUP(G460,Master!B:C,2,0),"") | I460: =_xlfn.IFNA(VLOOKUP(E460,Master!$J:$M,4,0),"") | J460: =_xlfn.IFNA(VLOOKUP($E460,Master!$J:$M,3,0),"") | AC460: =SUM(K460:P460) -> 0 | AD460: =SUM(Q460:AB460) -> 0
B461: =_xlfn.IFNA(VLOOKUP(C461,Master!$J:$K,2,0),"") | F461: =_xlfn.IFNA(VLOOKUP(G461,Master!B:C,2,0),"") | I461: =_xlfn.IFNA(VLOOKUP(E461,Master!$J:$M,4,0),"") | J461: =_xlfn.IFNA(VLOOKUP($E461,Master!$J:$M,3,0),"") | AC461: =SUM(K461:P461) -> 0 | AD461: =SUM(Q461:AB461) -> 0
B462: =_xlfn.IFNA(VLOOKUP(C462,Master!$J:$K,2,0),"") | F462: =_xlfn.IFNA(VLOOKUP(G462,Master!B:C,2,0),"") | I462: =_xlfn.IFNA(VLOOKUP(E462,Master!$J:$M,4,0),"") | J462: =_xlfn.IFNA(VLOOKUP($E462,Master!$J:$M,3,0),"") | AC462: =SUM(K462:P462) -> 0 | AD462: =SUM(Q462:AB462) -> 0
... B512: =_xlfn.IFNA(VLOOKUP(C512,Master!$J:$K,2,0),"") | F512: =_xlfn.IFNA(VLOOKUP(G512,Master!B:C,2,0),"") | I512: =_xlfn.IFNA(VLOOKUP(E512,Master!$J:$M,4,0),"") | J512: =_xlfn.IFNA(VLOOKUP($E512,Master!$J:$M,3,0),"") | AC512: =SUM(K512:P512) -> 0 | AD512: =SUM(Q512:AB512) -> 0
B513: =_xlfn.IFNA(VLOOKUP(C513,Master!$J:$K,2,0),"") | F513: =_xlfn.IFNA(VLOOKUP(G513,Master!B:C,2,0),"") | AC513: =SUM(K513:P513) -> 0 | AD513: =SUM(Q513:AB513) -> 0
B514: =_xlfn.IFNA(VLOOKUP(C514,Master!$J:$K,2,0),"") | F514: =_xlfn.IFNA(VLOOKUP(G514,Master!B:C,2,0),"") | AC514: =SUM(K514:P514) -> 0 | AD514: =SUM(Q514:AB514) -> 0
B515: =_xlfn.IFNA(VLOOKUP(C515,Master!$J:$K,2,0),"") | F515: =_xlfn.IFNA(VLOOKUP(G515,Master!B:C,2,0),"") | AC515: =SUM(K515:P515) -> 0 | AD515: =SUM(Q515:AB515) -> 0
B516: =_xlfn.IFNA(VLOOKUP(C516,Master!$J:$K,2,0),"") | F516: =_xlfn.IFNA(VLOOKUP(G516,Master!B:C,2,0),"") | AC516: =SUM(K516:P516) -> 0 | AD516: =SUM(Q516:AB516) -> 0
B517: =_xlfn.IFNA(VLOOKUP(C517,Master!$J:$K,2,0),"") | F517: =_xlfn.IFNA(VLOOKUP(G517,Master!B:C,2,0),"") | AC517: =SUM(K517:P517) -> 0 | AD517: =SUM(Q517:AB517) -> 0
B518: =_xlfn.IFNA(VLOOKUP(C518,Master!$J:$K,2,0),"") | F518: =_xlfn.IFNA(VLOOKUP(G518,Master!B:C,2,0),"") | AC518: =SUM(K518:P518) -> 0 | AD518: =SUM(Q518:AB518) -> 0
B519: =_xlfn.IFNA(VLOOKUP(C519,Master!$J:$K,2,0),"") | F519: =_xlfn.IFNA(VLOOKUP(G519,Master!B:C,2,0),"") | AC519: =SUM(K519:P519) -> 0 | AD519: =SUM(Q519:AB519) -> 0
B520: =_xlfn.IFNA(VLOOKUP(C520,Master!$J:$K,2,0),"") | F520: =_xlfn.IFNA(VLOOKUP(G520,Master!B:C,2,0),"") | AC520: =SUM(K520:P520) -> 0 | AD520: =SUM(Q520:AB520) -> 0
B521: =_xlfn.IFNA(VLOOKUP(C521,Master!$J:$K,2,0),"") | F521: =_xlfn.IFNA(VLOOKUP(G521,Master!B:C,2,0),"") | AC521: =SUM(K521:P521) -> 0 | AD521: =SUM(Q521:AB521) -> 0
B522: =_xlfn.IFNA(VLOOKUP(C522,Master!$J:$K,2,0),"") | F522: =_xlfn.IFNA(VLOOKUP(G522,Master!B:C,2,0),"") | AC522: =SUM(K522:P522) -> 0 | AD522: =SUM(Q522:AB522) -> 0
B523: =_xlfn.IFNA(VLOOKUP(C523,Master!$J:$K,2,0),"") | F523: =_xlfn.IFNA(VLOOKUP(G523,Master!B:C,2,0),"") | AC523: =SUM(K523:P523) -> 0 | AD523: =SUM(Q523:AB523) -> 0
B524: =_xlfn.IFNA(VLOOKUP(C524,Master!$J:$K,2,0),"") | F524: =_xlfn.IFNA(VLOOKUP(G524,Master!B:C,2,0),"") | AC524: =SUM(K524:P524) -> 0 | AD524: =SUM(Q524:AB524) -> 0
B525: =_xlfn.IFNA(VLOOKUP(C525,Master!$J:$K,2,0),"") | AC525: =SUM(K525:P525) -> 0 | AD525: =SUM(Q525:AB525) -> 0
...

Sheet Master
A1: COA AX | B1: Name COA AX | C1: COA AX | D1: COA AX | E1: Group Cost | F1: UNIQ | G1: COA Budget | H1: Description | J1: Name | K1: BNGK | L1: GROUP COST | M1: GROUP SECTION | N1: Name | P1: Code | Q1: Name | S1: Priority Code | T1: Priority Name | U1: Description
A2: 7511101 | B2: Salary for Commissioner | C2: 7511101 | D2: 7511101 | E2: SGA | F2: SGA-7511101 | G2: A502 | H2: Salary for Commissioner | J2: Top Management | K2: B1000 | L2: SGA | M2: ADM | N2: Top Management | P2: 53450 | Q2: NGK BUSI INDONESIA | S2: A | T2: Must | U2: If this is not done, the company or our team cannot continue its business.
A3: 7511102 | B3: Salary for Director | C3: 7511102 | D3: 7511102 | E3: SGA | F3: SGA-7511102 | G3: A502 | H3: Salary for Director & Expat | J3: Commissioner | K3: B1001 | L3: SGA | M3: ADM | N3: Commissioner | S3: B | T3: Want to | U3: We want to do it as a team this term. we need it.
A4: 7511103 | B4: Staff Labor - Baslc Salary | C4: 7511103 | D4: 7511103 | E4: SGA | F4: SGA-7511103 | G4: A501 | H4: Basic Salary of permanent employee | J4: Admin & HR | K4: B2200 | L4: SGA | M4: ADM | N4: Admin & HR | S4: C | T4: Challenge | U4: We want to do it for this term or the future. But it doesn't matter if it's not this term.
A5: 7511111 | B5: Staff Labor - Allowance | C5: 7511111 | D5: 7511111 | E5: SGA | F5: SGA-7511111 | G5: A501 | H5: Employee allowance | J5: General Affair | K5: B2210 | L5: SGA | M5: ADM | N5: General Affair
A6: 7511112 | B6: Staff Labor - Tax allowance (art.21) | C6: 7511112 | D6: 7511112 | E6: SGA | F6: SGA-7511112 | G6: A501 | H6: Empployee Tax allowance | J6: Human Resource | K6: B2220 | L6: SGA | M6: ADM | N6: Human Resource | P6: BEX
A7: 7511121 | B7: Staff Labor - BPJS JK & JKK (1.19%) | C7: 7511121 | D7: 7511121 | E7: SGA | F7: SGA-7511121 | G7: A501 | H7: BPJS JK & JKK (death warrant, Accident Insurance) | J7: Health, Safety & Environment | K7: B2230 | L7: SGA | M7: ADM | N7: Health, Safety & Environment | P7: BEL
A8: 7511122 | B8: Staff Labor - BPJS Kesehatan (4%) | C8: 7511122 | D8: 7511122 | E8: SGA | F8: SGA-7511122 | G8: A501 | H8: BPJS health insurance | J8: Accounting & Finance | K8: B2300 | L8: SGA | M8: ADM | N8: Accounting & Finance
A9: 7511201 | B9: Staff Overtime | C9: 7511201 | D9: 7511201 | E9: SGA | F9: SGA-7511201 | G9: A503 | H9: Overtime permanent employee | J9: Information Technology | K9: B2400 | L9: SGA | M9: ADM | N9: Information Technology
A10: 7512111 | B10: Staff Welfare - BPJS Dana pensiun (2%) | C10: 7512111 | D10: 7512111 | E10: SGA | F10: SGA-7512111 | G10: A504 | H10: BPJS pension fund | J10: Sales & MKTG Dept.- Automotive | K10: B3100 | L10: SGA | M10: ADM | N10: Sales & MKTG Dept.- Automotive
A11: 7512112 | B11: Staff Welfare - BPJS JHT (3.7%) | C11: 7512112 | D11: 7512112 | E11: SGA | F11: SGA-7512112 | G11: A504 | H11: BPJS Pension plan | J11: Marketing | K11: B3160 | L11: SGA | M11: ADM | N11: Marketing
A12: 7514101 | B12: Staff Bonus / TAT | C12: 7514101 | D12: 7514101 | E12: SGA | F12: SGA-7514101 | G12: A501 | H12: Year-end allowance & Alpha | J12: Sales - OEM | K12: B3110 | L12: SGA | M12: ADM | N12: Sales - OEM
A13: 7514102 | B13: Staff Ramadhan / THR | C13: 7514102 | D13: 7514102 | E13: SGA | F13: SGA-7514102 | G13: A501 | H13: Lebaran bonus | J13: Sales - OES | K13: B3120 | L13: SGA | M13: ADM | N13: Sales - OES
A14: 7515401 | B14: Staff Welfare - Outpatient (Medical) | C14: 7515401 | D14: 7515401 | E14: SGA | F14: SGA-7515401 | G14: A504 | H14: outpatient treatment costs | J14: Sales - IAM | K14: B3130 | L14: SGA | M14: ADM | N14: Sales - IAM
A15: 7515402 | B15: Staff Welfare - Hospitalization | C15: 7515402 | D15: 7515402 | E15: SGA | F15: SGA-7515402 | G15: A504 | H15: hospitalization costs | J15: SP PD- CF | K15: B4101 | L15: MFG | M15: DIR | N15: SP PD- CF
A16: 7515403 | B16: Staff Welfare - Glasses | C16: 7515403 | D16: 7515403 | E16: SGA | F16: SGA-7515403 | G16: A504 | H16: glasses costs | J16: SP PD- CM | K16: B4102 | L16: MFG | M16: DIR | N16: SP PD- CM
A17: 7515404 | B17: Staff Welfare - Dental | C17: 7515404 | D17: 7515404 | E17: SGA | F17: SGA-7515404 | G17: A504 | H17: dental costs | J17: SP PD- WT | K17: B4103 | L17: MFG | M17: DIR | N17: SP PD- WT
A18: 7515405 | B18: Staff Welfare - Medical Check Up | C18: 7515405 | D18: 7515405 | E18: SGA | F18: SGA-7515405 | G18: A504 | H18: Medical Check Up cost | J18: SP PD- Plating | K18: B4105 | L18: MFG | M18: DIR | N18: SP PD- Plating
A19: 7515406 | B19: Staff Welfare - Uniform | C19: 7515406 | D19: 7515406 | E19: SGA | F19: SGA-7515406 | G19: A504 | H19: uniform costs | J19: SP PD- MS Insp. | K19: B4109 | L19: MFG | M19: DIR | N19: SP PD- MS Insp.
A20: 7515407 | B20: Staff Welfare - Safety Shoes | C20: 7515407 | D20: 7515407 | E20: SGA | F20: SGA-7515407 | G20: A504 | J20: SP PD- Insulator Sealing | K20: B4106 | L20: MFG | M20: DIR | N20: SP PD- Insulator Sealing
A21: 7515408 | B21: Staff Welfare - Family Gathering / Anniversary | C21: 7515408 | D21: 7515408 | E21: SGA | F21: SGA-7515408 | G21: A504 | H21: Family Gathering / Anniversary | J21: SP PD- Assy | K21: B4110 | L21: MFG | M21: DIR | N21: SP PD- Assy
A22: 7515409 | B22: Staff Welfare - Meals of canteen & other meals | C22: 7515409 | D22: 7515409 | E22: SGA | F22: SGA-7515409 | G22: A504 | H22: Meals of canteen & other meals cost | J22: SP-PD-Assy-Auto Assembly | K22: B4115 | L22: MFG | M22: DIR | N22: SP-PD-Assy-Auto Assembly
A23: 7515410 | B23: Staff Welfare - Kaizen & QCC reward | C23: 7515410 | D23: 7515410 | E23: SGA | F23: SGA-7515410 | G23: A504 | H23: an expense, arising from Kaizen and QCC acitivity | J23: SP PD- Bending | K23: B4114 | L23: MFG | M23: DIR | N23: SP PD- Bending
A24: 7515499 | B24: Staff Welfare - Welfare Others | C24: 7515499 | D24: 7515499 | E24: SGA | F24: SGA-7515499 | G24: A504 | H24: an other welfare expense, arising besides the above welfare expense | J24: SP PD- Final Inspection | K24: B4120 | L24: MFG | M24: DIR | N24: SP PD- Final Inspection
A25: 7516102 | B25: Retirement Allowance | C25: 7516102 | D25: 7516102 | E25: SGA | F25: SGA-7516102 | G25: A505 | H25: employee retirement provission costs | J25: SP PD- QC - OEM | K25: B4121 | L25: MFG | M25: DIR | N25: SP PD- QC - OEM
A26: 7519101 | B26: House Rent Allowance | C26: 7519101 | D26: 7519101 | E26: SGA | F26: SGA-7519101 | G26: A502 | H26: House Rent Allowance for expat | J26: PC PD- Injection | K26: B4410 | L26: MFG | M26: DIR | N26: PC PD- Injection
A27: 7521101 | B27: Casual Staff Labor - Basic Salary | C27: 7521101 | D27: 7521101 | E27: SGA | F27: SGA-7521101 | G27: A501 | H27: All benefit for temporary worker | J27: PC PD- Assy | K27: B4430 | L27: MFG | M27: DIR | N27: PC PD- Assy
A28: 7521102 | B28: Casual Staff Labor - Overtime | C28: 7521102 | D28: 7521102 | E28: SGA | F28: SGA-7521102 | G28: A503 | H28: Overtime temporary worker | J28: PC PD- QC | K28: B4440 | L28: MFG | M28: DIR | N28: PC PD- QC
A29: 7571101 | B29: Personnel expense transferred | C29: 7571101 | D29: 7571101 | E29: SGA | F29: SGA-7571101 | G29: A506 | H29: Transfer Labor cost from one section into another section | J29: Plant Operation (Indirect Mfg) | K29: B5000 | L29: MFG | M29: IND | N29: Plant Operation (Indirect Mfg)
A30: 7611100 | B30: Depreciation-Building | C30: 7611100 | D30: 7611100 | E30: SGA | F30: SGA-7611100 | G30: A601 | H30: the amount of depreciation of tangible assets for building | J30: Production Office | K30: B5100 | L30: MFG | M30: IND | N30: Production Office
A31: 7611300 | B31: Depreciation-Machiney & equipment | C31: 7611300 | D31: 7611300 | E31: SGA | F31: SGA-7611300 | G31: A601 | H31: the amount of depreciation of tangible assets for machinery & factory equipment | J31: Production Office (SP) | K31: B5101 | L31: MFG | M31: IND | N31: Production Office (SP)
A32: 7611400 | B32: Depreciation-Lease Machinery & equipment | C32: 7611400 | D32: 7611400 | E32: SGA | F32: SGA-7611400 | G32: A601 | H32: the amount of depreciation of tangible assets for machinery & factory equipment (Leases) | J32: Production Office (PC) | K32: B5104 | L32: MFG | M32: IND | N32: Production Office (PC)
... A41: 7641101 | B41: Repair Building | C41: 7641101 | D41: 7641101 | E41: SGA | F41: SGA-7641101 | G41: A1002 | H41: expenses for repair and maintenance asset building | J41: Continuous Improvement | K41: B5007 | L41: MFG | M41: IND | N41: Continuous Improvement
A42: 7641102 | B42: Repair of Equipment | C42: 7641102 | D42: 7641102 | E42: SGA | F42: SGA-7641102 | G42: A1002 | H42: expenses for repair and maintenance tangible assets, intangible assets and other assets beside building | J42: All | K42: B0000 | N42: All
A43: 7641103 | B43: Factory Supply Expense | C43: 7641103 | D43: 7641103 | E43: SGA | F43: SGA-7641103 | G43: A1099 | H43: All cost that arrising to support factory acitivity
A44: 7641104 | B44: Calibration Cost | C44: 7641104 | D44: 7641104 | E44: SGA | F44: SGA-7641104 | G44: A1099 | H44: Cost of calibration for tools and equipment of factory and others
A45: 7651101 | B45: Transportation Fee for employee | C45: 7651101 | D45: 7651101 | E45: SGA | F45: SGA-7651101 | G45: A801 | H45: Gasoline of company cars & expense for Local transportation
A46: 7651102 | B46: Travel Expense-Domestic | C46: 7651102 | D46: 7651102 | E46: SGA | F46: SGA-7651102 | G46: A801 | H46: expenses for business trip, including allowance for business trip to an employee only for domestic travel
A47: 7651103 | B47: Travel Expense-Oversea | C47: 7651103 | D47: 7651103 | E47: SGA | F47: SGA-7651103 | G47: A801 | H47: expenses for business trip, including allowance for business trip to an employee only for overseas travel
A48: 7661101 | B48: Entertainment | C48: 7661101 | D48: 7661101 | E48: SGA | F48: SGA-7661101 | G48: A1001 | H48: the amount of expenses for the act of entertaining the business partner
A49: 7671102 | B49: Amortization of Land & Building tax (PBB) | C49: 7671102 | D49: 7671102 | E49: SGA | F49: SGA-7671102 | G49: A1099 | H49: the amount of depreciation of intangible of Land & Building Tax (PBB)
A50: 7671103 | B50: License fee | C50: 7671103 | D50: 7671103 | E50: SGA | F50: SGA-7671103 | G50: A1099 | H50: The expense related with the documentation process, such as : KIR, Car lisence, company lisence, etc.
A51: 7681101 | B51: Insurance Premium | C51: 7681101 | D51: 7681101 | E51: SGA | F51: SGA-7681101 | G51: A1099 | H51: expenses for risk management with no premium at the end of the term, such as fire insurance for plants and inventories
A52: 7691000 | B52: Office supply & Stationary Expense | C52: 7691000 | D52: 7691000 | E52: SGA | F52: SGA-7691000 | G52: A1099 | H52: the amount of supplies for office, such as stationery. Small office equipment included
A53: 7711101 | B53: Communication expenses | C53: 7711101 | D53: 7711101 | E53: SGA | F53: SGA-7711101 | G53: A1099 | H53: expenses for communication with a people in remote place, such as expense for telephone and postage
A54: 7711102 | B54: IT Expense | C54: 7711102 | D54: 7711102 | E54: SGA | F54: SGA-7711102 | G54: A1005 | H54: the amount of supplies for IT tools
... A76: 7461101 | B76: Cost of Samples | C76: 7461101 | D76: 7461101 | E76: SGA | F76: SGA-7461101 | G76: A499 | H76: Sample expense
A77: 7411105 | B77: Sales - Insurance of Delivery or Shipment | C77: 7411105 | D77: 7411105 | E77: SGA | F77: SGA-7411105 | G77: A299
A78: 7471201 | B78: Sales - Insurance of AR (Credit Insurance) | C78: 7471201 | D78: 7471201 | E78: SGA | F78: SGA-7471201 | G78: A299
A79: 7751101 | B79: Sales - Royalty to NGK Group | C79: 7751101 | D79: 7751101 | E79: SGA | F79: SGA-7751101
A80: 7751102 | B80: Sales - Royalty to Independence Party | C80: 7751102 | D80: 7751102 | E80: SGA | F80: SGA-7751102
A81: 7111211 | B81: Import Duty-purchased FG from NGK group | C81: 7111211 | D81: 7111211 | E81: MFG | F81: MFG-7111211
A82: 7111212 | B82: Import Duty-purchased FG from outside supplier | C82: 7111212 | D82: 7111212 | E82: MFG | F82: MFG-7111212
A83: 7111221 | B83: Import Duty-purchased KD&RM from NGK Japan | C83: 7111221 | D83: 7111221 | E83: MFG | F83: MFG-7111221
A84: 7111222 | B84: Import Duty-purchased KD&RM from NGK Group(Not fromJP) | C84: 7111222 | D84: 7111222 | E84: MFG | F84: MFG-7111222
A85: 7111223 | B85: Import Duty-purchased Comp Parts&RM from outside supplier | C85: 7111223 | D85: 7111223 | E85: MFG | F85: MFG-7111223
A86: 7111311 | B86: Import Expense-purchased FG from NGK group | C86: 7111311 | D86: 7111311 | E86: MFG | F86: MFG-7111311
A87: 7111312 | B87: Import Expense-purchased FG from outside supplier | C87: 7111312 | D87: 7111312 | E87: MFG | F87: MFG-7111312
A88: 7111321 | B88: Import Expense-purchased KD&RM from NGK Japan | C88: 7111321 | D88: 7111321 | E88: MFG | F88: MFG-7111321
A89: 7111322 | B89: Import Expense-purchased KD&RM from NGK Group(Not fromJP) | C89: 7111322 | D89: 7111322 | E89: MFG | F89: MFG-7111322
A90: 7111323 | B90: Import Expense-purchased Comp Parts&RM from outside supplier | C90: 7111323 | D90: 7111323 | E90: MFG | F90: MFG-7111323
... A94: 7211101 | B94: Cost of Factory Supply | C94: 7211101 | D94: 7211101 | E94: MFG | F94: MFG-7211101
A95: 7211102 | B95: Cost of Chemical | C95: 7211102 | D95: 7211102 | E95: MFG | F95: MFG-7211102 | G95: 901 | H95: The expenses of Chemicals consumption
A96: 7211103 | B96: Cost of Packaging | C96: 7211103 | D96: 7211103 | E96: MFG | F96: MFG-7211103
A97: 7211104 | B97: Cost of Oil | C97: 7211104 | D97: 7211104 | E97: MFG | F97: MFG-7211104 | G97: 302
A98: 7221101 | B98: Cost of Tooling | C98: 7221101 | D98: 7221101 | E98: MFG | F98: MFG-7221101 | G98: 302 | H98: The expenses of Tooling consumption
A99: 7221102 | B99: Cost of Machinery parts | C99: 7221102 | D99: 7221102 | E99: MFG | F99: MFG-7221102 | G99: 301 | H99: The expenses of Spare Parts consumption
A100: 7511101 | B100: Salary for Commissioner | C100: 7511101 | D100: 7511101 | E100: MFG | F100: MFG-7511101 | G100: 602 | H100: Salary for Commissioner
A101: 7511102 | B101: Salary for Director | C101: 7511102 | D101: 7511102 | E101: MFG | F101: MFG-7511102 | G101: 602 | H101: Salary for Director & Expat
A102: 7511103 | B102: Staff Labor - Baslc Salary | C102: 7511103 | D102: 7511103 | E102: MFG | F102: MFG-7511103 | G102: 601 | H102: Basic Salary of permanent employee
A103: 7511111 | B103: Staff Labor - Allowance | C103: 7511111 | D103: 7511111 | E103: MFG | F103: MFG-7511111 | G103: 601 | H103: Employee allowance
A104: 7511112 | B104: Staff Labor - Tax allowance (art.21) | C104: 7511112 | D104: 7511112 | E104: MFG | F104: MFG-7511112 | G104: 601 | H104: Empployee Tax allowance
A105: 7511121 | B105: Staff Labor - BPJS JK & JKK (1.19%) | C105: 7511121 | D105: 7511121 | E105: MFG | F105: MFG-7511121 | G105: 601 | H105: BPJS JK & JKK (death warrant, Accident Insurance)
A106: 7511122 | B106: Staff Labor - BPJS Kesehatan (4%) | C106: 7511122 | D106: 7511122 | E106: MFG | F106: MFG-7511122 | G106: 601 | H106: BPJS health insurance
A107: 7511201 | B107: Staff Overtime | C107: 7511201 | D107: 7511201 | E107: MFG | F107: MFG-7511201 | G107: 603 | H107: Overtime permanent employee
A108: 7512111 | B108: Staff Welfare - BPJS Dana pensiun (2%) | C108: 7512111 | D108: 7512111 | E108: MFG | F108: MFG-7512111 | G108: 604 | H108: BPJS pension fund
A109: 7512112 | B109: Staff Welfare - BPJS JHT (3.7%) | C109: 7512112 | D109: 7512112 | E109: MFG | F109: MFG-7512112 | G109: 604 | H109: BPJS Pension plan
... A117: 7515406 | B117: Staff Welfare - Uniform | C117: 7515406 | D117: 7515406 | E117: MFG | F117: MFG-7515406 | G117: 604 | H117: uniform costs
A118: 7515407 | B118: Staff Welfare - Safety Shoes | C118: 7515407 | D118: 7515407 | E118: MFG | F118: MFG-7515407 | G118: 604
A119: 7515408 | B119: Staff Welfare - Family Gathering / Anniversary | C119: 7515408 | D119: 7515408 | E119: MFG | F119: MFG-7515408 | G119: 604 | H119: Family Gathering / Anniversary
A120: 7515409 | B120: Staff Welfare - Meals of canteen & other meals | C120: 7515409 | D120: 7515409 | E120: MFG | F120: MFG-7515409 | G120: 604 | H120: Meals of canteen & other meals cost
A121: 7515410 | B121: Staff Welfare - Kaizen & QCC reward | C121: 7515410 | D121: 7515410 | E121: MFG | F121: MFG-7515410 | G121: 604 | H121: an expense, arising from Kaizen and QCC acitivity
A122: 7515499 | B122: Staff Welfare - Welfare Others | C122: 7515499 | D122: 7515499 | E122: MFG | F122: MFG-7515499 | G122: 604 | H122: an other welfare expense, arising besides the above welfare expense
A123: 7516102 | B123: Retirement Allowance | C123: 7516102 | D123: 7516102 | E123: MFG | F123: MFG-7516102 | G123: 605 | H123: employee retirement provission costs
A124: 7519101 | B124: House Rent Allowance | C124: 7519101 | D124: 7519101 | E124: MFG | F124: MFG-7519101 | G124: 602 | H124: House Rent Allowance for expat
A125: 7521101 | B125: Casual Staff Labor | C125: 7521101 | D125: 7521101 | E125: MFG | F125: MFG-7521101 | G125: 601 | H125: All benefit for temporary worker
A126: 7521102 | B126: Casual Staff Labor - Overtime | C126: 7521102 | D126: 7521102 | E126: MFG | F126: MFG-7521102 | G126: 603 | H126: Overtime temporary worker
A127: 7571101 | B127: Personnel expense transferred | C127: 7571101 | D127: 7571101 | E127: MFG | F127: MFG-7571101 | G127: 606 | H127: Transfer Labor cost from one section into another section
A128: 7611100 | B128: Depreciation-Building | C128: 7611100 | D128: 7611100 | E128: MFG | F128: MFG-7611100 | G128: 701 | H128: the amount of depreciation of tangible assets for building
A129: 7611300 | B129: Depreciation-Machiney & equipment | C129: 7611300 | D129: 7611300 | E129: MFG | F129: MFG-7611300 | G129: 701 | H129: the amount of depreciation of tangible assets for machinery & factory equipment
A130: 7611400 | B130: Depreciation-Lease Machinery & equipment | C130: 7611400 | D130: 7611400 | E130: MFG | F130: MFG-7611400 | G130: 701 | H130: the amount of depreciation of tangible assets for machinery & factory equipment (Leases)
... A166: 7781113 | B166: Expatriate fee Tax (BADORA) | C166: 7781113 | D166: 7781113 | E166: MFG | F166: MFG-7781113 | G166: 999 | H166: Tax income from expatriete
A167: 8291101 | B167: Others - Miscellaneous Waste | C167: 8291101 | D167: 8291101 | E167: OTH | F167: OTH-8291101
A168: 8291102 | B168: Others - Miscellaneous Tax | C168: 8291102 | D168: 8291102 | E168: OTH | F168: OTH-8291102
A169: 8291201 | B169: Others - Sport Activity | C169: 8291201 | D169: 8291201 | E169: OTH | F169: OTH-8291201
A170: 8291202 | B170: Others - Retribution / Garbage Cost | C170: 8291202 | D170: 8291202 | E170: OTH | F170: OTH-8291202
A171: 8291203 | B171: Others - Miscellaneous Non Operational Expense | C171: 8291203 | D171: 8291203 | E171: OTH | F171: OTH-8291203
A172: 8191101 | B172: Other Income | C172: 8191101 | D172: 8191101 | E172: OTH | F172: OTH-8191101
