Workbook
Name __j102: #REF!
Name __j102: #REF!
Name __j102: #REF!
Name __j102: #REF!
Name _1: #N/A
Name _j102: #REF!
Name _j102: #REF!
Name _j102: #REF!
Name _j102: #REF!
Name _j102: #REF!
Name _j102: #REF!
Name aa: #REF!
Name aa: #REF!
Name aa: #REF!
Name aa: #REF!
Name aa: #REF!
Name AB: #REF!
Name AB: #REF!
Name AB: #REF!
Name AB: #REF!
Name AB: #REF!
Name ai: #REF!
Name ai: #REF!
Name ai: #REF!
Name ai: #REF!
Name ai: #REF!
Name as: #REF!
Name as: #REF!
Name as: #REF!
Name as: #REF!
Name as: #REF!
Name assit: #REF!
Name assit: #REF!
Name assit: #REF!
Name assit: #REF!
Name assit: #REF!
Name b: #REF!
Name b: #REF!
Name b: #REF!
Name b: #REF!
Name b: #REF!
Name BC: #REF!
Name BC: #REF!
Name BC: #REF!
Name BC: #REF!
Name BC: #REF!
Name BI: #REF!
Name BI: #REF!
Name BI: #REF!
Name BI: #REF!
Name BI: #REF!
Name BO: #REF!
Name BO: #REF!
Name BO: #REF!
Name BO: #REF!
Name BO: #REF!
Name cc: #REF!
Name cc: #REF!
Name cc: #REF!
Name cc: #REF!

Sheet COA
A1: Name | B1: COA AX | C1: Group Cost | D1: UNIQ | E1: COA Budget | F1: Description
A2: Salary for Commissioner | B2: 7511101 | C2: SGA | D2: =C2&"-"&B2 -> SGA-7511101 | E2: A502 | F2: Salary for Commissioner
A3: Salary for Director | B3: 7511102 | C3: SGA | D3: =C3&"-"&B3 -> SGA-7511102 | E3: A502 | F3: Salary for Director & Expat
A4: Staff Labor - Baslc Salary | B4: 7511103 | C4: SGA | D4: =C4&"-"&B4 -> SGA-7511103 | E4: A501 | F4: Basic Salary of permanent employee
A5: Staff Labor - Allowance | B5: 7511111 | C5: SGA | D5: =C5&"-"&B5 -> SGA-7511111 | E5: A501 | F5: Employee allowance
A6: Staff Labor - Tax allowance (art.21) | B6: 7511112 | C6: SGA | D6: =C6&"-"&B6 -> SGA-7511112 | E6: A501 | F6: Empployee Tax allowance
A7: Staff Labor - BPJS JK & JKK (1.19%) | B7: 7511121 | C7: SGA | D7: =C7&"-"&B7 -> SGA-7511121 | E7: A501 | F7: BPJS JK & JKK (death warrant, Accident Insurance)
A8: Staff Labor - BPJS Kesehatan (4%) | B8: 7511122 | C8: SGA | D8: =C8&"-"&B8 -> SGA-7511122 | E8: A501 | F8: BPJS health insurance
A9: Staff Overtime | B9: 7511201 | C9: SGA | D9: =C9&"-"&B9 -> SGA-7511201 | E9: A503 | F9: Overtime permanent employee
A10: Staff Welfare - BPJS Dana pensiun (2%) | B10: 7512111 | C10: SGA | D10: =C10&"-"&B10 -> SGA-7512111 | E10: A504 | F10: BPJS pension fund
A11: Staff Welfare - BPJS JHT (3.7%) | B11: 7512112 | C11: SGA | D11: =C11&"-"&B11 -> SGA-7512112 | E11: A504 | F11: BPJS Pension plan
A12: Staff Bonus / TAT | B12: 7514101 | C12: SGA | D12: =C12&"-"&B12 -> SGA-7514101 | E12: A501 | F12: Year-end allowance & Alpha
A13: Staff Ramadhan / THR | B13: 7514102 | C13: SGA | D13: =C13&"-"&B13 -> SGA-7514102 | E13: A501 | F13: Lebaran bonus
... A70: Cost of Samples | B70: 7461101 | C70: SGA | D70: =C70&"-"&B70 -> SGA-7461101 | E70: A499 | F70: Sample expense
A71: Sales - Insurance of Delivery or Shipment | B71: 7411105 | C71: SGA | D71: =C71&"-"&B71 -> SGA-7411105 | E71: A299
A72: Sales - Insurance of AR (Credit Insurance) | B72: 7471201 | C72: SGA | D72: =C72&"-"&B72 -> SGA-7471201 | E72: A299
A73: Sales - Royalty to NGK Group | B73: 7751101 | C73: SGA | D73: =C73&"-"&B73 -> SGA-7751101
A74: Sales - Royalty to Independence Party | B74: 7751102 | C74: SGA | D74: =C74&"-"&B74 -> SGA-7751102
A75: Import Duty-purchased FG from NGK group | B75: 7111211 | C75: MFG | D75: =C75&"-"&B75 -> MFG-7111211
A76: Import Duty-purchased KD&RM from NGK Japan | B76: 7111221 | C76: MFG | D76: =C76&"-"&B76 -> MFG-7111221
A77: Import Duty-purchased KD&RM from NGK Group(Not fromJP) | B77: 7111222 | C77: MFG | D77: =C77&"-"&B77 -> MFG-7111222
A78: Import Duty-purchased Comp Parts&RM from outside supplier | B78: 7111223 | C78: MFG | D78: =C78&"-"&B78 -> MFG-7111223
A79: Import Expense-purchased FG from NGK group | B79: 7111311 | C79: MFG | D79: =C79&"-"&B79 -> MFG-7111311
A80: Import Expense-purchased KD&RM from NGK Japan | B80: 7111321 | C80: MFG | D80: =C80&"-"&B80 -> MFG-7111321
A81: Import Expense-purchased KD&RM from NGK Group(Not fromJP) | B81: 7111322 | C81: MFG | D81: =C81&"-"&B81 -> MFG-7111322
A82: Import Expense-purchased Comp Parts&RM from outside supplier | B82: 7111323 | C82: MFG | D82: =C82&"-"&B82 -> MFG-7111323
A83: Cost of Factory Supply | B83: 7211101 | C83: MFG | D83: =C83&"-"&B83 -> MFG-7211101
A84: Cost of Chemical | B84: 7211102 | C84: MFG | D84: =C84&"-"&B84 -> MFG-7211102 | E84: 901 | F84: The expenses of Chemicals consumption
A85: Cost of Packaging | B85: 7211103 | C85: MFG | D85: =C85&"-"&B85 -> MFG-7211103
A86: Cost of Tooling | B86: 7221101 | C86: MFG | D86: =C86&"-"&B86 -> MFG-7221101 | E86: 302 | F86: The expenses of Tooling consumption
A87: Cost of Machinery parts | B87: 7221102 | C87: MFG | D87: =C87&"-"&B87 -> MFG-7221102 | E87: 301 | F87: The expenses of Spare Parts consumption
A88: Salary for Commissioner | B88: 7511101 | C88: MFG | D88: =C88&"-"&B88 -> MFG-7511101 | E88: 602 | F88: Salary for Commissioner
A89: Salary for Director | B89: 7511102 | C89: MFG | D89: =C89&"-"&B89 -> MFG-7511102 | E89: 602 | F89: Salary for Director & Expat
A90: Staff Labor - Baslc Salary | B90: 7511103 | C90: MFG | D90: =C90&"-"&B90 -> MFG-7511103 | E90: 601 | F90: Basic Salary of permanent employee
A91: Staff Labor - Allowance | B91: 7511111 | C91: MFG | D91: =C91&"-"&B91 -> MFG-7511111 | E91: 601 | F91: Employee allowance
A92: Staff Labor - Tax allowance (art.21) | B92: 7511112 | C92: MFG | D92: =C92&"-"&B92 -> MFG-7511112 | E92: 601 | F92: Empployee Tax allowance
A93: Staff Labor - BPJS JK & JKK (1.19%) | B93: 7511121 | C93: MFG | D93: =C93&"-"&B93 -> MFG-7511121 | E93: 601 | F93: BPJS JK & JKK (death warrant, Accident Insurance)
A94: Staff Labor - BPJS Kesehatan (4%) | B94: 7511122 | C94: MFG | D94: =C94&"-"&B94 -> MFG-7511122 | E94: 601 | F94: BPJS health insurance
A95: Staff Overtime | B95: 7511201 | C95: MFG | D95: =C95&"-"&B95 -> MFG-7511201 | E95: 603 | F95: Overtime permanent employee
A96: Staff Welfare - BPJS Dana pensiun (2%) | B96: 7512111 | C96: MFG | D96: =C96&"-"&B96 -> MFG-7512111 | E96: 604 | F96: BPJS pension fund
A97: Staff Welfare - BPJS JHT (3.7%) | B97: 7512112 | C97: MFG | D97: =C97&"-"&B97 -> MFG-7512112 | E97: 604 | F97: BPJS Pension plan
... A148: Expatriate fee Tax (BADORA) | B148: 7781113 | C148: MFG | D148: =C148&"-"&B148 -> MFG-7781113 | E148: 999 | F148: Tax income from expatriete
A149: Others - Miscellaneous Waste | B149: 8291101 | C149: OTH | D149: =C149&"-"&B149 -> OTH-8291101
A150: Others - Miscellaneous Tax | B150: 8291102 | C150: OTH | D150: =C150&"-"&B150 -> OTH-8291102
A151: Others - Sport Activity | B151: 8291201 | C151: OTH | D151: =C151&"-"&B151 -> OTH-8291201
A152: Others - Retribution / Garbage Cost | B152: 8291202 | C152: OTH | D152: =C152&"-"&B152 -> OTH-8291202
A153: Others - Miscellaneous Non Operational Expense | B153: 8291203 | C153: OTH | D153: =C153&"-"&B153 -> OTH-8291203
A154: Other Income | B154: 8191101 | C154: OTH | D154: =C154&"-"&B154 -> OTH-8191101

Sheet Upload
A1: Budget Type | B1: Section From (Code) | C1: Section From (Name) | D1: To Section (Code) | E1: To Section (Name) | F1: Coa ID | G1: Coa Name | H1: Asset Name | I1: Acquisition Value | J1: Useful Life | K1: Allocation % | L1: Depre Start | M1: Priority Code | N1: Budget_Period | O1: Budget Allocation
A2: BIP | B2: =_xlfn.IFNA(VLOOKUP(C2,Sheet3!$H:$I,2,FALSE),"") -> B2400 | C2: Information Technology | D2: =_xlfn.IFNA(VLOOKUP(E2,Sheet3!$H:$I,2,FALSE),"") -> B2400 | E2: Information Technology | F2: 2141000 | G2: Tools, furniture & office equipment | H2: UPS For Rack 2 (AX, ASPROVA, Flexnet Server) | I2: 127990800 | J2: 60 | K2: 100 | L2: 43922 | M2: A | O2: 127990800
A3: BIP | B3: =_xlfn.IFNA(VLOOKUP(C3,Sheet3!$H:$I,2,FALSE),"") -> B2400 | C3: Information Technology | D3: =_xlfn.IFNA(VLOOKUP(E3,Sheet3!$H:$I,2,FALSE),"") -> B2400 | E3: Information Technology | F3: 2141000 | G3: Tools, furniture & office equipment | H3: UPS For Rack 1 (Domain, Application Server) | I3: 88905600 | J3: 60 | K3: 100 | L3: 43922 | M3: B | O3: 88905600
A4: BIP | B4: =_xlfn.IFNA(VLOOKUP(C4,Sheet3!$H:$I,2,FALSE),"") -> B2400 | C4: Information Technology | D4: =_xlfn.IFNA(VLOOKUP(E4,Sheet3!$H:$I,2,FALSE),"") -> B2400 | E4: Information Technology | F4: 2141000 | G4: Tools, furniture & office equipment | H4: Notebook for IT Member | I4: 15000000 | J4: 60 | K4: 100 | L4: 43983 | M4: C | O4: 15000000
A5: BIP | B5: =_xlfn.IFNA(VLOOKUP(C5,Sheet3!$H:$I,2,FALSE),"") -> B2210 | C5: GENERAL AFFAIR | D5: =_xlfn.IFNA(VLOOKUP(E5,Sheet3!$H:$I,2,FALSE),"") -> B2210 | E5: GENERAL AFFAIR | F5: 2141000 | G5: Tools, furniture & office equipment | H5: Auto Gate Machine | I5: 40000000 | J5: 60 | K5: 100 | L5: 44197 | M5: C | O5: 40000000
A6: BIP | B6: =_xlfn.IFNA(VLOOKUP(C6,Sheet3!$H:$I,2,FALSE),"") -> B2210 | C6: GENERAL AFFAIR | D6: =_xlfn.IFNA(VLOOKUP(E6,Sheet3!$H:$I,2,FALSE),"") -> B2210 | E6: GENERAL AFFAIR | F6: 2141000 | G6: Tools, furniture & office equipment | H6: AC Central Spark Plug 1 | I6: 40000000 | J6: 60 | K6: 100 | L6: 44197 | M6: C | O6: 40000000
A7: BIP | B7: =_xlfn.IFNA(VLOOKUP(C7,Sheet3!$H:$I,2,FALSE),"") -> B2210 | C7: GENERAL AFFAIR | D7: =_xlfn.IFNA(VLOOKUP(E7,Sheet3!$H:$I,2,FALSE),"") -> B2220 | E7: HUMAN RESOURCE | F7: 2141000 | G7: Tools, furniture & office equipment | H7: Personal Computer Recruitment Staff | I7: 8000000 | J7: 60 | K7: 100 | L7: 44287 | M7: C | O7: 8000000
A8: BIP | B8: =_xlfn.IFNA(VLOOKUP(C8,Sheet3!$H:$I,2,FALSE),"") -> B2210 | C8: GENERAL AFFAIR | D8: =_xlfn.IFNA(VLOOKUP(E8,Sheet3!$H:$I,2,FALSE),"") -> B2210 | E8: GENERAL AFFAIR | F8: 2141000 | G8: Tools, furniture & office equipment | H8: Personal Computer GA Staff | I8: 8000000 | J8: 60 | K8: 100 | L8: 44287 | M8: C | O8: 8000000
A9: BIP | B9: =_xlfn.IFNA(VLOOKUP(C9,Sheet3!$H:$I,2,FALSE),"") -> B2210 | C9: GENERAL AFFAIR | D9: =_xlfn.IFNA(VLOOKUP(E9,Sheet3!$H:$I,2,FALSE),"") -> B2220 | E9: HUMAN RESOURCE | F9: 2141000 | G9: Tools, furniture & office equipment | H9: Laptop Training | I9: 10000000 | J9: 60 | K9: 100 | L9: 44287 | M9: C | O9: 10000000
A10: BIP | B10: =_xlfn.IFNA(VLOOKUP(C10,Sheet3!$H:$I,2,FALSE),"") -> B2210 | C10: GENERAL AFFAIR | D10: =_xlfn.IFNA(VLOOKUP(E10,Sheet3!$H:$I,2,FALSE),"") -> B2210 | E10: GENERAL AFFAIR | F10: 2141000 | G10: Tools, furniture & office equipment | H10: Laptop IR & Legal | I10: 10000000 | J10: 60 | K10: 100 | L10: 44287 | M10: C | O10: 10000000
A11: BIP | B11: =_xlfn.IFNA(VLOOKUP(C11,Sheet3!$H:$I,2,FALSE),"") -> B2210 | C11: GENERAL AFFAIR | D11: =_xlfn.IFNA(VLOOKUP(E11,Sheet3!$H:$I,2,FALSE),"") -> B2210 | E11: GENERAL AFFAIR | F11: 2141000 | G11: Tools, furniture & office equipment | H11: Projector - Spark Plug 1 | I11: 8000000 | J11: 60 | K11: 100 | L11: 44348 | M11: C | O11: 8000000
A12: BIP | B12: =_xlfn.IFNA(VLOOKUP(C12,Sheet3!$H:$I,2,FALSE),"") -> B2210 | C12: GENERAL AFFAIR | D12: =_xlfn.IFNA(VLOOKUP(E12,Sheet3!$H:$I,2,FALSE),"") -> B2210 | E12: GENERAL AFFAIR | F12: 2141000 | G12: Tools, furniture & office equipment | H12: Projector - Spark Plug 2 | I12: 8000000 | J12: 60 | K12: 100 | L12: 44348 | M12: C | O12: 8000000
A13: BIP | B13: =_xlfn.IFNA(VLOOKUP(C13,Sheet3!$H:$I,2,FALSE),"") -> B2210 | C13: GENERAL AFFAIR | D13: =_xlfn.IFNA(VLOOKUP(E13,Sheet3!$H:$I,2,FALSE),"") -> B2210 | E13: GENERAL AFFAIR | F13: 2141000 | G13: Tools, furniture & office equipment | H13: Projector - Office | I13: 8000000 | J13: 60 | K13: 100 | L13: 44348 | M13: C | O13: 8000000
... A54: BIP | B54: =_xlfn.IFNA(VLOOKUP(C54,Sheet3!$H:$I,2,FALSE),"") -> B5500 | C54: Maintenance | D54: =_xlfn.IFNA(VLOOKUP(E54,Sheet3!$H:$I,2,FALSE),"") -> B2230 | E54: Health, Safety & Environment | F54: 2141000 | G54: Tools, furniture & office equipment | H54: Mini Crusher for composting | I54: 30000000 | J54: 60 | K54: 100 | L54: 45231 | M54: C | O54: 30000000
A55: BIP | B55: =_xlfn.IFNA(VLOOKUP(C55,Sheet3!$H:$I,2,FALSE),"") -> B5500 | C55: Maintenance | D55: =_xlfn.IFNA(VLOOKUP(E55,Sheet3!$H:$I,2,FALSE),"") -> B5500 | E55: Maintenance | F55: 2121000 | G55: Machinery & Equipment - New | H55: Transformer from Takenaka& Kinden | I55: 550000000 | J55: 120 | K55: 100 | L55: 44256 | M55: A | O55: =+I55 -> 550000000
A56: BIP | B56: =_xlfn.IFNA(VLOOKUP(C56,Sheet3!$H:$I,2,FALSE),"") -> B5600 | C56: Production Engineering | D56: =_xlfn.IFNA(VLOOKUP(E56,Sheet3!$H:$I,2,FALSE),"") -> B5900 | E56: Quality Control | F56: 2141000 | G56: Tools, furniture & office equipment | H56: Caliper for Rubber Measurement | I56: 14000000 | J56: 60 | K56: 100 | L56: 44378 | M56: B | O56: 14000000
A57: BIP | B57: =_xlfn.IFNA(VLOOKUP(C57,Sheet3!$H:$I,2,FALSE),"") -> B5600 | C57: Production Engineering | D57: =_xlfn.IFNA(VLOOKUP(E57,Sheet3!$H:$I,2,FALSE),"") -> B5900 | E57: Quality Control | F57: 2141000 | G57: Tools, furniture & office equipment | H57: Caliper for Rubber Measurement | I57: 14000000 | J57: 60 | K57: 100 | L57: 44378 | M57: B | O57: 14000000
A58: BIP | B58: =_xlfn.IFNA(VLOOKUP(C58,Sheet3!$H:$I,2,FALSE),"") -> B5600 | C58: Production Engineering | D58: =_xlfn.IFNA(VLOOKUP(E58,Sheet3!$H:$I,2,FALSE),"") -> B5900 | E58: Quality Control | F58: 2141000 | G58: Tools, furniture & office equipment | H58: Caliper for Rubber Measurement | I58: 14000000 | J58: 60 | K58: 100 | L58: 44378 | M58: B | O58: 14000000
A59: BIP | B59: =_xlfn.IFNA(VLOOKUP(C59,Sheet3!$H:$I,2,FALSE),"") -> B5600 | C59: Production Engineering | D59: =_xlfn.IFNA(VLOOKUP(E59,Sheet3!$H:$I,2,FALSE),"") -> B5600 | E59: Production Engineering | F59: 2141000 | G59: Tools, furniture & office equipment | H59: Notebook Replacement for Edy Haryono | I59: 10000000 | J59: 60 | K59: 100 | L59: 44409 | M59: B | O59: 10000000
A60: BIP | B60: =_xlfn.IFNA(VLOOKUP(C60,Sheet3!$H:$I,2,FALSE),"") -> B5600 | C60: Production Engineering | D60: =_xlfn.IFNA(VLOOKUP(E60,Sheet3!$H:$I,2,FALSE),"") -> B5600 | E60: Production Engineering | F60: 2141000 | G60: Tools, furniture & office equipment | H60: PC Replacement for Noviyanto | I60: 8000000 | J60: 60 | K60: 100 | L60: 44409 | M60: B | O60: 8000000
A61: BIP | B61: =_xlfn.IFNA(VLOOKUP(C61,Sheet3!$H:$I,2,FALSE),"") -> B5600 | C61: Production Engineering | D61: =_xlfn.IFNA(VLOOKUP(E61,Sheet3!$H:$I,2,FALSE),"") -> B4101 | E61: SP PD- CF | F61: 2141000 | G61: Tools, furniture & office equipment | H61: CF image inspection device for CF no. 1 | I61: 100000000 | J61: 60 | K61: 100 | L61: 44470 | M61: B | O61: 100000000
A62: BIP | B62: =_xlfn.IFNA(VLOOKUP(C62,Sheet3!$H:$I,2,FALSE),"") -> B5600 | C62: Production Engineering | D62: =_xlfn.IFNA(VLOOKUP(E62,Sheet3!$H:$I,2,FALSE),"") -> B4102 | E62: SP PD- CM | F62: 2121000 | G62: Machinery & Equipment - Second | H62: Periodic Maintenance CM Machine （№4）& Accessories | I62: 11167645280 | J62: 84 | K62: 100 | L62: 44593 | M62: A | O62: 11167645280
A63: BIP | B63: =_xlfn.IFNA(VLOOKUP(C63,Sheet3!$H:$I,2,FALSE),"") -> B5600 | C63: Production Engineering | D63: =_xlfn.IFNA(VLOOKUP(E63,Sheet3!$H:$I,2,FALSE),"") -> B4120 | E63: SP PD- Final Inspection | F63: 2121000 | G63: Machinery & Equipment - New | H63: Semi Auto Packaging Machine №2 | I63: 1.0544116e+09 | J63: 120 | K63: 100 | L63: 44593 | M63: A | O63: 1.0544116e+09
A64: BIP | B64: =_xlfn.IFNA(VLOOKUP(C64,Sheet3!$H:$I,2,FALSE),"") -> B5600 | C64: Production Engineering | D64: =_xlfn.IFNA(VLOOKUP(E64,Sheet3!$H:$I,2,FALSE),"") -> B5600 | E64: Production Engineering | F64: 2141000 | G64: Tools, furniture & office equipment | H64: End Mill Grinder | I64: 30000000 | J64: 60 | K64: 100 | L64: 44713 | M64: C | O64: 30000000
A65: BIP | B65: =_xlfn.IFNA(VLOOKUP(C65,Sheet3!$H:$I,2,FALSE),"") -> B5600 | C65: Production Engineering | D65: =_xlfn.IFNA(VLOOKUP(E65,Sheet3!$H:$I,2,FALSE),"") -> B4106 | E65: SP PD- Insulator Sealing | F65: 2121000 | G65: Machinery & Equipment - Second | H65: Periodic Maintenance Assy Insulator furnace Oven | I65: 1594117400 | J65: 84 | K65: 100 | L65: 44774 | M65: A | O65: 1594117400
A66: BIP | B66: =_xlfn.IFNA(VLOOKUP(C66,Sheet3!$H:$I,2,FALSE),"") -> B5600 | C66: Production Engineering | D66: =_xlfn.IFNA(VLOOKUP(E66,Sheet3!$H:$I,2,FALSE),"") -> B4106 | E66: SP PD- Insulator Sealing | F66: 2121000 | G66: Machinery & Equipment - New | H66: Update Setsugo Machine （№4）C2 NEW | I66: 14748527060 | J66: 120 | K66: 100 | L66: 44805 | M66: C | O66: 14748527060
A67: BIP | B67: =_xlfn.IFNA(VLOOKUP(C67,Sheet3!$H:$I,2,FALSE),"") -> B5600 | C67: Production Engineering | D67: =_xlfn.IFNA(VLOOKUP(E67,Sheet3!$H:$I,2,FALSE),"") -> B4102 | E67: SP PD- CM | F67: 2121000 | G67: Machinery & Equipment - Second | H67: Periodic Maintenance CM No.9 & Accessories | I67: 11167645280 | J67: 84 | K67: 100 | L67: 44866 | M67: A | O67: 11167645280
... A147: BIP | B147: =_xlfn.IFNA(VLOOKUP(C147,Sheet3!$H:$I,2,FALSE),"") -> B5000 | C147: Plant Operation (Indirect Mfg) | D147: =_xlfn.IFNA(VLOOKUP(E147,Sheet3!$H:$I,2,FALSE),"") -> B5000 | E147: Plant Operation (Indirect Mfg) | F147: 2141000 | G147: Tools, furniture & office equipment | H147: PC IWAIZAKO - BIP | I147: 10000000 | J147: 60 | K147: 100 | L147: 44621 | M147: B | O147: 10000000

Sheet Master
A1: Name | B1: BNGK | C1: GROUP COST | D1: GROUP SECTION | E1: Name | G1: Code | H1: Name | J1: Name COA AX | K1: COA AX | L1: Group Cost | M1: UNIQ | N1: COA Budget | O1: Description | Q1: Name | R1: BNGK | S1: GROUP COST | T1: GROUP SECTION | U1: Name | W1: Code | X1: Name | Z1: Priority Code | AA1: Priority Name | AB1: Description | AD1: COA Assets | AE1: Name of Asset | AF1: COA Depre | AG1: Name of Depre | AI1: Priority Code | AJ1: Priority Name | AK1: Description
A2: Top Management | B2: B1000 | C2: SGA | D2: ADM | E2: =A2 -> Top Management | G2: 53450 | H2: NGK BUSI INDONESIA | J2: Salary for Commissioner | K2: 7511101 | L2: SGA | M2: =L2&"-"&K2 -> SGA-7511101 | N2: A502 | O2: Salary for Commissioner | Q2: Top Management | R2: B1000 | S2: SGA | T2: ADM | U2: =Q2 -> Top Management | W2: 53450 | X2: NGK BUSI INDONESIA | Z2: A | AA2: Must | AB2: If this is not done, the company or our team cannot continue its business. | AD2: 2111100 | AE2: Building | AF2: 7611100 | AG2: Depreciation-Building | AI2: A | AJ2: Must | AK2: If this is not done, the company or our team cannot continue its business.
A3: Commissioner | B3: B1001 | C3: SGA | D3: ADM | E3: =A3 -> Commissioner | J3: Salary for Director | K3: 7511102 | L3: SGA | M3: =L3&"-"&K3 -> SGA-7511102 | N3: A502 | O3: Salary for Director & Expat | Q3: Commissioner | R3: B1001 | S3: SGA | T3: ADM | U3: =Q3 -> Commissioner | Z3: B | AA3: Want to | AB3: We want to do it as a team this term. we need it. | AD3: 2121000 | AE3: Machinery & Equipment | AF3: 7611300 | AG3: Depreciation-Machiney & equipment | AI3: B | AJ3: Want to | AK3: We want to do it as a team this term. we need it.
A4: Admin & HR | B4: B2200 | C4: SGA | D4: ADM | E4: =A4 -> Admin & HR | J4: Staff Labor - Baslc Salary | K4: 7511103 | L4: SGA | M4: =L4&"-"&K4 -> SGA-7511103 | N4: A501 | O4: Basic Salary of permanent employee | Q4: Admin & HR | R4: B2200 | S4: SGA | T4: ADM | U4: =Q4 -> Admin & HR | Z4: C | AA4: Challenge | AB4: We want to do it for this term or the future. But it doesn't matter if it's not this term. | AD4: 2131000 | AE4: Vehicles | AF4: 7611500 | AG4: Depreciation-Vehicles | AI4: C | AJ4: Challenge | AK4: We want to do it for this term or the future. But it doesn't matter if it's not this term.
A5: General Affair | B5: B2210 | C5: SGA | D5: ADM | E5: =A5 -> General Affair | J5: Staff Labor - Allowance | K5: 7511111 | L5: SGA | M5: =L5&"-"&K5 -> SGA-7511111 | N5: A501 | O5: Employee allowance | Q5: General Affair | R5: B2210 | S5: SGA | T5: ADM | U5: =Q5 -> General Affair | AD5: 2141000 | AE5: Tools, furniture & office equipment | AF5: 7611600 | AG5: Depreciation-Tools, furniture & office equipment
A6: Human Resource | B6: B2220 | C6: SGA | D6: ADM | E6: =A6 -> Human Resource | J6: Staff Labor - Tax allowance (art.21) | K6: 7511112 | L6: SGA | M6: =L6&"-"&K6 -> SGA-7511112 | N6: A501 | O6: Empployee Tax allowance | Q6: Human Resource | R6: B2220 | S6: SGA | T6: ADM | U6: =Q6 -> Human Resource | AD6: 2221101 | AE6: Software | AF6: 7611700 | AG6: Depreciation-Software
A7: Health, Safety & Environment | B7: B2230 | C7: SGA | D7: ADM | E7: =A7 -> Health, Safety & Environment | J7: Staff Labor - BPJS JK & JKK (1.19%) | K7: 7511121 | L7: SGA | M7: =L7&"-"&K7 -> SGA-7511121 | N7: A501 | O7: BPJS JK & JKK (death warrant, Accident Insurance) | Q7: Health, Safety & Environment | R7: B2230 | S7: SGA | T7: ADM | U7: =Q7 -> Health, Safety & Environment
A8: Accounting & Finance | B8: B2300 | C8: SGA | D8: ADM | E8: =A8 -> Accounting & Finance | J8: Staff Labor - BPJS Kesehatan (4%) | K8: 7511122 | L8: SGA | M8: =L8&"-"&K8 -> SGA-7511122 | N8: A501 | O8: BPJS health insurance | Q8: Accounting & Finance | R8: B2300 | S8: SGA | T8: ADM | U8: =Q8 -> Accounting & Finance
A9: Information Technology | B9: B2400 | C9: SGA | D9: ADM | E9: =A9 -> Information Technology | J9: Staff Overtime | K9: 7511201 | L9: SGA | M9: =L9&"-"&K9 -> SGA-7511201 | N9: A503 | O9: Overtime permanent employee | Q9: Information Technology | R9: B2400 | S9: SGA | T9: ADM | U9: =Q9 -> Information Technology
A10: Sales & MKTG Dept.- Automotive | B10: B3100 | C10: SGA | D10: ADM | E10: =A10 -> Sales & MKTG Dept.- Automotive | J10: Staff Welfare - BPJS Dana pensiun (2%) | K10: 7512111 | L10: SGA | M10: =L10&"-"&K10 -> SGA-7512111 | N10: A504 | O10: BPJS pension fund | Q10: Sales & MKTG Dept.- Automotive | R10: B3100 | S10: SGA | T10: ADM | U10: =Q10 -> Sales & MKTG Dept.- Automotive
A11: Marketing | B11: B3160 | C11: SGA | D11: ADM | E11: =A11 -> Marketing | J11: Staff Welfare - BPJS JHT (3.7%) | K11: 7512112 | L11: SGA | M11: =L11&"-"&K11 -> SGA-7512112 | N11: A504 | O11: BPJS Pension plan | Q11: Marketing | R11: B3160 | S11: SGA | T11: ADM | U11: =Q11 -> Marketing
A12: Sales - OEM | B12: B3110 | C12: SGA | D12: ADM | E12: =A12 -> Sales - OEM | J12: Staff Bonus / TAT | K12: 7514101 | L12: SGA | M12: =L12&"-"&K12 -> SGA-7514101 | N12: A501 | O12: Year-end allowance & Alpha | Q12: Sales - OEM | R12: B3110 | S12: SGA | T12: ADM | U12: =Q12 -> Sales - OEM
A13: Sales - OES | B13: B3120 | C13: SGA | D13: ADM | E13: =A13 -> Sales - OES | J13: Staff Ramadhan / THR | K13: 7514102 | L13: SGA | M13: =L13&"-"&K13 -> SGA-7514102 | N13: A501 | O13: Lebaran bonus | Q13: Sales - OES | R13: B3120 | S13: SGA | T13: ADM | U13: =Q13 -> Sales - OES
A14: Sales - IAM | B14: B3130 | C14: SGA | D14: ADM | E14: =A14 -> Sales - IAM | J14: Staff Welfare - Outpatient (Medical) | K14: 7515401 | L14: SGA | M14: =L14&"-"&K14 -> SGA-7515401 | N14: A504 | O14: outpatient treatment costs | Q14: Sales - IAM | R14: B3130 | S14: SGA | T14: ADM | U14: =Q14 -> Sales - IAM
A15: SP PD- CF | B15: B4101 | C15: MFG | D15: DIR | E15: =A15 -> SP PD- CF | J15: Staff Welfare - Hospitalization | K15: 7515402 | L15: SGA | M15: =L15&"-"&K15 -> SGA-7515402 | N15: A504 | O15: hospitalization costs | Q15: SP PD- CF | R15: B4101 | S15: MFG | T15: DIR | U15: =Q15 -> SP PD- CF
A16: SP PD- CM | B16: B4102 | C16: MFG | D16: DIR | E16: =A16 -> SP PD- CM | J16: Staff Welfare - Glasses | K16: 7515403 | L16: SGA | M16: =L16&"-"&K16 -> SGA-7515403 | N16: A504 | O16: glasses costs | Q16: SP PD- CM | R16: B4102 | S16: MFG | T16: DIR | U16: =Q16 -> SP PD- CM
A17: SP PD- WT | B17: B4103 | C17: MFG | D17: DIR | E17: =A17 -> SP PD- WT | J17: Staff Welfare - Dental | K17: 7515404 | L17: SGA | M17: =L17&"-"&K17 -> SGA-7515404 | N17: A504 | O17: dental costs | Q17: SP PD- WT | R17: B4103 | S17: MFG | T17: DIR | U17: =Q17 -> SP PD- WT
A18: SP PD- Plating | B18: B4105 | C18: MFG | D18: DIR | E18: =A18 -> SP PD- Plating | J18: Staff Welfare - Medical Check Up | K18: 7515405 | L18: SGA | M18: =L18&"-"&K18 -> SGA-7515405 | N18: A504 | O18: Medical Check Up cost | Q18: SP PD- Plating | R18: B4105 | S18: MFG | T18: DIR | U18: =Q18 -> SP PD- Plating
A19: SP PD- MS Insp. | B19: B4109 | C19: MFG | D19: DIR | E19: =A19 -> SP PD- MS Insp. | J19: Staff Welfare - Uniform | K19: 7515406 | L19: SGA | M19: =L19&"-"&K19 -> SGA-7515406 | N19: A504 | O19: uniform costs | Q19: SP PD- MS Insp. | R19: B4109 | S19: MFG | T19: DIR | U19: =Q19 -> SP PD- MS Insp.
A20: SP PD- Insulator Sealing | B20: B4106 | C20: MFG | D20: DIR | E20: =A20 -> SP PD- Insulator Sealing | J20: Staff Welfare - Safety Shoes | K20: 7515407 | L20: SGA | M20: =L20&"-"&K20 -> SGA-7515407 | N20: A504
A21: SP PD- Assy | B21: B4110 | C21: MFG | D21: DIR | E21: =A21 -> SP PD- Assy | J21: Staff Welfare - Family Gathering / Anniversary | K21: 7515408 | L21: SGA | M21: =L21&"-"&K21 -> SGA-7515408 | N21: A504 | O21: Family Gathering / Anniversary | Q21: SP PD- Insulator Sealing | R21: B4106 | S21: MFG | T21: DIR | U21: =Q21 -> SP PD- Insulator Sealing
A22: SP-PD-Assy-Auto Assembly | B22: B4115 | C22: MFG | D22: DIR | E22: =A22 -> SP-PD-Assy-Auto Assembly | J22: Staff Welfare - Meals of canteen & other meals | K22: 7515409 | L22: SGA | M22: =L22&"-"&K22 -> SGA-7515409 | N22: A504 | O22: Meals of canteen & other meals cost | Q22: SP PD- Assy | R22: B4110 | S22: MFG | T22: DIR | U22: =Q22 -> SP PD- Assy
A23: SP PD- Bending | B23: B4114 | C23: MFG | D23: DIR | E23: =A23 -> SP PD- Bending | J23: Staff Welfare - Kaizen & QCC reward | K23: 7515410 | L23: SGA | M23: =L23&"-"&K23 -> SGA-7515410 | N23: A504 | O23: an expense, arising from Kaizen and QCC acitivity | Q23: SP-PD-Assy-Auto Assembly | R23: B4115 | S23: MFG | T23: DIR | U23: =Q23 -> SP-PD-Assy-Auto Assembly
A24: SP PD- Final Inspection | B24: B4120 | C24: MFG | D24: DIR | E24: =A24 -> SP PD- Final Inspection | J24: Staff Welfare - Welfare Others | K24: 7515499 | L24: SGA | M24: =L24&"-"&K24 -> SGA-7515499 | N24: A504 | O24: an other welfare expense, arising besides the above welfare expense | Q24: SP PD- Bending | R24: B4114 | S24: MFG | T24: DIR | U24: =Q24 -> SP PD- Bending
A25: SP PD- QC - OEM | B25: B4121 | C25: MFG | D25: DIR | E25: =A25 -> SP PD- QC - OEM | J25: Retirement Allowance | K25: 7516102 | L25: SGA | M25: =L25&"-"&K25 -> SGA-7516102 | N25: A505 | O25: employee retirement provission costs | Q25: SP PD- Final Inspection | R25: B4120 | S25: MFG | T25: DIR | U25: =Q25 -> SP PD- Final Inspection
A26: PC PD- Injection | B26: B4410 | C26: MFG | D26: DIR | E26: =A26 -> PC PD- Injection | J26: House Rent Allowance | K26: 7519101 | L26: SGA | M26: =L26&"-"&K26 -> SGA-7519101 | N26: A502 | O26: House Rent Allowance for expat | Q26: SP PD- QC - OEM | R26: B4121 | S26: MFG | T26: DIR | U26: =Q26 -> SP PD- QC - OEM
A27: PC PD- Assy | B27: B4430 | C27: MFG | D27: DIR | E27: =A27 -> PC PD- Assy | J27: Casual Staff Labor - Basic Salary | K27: 7521101 | L27: SGA | M27: =L27&"-"&K27 -> SGA-7521101 | N27: A501 | O27: All benefit for temporary worker | Q27: PC PD- Injection | R27: B4410 | S27: MFG | T27: DIR | U27: =Q27 -> PC PD- Injection
A28: PC PD- QC | B28: B4440 | C28: MFG | D28: DIR | E28: =A28 -> PC PD- QC | J28: Casual Staff Labor - Overtime | K28: 7521102 | L28: SGA | M28: =L28&"-"&K28 -> SGA-7521102 | N28: A503 | O28: Overtime temporary worker | Q28: PC PD- Assy | R28: B4430 | S28: MFG | T28: DIR | U28: =Q28 -> PC PD- Assy
A29: Plant Operation (Indirect Mfg) | B29: B5000 | C29: MFG | D29: IND | E29: =A29 -> Plant Operation (Indirect Mfg) | J29: Personnel expense transferred | K29: 7571101 | L29: SGA | M29: =L29&"-"&K29 -> SGA-7571101 | N29: A506 | O29: Transfer Labor cost from one section into another section | Q29: PC PD- QC | R29: B4440 | S29: MFG | T29: DIR | U29: =Q29 -> PC PD- QC
A30: Production Office | B30: B5100 | C30: MFG | D30: IND | E30: =A30 -> Production Office | J30: Depreciation-Building | K30: 7611100 | L30: SGA | M30: =L30&"-"&K30 -> SGA-7611100 | N30: A601 | O30: the amount of depreciation of tangible assets for building | Q30: Plant Operation (Indirect Mfg) | R30: B5000 | S30: MFG | T30: IND | U30: =Q30 -> Plant Operation (Indirect Mfg)
A31: Production Office (SP) | B31: B5101 | C31: MFG | D31: IND | E31: =A31 -> Production Office (SP) | J31: Depreciation-Machiney & equipment | K31: 7611300 | L31: SGA | M31: =L31&"-"&K31 -> SGA-7611300 | N31: A601 | O31: the amount of depreciation of tangible assets for machinery & factory equipment | Q31: Production Office | R31: B5100 | S31: MFG | T31: IND | U31: =Q31 -> Production Office
A32: Production Office (PC) | B32: B5104 | C32: MFG | D32: IND | E32: =A32 -> Production Office (PC) | J32: Depreciation-Lease Machinery & equipment | K32: 7611400 | L32: SGA | M32: =L32&"-"&K32 -> SGA-7611400 | N32: A601 | O32: the amount of depreciation of tangible assets for machinery & factory equipment (Leases) | Q32: Production Office (SP) | R32: B5101 | S32: MFG | T32: IND | U32: =Q32 -> Production Office (SP)
... A42: WH Dept.- KD & RM | B42: B5710 | C42: MFG | D42: IND | E42: =A42 -> WH Dept.- KD & RM | J42: Repair of Equipment | K42: 7641102 | L42: SGA | M42: =L42&"-"&K42 -> SGA-7641102 | N42: A1002 | O42: expenses for repair and maintenance tangible assets, intangible assets and other assets beside building | Q42: Continuous Improvement | R42: B5007 | S42: MFG | T42: IND | U42: =Q42 -> Continuous Improvement
A43: Continuous Improvement | B43: B5007 | C43: MFG | D43: IND | E43: =A43 -> Continuous Improvement | J43: Factory Supply Expense | K43: 7641103 | L43: SGA | M43: =L43&"-"&K43 -> SGA-7641103 | N43: A1099 | O43: All cost that arrising to support factory acitivity | Q43: All | R43: B0000 | U43: =Q43 -> All
J44: Calibration Cost | K44: 7641104 | L44: SGA | M44: =L44&"-"&K44 -> SGA-7641104 | N44: A1099 | O44: Cost of calibration for tools and equipment of factory and others
J45: Transportation Fee for employee | K45: 7651101 | L45: SGA | M45: =L45&"-"&K45 -> SGA-7651101 | N45: A801 | O45: Gasoline of company cars & expense for Local transportation
J46: Travel Expense-Domestic | K46: 7651102 | L46: SGA | M46: =L46&"-"&K46 -> SGA-7651102 | N46: A801 | O46: expenses for business trip, including allowance for business trip to an employee only for domestic travel
J47: Travel Expense-Oversea | K47: 7651103 | L47: SGA | M47: =L47&"-"&K47 -> SGA-7651103 | N47: A801 | O47: expenses for business trip, including allowance for business trip to an employee only for overseas travel
J48: Entertainment | K48: 7661101 | L48: SGA | M48: =L48&"-"&K48 -> SGA-7661101 | N48: A1001 | O48: the amount of expenses for the act of entertaining the business partner
J49: Amortization of Land & Building tax (PBB) | K49: 7671102 | L49: SGA | M49: =L49&"-"&K49 -> SGA-7671102 | N49: A1099 | O49: the amount of depreciation of intangible of Land & Building Tax (PBB)
J50: License fee | K50: 7671103 | L50: SGA | M50: =L50&"-"&K50 -> SGA-7671103 | N50: A1099 | O50: The expense related with the documentation process, such as : KIR, Car lisence, company lisence, etc.
J51: Insurance Premium | K51: 7681101 | L51: SGA | M51: =L51&"-"&K51 -> SGA-7681101 | N51: A1099 | O51: expenses for risk management with no premium at the end of the term, such as fire insurance for plants and inventories
J52: Office supply & Stationary Expense | K52: 7691000 | L52: SGA | M52: =L52&"-"&K52 -> SGA-7691000 | N52: A1099 | O52: the amount of supplies for office, such as stationery. Small office equipment included
J53: Communication expenses | K53: 7711101 | L53: SGA | M53: =L53&"-"&K53 -> SGA-7711101 | N53: A1099 | O53: expenses for communication with a people in remote place, such as expense for telephone and postage
J54: IT Expense | K54: 7711102 | L54: SGA | M54: =L54&"-"&K54 -> SGA-7711102 | N54: A1005 | O54: the amount of supplies for IT tools
J55: Stamp/Post Fee | K55: 7711103 | L55: SGA | M55: =L55&"-"&K55 -> SGA-7711103 | N55: A1099 | O55: The expenses related with stamp duty
... J76: Cost of Samples | K76: 7461101 | L76: SGA | M76: =L76&"-"&K76 -> SGA-7461101 | N76: A499 | O76: Sample expense
J77: Sales - Insurance of Delivery or Shipment | K77: 7411105 | L77: SGA | M77: =L77&"-"&K77 -> SGA-7411105 | N77: A299
J78: Sales - Insurance of AR (Credit Insurance) | K78: 7471201 | L78: SGA | M78: =L78&"-"&K78 -> SGA-7471201 | N78: A299
J79: Sales - Royalty to NGK Group | K79: 7751101 | L79: SGA | M79: =L79&"-"&K79 -> SGA-7751101
J80: Sales - Royalty to Independence Party | K80: 7751102 | L80: SGA | M80: =L80&"-"&K80 -> SGA-7751102
J81: Import Duty-purchased FG from NGK group | K81: 7111211 | L81: MFG | M81: =L81&"-"&K81 -> MFG-7111211
J82: Import Duty-purchased FG from outside supplier | K82: 7111212 | L82: MFG | M82: =L82&"-"&K82 -> MFG-7111212
J83: Import Duty-purchased KD&RM from NGK Japan | K83: 7111221 | L83: MFG | M83: =L83&"-"&K83 -> MFG-7111221
J84: Import Duty-purchased KD&RM from NGK Group(Not fromJP) | K84: 7111222 | L84: MFG | M84: =L84&"-"&K84 -> MFG-7111222
J85: Import Duty-purchased Comp Parts&RM from outside supplier | K85: 7111223 | L85: MFG | M85: =L85&"-"&K85 -> MFG-7111223
J86: Import Expense-purchased FG from NGK group | K86: 7111311 | L86: MFG | M86: =L86&"-"&K86 -> MFG-7111311
J87: Import Expense-purchased FG from outside supplier | K87: 7111312 | L87: MFG | M87: =L87&"-"&K87 -> MFG-7111312
J88: Import Expense-purchased KD&RM from NGK Japan | K88: 7111321 | L88: MFG | M88: =L88&"-"&K88 -> MFG-7111321
J89: Import Expense-purchased KD&RM from NGK Group(Not fromJP) | K89: 7111322 | L89: MFG | M89: =L89&"-"&K89 -> MFG-7111322
J90: Import Expense-purchased Comp Parts&RM from outside supplier | K90: 7111323 | L90: MFG | M90: =L90&"-"&K90 -> MFG-7111323
... J94: Cost of Factory Supply | K94: 7211101 | L94: MFG | M94: =L94&"-"&K94 -> MFG-7211101
J95: Cost of Chemical | K95: 7211102 | L95: MFG | M95: =L95&"-"&K95 -> MFG-7211102 | N95: 901 | O95: The expenses of Chemicals consumption
J96: Cost of Packaging | K96: 7211103 | L96: MFG | M96: =L96&"-"&K96 -> MFG-7211103
J97: Cost of Oil | K97: 7211104 | L97: MFG | M97: =L97&"-"&K97 -> MFG-7211104 | N97: 302
J98: Cost of Tooling | K98: 7221101 | L98: MFG | M98: =L98&"-"&K98 -> MFG-7221101 | N98: 302 | O98: The expenses of Tooling consumption
J99: Cost of Machinery parts | K99: 7221102 | L99: MFG | M99: =L99&"-"&K99 -> MFG-7221102 | N99: 301 | O99: The expenses of Spare Parts consumption
J100: Salary for Commissioner | K100: 7511101 | L100: MFG | M100: =L100&"-"&K100 -> MFG-7511101 | N100: 602 | O100: Salary for Commissioner
J101: Salary for Director | K101: 7511102 | L101: MFG | M101: =L101&"-"&K101 -> MFG-7511102 | N101: 602 | O101: Salary for Director & Expat
J102: Staff Labor - Baslc Salary | K102: 7511103 | L102: MFG | M102: =L102&"-"&K102 -> MFG-7511103 | N102: 601 | O102: Basic Salary of permanent employee
J103: Staff Labor - Allowance | K103: 7511111 | L103: MFG | M103: =L103&"-"&K103 -> MFG-7511111 | N103: 601 | O103: Employee allowance
J104: Staff Labor - Tax allowance (art.21) | K104: 7511112 | L104: MFG | M104: =L104&"-"&K104 -> MFG-7511112 | N104: 601 | O104: Empployee Tax allowance
J105: Staff Labor - BPJS JK & JKK (1.19%) | K105: 7511121 | L105: MFG | M105: =L105&"-"&K105 -> MFG-7511121 | N105: 601 | O105: BPJS JK & JKK (death warrant, Accident Insurance)
J106: Staff Labor - BPJS Kesehatan (4%) | K106: 7511122 | L106: MFG | M106: =L106&"-"&K106 -> MFG-7511122 | N106: 601 | O106: BPJS health insurance
J107: Staff Overtime | K107: 7511201 | L107: MFG | M107: =L107&"-"&K107 -> MFG-7511201 | N107: 603 | O107: Overtime permanent employee
J108: Staff Welfare - BPJS Dana pensiun (2%) | K108: 7512111 | L108: MFG | M108: =L108&"-"&K108 -> MFG-7512111 | N108: 604 | O108: BPJS pension fund
J109: Staff Welfare - BPJS JHT (3.7%) | K109: 7512112 | L109: MFG | M109: =L109&"-"&K109 -> MFG-7512112 | N109: 604 | O109: BPJS Pension plan
... J117: Staff Welfare - Uniform | K117: 7515406 | L117: MFG | M117: =L117&"-"&K117 -> MFG-7515406 | N117: 604 | O117: uniform costs
J118: Staff Welfare - Safety Shoes | K118: 7515407 | L118: MFG | M118: =L118&"-"&K118 -> MFG-7515407 | N118: 604
J119: Staff Welfare - Family Gathering / Anniversary | K119: 7515408 | L119: MFG | M119: =L119&"-"&K119 -> MFG-7515408 | N119: 604 | O119: Family Gathering / Anniversary
J120: Staff Welfare - Meals of canteen & other meals | K120: 7515409 | L120: MFG | M120: =L120&"-"&K120 -> MFG-7515409 | N120: 604 | O120: Meals of canteen & other meals cost
J121: Staff Welfare - Kaizen & QCC reward | K121: 7515410 | L121: MFG | M121: =L121&"-"&K121 -> MFG-7515410 | N121: 604 | O121: an expense, arising from Kaizen and QCC acitivity
J122: Staff Welfare - Welfare Others | K122: 7515499 | L122: MFG | M122: =L122&"-"&K122 -> MFG-7515499 | N122: 604 | O122: an other welfare expense, arising besides the above welfare expense
J123: Retirement Allowance | K123: 7516102 | L123: MFG | M123: =L123&"-"&K123 -> MFG-7516102 | N123: 605 | O123: employee retirement provission costs
J124: House Rent Allowance | K124: 7519101 | L124: MFG | M124: =L124&"-"&K124 -> MFG-7519101 | N124: 602 | O124: House Rent Allowance for expat
J125: Casual Staff Labor | K125: 7521101 | L125: MFG | M125: =L125&"-"&K125 -> MFG-7521101 | N125: 601 | O125: All benefit for temporary worker
J126: Casual Staff Labor - Overtime | K126: 7521102 | L126: MFG | M126: =L126&"-"&K126 -> MFG-7521102 | N126: 603 | O126: Overtime temporary worker
J127: Personnel expense transferred | K127: 7571101 | L127: MFG | M127: =L127&"-"&K127 -> MFG-7571101 | N127: 606 | O127: Transfer Labor cost from one section into another section
J128: Depreciation-Building | K128: 7611100 | L128: MFG | M128: =L128&"-"&K128 -> MFG-7611100 | N128: 701 | O128: the amount of depreciation of tangible assets for building
J129: Depreciation-Machiney & equipment | K129: 7611300 | L129: MFG | M129: =L129&"-"&K129 -> MFG-7611300 | N129: 701 | O129: the amount of depreciation of tangible assets for machinery & factory equipment
J130: Depreciation-Lease Machinery & equipment | K130: 7611400 | L130: MFG | M130: =L130&"-"&K130 -> MFG-7611400 | N130: 701 | O130: the amount of depreciation of tangible assets for machinery & factory equipment (Leases)
... J166: Expatriate fee Tax (BADORA) | K166: 7781113 | L166: MFG | M166: =L166&"-"&K166 -> MFG-7781113 | N166: 999 | O166: Tax income from expatriete
J167: Others - Miscellaneous Waste | K167: 8291101 | L167: OTH | M167: =L167&"-"&K167 -> OTH-8291101
J168: Others - Miscellaneous Tax | K168: 8291102 | L168: OTH | M168: =L168&"-"&K168 -> OTH-8291102
J169: Others - Sport Activity | K169: 8291201 | L169: OTH | M169: =L169&"-"&K169 -> OTH-8291201
J170: Others - Retribution / Garbage Cost | K170: 8291202 | L170: OTH | M170: =L170&"-"&K170 -> OTH-8291202
J171: Others - Miscellaneous Non Operational Expense | K171: 8291203 | L171: OTH | M171: =L171&"-"&K171 -> OTH-8291203
J172: Other Income | K172: 8191101 | L172: OTH | M172: =L172&"-"&K172 -> OTH-8191101

Sheet Sheet3
A1: Name COA AX | B1: COA AX | C1: Group Cost | D1: UNIQ | E1: COA Budget | F1: Description | H1: Name | I1: BNGK | J1: GROUP COST | K1: GROUP SECTION | L1: Name | N1: Code | O1: Name | Q1: Priority Code | R1: Priority Name | S1: Description
A2: Salary for Commissioner | B2: 7511101 | C2: SGA | D2: =C2&"-"&B2 -> SGA-7511101 | E2: A502 | F2: Salary for Commissioner | H2: Top Management | I2: B1000 | J2: SGA | K2: ADM | L2: =H2 -> Top Management | N2: 53450 | O2: NGK BUSI INDONESIA | Q2: A | R2: Must | S2: If this is not done, the company or our team cannot continue its business.
A3: Salary for Director | B3: 7511102 | C3: SGA | D3: =C3&"-"&B3 -> SGA-7511102 | E3: A502 | F3: Salary for Director & Expat | H3: Commissioner | I3: B1001 | J3: SGA | K3: ADM | L3: =H3 -> Commissioner | Q3: B | R3: Want to | S3: We want to do it as a team this term. we need it.
A4: Staff Labor - Baslc Salary | B4: 7511103 | C4: SGA | D4: =C4&"-"&B4 -> SGA-7511103 | E4: A501 | F4: Basic Salary of permanent employee | H4: Admin & HR | I4: B2200 | J4: SGA | K4: ADM | L4: =H4 -> Admin & HR | Q4: C | R4: Challenge | S4: We want to do it for this term or the future. But it doesn't matter if it's not this term.
A5: Staff Labor - Allowance | B5: 7511111 | C5: SGA | D5: =C5&"-"&B5 -> SGA-7511111 | E5: A501 | F5: Employee allowance | H5: General Affair | I5: B2210 | J5: SGA | K5: ADM | L5: =H5 -> General Affair
A6: Staff Labor - Tax allowance (art.21) | B6: 7511112 | C6: SGA | D6: =C6&"-"&B6 -> SGA-7511112 | E6: A501 | F6: Empployee Tax allowance | H6: Human Resource | I6: B2220 | J6: SGA | K6: ADM | L6: =H6 -> Human Resource
A7: Staff Labor - BPJS JK & JKK (1.19%) | B7: 7511121 | C7: SGA | D7: =C7&"-"&B7 -> SGA-7511121 | E7: A501 | F7: BPJS JK & JKK (death warrant, Accident Insurance) | H7: Health, Safety & Environment | I7: B2230 | J7: SGA | K7: ADM | L7: =H7 -> Health, Safety & Environment
A8: Staff Labor - BPJS Kesehatan (4%) | B8: 7511122 | C8: SGA | D8: =C8&"-"&B8 -> SGA-7511122 | E8: A501 | F8: BPJS health insurance | H8: Accounting & Finance | I8: B2300 | J8: SGA | K8: ADM | L8: =H8 -> Accounting & Finance
A9: Staff Overtime | B9: 7511201 | C9: SGA | D9: =C9&"-"&B9 -> SGA-7511201 | E9: A503 | F9: Overtime permanent employee | H9: Information Technology | I9: B2400 | J9: SGA | K9: ADM | L9: =H9 -> Information Technology
A10: Staff Welfare - BPJS Dana pensiun (2%) | B10: 7512111 | C10: SGA | D10: =C10&"-"&B10 -> SGA-7512111 | E10: A504 | F10: BPJS pension fund | H10: Sales & MKTG Dept.- Automotive | I10: B3100 | J10: SGA | K10: ADM | L10: =H10 -> Sales & MKTG Dept.- Automotive
A11: Staff Welfare - BPJS JHT (3.7%) | B11: 7512112 | C11: SGA | D11: =C11&"-"&B11 -> SGA-7512112 | E11: A504 | F11: BPJS Pension plan | H11: Marketing | I11: B3160 | J11: SGA | K11: ADM | L11: =H11 -> Marketing
A12: Staff Bonus / TAT | B12: 7514101 | C12: SGA | D12: =C12&"-"&B12 -> SGA-7514101 | E12: A501 | F12: Year-end allowance & Alpha | H12: Sales - OEM | I12: B3110 | J12: SGA | K12: ADM | L12: =H12 -> Sales - OEM
A13: Staff Ramadhan / THR | B13: 7514102 | C13: SGA | D13: =C13&"-"&B13 -> SGA-7514102 | E13: A501 | F13: Lebaran bonus | H13: Sales - OES | I13: B3120 | J13: SGA | K13: ADM | L13: =H13 -> Sales - OES
A14: Staff Welfare - Outpatient (Medical) | B14: 7515401 | C14: SGA | D14: =C14&"-"&B14 -> SGA-7515401 | E14: A504 | F14: outpatient treatment costs | H14: Sales - IAM | I14: B3130 | J14: SGA | K14: ADM | L14: =H14 -> Sales - IAM
A15: Staff Welfare - Hospitalization | B15: 7515402 | C15: SGA | D15: =C15&"-"&B15 -> SGA-7515402 | E15: A504 | F15: hospitalization costs | H15: SP PD- CF | I15: B4101 | J15: MFG | K15: DIR | L15: =H15 -> SP PD- CF
A16: Staff Welfare - Glasses | B16: 7515403 | C16: SGA | D16: =C16&"-"&B16 -> SGA-7515403 | E16: A504 | F16: glasses costs | H16: SP PD- CM | I16: B4102 | J16: MFG | K16: DIR | L16: =H16 -> SP PD- CM
... A19: Staff Welfare - Uniform | B19: 7515406 | C19: SGA | D19: =C19&"-"&B19 -> SGA-7515406 | E19: A504 | F19: uniform costs | H19: SP PD- MS Insp. | I19: B4109 | J19: MFG | K19: DIR | L19: =H19 -> SP PD- MS Insp.
A20: Staff Welfare - Safety Shoes | B20: 7515407 | C20: SGA | D20: =C20&"-"&B20 -> SGA-7515407 | E20: A504 | H20: SP PD- Insulator Sealing | I20: B4106 | J20: MFG | K20: DIR | L20: =H20 -> SP PD- Insulator Sealing
A21: Staff Welfare - Family Gathering / Anniversary | B21: 7515408 | C21: SGA | D21: =C21&"-"&B21 -> SGA-7515408 | E21: A504 | F21: Family Gathering / Anniversary | H21: SP PD- Assy | I21: B4110 | J21: MFG | K21: DIR | L21: =H21 -> SP PD- Assy
A22: Staff Welfare - Meals of canteen & other meals | B22: 7515409 | C22: SGA | D22: =C22&"-"&B22 -> SGA-7515409 | E22: A504 | F22: Meals of canteen & other meals cost | H22: SP-PD-Assy-Auto Assembly | I22: B4115 | J22: MFG | K22: DIR | L22: =H22 -> SP-PD-Assy-Auto Assembly
A23: Staff Welfare - Kaizen & QCC reward | B23: 7515410 | C23: SGA | D23: =C23&"-"&B23 -> SGA-7515410 | E23: A504 | F23: an expense, arising from Kaizen and QCC acitivity | H23: SP PD- Bending | I23: B4114 | J23: MFG | K23: DIR | L23: =H23 -> SP PD- Bending
A24: Staff Welfare - Welfare Others | B24: 7515499 | C24: SGA | D24: =C24&"-"&B24 -> SGA-7515499 | E24: A504 | F24: an other welfare expense, arising besides the above welfare expense | H24: SP PD- Final Inspection | I24: B4120 | J24: MFG | K24: DIR | L24: =H24 -> SP PD- Final Inspection
A25: Retirement Allowance | B25: 7516102 | C25: SGA | D25: =C25&"-"&B25 -> SGA-7516102 | E25: A505 | F25: employee retirement provission costs | H25: SP PD- QC - OEM | I25: B4121 | J25: MFG | K25: DIR | L25: =H25 -> SP PD- QC - OEM
A26: House Rent Allowance | B26: 7519101 | C26: SGA | D26: =C26&"-"&B26 -> SGA-7519101 | E26: A502 | F26: House Rent Allowance for expat | H26: PC PD- Injection | I26: B4410 | J26: MFG | K26: DIR | L26: =H26 -> PC PD- Injection
A27: Casual Staff Labor - Basic Salary | B27: 7521101 | C27: SGA | D27: =C27&"-"&B27 -> SGA-7521101 | E27: A501 | F27: All benefit for temporary worker | H27: PC PD- Assy | I27: B4430 | J27: MFG | K27: DIR | L27: =H27 -> PC PD- Assy
A28: Casual Staff Labor - Overtime | B28: 7521102 | C28: SGA | D28: =C28&"-"&B28 -> SGA-7521102 | E28: A503 | F28: Overtime temporary worker | H28: PC PD- QC | I28: B4440 | J28: MFG | K28: DIR | L28: =H28 -> PC PD- QC
A29: Personnel expense transferred | B29: 7571101 | C29: SGA | D29: =C29&"-"&B29 -> SGA-7571101 | E29: A506 | F29: Transfer Labor cost from one section into another section | H29: Plant Operation (Indirect Mfg) | I29: B5000 | J29: MFG | K29: IND | L29: =H29 -> Plant Operation (Indirect Mfg)
A30: Depreciation-Building | B30: 7611100 | C30: SGA | D30: =C30&"-"&B30 -> SGA-7611100 | E30: A601 | F30: the amount of depreciation of tangible assets for building | H30: Production Office | I30: B5100 | J30: MFG | K30: IND | L30: =H30 -> Production Office
A31: Depreciation-Machiney & equipment | B31: 7611300 | C31: SGA | D31: =C31&"-"&B31 -> SGA-7611300 | E31: A601 | F31: the amount of depreciation of tangible assets for machinery & factory equipment | H31: Production Office (SP) | I31: B5101 | J31: MFG | K31: IND | L31: =H31 -> Production Office (SP)
A32: Depreciation-Lease Machinery & equipment | B32: 7611400 | C32: SGA | D32: =C32&"-"&B32 -> SGA-7611400 | E32: A601 | F32: the amount of depreciation of tangible assets for machinery & factory equipment (Leases) | H32: Production Office (PC) | I32: B5104 | J32: MFG | K32: IND | L32: =H32 -> Production Office (PC)
... A41: Repair Building | B41: 7641101 | C41: SGA | D41: =C41&"-"&B41 -> SGA-7641101 | E41: A1002 | F41: expenses for repair and maintenance asset building | H41: Continuous Improvement | I41: B5007 | J41: MFG | K41: IND | L41: =H41 -> Continuous Improvement
A42: Repair of Equipment | B42: 7641102 | C42: SGA | D42: =C42&"-"&B42 -> SGA-7641102 | E42: A1002 | F42: expenses for repair and maintenance tangible assets, intangible assets and other assets beside building | H42: All | I42: B0000 | L42: =H42 -> All
A43: Factory Supply Expense | B43: 7641103 | C43: SGA | D43: =C43&"-"&B43 -> SGA-7641103 | E43: A1099 | F43: All cost that arrising to support factory acitivity
A44: Calibration Cost | B44: 7641104 | C44: SGA | D44: =C44&"-"&B44 -> SGA-7641104 | E44: A1099 | F44: Cost of calibration for tools and equipment of factory and others
A45: Transportation Fee for employee | B45: 7651101 | C45: SGA | D45: =C45&"-"&B45 -> SGA-7651101 | E45: A801 | F45: Gasoline of company cars & expense for Local transportation
A46: Travel Expense-Domestic | B46: 7651102 | C46: SGA | D46: =C46&"-"&B46 -> SGA-7651102 | E46: A801 | F46: expenses for business trip, including allowance for business trip to an employee only for domestic travel
A47: Travel Expense-Oversea | B47: 7651103 | C47: SGA | D47: =C47&"-"&B47 -> SGA-7651103 | E47: A801 | F47: expenses for business trip, including allowance for business trip to an employee only for overseas travel
A48: Entertainment | B48: 7661101 | C48: SGA | D48: =C48&"-"&B48 -> SGA-7661101 | E48: A1001 | F48: the amount of expenses for the act of entertaining the business partner
A49: Amortization of Land & Building tax (PBB) | B49: 7671102 | C49: SGA | D49: =C49&"-"&B49 -> SGA-7671102 | E49: A1099 | F49: the amount of depreciation of intangible of Land & Building Tax (PBB)
A50: License fee | B50: 7671103 | C50: SGA | D50: =C50&"-"&B50 -> SGA-7671103 | E50: A1099 | F50: The expense related with the documentation process, such as : KIR, Car lisence, company lisence, etc.
A51: Insurance Premium | B51: 7681101 | C51: SGA | D51: =C51&"-"&B51 -> SGA-7681101 | E51: A1099 | F51: expenses for risk management with no premium at the end of the term, such as fire insurance for plants and inventories
A52: Office supply & Stationary Expense | B52: 7691000 | C52: SGA | D52: =C52&"-"&B52 -> SGA-7691000 | E52: A1099 | F52: the amount of supplies for office, such as stationery. Small office equipment included
A53: Communication expenses | B53: 7711101 | C53: SGA | D53: =C53&"-"&B53 -> SGA-7711101 | E53: A1099 | F53: expenses for communication with a people in remote place, such as expense for telephone and postage
A54: IT Expense | B54: 7711102 | C54: SGA | D54: =C54&"-"&B54 -> SGA-7711102 | E54: A1005 | F54: the amount of supplies for IT tools
... A76: Cost of Samples | B76: 7461101 | C76: SGA | D76: =C76&"-"&B76 -> SGA-7461101 | E76: A499 | F76: Sample expense
A77: Sales - Insurance of Delivery or Shipment | B77: 7411105 | C77: SGA | D77: =C77&"-"&B77 -> SGA-7411105 | E77: A299
A78: Sales - Insurance of AR (Credit Insurance) | B78: 7471201 | C78: SGA | D78: =C78&"-"&B78 -> SGA-7471201 | E78: A299
A79: Sales - Royalty to NGK Group | B79: 7751101 | C79: SGA | D79: =C79&"-"&B79 -> SGA-7751101
A80: Sales - Royalty to Independence Party | B80: 7751102 | C80: SGA | D80: =C80&"-"&B80 -> SGA-7751102
A81: Import Duty-purchased FG from NGK group | B81: 7111211 | C81: MFG | D81: =C81&"-"&B81 -> MFG-7111211
A82: Import Duty-purchased FG from outside supplier | B82: 7111212 | C82: MFG | D82: =C82&"-"&B82 -> MFG-7111212
A83: Import Duty-purchased KD&RM from NGK Japan | B83: 7111221 | C83: MFG | D83: =C83&"-"&B83 -> MFG-7111221
A84: Import Duty-purchased KD&RM from NGK Group(Not fromJP) | B84: 7111222 | C84: MFG | D84: =C84&"-"&B84 -> MFG-7111222
A85: Import Duty-purchased Comp Parts&RM from outside supplier | B85: 7111223 | C85: MFG | D85: =C85&"-"&B85 -> MFG-7111223
A86: Import Expense-purchased FG from NGK group | B86: 7111311 | C86: MFG | D86: =C86&"-"&B86 -> MFG-7111311
A87: Import Expense-purchased FG from outside supplier | B87: 7111312 | C87: MFG | D87: =C87&"-"&B87 -> MFG-7111312
A88: Import Expense-purchased KD&RM from NGK Japan | B88: 7111321 | C88: MFG | D88: =C88&"-"&B88 -> MFG-7111321
A89: Import Expense-purchased KD&RM from NGK Group(Not fromJP) | B89: 7111322 | C89: MFG | D89: =C89&"-"&B89 -> MFG-7111322
A90: Import Expense-purchased Comp Parts&RM from outside supplier | B90: 7111323 | C90: MFG | D90: =C90&"-"&B90 -> MFG-7111323
... A94: Cost of Factory Supply | B94: 7211101 | C94: MFG | D94: =C94&"-"&B94 -> MFG-7211101
A95: Cost of Chemical | B95: 7211102 | C95: MFG | D95: =C95&"-"&B95 -> MFG-7211102 | E95: 901 | F95: The expenses of Chemicals consumption
A96: Cost of Packaging | B96: 7211103 | C96: MFG | D96: =C96&"-"&B96 -> MFG-7211103
A97: Cost of Oil | B97: 7211104 | C97: MFG | D97: =C97&"-"&B97 -> MFG-7211104 | E97: 302
A98: Cost of Tooling | B98: 7221101 | C98: MFG | D98: =C98&"-"&B98 -> MFG-7221101 | E98: 302 | F98: The expenses of Tooling consumption
A99: Cost of Machinery parts | B99: 7221102 | C99: MFG | D99: =C99&"-"&B99 -> MFG-7221102 | E99: 301 | F99: The expenses of Spare Parts consumption
A100: Salary for Commissioner | B100: 7511101 | C100: MFG | D100: =C100&"-"&B100 -> MFG-7511101 | E100: 602 | F100: Salary for Commissioner
A101: Salary for Director | B101: 7511102 | C101: MFG | D101: =C101&"-"&B101 -> MFG-7511102 | E101: 602 | F101: Salary for Director & Expat
A102: Staff Labor - Baslc Salary | B102: 7511103 | C102: MFG | D102: =C102&"-"&B102 -> MFG-7511103 | E102: 601 | F102: Basic Salary of permanent employee
A103: Staff Labor - Allowance | B103: 7511111 | C103: MFG | D103: =C103&"-"&B103 -> MFG-7511111 | E103: 601 | F103: Employee allowance
A104: Staff Labor - Tax allowance (art.21) | B104: 7511112 | C104: MFG | D104: =C104&"-"&B104 -> MFG-7511112 | E104: 601 | F104: Empployee Tax allowance
A105: Staff Labor - BPJS JK & JKK (1.19%) | B105: 7511121 | C105: MFG | D105: =C105&"-"&B105 -> MFG-7511121 | E105: 601 | F105: BPJS JK & JKK (death warrant, Accident Insurance)
A106: Staff Labor - BPJS Kesehatan (4%) | B106: 7511122 | C106: MFG | D106: =C106&"-"&B106 -> MFG-7511122 | E106: 601 | F106: BPJS health insurance
A107: Staff Overtime | B107: 7511201 | C107: MFG | D107: =C107&"-"&B107 -> MFG-7511201 | E107: 603 | F107: Overtime permanent employee
A108: Staff Welfare - BPJS Dana pensiun (2%) | B108: 7512111 | C108: MFG | D108: =C108&"-"&B108 -> MFG-7512111 | E108: 604 | F108: BPJS pension fund
A109: Staff Welfare - BPJS JHT (3.7%) | B109: 7512112 | C109: MFG | D109: =C109&"-"&B109 -> MFG-7512112 | E109: 604 | F109: BPJS Pension plan
... A117: Staff Welfare - Uniform | B117: 7515406 | C117: MFG | D117: =C117&"-"&B117 -> MFG-7515406 | E117: 604 | F117: uniform costs
A118: Staff Welfare - Safety Shoes | B118: 7515407 | C118: MFG | D118: =C118&"-"&B118 -> MFG-7515407 | E118: 604
A119: Staff Welfare - Family Gathering / Anniversary | B119: 7515408 | C119: MFG | D119: =C119&"-"&B119 -> MFG-7515408 | E119: 604 | F119: Family Gathering / Anniversary
A120: Staff Welfare - Meals of canteen & other meals | B120: 7515409 | C120: MFG | D120: =C120&"-"&B120 -> MFG-7515409 | E120: 604 | F120: Meals of canteen & other meals cost
A121: Staff Welfare - Kaizen & QCC reward | B121: 7515410 | C121: MFG | D121: =C121&"-"&B121 -> MFG-7515410 | E121: 604 | F121: an expense, arising from Kaizen and QCC acitivity
A122: Staff Welfare - Welfare Others | B122: 7515499 | C122: MFG | D122: =C122&"-"&B122 -> MFG-7515499 | E122: 604 | F122: an other welfare expense, arising besides the above welfare expense
A123: Retirement Allowance | B123: 7516102 | C123: MFG | D123: =C123&"-"&B123 -> MFG-7516102 | E123: 605 | F123: employee retirement provission costs
A124: House Rent Allowance | B124: 7519101 | C124: MFG | D124: =C124&"-"&B124 -> MFG-7519101 | E124: 602 | F124: House Rent Allowance for expat
A125: Casual Staff Labor | B125: 7521101 | C125: MFG | D125: =C125&"-"&B125 -> MFG-7521101 | E125: 601 | F125: All benefit for temporary worker
A126: Casual Staff Labor - Overtime | B126: 7521102 | C126: MFG | D126: =C126&"-"&B126 -> MFG-7521102 | E126: 603 | F126: Overtime temporary worker
A127: Personnel expense transferred | B127: 7571101 | C127: MFG | D127: =C127&"-"&B127 -> MFG-7571101 | E127: 606 | F127: Transfer Labor cost from one section into another section
A128: Depreciation-Building | B128: 7611100 | C128: MFG | D128: =C128&"-"&B128 -> MFG-7611100 | E128: 701 | F128: the amount of depreciation of tangible assets for building
A129: Depreciation-Machiney & equipment | B129: 7611300 | C129: MFG | D129: =C129&"-"&B129 -> MFG-7611300 | E129: 701 | F129: the amount of depreciation of tangible assets for machinery & factory equipment
A130: Depreciation-Lease Machinery & equipment | B130: 7611400 | C130: MFG | D130: =C130&"-"&B130 -> MFG-7611400 | E130: 701 | F130: the amount of depreciation of tangible assets for machinery & factory equipment (Leases)
... A166: Expatriate fee Tax (BADORA) | B166: 7781113 | C166: MFG | D166: =C166&"-"&B166 -> MFG-7781113 | E166: 999 | F166: Tax income from expatriete
A167: Others - Miscellaneous Waste | B167: 8291101 | C167: OTH | D167: =C167&"-"&B167 -> OTH-8291101
A168: Others - Miscellaneous Tax | B168: 8291102 | C168: OTH | D168: =C168&"-"&B168 -> OTH-8291102
A169: Others - Sport Activity | B169: 8291201 | C169: OTH | D169: =C169&"-"&B169 -> OTH-8291201
A170: Others - Retribution / Garbage Cost | B170: 8291202 | C170: OTH | D170: =C170&"-"&B170 -> OTH-8291202
A171: Others - Miscellaneous Non Operational Expense | B171: 8291203 | C171: OTH | D171: =C171&"-"&B171 -> OTH-8291203
A172: Other Income | B172: 8191101 | C172: OTH | D172: =C172&"-"&B172 -> OTH-8191101

Sheet Depre Calculation
A1: No Asset | B1: Asset Name | C1: Coa Name | D1: Coa ID | E1: Acquisition Value | F1: Useful Life | G1: To Section | H1: Allocation % | I1: Depre Start | J1: Status (BIP / CIP) | K1: Section From | L1: Priority Code | M1: Period | N1: Assets Allocation | O1: Montly Depre | P1: End Depre | Q1: 2020_11 | R1: 2020_12 | S1: 2021_01 | T1: 2021_02 | U1: 2021_03 | V1: 2021_04 | W1: 2021_05 | X1: 2021_06 | Y1: 2021_07 | Z1: 2021_08 | AA1: 2021_09 | AB1: 2021_10 | AC1: 2021_11 | AD1: 2021_12 | AE1: 2022_01 | AF1: 2022_02 | AG1: 2022_03 | AH1: 2022_04 | AI1: 2022_05 | AJ1: 2022_06 | AK1: 2022_07 | AL1: 2022_08 | AM1: 2022_09 | AN1: 2022_10 | AO1: 2022_11 | AP1: 2022_12 | AQ1: 2023_01 | AR1: 2023_02 | AS1: 2023_03 | AT1: 2023_04 | AU1: 2023_05 | AV1: 2023_06 | AW1: 2023_07 | AX1: 2023_08 | AY1: 2023_09 | AZ1: 2023_10 | BA1: 2023_11 | BB1: 2023_12 | BC1: 2024_01 | BD1: 2024_02 | BE1: 2024_03 | BF1: TOTAL FY121 | BG1: TOTAL FY122 | BH1: TOTAL FY123 | BI1: TOTAL FY124 | BJ1: COA Depre | BK1: COA Name of Depre
A2: 001 | B2: UPS For Rack 2 (AX, ASPROVA, Flexnet Server) | C2: Tools, furniture & office equipment | D2: 2141000 | E2: 127990800 | F2: 60 | G2: Information Technology | H2: 1 | I2: 43922 | J2: BIP | K2: Information Technology | L2: A | M2: BGT.FY121 | N2: =H2*E2 -> 127990800 | O2: =N2/F2 -> 2133180 | P2: =DATE(YEAR(I2),MONTH(I2)+F2,DAY(I2)) -> 45748 | Q2: =IF(AND(LEFT(Q$1,FIND("_",Q$1)-1)&RIGHT(Q$1,LEN(Q$1)-FIND("_",Q$1)) >= YEAR($I2) & TEXT(MONTH($I2),"00"),LEFT(Q$1,FIND("_",Q$1)-1)&RIGHT(Q$1,LEN(Q$1)-FIND("_",Q$1)) < YEAR($P2) & TEXT(MONTH($P2),"00")),$O2,"") -> 2133180 | R2: =IF(AND(LEFT(R$1,FIND("_",R$1)-1)&RIGHT(R$1,LEN(R$1)-FIND("_",R$1)) >= YEAR($I2) & TEXT(MONTH($I2),"00"),LEFT(R$1,FIND("_",R$1)-1)&RIGHT(R$1,LEN(R$1)-FIND("_",R$1)) < YEAR($P2) & TEXT(MONTH($P2),"00")),$O2,"") -> 2133180 | S2: =IF(AND(LEFT(S$1,FIND("_",S$1)-1)&RIGHT(S$1,LEN(S$1)-FIND("_",S$1)) >= YEAR($I2) & TEXT(MONTH($I2),"00"),LEFT(S$1,FIND("_",S$1)-1)&RIGHT(S$1,LEN(S$1)-FIND("_",S$1)) < YEAR($P2) & TEXT(MONTH($P2),"00")),$O2,"") -> 2133180 | T2: =IF(AND(LEFT(T$1,FIND("_",T$1)-1)&RIGHT(T$1,LEN(T$1)-FIND("_",T$1)) >= YEAR($I2) & TEXT(MONTH($I2),"00"),LEFT(T$1,FIND("_",T$1)-1)&RIGHT(T$1,LEN(T$1)-FIND("_",T$1)) < YEAR($P2) & TEXT(MONTH($P2),"00")),$O2,"") -> 2133180 | U2: =IF(AND(LEFT(U$1,FIND("_",U$1)-1)&RIGHT(U$1,LEN(U$1)-FIND("_",U$1)) >= YEAR($I2) & TEXT(MONTH($I2),"00"),LEFT(U$1,FIND("_",U$1)-1)&RIGHT(U$1,LEN(U$1)-FIND("_",U$1)) < YEAR($P2) & TEXT(MONTH($P2),"00")),$O2,"") -> 2133180 | V2: =IF(AND(LEFT(V$1,FIND("_",V$1)-1)&RIGHT(V$1,LEN(V$1)-FIND("_",V$1)) >= YEAR($I2) & TEXT(MONTH($I2),"00"),LEFT(V$1,FIND("_",V$1)-1)&RIGHT(V$1,LEN(V$1)-FIND("_",V$1)) < YEAR($P2) & TEXT(MONTH($P2),"00")),$O2,"") -> 2133180 | W2: =IF(AND(LEFT(W$1,FIND("_",W$1)-1)&RIGHT(W$1,LEN(W$1)-FIND("_",W$1)) >= YEAR($I2) & TEXT(MONTH($I2),"00"),LEFT(W$1,FIND("_",W$1)-1)&RIGHT(W$1,LEN(W$1)-FIND("_",W$1)) < YEAR($P2) & TEXT(MONTH($P2),"00")),$O2,"") -> 2133180 | X2: =IF(AND(LEFT(X$1,FIND("_",X$1)-1)&RIGHT(X$1,LEN(X$1)-FIND("_",X$1)) >= YEAR($I2) & TEXT(MONTH($I2),"00"),LEFT(X$1,FIND("_",X$1)-1)&RIGHT(X$1,LEN(X$1)-FIND("_",X$1)) < YEAR($P2) & TEXT(MONTH($P2),"00")),$O2,"") -> 2133180 | ... BE2: =IF(AND(LEFT(BE$1,FIND("_",BE$1)-1)&RIGHT(BE$1,LEN(BE$1)-FIND("_",BE$1)) >= YEAR($I2) & TEXT(MONTH($I2),"00"),LEFT(BE$1,FIND("_",BE$1)-1)&RIGHT(BE$1,LEN(BE$1)-FIND("_",BE$1)) < YEAR($P2) & TEXT(MONTH($P2),"00")),$O2,"") -> 2133180 | BF2: =SUM(Q2:U2) -> 10665900 | BG2: =SUM(V2:AG2) -> 25598160 | BH2: =SUM(AH2:AS2) -> 25598160 | BI2: =SUM(AT2:BE2) -> 25598160 | BJ2: =VLOOKUP(D2,Master!AD:AG,3,FALSE) -> 7611600 | BK2: =VLOOKUP(D2,Master!AD:AG,4,FALSE) -> Depreciation-Tools, furniture & office equipment
A3: 002 | B3: UPS For Rack 1 (Domain, Application Server) | C3: Tools, furniture & office equipment | D3: 2141000 | E3: 88905600 | F3: 60 | G3: Information Technology | H3: 1 | I3: 43922 | J3: BIP | K3: Information Technology | L3: B | M3: BGT.FY121 | N3: =H3*E3 -> 88905600 | O3: =N3/F3 -> 1481760 | P3: =DATE(YEAR(I3),MONTH(I3)+F3,DAY(I3)) -> 45748 | Q3: =IF(AND(LEFT(Q$1,FIND("_",Q$1)-1)&RIGHT(Q$1,LEN(Q$1)-FIND("_",Q$1)) >= YEAR($I3) & TEXT(MONTH($I3),"00"),LEFT(Q$1,FIND("_",Q$1)-1)&RIGHT(Q$1,LEN(Q$1)-FIND("_",Q$1)) < YEAR($P3) & TEXT(MONTH($P3),"00")),$O3,"") -> 1481760 | R3: =IF(AND(LEFT(R$1,FIND("_",R$1)-1)&RIGHT(R$1,LEN(R$1)-FIND("_",R$1)) >= YEAR($I3) & TEXT(MONTH($I3),"00"),LEFT(R$1,FIND("_",R$1)-1)&RIGHT(R$1,LEN(R$1)-FIND("_",R$1)) < YEAR($P3) & TEXT(MONTH($P3),"00")),$O3,"") -> 1481760 | S3: =IF(AND(LEFT(S$1,FIND("_",S$1)-1)&RIGHT(S$1,LEN(S$1)-FIND("_",S$1)) >= YEAR($I3) & TEXT(MONTH($I3),"00"),LEFT(S$1,FIND("_",S$1)-1)&RIGHT(S$1,LEN(S$1)-FIND("_",S$1)) < YEAR($P3) & TEXT(MONTH($P3),"00")),$O3,"") -> 1481760 | T3: =IF(AND(LEFT(T$1,FIND("_",T$1)-1)&RIGHT(T$1,LEN(T$1)-FIND("_",T$1)) >= YEAR($I3) & TEXT(MONTH($I3),"00"),LEFT(T$1,FIND("_",T$1)-1)&RIGHT(T$1,LEN(T$1)-FIND("_",T$1)) < YEAR($P3) & TEXT(MONTH($P3),"00")),$O3,"") -> 1481760 | U3: =IF(AND(LEFT(U$1,FIND("_",U$1)-1)&RIGHT(U$1,LEN(U$1)-FIND("_",U$1)) >= YEAR($I3) & TEXT(MONTH($I3),"00"),LEFT(U$1,FIND("_",U$1)-1)&RIGHT(U$1,LEN(U$1)-FIND("_",U$1)) < YEAR($P3) & TEXT(MONTH($P3),"00")),$O3,"") -> 1481760 | V3: =IF(AND(LEFT(V$1,FIND("_",V$1)-1)&RIGHT(V$1,LEN(V$1)-FIND("_",V$1)) >= YEAR($I3) & TEXT(MONTH($I3),"00"),LEFT(V$1,FIND("_",V$1)-1)&RIGHT(V$1,LEN(V$1)-FIND("_",V$1)) < YEAR($P3) & TEXT(MONTH($P3),"00")),$O3,"") -> 1481760 | W3: =IF(AND(LEFT(W$1,FIND("_",W$1)-1)&RIGHT(W$1,LEN(W$1)-FIND("_",W$1)) >= YEAR($I3) & TEXT(MONTH($I3),"00"),LEFT(W$1,FIND("_",W$1)-1)&RIGHT(W$1,LEN(W$1)-FIND("_",W$1)) < YEAR($P3) & TEXT(MONTH($P3),"00")),$O3,"") -> 1481760 | X3: =IF(AND(LEFT(X$1,FIND("_",X$1)-1)&RIGHT(X$1,LEN(X$1)-FIND("_",X$1)) >= YEAR($I3) & TEXT(MONTH($I3),"00"),LEFT(X$1,FIND("_",X$1)-1)&RIGHT(X$1,LEN(X$1)-FIND("_",X$1)) < YEAR($P3) & TEXT(MONTH($P3),"00")),$O3,"") -> 1481760 | ... BE3: =IF(AND(LEFT(BE$1,FIND("_",BE$1)-1)&RIGHT(BE$1,LEN(BE$1)-FIND("_",BE$1)) >= YEAR($I3) & TEXT(MONTH($I3),"00"),LEFT(BE$1,FIND("_",BE$1)-1)&RIGHT(BE$1,LEN(BE$1)-FIND("_",BE$1)) < YEAR($P3) & TEXT(MONTH($P3),"00")),$O3,"") -> 1481760 | BF3: =SUM(Q3:U3) -> 7408800 | BG3: =SUM(V3:AG3) -> 17781120 | BH3: =SUM(AH3:AS3) -> 17781120 | BI3: =SUM(AT3:BE3) -> 17781120 | BJ3: =VLOOKUP(D3,Master!AD:AG,3,FALSE) -> 7611600 | BK3: =VLOOKUP(D3,Master!AD:AG,4,FALSE) -> Depreciation-Tools, furniture & office equipment
A4: 003 | B4: Notebook for IT Member | C4: Tools, furniture & office equipment | D4: 2141000 | E4: 15000000 | F4: 60 | G4: Information Technology | H4: 1 | I4: 43983 | J4: BIP | K4: Information Technology | L4: C | M4: BGT.FY121 | N4: =H4*E4 -> 15000000 | O4: =N4/F4 -> 250000 | P4: =DATE(YEAR(I4),MONTH(I4)+F4,DAY(I4)) -> 45809 | Q4: =IF(AND(LEFT(Q$1,FIND("_",Q$1)-1)&RIGHT(Q$1,LEN(Q$1)-FIND("_",Q$1)) >= YEAR($I4) & TEXT(MONTH($I4),"00"),LEFT(Q$1,FIND("_",Q$1)-1)&RIGHT(Q$1,LEN(Q$1)-FIND("_",Q$1)) < YEAR($P4) & TEXT(MONTH($P4),"00")),$O4,"") -> 250000 | R4: =IF(AND(LEFT(R$1,FIND("_",R$1)-1)&RIGHT(R$1,LEN(R$1)-FIND("_",R$1)) >= YEAR($I4) & TEXT(MONTH($I4),"00"),LEFT(R$1,FIND("_",R$1)-1)&RIGHT(R$1,LEN(R$1)-FIND("_",R$1)) < YEAR($P4) & TEXT(MONTH($P4),"00")),$O4,"") -> 250000 | S4: =IF(AND(LEFT(S$1,FIND("_",S$1)-1)&RIGHT(S$1,LEN(S$1)-FIND("_",S$1)) >= YEAR($I4) & TEXT(MONTH($I4),"00"),LEFT(S$1,FIND("_",S$1)-1)&RIGHT(S$1,LEN(S$1)-FIND("_",S$1)) < YEAR($P4) & TEXT(MONTH($P4),"00")),$O4,"") -> 250000 | T4: =IF(AND(LEFT(T$1,FIND("_",T$1)-1)&RIGHT(T$1,LEN(T$1)-FIND("_",T$1)) >= YEAR($I4) & TEXT(MONTH($I4),"00"),LEFT(T$1,FIND("_",T$1)-1)&RIGHT(T$1,LEN(T$1)-FIND("_",T$1)) < YEAR($P4) & TEXT(MONTH($P4),"00")),$O4,"") -> 250000 | U4: =IF(AND(LEFT(U$1,FIND("_",U$1)-1)&RIGHT(U$1,LEN(U$1)-FIND("_",U$1)) >= YEAR($I4) & TEXT(MONTH($I4),"00"),LEFT(U$1,FIND("_",U$1)-1)&RIGHT(U$1,LEN(U$1)-FIND("_",U$1)) < YEAR($P4) & TEXT(MONTH($P4),"00")),$O4,"") -> 250000 | V4: =IF(AND(LEFT(V$1,FIND("_",V$1)-1)&RIGHT(V$1,LEN(V$1)-FIND("_",V$1)) >= YEAR($I4) & TEXT(MONTH($I4),"00"),LEFT(V$1,FIND("_",V$1)-1)&RIGHT(V$1,LEN(V$1)-FIND("_",V$1)) < YEAR($P4) & TEXT(MONTH($P4),"00")),$O4,"") -> 250000 | W4: =IF(AND(LEFT(W$1,FIND("_",W$1)-1)&RIGHT(W$1,LEN(W$1)-FIND("_",W$1)) >= YEAR($I4) & TEXT(MONTH($I4),"00"),LEFT(W$1,FIND("_",W$1)-1)&RIGHT(W$1,LEN(W$1)-FIND("_",W$1)) < YEAR($P4) & TEXT(MONTH($P4),"00")),$O4,"") -> 250000 | X4: =IF(AND(LEFT(X$1,FIND("_",X$1)-1)&RIGHT(X$1,LEN(X$1)-FIND("_",X$1)) >= YEAR($I4) & TEXT(MONTH($I4),"00"),LEFT(X$1,FIND("_",X$1)-1)&RIGHT(X$1,LEN(X$1)-FIND("_",X$1)) < YEAR($P4) & TEXT(MONTH($P4),"00")),$O4,"") -> 250000 | ... BE4: =IF(AND(LEFT(BE$1,FIND("_",BE$1)-1)&RIGHT(BE$1,LEN(BE$1)-FIND("_",BE$1)) >= YEAR($I4) & TEXT(MONTH($I4),"00"),LEFT(BE$1,FIND("_",BE$1)-1)&RIGHT(BE$1,LEN(BE$1)-FIND("_",BE$1)) < YEAR($P4) & TEXT(MONTH($P4),"00")),$O4,"") -> 250000 | BF4: =SUM(Q4:U4) -> 1250000 | BG4: =SUM(V4:AG4) -> 3000000 | BH4: =SUM(AH4:AS4) -> 3000000 | BI4: =SUM(AT4:BE4) -> 3000000 | BJ4: =VLOOKUP(D4,Master!AD:AG,3,FALSE) -> 7611600 | BK4: =VLOOKUP(D4,Master!AD:AG,4,FALSE) -> Depreciation-Tools, furniture & office equipment
A5: 001 | B5: Auto Gate Machine | C5: Tools, furniture & office equipment | D5: 2141000 | E5: 40000000 | F5: 60 | G5: GENERAL AFFAIR | H5: 1 | I5: 44197 | J5: BIP | K5: GENERAL AFFAIR | M5: BGT.FY121 | N5: =H5*E5 -> 40000000 | O5: =N5/F5 -> 666666.67 | P5: =DATE(YEAR(I5),MONTH(I5)+F5,DAY(I5)) -> 46023 | Q5: =IF(AND(LEFT(Q$1,FIND("_",Q$1)-1)&RIGHT(Q$1,LEN(Q$1)-FIND("_",Q$1)) >= YEAR($I5) & TEXT(MONTH($I5),"00"),LEFT(Q$1,FIND("_",Q$1)-1)&RIGHT(Q$1,LEN(Q$1)-FIND("_",Q$1)) < YEAR($P5) & TEXT(MONTH($P5),"00")),$O5,"") | R5: =IF(AND(LEFT(R$1,FIND("_",R$1)-1)&RIGHT(R$1,LEN(R$1)-FIND("_",R$1)) >= YEAR($I5) & TEXT(MONTH($I5),"00"),LEFT(R$1,FIND("_",R$1)-1)&RIGHT(R$1,LEN(R$1)-FIND("_",R$1)) < YEAR($P5) & TEXT(MONTH($P5),"00")),$O5,"") | S5: =IF(AND(LEFT(S$1,FIND("_",S$1)-1)&RIGHT(S$1,LEN(S$1)-FIND("_",S$1)) >= YEAR($I5) & TEXT(MONTH($I5),"00"),LEFT(S$1,FIND("_",S$1)-1)&RIGHT(S$1,LEN(S$1)-FIND("_",S$1)) < YEAR($P5) & TEXT(MONTH($P5),"00")),$O5,"") -> 666666.67 | T5: =IF(AND(LEFT(T$1,FIND("_",T$1)-1)&RIGHT(T$1,LEN(T$1)-FIND("_",T$1)) >= YEAR($I5) & TEXT(MONTH($I5),"00"),LEFT(T$1,FIND("_",T$1)-1)&RIGHT(T$1,LEN(T$1)-FIND("_",T$1)) < YEAR($P5) & TEXT(MONTH($P5),"00")),$O5,"") -> 666666.67 | U5: =IF(AND(LEFT(U$1,FIND("_",U$1)-1)&RIGHT(U$1,LEN(U$1)-FIND("_",U$1)) >= YEAR($I5) & TEXT(MONTH($I5),"00"),LEFT(U$1,FIND("_",U$1)-1)&RIGHT(U$1,LEN(U$1)-FIND("_",U$1)) < YEAR($P5) & TEXT(MONTH($P5),"00")),$O5,"") -> 666666.67 | V5: =IF(AND(LEFT(V$1,FIND("_",V$1)-1)&RIGHT(V$1,LEN(V$1)-FIND("_",V$1)) >= YEAR($I5) & TEXT(MONTH($I5),"00"),LEFT(V$1,FIND("_",V$1)-1)&RIGHT(V$1,LEN(V$1)-FIND("_",V$1)) < YEAR($P5) & TEXT(MONTH($P5),"00")),$O5,"") -> 666666.67 | W5: =IF(AND(LEFT(W$1,FIND("_",W$1)-1)&RIGHT(W$1,LEN(W$1)-FIND("_",W$1)) >= YEAR($I5) & TEXT(MONTH($I5),"00"),LEFT(W$1,FIND("_",W$1)-1)&RIGHT(W$1,LEN(W$1)-FIND("_",W$1)) < YEAR($P5) & TEXT(MONTH($P5),"00")),$O5,"") -> 666666.67 | X5: =IF(AND(LEFT(X$1,FIND("_",X$1)-1)&RIGHT(X$1,LEN(X$1)-FIND("_",X$1)) >= YEAR($I5) & TEXT(MONTH($I5),"00"),LEFT(X$1,FIND("_",X$1)-1)&RIGHT(X$1,LEN(X$1)-FIND("_",X$1)) < YEAR($P5) & TEXT(MONTH($P5),"00")),$O5,"") -> 666666.67 | ... BE5: =IF(AND(LEFT(BE$1,FIND("_",BE$1)-1)&RIGHT(BE$1,LEN(BE$1)-FIND("_",BE$1)) >= YEAR($I5) & TEXT(MONTH($I5),"00"),LEFT(BE$1,FIND("_",BE$1)-1)&RIGHT(BE$1,LEN(BE$1)-FIND("_",BE$1)) < YEAR($P5) & TEXT(MONTH($P5),"00")),$O5,"") -> 666666.67 | BF5: =SUM(Q5:U5) -> 2000000 | BG5: =SUM(V5:AG5) -> 8000000 | BH5: =SUM(AH5:AS5) -> 8000000 | BI5: =SUM(AT5:BE5) -> 8000000 | BJ5: =VLOOKUP(D5,Master!AD:AG,3,FALSE) -> 7611600 | BK5: =VLOOKUP(D5,Master!AD:AG,4,FALSE) -> Depreciation-Tools, furniture & office equipment
A6: 002 | B6: AC Central Spark Plug 1 | C6: Tools, furniture & office equipment | D6: 2141000 | E6: 40000000 | F6: 60 | G6: GENERAL AFFAIR | H6: 1 | I6: 44197 | J6: BIP | K6: GENERAL AFFAIR | M6: BGT.FY121 | N6: =H6*E6 -> 40000000 | O6: =N6/F6 -> 666666.67 | P6: =DATE(YEAR(I6),MONTH(I6)+F6,DAY(I6)) -> 46023 | Q6: =IF(AND(LEFT(Q$1,FIND("_",Q$1)-1)&RIGHT(Q$1,LEN(Q$1)-FIND("_",Q$1)) >= YEAR($I6) & TEXT(MONTH($I6),"00"),LEFT(Q$1,FIND("_",Q$1)-1)&RIGHT(Q$1,LEN(Q$1)-FIND("_",Q$1)) < YEAR($P6) & TEXT(MONTH($P6),"00")),$O6,"") | R6: =IF(AND(LEFT(R$1,FIND("_",R$1)-1)&RIGHT(R$1,LEN(R$1)-FIND("_",R$1)) >= YEAR($I6) & TEXT(MONTH($I6),"00"),LEFT(R$1,FIND("_",R$1)-1)&RIGHT(R$1,LEN(R$1)-FIND("_",R$1)) < YEAR($P6) & TEXT(MONTH($P6),"00")),$O6,"") | S6: =IF(AND(LEFT(S$1,FIND("_",S$1)-1)&RIGHT(S$1,LEN(S$1)-FIND("_",S$1)) >= YEAR($I6) & TEXT(MONTH($I6),"00"),LEFT(S$1,FIND("_",S$1)-1)&RIGHT(S$1,LEN(S$1)-FIND("_",S$1)) < YEAR($P6) & TEXT(MONTH($P6),"00")),$O6,"") -> 666666.67 | T6: =IF(AND(LEFT(T$1,FIND("_",T$1)-1)&RIGHT(T$1,LEN(T$1)-FIND("_",T$1)) >= YEAR($I6) & TEXT(MONTH($I6),"00"),LEFT(T$1,FIND("_",T$1)-1)&RIGHT(T$1,LEN(T$1)-FIND("_",T$1)) < YEAR($P6) & TEXT(MONTH($P6),"00")),$O6,"") -> 666666.67 | U6: =IF(AND(LEFT(U$1,FIND("_",U$1)-1)&RIGHT(U$1,LEN(U$1)-FIND("_",U$1)) >= YEAR($I6) & TEXT(MONTH($I6),"00"),LEFT(U$1,FIND("_",U$1)-1)&RIGHT(U$1,LEN(U$1)-FIND("_",U$1)) < YEAR($P6) & TEXT(MONTH($P6),"00")),$O6,"") -> 666666.67 | V6: =IF(AND(LEFT(V$1,FIND("_",V$1)-1)&RIGHT(V$1,LEN(V$1)-FIND("_",V$1)) >= YEAR($I6) & TEXT(MONTH($I6),"00"),LEFT(V$1,FIND("_",V$1)-1)&RIGHT(V$1,LEN(V$1)-FIND("_",V$1)) < YEAR($P6) & TEXT(MONTH($P6),"00")),$O6,"") -> 666666.67 | W6: =IF(AND(LEFT(W$1,FIND("_",W$1)-1)&RIGHT(W$1,LEN(W$1)-FIND("_",W$1)) >= YEAR($I6) & TEXT(MONTH($I6),"00"),LEFT(W$1,FIND("_",W$1)-1)&RIGHT(W$1,LEN(W$1)-FIND("_",W$1)) < YEAR($P6) & TEXT(MONTH($P6),"00")),$O6,"") -> 666666.67 | X6: =IF(AND(LEFT(X$1,FIND("_",X$1)-1)&RIGHT(X$1,LEN(X$1)-FIND("_",X$1)) >= YEAR($I6) & TEXT(MONTH($I6),"00"),LEFT(X$1,FIND("_",X$1)-1)&RIGHT(X$1,LEN(X$1)-FIND("_",X$1)) < YEAR($P6) & TEXT(MONTH($P6),"00")),$O6,"") -> 666666.67 | ... BE6: =IF(AND(LEFT(BE$1,FIND("_",BE$1)-1)&RIGHT(BE$1,LEN(BE$1)-FIND("_",BE$1)) >= YEAR($I6) & TEXT(MONTH($I6),"00"),LEFT(BE$1,FIND("_",BE$1)-1)&RIGHT(BE$1,LEN(BE$1)-FIND("_",BE$1)) < YEAR($P6) & TEXT(MONTH($P6),"00")),$O6,"") -> 666666.67 | BF6: =SUM(Q6:U6) -> 2000000 | BG6: =SUM(V6:AG6) -> 8000000 | BH6: =SUM(AH6:AS6) -> 8000000 | BI6: =SUM(AT6:BE6) -> 8000000 | BJ6: =VLOOKUP(D6,Master!AD:AG,3,FALSE) -> 7611600 | BK6: =VLOOKUP(D6,Master!AD:AG,4,FALSE) -> Depreciation-Tools, furniture & office equipment
A7: 003 | B7: Personal Computer Recruitment Staff | C7: Tools, furniture & office equipment | D7: 2141000 | E7: 8000000 | F7: 60 | G7: HUMAN RESOURCE | H7: 1 | I7: 44287 | J7: BIP | K7: GENERAL AFFAIR | M7: BGT.FY122 | N7: =H7*E7 -> 8000000 | O7: =N7/F7 -> 133333.33 | P7: =DATE(YEAR(I7),MONTH(I7)+F7,DAY(I7)) -> 46113 | Q7: =IF(AND(LEFT(Q$1,FIND("_",Q$1)-1)&RIGHT(Q$1,LEN(Q$1)-FIND("_",Q$1)) >= YEAR($I7) & TEXT(MONTH($I7),"00"),LEFT(Q$1,FIND("_",Q$1)-1)&RIGHT(Q$1,LEN(Q$1)-FIND("_",Q$1)) < YEAR($P7) & TEXT(MONTH($P7),"00")),$O7,"") | R7: =IF(AND(LEFT(R$1,FIND("_",R$1)-1)&RIGHT(R$1,LEN(R$1)-FIND("_",R$1)) >= YEAR($I7) & TEXT(MONTH($I7),"00"),LEFT(R$1,FIND("_",R$1)-1)&RIGHT(R$1,LEN(R$1)-FIND("_",R$1)) < YEAR($P7) & TEXT(MONTH($P7),"00")),$O7,"") | S7: =IF(AND(LEFT(S$1,FIND("_",S$1)-1)&RIGHT(S$1,LEN(S$1)-FIND("_",S$1)) >= YEAR($I7) & TEXT(MONTH($I7),"00"),LEFT(S$1,FIND("_",S$1)-1)&RIGHT(S$1,LEN(S$1)-FIND("_",S$1)) < YEAR($P7) & TEXT(MONTH($P7),"00")),$O7,"") | T7: =IF(AND(LEFT(T$1,FIND("_",T$1)-1)&RIGHT(T$1,LEN(T$1)-FIND("_",T$1)) >= YEAR($I7) & TEXT(MONTH($I7),"00"),LEFT(T$1,FIND("_",T$1)-1)&RIGHT(T$1,LEN(T$1)-FIND("_",T$1)) < YEAR($P7) & TEXT(MONTH($P7),"00")),$O7,"") | U7: =IF(AND(LEFT(U$1,FIND("_",U$1)-1)&RIGHT(U$1,LEN(U$1)-FIND("_",U$1)) >= YEAR($I7) & TEXT(MONTH($I7),"00"),LEFT(U$1,FIND("_",U$1)-1)&RIGHT(U$1,LEN(U$1)-FIND("_",U$1)) < YEAR($P7) & TEXT(MONTH($P7),"00")),$O7,"") | V7: =IF(AND(LEFT(V$1,FIND("_",V$1)-1)&RIGHT(V$1,LEN(V$1)-FIND("_",V$1)) >= YEAR($I7) & TEXT(MONTH($I7),"00"),LEFT(V$1,FIND("_",V$1)-1)&RIGHT(V$1,LEN(V$1)-FIND("_",V$1)) < YEAR($P7) & TEXT(MONTH($P7),"00")),$O7,"") -> 133333.33 | W7: =IF(AND(LEFT(W$1,FIND("_",W$1)-1)&RIGHT(W$1,LEN(W$1)-FIND("_",W$1)) >= YEAR($I7) & TEXT(MONTH($I7),"00"),LEFT(W$1,FIND("_",W$1)-1)&RIGHT(W$1,LEN(W$1)-FIND("_",W$1)) < YEAR($P7) & TEXT(MONTH($P7),"00")),$O7,"") -> 133333.33 | X7: =IF(AND(LEFT(X$1,FIND("_",X$1)-1)&RIGHT(X$1,LEN(X$1)-FIND("_",X$1)) >= YEAR($I7) & TEXT(MONTH($I7),"00"),LEFT(X$1,FIND("_",X$1)-1)&RIGHT(X$1,LEN(X$1)-FIND("_",X$1)) < YEAR($P7) & TEXT(MONTH($P7),"00")),$O7,"") -> 133333.33 | ... BE7: =IF(AND(LEFT(BE$1,FIND("_",BE$1)-1)&RIGHT(BE$1,LEN(BE$1)-FIND("_",BE$1)) >= YEAR($I7) & TEXT(MONTH($I7),"00"),LEFT(BE$1,FIND("_",BE$1)-1)&RIGHT(BE$1,LEN(BE$1)-FIND("_",BE$1)) < YEAR($P7) & TEXT(MONTH($P7),"00")),$O7,"") -> 133333.33 | BF7: =SUM(Q7:U7) -> 0 | BG7: =SUM(V7:AG7) -> 1600000 | BH7: =SUM(AH7:AS7) -> 1600000 | BI7: =SUM(AT7:BE7) -> 1600000 | BJ7: =VLOOKUP(D7,Master!AD:AG,3,FALSE) -> 7611600 | BK7: =VLOOKUP(D7,Master!AD:AG,4,FALSE) -> Depreciation-Tools, furniture & office equipment
A8: 004 | B8: Personal Computer GA Staff | C8: Tools, furniture & office equipment | D8: 2141000 | E8: 8000000 | F8: 60 | G8: GENERAL AFFAIR | H8: 1 | I8: 44287 | J8: BIP | K8: GENERAL AFFAIR | M8: BGT.FY122 | N8: =H8*E8 -> 8000000 | O8: =N8/F8 -> 133333.33 | P8: =DATE(YEAR(I8),MONTH(I8)+F8,DAY(I8)) -> 46113 | Q8: =IF(AND(LEFT(Q$1,FIND("_",Q$1)-1)&RIGHT(Q$1,LEN(Q$1)-FIND("_",Q$1)) >= YEAR($I8) & TEXT(MONTH($I8),"00"),LEFT(Q$1,FIND("_",Q$1)-1)&RIGHT(Q$1,LEN(Q$1)-FIND("_",Q$1)) < YEAR($P8) & TEXT(MONTH($P8),"00")),$O8,"") | R8: =IF(AND(LEFT(R$1,FIND("_",R$1)-1)&RIGHT(R$1,LEN(R$1)-FIND("_",R$1)) >= YEAR($I8) & TEXT(MONTH($I8),"00"),LEFT(R$1,FIND("_",R$1)-1)&RIGHT(R$1,LEN(R$1)-FIND("_",R$1)) < YEAR($P8) & TEXT(MONTH($P8),"00")),$O8,"") | S8: =IF(AND(LEFT(S$1,FIND("_",S$1)-1)&RIGHT(S$1,LEN(S$1)-FIND("_",S$1)) >= YEAR($I8) & TEXT(MONTH($I8),"00"),LEFT(S$1,FIND("_",S$1)-1)&RIGHT(S$1,LEN(S$1)-FIND("_",S$1)) < YEAR($P8) & TEXT(MONTH($P8),"00")),$O8,"") | T8: =IF(AND(LEFT(T$1,FIND("_",T$1)-1)&RIGHT(T$1,LEN(T$1)-FIND("_",T$1)) >= YEAR($I8) & TEXT(MONTH($I8),"00"),LEFT(T$1,FIND("_",T$1)-1)&RIGHT(T$1,LEN(T$1)-FIND("_",T$1)) < YEAR($P8) & TEXT(MONTH($P8),"00")),$O8,"") | U8: =IF(AND(LEFT(U$1,FIND("_",U$1)-1)&RIGHT(U$1,LEN(U$1)-FIND("_",U$1)) >= YEAR($I8) & TEXT(MONTH($I8),"00"),LEFT(U$1,FIND("_",U$1)-1)&RIGHT(U$1,LEN(U$1)-FIND("_",U$1)) < YEAR($P8) & TEXT(MONTH($P8),"00")),$O8,"") | V8: =IF(AND(LEFT(V$1,FIND("_",V$1)-1)&RIGHT(V$1,LEN(V$1)-FIND("_",V$1)) >= YEAR($I8) & TEXT(MONTH($I8),"00"),LEFT(V$1,FIND("_",V$1)-1)&RIGHT(V$1,LEN(V$1)-FIND("_",V$1)) < YEAR($P8) & TEXT(MONTH($P8),"00")),$O8,"") -> 133333.33 | W8: =IF(AND(LEFT(W$1,FIND("_",W$1)-1)&RIGHT(W$1,LEN(W$1)-FIND("_",W$1)) >= YEAR($I8) & TEXT(MONTH($I8),"00"),LEFT(W$1,FIND("_",W$1)-1)&RIGHT(W$1,LEN(W$1)-FIND("_",W$1)) < YEAR($P8) & TEXT(MONTH($P8),"00")),$O8,"") -> 133333.33 | X8: =IF(AND(LEFT(X$1,FIND("_",X$1)-1)&RIGHT(X$1,LEN(X$1)-FIND("_",X$1)) >= YEAR($I8) & TEXT(MONTH($I8),"00"),LEFT(X$1,FIND("_",X$1)-1)&RIGHT(X$1,LEN(X$1)-FIND("_",X$1)) < YEAR($P8) & TEXT(MONTH($P8),"00")),$O8,"") -> 133333.33 | ... BE8: =IF(AND(LEFT(BE$1,FIND("_",BE$1)-1)&RIGHT(BE$1,LEN(BE$1)-FIND("_",BE$1)) >= YEAR($I8) & TEXT(MONTH($I8),"00"),LEFT(BE$1,FIND("_",BE$1)-1)&RIGHT(BE$1,LEN(BE$1)-FIND("_",BE$1)) < YEAR($P8) & TEXT(MONTH($P8),"00")),$O8,"") -> 133333.33 | BF8: =SUM(Q8:U8) -> 0 | BG8: =SUM(V8:AG8) -> 1600000 | BH8: =SUM(AH8:AS8) -> 1600000 | BI8: =SUM(AT8:BE8) -> 1600000 | BJ8: =VLOOKUP(D8,Master!AD:AG,3,FALSE) -> 7611600 | BK8: =VLOOKUP(D8,Master!AD:AG,4,FALSE) -> Depreciation-Tools, furniture & office equipment
A9: 005 | B9: Laptop Training | C9: Tools, furniture & office equipment | D9: 2141000 | E9: 10000000 | F9: 60 | G9: HUMAN RESOURCE | H9: 1 | I9: 44287 | J9: BIP | K9: GENERAL AFFAIR | M9: BGT.FY122 | N9: =H9*E9 -> 10000000 | O9: =N9/F9 -> 166666.67 | P9: =DATE(YEAR(I9),MONTH(I9)+F9,DAY(I9)) -> 46113 | Q9: =IF(AND(LEFT(Q$1,FIND("_",Q$1)-1)&RIGHT(Q$1,LEN(Q$1)-FIND("_",Q$1)) >= YEAR($I9) & TEXT(MONTH($I9),"00"),LEFT(Q$1,FIND("_",Q$1)-1)&RIGHT(Q$1,LEN(Q$1)-FIND("_",Q$1)) < YEAR($P9) & TEXT(MONTH($P9),"00")),$O9,"") | R9: =IF(AND(LEFT(R$1,FIND("_",R$1)-1)&RIGHT(R$1,LEN(R$1)-FIND("_",R$1)) >= YEAR($I9) & TEXT(MONTH($I9),"00"),LEFT(R$1,FIND("_",R$1)-1)&RIGHT(R$1,LEN(R$1)-FIND("_",R$1)) < YEAR($P9) & TEXT(MONTH($P9),"00")),$O9,"") | S9: =IF(AND(LEFT(S$1,FIND("_",S$1)-1)&RIGHT(S$1,LEN(S$1)-FIND("_",S$1)) >= YEAR($I9) & TEXT(MONTH($I9),"00"),LEFT(S$1,FIND("_",S$1)-1)&RIGHT(S$1,LEN(S$1)-FIND("_",S$1)) < YEAR($P9) & TEXT(MONTH($P9),"00")),$O9,"") | T9: =IF(AND(LEFT(T$1,FIND("_",T$1)-1)&RIGHT(T$1,LEN(T$1)-FIND("_",T$1)) >= YEAR($I9) & TEXT(MONTH($I9),"00"),LEFT(T$1,FIND("_",T$1)-1)&RIGHT(T$1,LEN(T$1)-FIND("_",T$1)) < YEAR($P9) & TEXT(MONTH($P9),"00")),$O9,"") | U9: =IF(AND(LEFT(U$1,FIND("_",U$1)-1)&RIGHT(U$1,LEN(U$1)-FIND("_",U$1)) >= YEAR($I9) & TEXT(MONTH($I9),"00"),LEFT(U$1,FIND("_",U$1)-1)&RIGHT(U$1,LEN(U$1)-FIND("_",U$1)) < YEAR($P9) & TEXT(MONTH($P9),"00")),$O9,"") | V9: =IF(AND(LEFT(V$1,FIND("_",V$1)-1)&RIGHT(V$1,LEN(V$1)-FIND("_",V$1)) >= YEAR($I9) & TEXT(MONTH($I9),"00"),LEFT(V$1,FIND("_",V$1)-1)&RIGHT(V$1,LEN(V$1)-FIND("_",V$1)) < YEAR($P9) & TEXT(MONTH($P9),"00")),$O9,"") -> 166666.67 | W9: =IF(AND(LEFT(W$1,FIND("_",W$1)-1)&RIGHT(W$1,LEN(W$1)-FIND("_",W$1)) >= YEAR($I9) & TEXT(MONTH($I9),"00"),LEFT(W$1,FIND("_",W$1)-1)&RIGHT(W$1,LEN(W$1)-FIND("_",W$1)) < YEAR($P9) & TEXT(MONTH($P9),"00")),$O9,"") -> 166666.67 | X9: =IF(AND(LEFT(X$1,FIND("_",X$1)-1)&RIGHT(X$1,LEN(X$1)-FIND("_",X$1)) >= YEAR($I9) & TEXT(MONTH($I9),"00"),LEFT(X$1,FIND("_",X$1)-1)&RIGHT(X$1,LEN(X$1)-FIND("_",X$1)) < YEAR($P9) & TEXT(MONTH($P9),"00")),$O9,"") -> 166666.67 | ... BE9: =IF(AND(LEFT(BE$1,FIND("_",BE$1)-1)&RIGHT(BE$1,LEN(BE$1)-FIND("_",BE$1)) >= YEAR($I9) & TEXT(MONTH($I9),"00"),LEFT(BE$1,FIND("_",BE$1)-1)&RIGHT(BE$1,LEN(BE$1)-FIND("_",BE$1)) < YEAR($P9) & TEXT(MONTH($P9),"00")),$O9,"") -> 166666.67 | BF9: =SUM(Q9:U9) -> 0 | BG9: =SUM(V9:AG9) -> 2000000 | BH9: =SUM(AH9:AS9) -> 2000000 | BI9: =SUM(AT9:BE9) -> 2000000 | BJ9: =VLOOKUP(D9,Master!AD:AG,3,FALSE) -> 7611600 | BK9: =VLOOKUP(D9,Master!AD:AG,4,FALSE) -> Depreciation-Tools, furniture & office equipment
A10: 006 | B10: Laptop IR & Legal | C10: Tools, furniture & office equipment | D10: 2141000 | E10: 10000000 | F10: 60 | G10: GENERAL AFFAIR | H10: 1 | I10: 44287 | J10: BIP | K10: GENERAL AFFAIR | M10: BGT.FY122 | N10: =H10*E10 -> 10000000 | O10: =N10/F10 -> 166666.67 | P10: =DATE(YEAR(I10),MONTH(I10)+F10,DAY(I10)) -> 46113 | Q10: =IF(AND(LEFT(Q$1,FIND("_",Q$1)-1)&RIGHT(Q$1,LEN(Q$1)-FIND("_",Q$1)) >= YEAR($I10) & TEXT(MONTH($I10),"00"),LEFT(Q$1,FIND("_",Q$1)-1)&RIGHT(Q$1,LEN(Q$1)-FIND("_",Q$1)) < YEAR($P10) & TEXT(MONTH($P10),"00")),$O10,"") | R10: =IF(AND(LEFT(R$1,FIND("_",R$1)-1)&RIGHT(R$1,LEN(R$1)-FIND("_",R$1)) >= YEAR($I10) & TEXT(MONTH($I10),"00"),LEFT(R$1,FIND("_",R$1)-1)&RIGHT(R$1,LEN(R$1)-FIND("_",R$1)) < YEAR($P10) & TEXT(MONTH($P10),"00")),$O10,"") | S10: =IF(AND(LEFT(S$1,FIND("_",S$1)-1)&RIGHT(S$1,LEN(S$1)-FIND("_",S$1)) >= YEAR($I10) & TEXT(MONTH($I10),"00"),LEFT(S$1,FIND("_",S$1)-1)&RIGHT(S$1,LEN(S$1)-FIND("_",S$1)) < YEAR($P10) & TEXT(MONTH($P10),"00")),$O10,"") | T10: =IF(AND(LEFT(T$1,FIND("_",T$1)-1)&RIGHT(T$1,LEN(T$1)-FIND("_",T$1)) >= YEAR($I10) & TEXT(MONTH($I10),"00"),LEFT(T$1,FIND("_",T$1)-1)&RIGHT(T$1,LEN(T$1)-FIND("_",T$1)) < YEAR($P10) & TEXT(MONTH($P10),"00")),$O10,"") | U10: =IF(AND(LEFT(U$1,FIND("_",U$1)-1)&RIGHT(U$1,LEN(U$1)-FIND("_",U$1)) >= YEAR($I10) & TEXT(MONTH($I10),"00"),LEFT(U$1,FIND("_",U$1)-1)&RIGHT(U$1,LEN(U$1)-FIND("_",U$1)) < YEAR($P10) & TEXT(MONTH($P10),"00")),$O10,"") | V10: =IF(AND(LEFT(V$1,FIND("_",V$1)-1)&RIGHT(V$1,LEN(V$1)-FIND("_",V$1)) >= YEAR($I10) & TEXT(MONTH($I10),"00"),LEFT(V$1,FIND("_",V$1)-1)&RIGHT(V$1,LEN(V$1)-FIND("_",V$1)) < YEAR($P10) & TEXT(MONTH($P10),"00")),$O10,"") -> 166666.67 | W10: =IF(AND(LEFT(W$1,FIND("_",W$1)-1)&RIGHT(W$1,LEN(W$1)-FIND("_",W$1)) >= YEAR($I10) & TEXT(MONTH($I10),"00"),LEFT(W$1,FIND("_",W$1)-1)&RIGHT(W$1,LEN(W$1)-FIND("_",W$1)) < YEAR($P10) & TEXT(MONTH($P10),"00")),$O10,"") -> 166666.67 | X10: =IF(AND(LEFT(X$1,FIND("_",X$1)-1)&RIGHT(X$1,LEN(X$1)-FIND("_",X$1)) >= YEAR($I10) & TEXT(MONTH($I10),"00"),LEFT(X$1,FIND("_",X$1)-1)&RIGHT(X$1,LEN(X$1)-FIND("_",X$1)) < YEAR($P10) & TEXT(MONTH($P10),"00")),$O10,"") -> 166666.67 | ... BE10: =IF(AND(LEFT(BE$1,FIND("_",BE$1)-1)&RIGHT(BE$1,LEN(BE$1)-FIND("_",BE$1)) >= YEAR($I10) & TEXT(MONTH($I10),"00"),LEFT(BE$1,FIND("_",BE$1)-1)&RIGHT(BE$1,LEN(BE$1)-FIND("_",BE$1)) < YEAR($P10) & TEXT(MONTH($P10),"00")),$O10,"") -> 166666.67 | BF10: =SUM(Q10:U10) -> 0 | BG10: =SUM(V10:AG10) -> 2000000 | BH10: =SUM(AH10:AS10) -> 2000000 | BI10: =SUM(AT10:BE10) -> 2000000 | BJ10: =VLOOKUP(D10,Master!AD:AG,3,FALSE) -> 7611600 | BK10: =VLOOKUP(D10,Master!AD:AG,4,FALSE) -> Depreciation-Tools, furniture & office equipment
A11: 007 | B11: Projector - Spark Plug 1 | C11: Tools, furniture & office equipment | D11: 2141000 | E11: 8000000 | F11: 60 | G11: GENERAL AFFAIR | H11: 1 | I11: 44348 | J11: BIP | K11: GENERAL AFFAIR | M11: BGT.FY122 | N11: =H11*E11 -> 8000000 | O11: =N11/F11 -> 133333.33 | P11: =DATE(YEAR(I11),MONTH(I11)+F11,DAY(I11)) -> 46174 | Q11: =IF(AND(LEFT(Q$1,FIND("_",Q$1)-1)&RIGHT(Q$1,LEN(Q$1)-FIND("_",Q$1)) >= YEAR($I11) & TEXT(MONTH($I11),"00"),LEFT(Q$1,FIND("_",Q$1)-1)&RIGHT(Q$1,LEN(Q$1)-FIND("_",Q$1)) < YEAR($P11) & TEXT(MONTH($P11),"00")),$O11,"") | R11: =IF(AND(LEFT(R$1,FIND("_",R$1)-1)&RIGHT(R$1,LEN(R$1)-FIND("_",R$1)) >= YEAR($I11) & TEXT(MONTH($I11),"00"),LEFT(R$1,FIND("_",R$1)-1)&RIGHT(R$1,LEN(R$1)-FIND("_",R$1)) < YEAR($P11) & TEXT(MONTH($P11),"00")),$O11,"") | S11: =IF(AND(LEFT(S$1,FIND("_",S$1)-1)&RIGHT(S$1,LEN(S$1)-FIND("_",S$1)) >= YEAR($I11) & TEXT(MONTH($I11),"00"),LEFT(S$1,FIND("_",S$1)-1)&RIGHT(S$1,LEN(S$1)-FIND("_",S$1)) < YEAR($P11) & TEXT(MONTH($P11),"00")),$O11,"") | T11: =IF(AND(LEFT(T$1,FIND("_",T$1)-1)&RIGHT(T$1,LEN(T$1)-FIND("_",T$1)) >= YEAR($I11) & TEXT(MONTH($I11),"00"),LEFT(T$1,FIND("_",T$1)-1)&RIGHT(T$1,LEN(T$1)-FIND("_",T$1)) < YEAR($P11) & TEXT(MONTH($P11),"00")),$O11,"") | U11: =IF(AND(LEFT(U$1,FIND("_",U$1)-1)&RIGHT(U$1,LEN(U$1)-FIND("_",U$1)) >= YEAR($I11) & TEXT(MONTH($I11),"00"),LEFT(U$1,FIND("_",U$1)-1)&RIGHT(U$1,LEN(U$1)-FIND("_",U$1)) < YEAR($P11) & TEXT(MONTH($P11),"00")),$O11,"") | V11: =IF(AND(LEFT(V$1,FIND("_",V$1)-1)&RIGHT(V$1,LEN(V$1)-FIND("_",V$1)) >= YEAR($I11) & TEXT(MONTH($I11),"00"),LEFT(V$1,FIND("_",V$1)-1)&RIGHT(V$1,LEN(V$1)-FIND("_",V$1)) < YEAR($P11) & TEXT(MONTH($P11),"00")),$O11,"") | W11: =IF(AND(LEFT(W$1,FIND("_",W$1)-1)&RIGHT(W$1,LEN(W$1)-FIND("_",W$1)) >= YEAR($I11) & TEXT(MONTH($I11),"00"),LEFT(W$1,FIND("_",W$1)-1)&RIGHT(W$1,LEN(W$1)-FIND("_",W$1)) < YEAR($P11) & TEXT(MONTH($P11),"00")),$O11,"") | X11: =IF(AND(LEFT(X$1,FIND("_",X$1)-1)&RIGHT(X$1,LEN(X$1)-FIND("_",X$1)) >= YEAR($I11) & TEXT(MONTH($I11),"00"),LEFT(X$1,FIND("_",X$1)-1)&RIGHT(X$1,LEN(X$1)-FIND("_",X$1)) < YEAR($P11) & TEXT(MONTH($P11),"00")),$O11,"") -> 133333.33 | ... BE11: =IF(AND(LEFT(BE$1,FIND("_",BE$1)-1)&RIGHT(BE$1,LEN(BE$1)-FIND("_",BE$1)) >= YEAR($I11) & TEXT(MONTH($I11),"00"),LEFT(BE$1,FIND("_",BE$1)-1)&RIGHT(BE$1,LEN(BE$1)-FIND("_",BE$1)) < YEAR($P11) & TEXT(MONTH($P11),"00")),$O11,"") -> 133333.33 | BF11: =SUM(Q11:U11) -> 0 | BG11: =SUM(V11:AG11) -> 1333333.3 | BH11: =SUM(AH11:AS11) -> 1600000 | BI11: =SUM(AT11:BE11) -> 1600000 | BJ11: =VLOOKUP(D11,Master!AD:AG,3,FALSE) -> 7611600 | BK11: =VLOOKUP(D11,Master!AD:AG,4,FALSE) -> Depreciation-Tools, furniture & office equipment
A12: 008 | B12: Projector - Spark Plug 2 | C12: Tools, furniture & office equipment | D12: 2141000 | E12: 8000000 | F12: 60 | G12: GENERAL AFFAIR | H12: 1 | I12: 44348 | J12: BIP | K12: GENERAL AFFAIR | M12: BGT.FY122 | N12: =H12*E12 -> 8000000 | O12: =N12/F12 -> 133333.33 | P12: =DATE(YEAR(I12),MONTH(I12)+F12,DAY(I12)) -> 46174 | Q12: =IF(AND(LEFT(Q$1,FIND("_",Q$1)-1)&RIGHT(Q$1,LEN(Q$1)-FIND("_",Q$1)) >= YEAR($I12) & TEXT(MONTH($I12),"00"),LEFT(Q$1,FIND("_",Q$1)-1)&RIGHT(Q$1,LEN(Q$1)-FIND("_",Q$1)) < YEAR($P12) & TEXT(MONTH($P12),"00")),$O12,"") | R12: =IF(AND(LEFT(R$1,FIND("_",R$1)-1)&RIGHT(R$1,LEN(R$1)-FIND("_",R$1)) >= YEAR($I12) & TEXT(MONTH($I12),"00"),LEFT(R$1,FIND("_",R$1)-1)&RIGHT(R$1,LEN(R$1)-FIND("_",R$1)) < YEAR($P12) & TEXT(MONTH($P12),"00")),$O12,"") | S12: =IF(AND(LEFT(S$1,FIND("_",S$1)-1)&RIGHT(S$1,LEN(S$1)-FIND("_",S$1)) >= YEAR($I12) & TEXT(MONTH($I12),"00"),LEFT(S$1,FIND("_",S$1)-1)&RIGHT(S$1,LEN(S$1)-FIND("_",S$1)) < YEAR($P12) & TEXT(MONTH($P12),"00")),$O12,"") | T12: =IF(AND(LEFT(T$1,FIND("_",T$1)-1)&RIGHT(T$1,LEN(T$1)-FIND("_",T$1)) >= YEAR($I12) & TEXT(MONTH($I12),"00"),LEFT(T$1,FIND("_",T$1)-1)&RIGHT(T$1,LEN(T$1)-FIND("_",T$1)) < YEAR($P12) & TEXT(MONTH($P12),"00")),$O12,"") | U12: =IF(AND(LEFT(U$1,FIND("_",U$1)-1)&RIGHT(U$1,LEN(U$1)-FIND("_",U$1)) >= YEAR($I12) & TEXT(MONTH($I12),"00"),LEFT(U$1,FIND("_",U$1)-1)&RIGHT(U$1,LEN(U$1)-FIND("_",U$1)) < YEAR($P12) & TEXT(MONTH($P12),"00")),$O12,"") | V12: =IF(AND(LEFT(V$1,FIND("_",V$1)-1)&RIGHT(V$1,LEN(V$1)-FIND("_",V$1)) >= YEAR($I12) & TEXT(MONTH($I12),"00"),LEFT(V$1,FIND("_",V$1)-1)&RIGHT(V$1,LEN(V$1)-FIND("_",V$1)) < YEAR($P12) & TEXT(MONTH($P12),"00")),$O12,"") | W12: =IF(AND(LEFT(W$1,FIND("_",W$1)-1)&RIGHT(W$1,LEN(W$1)-FIND("_",W$1)) >= YEAR($I12) & TEXT(MONTH($I12),"00"),LEFT(W$1,FIND("_",W$1)-1)&RIGHT(W$1,LEN(W$1)-FIND("_",W$1)) < YEAR($P12) & TEXT(MONTH($P12),"00")),$O12,"") | X12: =IF(AND(LEFT(X$1,FIND("_",X$1)-1)&RIGHT(X$1,LEN(X$1)-FIND("_",X$1)) >= YEAR($I12) & TEXT(MONTH($I12),"00"),LEFT(X$1,FIND("_",X$1)-1)&RIGHT(X$1,LEN(X$1)-FIND("_",X$1)) < YEAR($P12) & TEXT(MONTH($P12),"00")),$O12,"") -> 133333.33 | ... BE12: =IF(AND(LEFT(BE$1,FIND("_",BE$1)-1)&RIGHT(BE$1,LEN(BE$1)-FIND("_",BE$1)) >= YEAR($I12) & TEXT(MONTH($I12),"00"),LEFT(BE$1,FIND("_",BE$1)-1)&RIGHT(BE$1,LEN(BE$1)-FIND("_",BE$1)) < YEAR($P12) & TEXT(MONTH($P12),"00")),$O12,"") -> 133333.33 | BF12: =SUM(Q12:U12) -> 0 | BG12: =SUM(V12:AG12) -> 1333333.3 | BH12: =SUM(AH12:AS12) -> 1600000 | BI12: =SUM(AT12:BE12) -> 1600000 | BJ12: =VLOOKUP(D12,Master!AD:AG,3,FALSE) -> 7611600 | BK12: =VLOOKUP(D12,Master!AD:AG,4,FALSE) -> Depreciation-Tools, furniture & office equipment
A13: 009 | B13: Projector - Office | C13: Tools, furniture & office equipment | D13: 2141000 | E13: 8000000 | F13: 60 | G13: GENERAL AFFAIR | H13: 1 | I13: 44348 | J13: BIP | K13: GENERAL AFFAIR | M13: BGT.FY122 | N13: =H13*E13 -> 8000000 | O13: =N13/F13 -> 133333.33 | P13: =DATE(YEAR(I13),MONTH(I13)+F13,DAY(I13)) -> 46174 | Q13: =IF(AND(LEFT(Q$1,FIND("_",Q$1)-1)&RIGHT(Q$1,LEN(Q$1)-FIND("_",Q$1)) >= YEAR($I13) & TEXT(MONTH($I13),"00"),LEFT(Q$1,FIND("_",Q$1)-1)&RIGHT(Q$1,LEN(Q$1)-FIND("_",Q$1)) < YEAR($P13) & TEXT(MONTH($P13),"00")),$O13,"") | R13: =IF(AND(LEFT(R$1,FIND("_",R$1)-1)&RIGHT(R$1,LEN(R$1)-FIND("_",R$1)) >= YEAR($I13) & TEXT(MONTH($I13),"00"),LEFT(R$1,FIND("_",R$1)-1)&RIGHT(R$1,LEN(R$1)-FIND("_",R$1)) < YEAR($P13) & TEXT(MONTH($P13),"00")),$O13,"") | S13: =IF(AND(LEFT(S$1,FIND("_",S$1)-1)&RIGHT(S$1,LEN(S$1)-FIND("_",S$1)) >= YEAR($I13) & TEXT(MONTH($I13),"00"),LEFT(S$1,FIND("_",S$1)-1)&RIGHT(S$1,LEN(S$1)-FIND("_",S$1)) < YEAR($P13) & TEXT(MONTH($P13),"00")),$O13,"") | T13: =IF(AND(LEFT(T$1,FIND("_",T$1)-1)&RIGHT(T$1,LEN(T$1)-FIND("_",T$1)) >= YEAR($I13) & TEXT(MONTH($I13),"00"),LEFT(T$1,FIND("_",T$1)-1)&RIGHT(T$1,LEN(T$1)-FIND("_",T$1)) < YEAR($P13) & TEXT(MONTH($P13),"00")),$O13,"") | U13: =IF(AND(LEFT(U$1,FIND("_",U$1)-1)&RIGHT(U$1,LEN(U$1)-FIND("_",U$1)) >= YEAR($I13) & TEXT(MONTH($I13),"00"),LEFT(U$1,FIND("_",U$1)-1)&RIGHT(U$1,LEN(U$1)-FIND("_",U$1)) < YEAR($P13) & TEXT(MONTH($P13),"00")),$O13,"") | V13: =IF(AND(LEFT(V$1,FIND("_",V$1)-1)&RIGHT(V$1,LEN(V$1)-FIND("_",V$1)) >= YEAR($I13) & TEXT(MONTH($I13),"00"),LEFT(V$1,FIND("_",V$1)-1)&RIGHT(V$1,LEN(V$1)-FIND("_",V$1)) < YEAR($P13) & TEXT(MONTH($P13),"00")),$O13,"") | W13: =IF(AND(LEFT(W$1,FIND("_",W$1)-1)&RIGHT(W$1,LEN(W$1)-FIND("_",W$1)) >= YEAR($I13) & TEXT(MONTH($I13),"00"),LEFT(W$1,FIND("_",W$1)-1)&RIGHT(W$1,LEN(W$1)-FIND("_",W$1)) < YEAR($P13) & TEXT(MONTH($P13),"00")),$O13,"") | X13: =IF(AND(LEFT(X$1,FIND("_",X$1)-1)&RIGHT(X$1,LEN(X$1)-FIND("_",X$1)) >= YEAR($I13) & TEXT(MONTH($I13),"00"),LEFT(X$1,FIND("_",X$1)-1)&RIGHT(X$1,LEN(X$1)-FIND("_",X$1)) < YEAR($P13) & TEXT(MONTH($P13),"00")),$O13,"") -> 133333.33 | ... BE13: =IF(AND(LEFT(BE$1,FIND("_",BE$1)-1)&RIGHT(BE$1,LEN(BE$1)-FIND("_",BE$1)) >= YEAR($I13) & TEXT(MONTH($I13),"00"),LEFT(BE$1,FIND("_",BE$1)-1)&RIGHT(BE$1,LEN(BE$1)-FIND("_",BE$1)) < YEAR($P13) & TEXT(MONTH($P13),"00")),$O13,"") -> 133333.33 | BF13: =SUM(Q13:U13) -> 0 | BG13: =SUM(V13:AG13) -> 1333333.3 | BH13: =SUM(AH13:AS13) -> 1600000 | BI13: =SUM(AT13:BE13) -> 1600000 | BJ13: =VLOOKUP(D13,Master!AD:AG,3,FALSE) -> 7611600 | BK13: =VLOOKUP(D13,Master!AD:AG,4,FALSE) -> Depreciation-Tools, furniture & office equipment
A14: 010 | B14: TV For Projector Guest Room | C14: Tools, furniture & office equipment | D14: 2141000 | E14: 10000000 | F14: 60 | G14: GENERAL AFFAIR | H14: 1 | I14: 44348 | J14: BIP | K14: GENERAL AFFAIR | M14: BGT.FY122 | N14: =H14*E14 -> 10000000 | O14: =N14/F14 -> 166666.67 | P14: =DATE(YEAR(I14),MONTH(I14)+F14,DAY(I14)) -> 46174 | Q14: =IF(AND(LEFT(Q$1,FIND("_",Q$1)-1)&RIGHT(Q$1,LEN(Q$1)-FIND("_",Q$1)) >= YEAR($I14) & TEXT(MONTH($I14),"00"),LEFT(Q$1,FIND("_",Q$1)-1)&RIGHT(Q$1,LEN(Q$1)-FIND("_",Q$1)) < YEAR($P14) & TEXT(MONTH($P14),"00")),$O14,"") | R14: =IF(AND(LEFT(R$1,FIND("_",R$1)-1)&RIGHT(R$1,LEN(R$1)-FIND("_",R$1)) >= YEAR($I14) & TEXT(MONTH($I14),"00"),LEFT(R$1,FIND("_",R$1)-1)&RIGHT(R$1,LEN(R$1)-FIND("_",R$1)) < YEAR($P14) & TEXT(MONTH($P14),"00")),$O14,"") | S14: =IF(AND(LEFT(S$1,FIND("_",S$1)-1)&RIGHT(S$1,LEN(S$1)-FIND("_",S$1)) >= YEAR($I14) & TEXT(MONTH($I14),"00"),LEFT(S$1,FIND("_",S$1)-1)&RIGHT(S$1,LEN(S$1)-FIND("_",S$1)) < YEAR($P14) & TEXT(MONTH($P14),"00")),$O14,"") | T14: =IF(AND(LEFT(T$1,FIND("_",T$1)-1)&RIGHT(T$1,LEN(T$1)-FIND("_",T$1)) >= YEAR($I14) & TEXT(MONTH($I14),"00"),LEFT(T$1,FIND("_",T$1)-1)&RIGHT(T$1,LEN(T$1)-FIND("_",T$1)) < YEAR($P14) & TEXT(MONTH($P14),"00")),$O14,"") | U14: =IF(AND(LEFT(U$1,FIND("_",U$1)-1)&RIGHT(U$1,LEN(U$1)-FIND("_",U$1)) >= YEAR($I14) & TEXT(MONTH($I14),"00"),LEFT(U$1,FIND("_",U$1)-1)&RIGHT(U$1,LEN(U$1)-FIND("_",U$1)) < YEAR($P14) & TEXT(MONTH($P14),"00")),$O14,"") | V14: =IF(AND(LEFT(V$1,FIND("_",V$1)-1)&RIGHT(V$1,LEN(V$1)-FIND("_",V$1)) >= YEAR($I14) & TEXT(MONTH($I14),"00"),LEFT(V$1,FIND("_",V$1)-1)&RIGHT(V$1,LEN(V$1)-FIND("_",V$1)) < YEAR($P14) & TEXT(MONTH($P14),"00")),$O14,"") | W14: =IF(AND(LEFT(W$1,FIND("_",W$1)-1)&RIGHT(W$1,LEN(W$1)-FIND("_",W$1)) >= YEAR($I14) & TEXT(MONTH($I14),"00"),LEFT(W$1,FIND("_",W$1)-1)&RIGHT(W$1,LEN(W$1)-FIND("_",W$1)) < YEAR($P14) & TEXT(MONTH($P14),"00")),$O14,"") | X14: =IF(AND(LEFT(X$1,FIND("_",X$1)-1)&RIGHT(X$1,LEN(X$1)-FIND("_",X$1)) >= YEAR($I14) & TEXT(MONTH($I14),"00"),LEFT(X$1,FIND("_",X$1)-1)&RIGHT(X$1,LEN(X$1)-FIND("_",X$1)) < YEAR($P14) & TEXT(MONTH($P14),"00")),$O14,"") -> 166666.67 | ... BE14: =IF(AND(LEFT(BE$1,FIND("_",BE$1)-1)&RIGHT(BE$1,LEN(BE$1)-FIND("_",BE$1)) >= YEAR($I14) & TEXT(MONTH($I14),"00"),LEFT(BE$1,FIND("_",BE$1)-1)&RIGHT(BE$1,LEN(BE$1)-FIND("_",BE$1)) < YEAR($P14) & TEXT(MONTH($P14),"00")),$O14,"") -> 166666.67 | BF14: =SUM(Q14:U14) -> 0 | BG14: =SUM(V14:AG14) -> 1666666.7 | BH14: =SUM(AH14:AS14) -> 2000000 | BI14: =SUM(AT14:BE14) -> 2000000 | BJ14: =VLOOKUP(D14,Master!AD:AG,3,FALSE) -> 7611600 | BK14: =VLOOKUP(D14,Master!AD:AG,4,FALSE) -> Depreciation-Tools, furniture & office equipment
A15: 011 | B15: TV For Projector Sensor O2 | C15: Tools, furniture & office equipment | D15: 2141000 | E15: 10000000 | F15: 60 | G15: GENERAL AFFAIR | H15: 1 | I15: 44348 | J15: BIP | K15: GENERAL AFFAIR | M15: BGT.FY122 | N15: =H15*E15 -> 10000000 | O15: =N15/F15 -> 166666.67 | P15: =DATE(YEAR(I15),MONTH(I15)+F15,DAY(I15)) -> 46174 | Q15: =IF(AND(LEFT(Q$1,FIND("_",Q$1)-1)&RIGHT(Q$1,LEN(Q$1)-FIND("_",Q$1)) >= YEAR($I15) & TEXT(MONTH($I15),"00"),LEFT(Q$1,FIND("_",Q$1)-1)&RIGHT(Q$1,LEN(Q$1)-FIND("_",Q$1)) < YEAR($P15) & TEXT(MONTH($P15),"00")),$O15,"") | R15: =IF(AND(LEFT(R$1,FIND("_",R$1)-1)&RIGHT(R$1,LEN(R$1)-FIND("_",R$1)) >= YEAR($I15) & TEXT(MONTH($I15),"00"),LEFT(R$1,FIND("_",R$1)-1)&RIGHT(R$1,LEN(R$1)-FIND("_",R$1)) < YEAR($P15) & TEXT(MONTH($P15),"00")),$O15,"") | S15: =IF(AND(LEFT(S$1,FIND("_",S$1)-1)&RIGHT(S$1,LEN(S$1)-FIND("_",S$1)) >= YEAR($I15) & TEXT(MONTH($I15),"00"),LEFT(S$1,FIND("_",S$1)-1)&RIGHT(S$1,LEN(S$1)-FIND("_",S$1)) < YEAR($P15) & TEXT(MONTH($P15),"00")),$O15,"") | T15: =IF(AND(LEFT(T$1,FIND("_",T$1)-1)&RIGHT(T$1,LEN(T$1)-FIND("_",T$1)) >= YEAR($I15) & TEXT(MONTH($I15),"00"),LEFT(T$1,FIND("_",T$1)-1)&RIGHT(T$1,LEN(T$1)-FIND("_",T$1)) < YEAR($P15) & TEXT(MONTH($P15),"00")),$O15,"") | U15: =IF(AND(LEFT(U$1,FIND("_",U$1)-1)&RIGHT(U$1,LEN(U$1)-FIND("_",U$1)) >= YEAR($I15) & TEXT(MONTH($I15),"00"),LEFT(U$1,FIND("_",U$1)-1)&RIGHT(U$1,LEN(U$1)-FIND("_",U$1)) < YEAR($P15) & TEXT(MONTH($P15),"00")),$O15,"") | V15: =IF(AND(LEFT(V$1,FIND("_",V$1)-1)&RIGHT(V$1,LEN(V$1)-FIND("_",V$1)) >= YEAR($I15) & TEXT(MONTH($I15),"00"),LEFT(V$1,FIND("_",V$1)-1)&RIGHT(V$1,LEN(V$1)-FIND("_",V$1)) < YEAR($P15) & TEXT(MONTH($P15),"00")),$O15,"") | W15: =IF(AND(LEFT(W$1,FIND("_",W$1)-1)&RIGHT(W$1,LEN(W$1)-FIND("_",W$1)) >= YEAR($I15) & TEXT(MONTH($I15),"00"),LEFT(W$1,FIND("_",W$1)-1)&RIGHT(W$1,LEN(W$1)-FIND("_",W$1)) < YEAR($P15) & TEXT(MONTH($P15),"00")),$O15,"") | X15: =IF(AND(LEFT(X$1,FIND("_",X$1)-1)&RIGHT(X$1,LEN(X$1)-FIND("_",X$1)) >= YEAR($I15) & TEXT(MONTH($I15),"00"),LEFT(X$1,FIND("_",X$1)-1)&RIGHT(X$1,LEN(X$1)-FIND("_",X$1)) < YEAR($P15) & TEXT(MONTH($P15),"00")),$O15,"") -> 166666.67 | ... BE15: =IF(AND(LEFT(BE$1,FIND("_",BE$1)-1)&RIGHT(BE$1,LEN(BE$1)-FIND("_",BE$1)) >= YEAR($I15) & TEXT(MONTH($I15),"00"),LEFT(BE$1,FIND("_",BE$1)-1)&RIGHT(BE$1,LEN(BE$1)-FIND("_",BE$1)) < YEAR($P15) & TEXT(MONTH($P15),"00")),$O15,"") -> 166666.67 | BF15: =SUM(Q15:U15) -> 0 | BG15: =SUM(V15:AG15) -> 1666666.7 | BH15: =SUM(AH15:AS15) -> 2000000 | BI15: =SUM(AT15:BE15) -> 2000000 | BJ15: =VLOOKUP(D15,Master!AD:AG,3,FALSE) -> 7611600 | BK15: =VLOOKUP(D15,Master!AD:AG,4,FALSE) -> Depreciation-Tools, furniture & office equipment
A16: 012 | B16: TV For Projector Kaizen | C16: Tools, furniture & office equipment | D16: 2141000 | E16: 10000000 | F16: 60 | G16: GENERAL AFFAIR | H16: 1 | I16: 44348 | J16: BIP | K16: GENERAL AFFAIR | M16: BGT.FY122 | N16: =H16*E16 -> 10000000 | O16: =N16/F16 -> 166666.67 | P16: =DATE(YEAR(I16),MONTH(I16)+F16,DAY(I16)) -> 46174 | Q16: =IF(AND(LEFT(Q$1,FIND("_",Q$1)-1)&RIGHT(Q$1,LEN(Q$1)-FIND("_",Q$1)) >= YEAR($I16) & TEXT(MONTH($I16),"00"),LEFT(Q$1,FIND("_",Q$1)-1)&RIGHT(Q$1,LEN(Q$1)-FIND("_",Q$1)) < YEAR($P16) & TEXT(MONTH($P16),"00")),$O16,"") | R16: =IF(AND(LEFT(R$1,FIND("_",R$1)-1)&RIGHT(R$1,LEN(R$1)-FIND("_",R$1)) >= YEAR($I16) & TEXT(MONTH($I16),"00"),LEFT(R$1,FIND("_",R$1)-1)&RIGHT(R$1,LEN(R$1)-FIND("_",R$1)) < YEAR($P16) & TEXT(MONTH($P16),"00")),$O16,"") | S16: =IF(AND(LEFT(S$1,FIND("_",S$1)-1)&RIGHT(S$1,LEN(S$1)-FIND("_",S$1)) >= YEAR($I16) & TEXT(MONTH($I16),"00"),LEFT(S$1,FIND("_",S$1)-1)&RIGHT(S$1,LEN(S$1)-FIND("_",S$1)) < YEAR($P16) & TEXT(MONTH($P16),"00")),$O16,"") | T16: =IF(AND(LEFT(T$1,FIND("_",T$1)-1)&RIGHT(T$1,LEN(T$1)-FIND("_",T$1)) >= YEAR($I16) & TEXT(MONTH($I16),"00"),LEFT(T$1,FIND("_",T$1)-1)&RIGHT(T$1,LEN(T$1)-FIND("_",T$1)) < YEAR($P16) & TEXT(MONTH($P16),"00")),$O16,"") | U16: =IF(AND(LEFT(U$1,FIND("_",U$1)-1)&RIGHT(U$1,LEN(U$1)-FIND("_",U$1)) >= YEAR($I16) & TEXT(MONTH($I16),"00"),LEFT(U$1,FIND("_",U$1)-1)&RIGHT(U$1,LEN(U$1)-FIND("_",U$1)) < YEAR($P16) & TEXT(MONTH($P16),"00")),$O16,"") | V16: =IF(AND(LEFT(V$1,FIND("_",V$1)-1)&RIGHT(V$1,LEN(V$1)-FIND("_",V$1)) >= YEAR($I16) & TEXT(MONTH($I16),"00"),LEFT(V$1,FIND("_",V$1)-1)&RIGHT(V$1,LEN(V$1)-FIND("_",V$1)) < YEAR($P16) & TEXT(MONTH($P16),"00")),$O16,"") | W16: =IF(AND(LEFT(W$1,FIND("_",W$1)-1)&RIGHT(W$1,LEN(W$1)-FIND("_",W$1)) >= YEAR($I16) & TEXT(MONTH($I16),"00"),LEFT(W$1,FIND("_",W$1)-1)&RIGHT(W$1,LEN(W$1)-FIND("_",W$1)) < YEAR($P16) & TEXT(MONTH($P16),"00")),$O16,"") | X16: =IF(AND(LEFT(X$1,FIND("_",X$1)-1)&RIGHT(X$1,LEN(X$1)-FIND("_",X$1)) >= YEAR($I16) & TEXT(MONTH($I16),"00"),LEFT(X$1,FIND("_",X$1)-1)&RIGHT(X$1,LEN(X$1)-FIND("_",X$1)) < YEAR($P16) & TEXT(MONTH($P16),"00")),$O16,"") -> 166666.67 | ... BE16: =IF(AND(LEFT(BE$1,FIND("_",BE$1)-1)&RIGHT(BE$1,LEN(BE$1)-FIND("_",BE$1)) >= YEAR($I16) & TEXT(MONTH($I16),"00"),LEFT(BE$1,FIND("_",BE$1)-1)&RIGHT(BE$1,LEN(BE$1)-FIND("_",BE$1)) < YEAR($P16) & TEXT(MONTH($P16),"00")),$O16,"") -> 166666.67 | BF16: =SUM(Q16:U16) -> 0 | BG16: =SUM(V16:AG16) -> 1666666.7 | BH16: =SUM(AH16:AS16) -> 2000000 | BI16: =SUM(AT16:BE16) -> 2000000 | BJ16: =VLOOKUP(D16,Master!AD:AG,3,FALSE) -> 7611600 | BK16: =VLOOKUP(D16,Master!AD:AG,4,FALSE) -> Depreciation-Tools, furniture & office equipment
... A30: 026 | B30: Operational Car Expats FA (Innova) | C30: Vehicles | D30: 2131000 | E30: 335000000 | F30: 60 | G30: Accounting & Finance | H30: 1 | I30: 45469 | J30: BIP | K30: GENERAL AFFAIR | M30: BGT.FY125 | N30: =H30*E30 -> 335000000 | O30: =N30/F30 -> 5583333.3 | P30: =DATE(YEAR(I30),MONTH(I30)+F30,DAY(I30)) -> 47295 | Q30: =IF(AND(LEFT(Q$1,FIND("_",Q$1)-1)&RIGHT(Q$1,LEN(Q$1)-FIND("_",Q$1)) >= YEAR($I30) & TEXT(MONTH($I30),"00"),LEFT(Q$1,FIND("_",Q$1)-1)&RIGHT(Q$1,LEN(Q$1)-FIND("_",Q$1)) < YEAR($P30) & TEXT(MONTH($P30),"00")),$O30,"") | R30: =IF(AND(LEFT(R$1,FIND("_",R$1)-1)&RIGHT(R$1,LEN(R$1)-FIND("_",R$1)) >= YEAR($I30) & TEXT(MONTH($I30),"00"),LEFT(R$1,FIND("_",R$1)-1)&RIGHT(R$1,LEN(R$1)-FIND("_",R$1)) < YEAR($P30) & TEXT(MONTH($P30),"00")),$O30,"") | S30: =IF(AND(LEFT(S$1,FIND("_",S$1)-1)&RIGHT(S$1,LEN(S$1)-FIND("_",S$1)) >= YEAR($I30) & TEXT(MONTH($I30),"00"),LEFT(S$1,FIND("_",S$1)-1)&RIGHT(S$1,LEN(S$1)-FIND("_",S$1)) < YEAR($P30) & TEXT(MONTH($P30),"00")),$O30,"") | T30: =IF(AND(LEFT(T$1,FIND("_",T$1)-1)&RIGHT(T$1,LEN(T$1)-FIND("_",T$1)) >= YEAR($I30) & TEXT(MONTH($I30),"00"),LEFT(T$1,FIND("_",T$1)-1)&RIGHT(T$1,LEN(T$1)-FIND("_",T$1)) < YEAR($P30) & TEXT(MONTH($P30),"00")),$O30,"") | U30: =IF(AND(LEFT(U$1,FIND("_",U$1)-1)&RIGHT(U$1,LEN(U$1)-FIND("_",U$1)) >= YEAR($I30) & TEXT(MONTH($I30),"00"),LEFT(U$1,FIND("_",U$1)-1)&RIGHT(U$1,LEN(U$1)-FIND("_",U$1)) < YEAR($P30) & TEXT(MONTH($P30),"00")),$O30,"") | V30: =IF(AND(LEFT(V$1,FIND("_",V$1)-1)&RIGHT(V$1,LEN(V$1)-FIND("_",V$1)) >= YEAR($I30) & TEXT(MONTH($I30),"00"),LEFT(V$1,FIND("_",V$1)-1)&RIGHT(V$1,LEN(V$1)-FIND("_",V$1)) < YEAR($P30) & TEXT(MONTH($P30),"00")),$O30,"") | W30: =IF(AND(LEFT(W$1,FIND("_",W$1)-1)&RIGHT(W$1,LEN(W$1)-FIND("_",W$1)) >= YEAR($I30) & TEXT(MONTH($I30),"00"),LEFT(W$1,FIND("_",W$1)-1)&RIGHT(W$1,LEN(W$1)-FIND("_",W$1)) < YEAR($P30) & TEXT(MONTH($P30),"00")),$O30,"") | X30: =IF(AND(LEFT(X$1,FIND("_",X$1)-1)&RIGHT(X$1,LEN(X$1)-FIND("_",X$1)) >= YEAR($I30) & TEXT(MONTH($I30),"00"),LEFT(X$1,FIND("_",X$1)-1)&RIGHT(X$1,LEN(X$1)-FIND("_",X$1)) < YEAR($P30) & TEXT(MONTH($P30),"00")),$O30,"") | ... BE30: =IF(AND(LEFT(BE$1,FIND("_",BE$1)-1)&RIGHT(BE$1,LEN(BE$1)-FIND("_",BE$1)) >= YEAR($I30) & TEXT(MONTH($I30),"00"),LEFT(BE$1,FIND("_",BE$1)-1)&RIGHT(BE$1,LEN(BE$1)-FIND("_",BE$1)) < YEAR($P30) & TEXT(MONTH($P30),"00")),$O30,"") | BF30: =SUM(Q30:U30) -> 0 | BG30: =SUM(V30:AG30) -> 0 | BH30: =SUM(AH30:AS30) -> 0 | BI30: =SUM(AT30:BE30) -> 0 | BJ30: =VLOOKUP(D30,Master!AD:AG,3,FALSE) -> 7611500 | BK30: =VLOOKUP(D30,Master!AD:AG,4,FALSE) -> Depreciation-Vehicles
A31: 001 | B31: PC for Wisnu | C31: Tools, furniture & office equipment | D31: 2141000 | E31: 10000000 | F31: 60 | G31: Health, Safety & Environment | H31: 1 | I31: 44197 | J31: BIP | K31: Health, Safety & Environment | L31: A | M31: BGT.FY121 | N31: =H31*E31 -> 10000000 | O31: =N31/F31 -> 166666.67 | P31: =DATE(YEAR(I31),MONTH(I31)+F31,DAY(I31)) -> 46023 | Q31: =IF(AND(LEFT(Q$1,FIND("_",Q$1)-1)&RIGHT(Q$1,LEN(Q$1)-FIND("_",Q$1)) >= YEAR($I31) & TEXT(MONTH($I31),"00"),LEFT(Q$1,FIND("_",Q$1)-1)&RIGHT(Q$1,LEN(Q$1)-FIND("_",Q$1)) < YEAR($P31) & TEXT(MONTH($P31),"00")),$O31,"") | R31: =IF(AND(LEFT(R$1,FIND("_",R$1)-1)&RIGHT(R$1,LEN(R$1)-FIND("_",R$1)) >= YEAR($I31) & TEXT(MONTH($I31),"00"),LEFT(R$1,FIND("_",R$1)-1)&RIGHT(R$1,LEN(R$1)-FIND("_",R$1)) < YEAR($P31) & TEXT(MONTH($P31),"00")),$O31,"") | S31: =IF(AND(LEFT(S$1,FIND("_",S$1)-1)&RIGHT(S$1,LEN(S$1)-FIND("_",S$1)) >= YEAR($I31) & TEXT(MONTH($I31),"00"),LEFT(S$1,FIND("_",S$1)-1)&RIGHT(S$1,LEN(S$1)-FIND("_",S$1)) < YEAR($P31) & TEXT(MONTH($P31),"00")),$O31,"") -> 166666.67 | T31: =IF(AND(LEFT(T$1,FIND("_",T$1)-1)&RIGHT(T$1,LEN(T$1)-FIND("_",T$1)) >= YEAR($I31) & TEXT(MONTH($I31),"00"),LEFT(T$1,FIND("_",T$1)-1)&RIGHT(T$1,LEN(T$1)-FIND("_",T$1)) < YEAR($P31) & TEXT(MONTH($P31),"00")),$O31,"") -> 166666.67 | U31: =IF(AND(LEFT(U$1,FIND("_",U$1)-1)&RIGHT(U$1,LEN(U$1)-FIND("_",U$1)) >= YEAR($I31) & TEXT(MONTH($I31),"00"),LEFT(U$1,FIND("_",U$1)-1)&RIGHT(U$1,LEN(U$1)-FIND("_",U$1)) < YEAR($P31) & TEXT(MONTH($P31),"00")),$O31,"") -> 166666.67 | V31: =IF(AND(LEFT(V$1,FIND("_",V$1)-1)&RIGHT(V$1,LEN(V$1)-FIND("_",V$1)) >= YEAR($I31) & TEXT(MONTH($I31),"00"),LEFT(V$1,FIND("_",V$1)-1)&RIGHT(V$1,LEN(V$1)-FIND("_",V$1)) < YEAR($P31) & TEXT(MONTH($P31),"00")),$O31,"") -> 166666.67 | W31: =IF(AND(LEFT(W$1,FIND("_",W$1)-1)&RIGHT(W$1,LEN(W$1)-FIND("_",W$1)) >= YEAR($I31) & TEXT(MONTH($I31),"00"),LEFT(W$1,FIND("_",W$1)-1)&RIGHT(W$1,LEN(W$1)-FIND("_",W$1)) < YEAR($P31) & TEXT(MONTH($P31),"00")),$O31,"") -> 166666.67 | X31: =IF(AND(LEFT(X$1,FIND("_",X$1)-1)&RIGHT(X$1,LEN(X$1)-FIND("_",X$1)) >= YEAR($I31) & TEXT(MONTH($I31),"00"),LEFT(X$1,FIND("_",X$1)-1)&RIGHT(X$1,LEN(X$1)-FIND("_",X$1)) < YEAR($P31) & TEXT(MONTH($P31),"00")),$O31,"") -> 166666.67 | ... BE31: =IF(AND(LEFT(BE$1,FIND("_",BE$1)-1)&RIGHT(BE$1,LEN(BE$1)-FIND("_",BE$1)) >= YEAR($I31) & TEXT(MONTH($I31),"00"),LEFT(BE$1,FIND("_",BE$1)-1)&RIGHT(BE$1,LEN(BE$1)-FIND("_",BE$1)) < YEAR($P31) & TEXT(MONTH($P31),"00")),$O31,"") -> 166666.67 | BF31: =SUM(Q31:U31) -> 500000 | BG31: =SUM(V31:AG31) -> 2000000 | BH31: =SUM(AH31:AS31) -> 2000000 | BI31: =SUM(AT31:BE31) -> 2000000 | BJ31: =VLOOKUP(D31,Master!AD:AG,3,FALSE) -> 7611600 | BK31: =VLOOKUP(D31,Master!AD:AG,4,FALSE) -> Depreciation-Tools, furniture & office equipment
A32: 002 | B32: PC for Andika | C32: Tools, furniture & office equipment | D32: 2141000 | E32: 10000000 | F32: 60 | G32: Health, Safety & Environment | H32: 1 | I32: 44197 | J32: BIP | K32: Health, Safety & Environment | L32: A | M32: BGT.FY121 | N32: =H32*E32 -> 10000000 | O32: =N32/F32 -> 166666.67 | P32: =DATE(YEAR(I32),MONTH(I32)+F32,DAY(I32)) -> 46023 | Q32: =IF(AND(LEFT(Q$1,FIND("_",Q$1)-1)&RIGHT(Q$1,LEN(Q$1)-FIND("_",Q$1)) >= YEAR($I32) & TEXT(MONTH($I32),"00"),LEFT(Q$1,FIND("_",Q$1)-1)&RIGHT(Q$1,LEN(Q$1)-FIND("_",Q$1)) < YEAR($P32) & TEXT(MONTH($P32),"00")),$O32,"") | R32: =IF(AND(LEFT(R$1,FIND("_",R$1)-1)&RIGHT(R$1,LEN(R$1)-FIND("_",R$1)) >= YEAR($I32) & TEXT(MONTH($I32),"00"),LEFT(R$1,FIND("_",R$1)-1)&RIGHT(R$1,LEN(R$1)-FIND("_",R$1)) < YEAR($P32) & TEXT(MONTH($P32),"00")),$O32,"") | S32: =IF(AND(LEFT(S$1,FIND("_",S$1)-1)&RIGHT(S$1,LEN(S$1)-FIND("_",S$1)) >= YEAR($I32) & TEXT(MONTH($I32),"00"),LEFT(S$1,FIND("_",S$1)-1)&RIGHT(S$1,LEN(S$1)-FIND("_",S$1)) < YEAR($P32) & TEXT(MONTH($P32),"00")),$O32,"") -> 166666.67 | T32: =IF(AND(LEFT(T$1,FIND("_",T$1)-1)&RIGHT(T$1,LEN(T$1)-FIND("_",T$1)) >= YEAR($I32) & TEXT(MONTH($I32),"00"),LEFT(T$1,FIND("_",T$1)-1)&RIGHT(T$1,LEN(T$1)-FIND("_",T$1)) < YEAR($P32) & TEXT(MONTH($P32),"00")),$O32,"") -> 166666.67 | U32: =IF(AND(LEFT(U$1,FIND("_",U$1)-1)&RIGHT(U$1,LEN(U$1)-FIND("_",U$1)) >= YEAR($I32) & TEXT(MONTH($I32),"00"),LEFT(U$1,FIND("_",U$1)-1)&RIGHT(U$1,LEN(U$1)-FIND("_",U$1)) < YEAR($P32) & TEXT(MONTH($P32),"00")),$O32,"") -> 166666.67 | V32: =IF(AND(LEFT(V$1,FIND("_",V$1)-1)&RIGHT(V$1,LEN(V$1)-FIND("_",V$1)) >= YEAR($I32) & TEXT(MONTH($I32),"00"),LEFT(V$1,FIND("_",V$1)-1)&RIGHT(V$1,LEN(V$1)-FIND("_",V$1)) < YEAR($P32) & TEXT(MONTH($P32),"00")),$O32,"") -> 166666.67 | W32: =IF(AND(LEFT(W$1,FIND("_",W$1)-1)&RIGHT(W$1,LEN(W$1)-FIND("_",W$1)) >= YEAR($I32) & TEXT(MONTH($I32),"00"),LEFT(W$1,FIND("_",W$1)-1)&RIGHT(W$1,LEN(W$1)-FIND("_",W$1)) < YEAR($P32) & TEXT(MONTH($P32),"00")),$O32,"") -> 166666.67 | X32: =IF(AND(LEFT(X$1,FIND("_",X$1)-1)&RIGHT(X$1,LEN(X$1)-FIND("_",X$1)) >= YEAR($I32) & TEXT(MONTH($I32),"00"),LEFT(X$1,FIND("_",X$1)-1)&RIGHT(X$1,LEN(X$1)-FIND("_",X$1)) < YEAR($P32) & TEXT(MONTH($P32),"00")),$O32,"") -> 166666.67 | ... BE32: =IF(AND(LEFT(BE$1,FIND("_",BE$1)-1)&RIGHT(BE$1,LEN(BE$1)-FIND("_",BE$1)) >= YEAR($I32) & TEXT(MONTH($I32),"00"),LEFT(BE$1,FIND("_",BE$1)-1)&RIGHT(BE$1,LEN(BE$1)-FIND("_",BE$1)) < YEAR($P32) & TEXT(MONTH($P32),"00")),$O32,"") -> 166666.67 | BF32: =SUM(Q32:U32) -> 500000 | BG32: =SUM(V32:AG32) -> 2000000 | BH32: =SUM(AH32:AS32) -> 2000000 | BI32: =SUM(AT32:BE32) -> 2000000 | BJ32: =VLOOKUP(D32,Master!AD:AG,3,FALSE) -> 7611600 | BK32: =VLOOKUP(D32,Master!AD:AG,4,FALSE) -> Depreciation-Tools, furniture & office equipment
A33: 003 | B33: PC for Ibit R | C33: Tools, furniture & office equipment | D33: 2141000 | E33: 10000000 | F33: 60 | G33: Health, Safety & Environment | H33: 1 | I33: 44378 | J33: BIP | K33: Health, Safety & Environment | L33: A | M33: BGT.FY122 | N33: =H33*E33 -> 10000000 | O33: =N33/F33 -> 166666.67 | P33: =DATE(YEAR(I33),MONTH(I33)+F33,DAY(I33)) -> 46204 | Q33: =IF(AND(LEFT(Q$1,FIND("_",Q$1)-1)&RIGHT(Q$1,LEN(Q$1)-FIND("_",Q$1)) >= YEAR($I33) & TEXT(MONTH($I33),"00"),LEFT(Q$1,FIND("_",Q$1)-1)&RIGHT(Q$1,LEN(Q$1)-FIND("_",Q$1)) < YEAR($P33) & TEXT(MONTH($P33),"00")),$O33,"") | R33: =IF(AND(LEFT(R$1,FIND("_",R$1)-1)&RIGHT(R$1,LEN(R$1)-FIND("_",R$1)) >= YEAR($I33) & TEXT(MONTH($I33),"00"),LEFT(R$1,FIND("_",R$1)-1)&RIGHT(R$1,LEN(R$1)-FIND("_",R$1)) < YEAR($P33) & TEXT(MONTH($P33),"00")),$O33,"") | S33: =IF(AND(LEFT(S$1,FIND("_",S$1)-1)&RIGHT(S$1,LEN(S$1)-FIND("_",S$1)) >= YEAR($I33) & TEXT(MONTH($I33),"00"),LEFT(S$1,FIND("_",S$1)-1)&RIGHT(S$1,LEN(S$1)-FIND("_",S$1)) < YEAR($P33) & TEXT(MONTH($P33),"00")),$O33,"") | T33: =IF(AND(LEFT(T$1,FIND("_",T$1)-1)&RIGHT(T$1,LEN(T$1)-FIND("_",T$1)) >= YEAR($I33) & TEXT(MONTH($I33),"00"),LEFT(T$1,FIND("_",T$1)-1)&RIGHT(T$1,LEN(T$1)-FIND("_",T$1)) < YEAR($P33) & TEXT(MONTH($P33),"00")),$O33,"") | U33: =IF(AND(LEFT(U$1,FIND("_",U$1)-1)&RIGHT(U$1,LEN(U$1)-FIND("_",U$1)) >= YEAR($I33) & TEXT(MONTH($I33),"00"),LEFT(U$1,FIND("_",U$1)-1)&RIGHT(U$1,LEN(U$1)-FIND("_",U$1)) < YEAR($P33) & TEXT(MONTH($P33),"00")),$O33,"") | V33: =IF(AND(LEFT(V$1,FIND("_",V$1)-1)&RIGHT(V$1,LEN(V$1)-FIND("_",V$1)) >= YEAR($I33) & TEXT(MONTH($I33),"00"),LEFT(V$1,FIND("_",V$1)-1)&RIGHT(V$1,LEN(V$1)-FIND("_",V$1)) < YEAR($P33) & TEXT(MONTH($P33),"00")),$O33,"") | W33: =IF(AND(LEFT(W$1,FIND("_",W$1)-1)&RIGHT(W$1,LEN(W$1)-FIND("_",W$1)) >= YEAR($I33) & TEXT(MONTH($I33),"00"),LEFT(W$1,FIND("_",W$1)-1)&RIGHT(W$1,LEN(W$1)-FIND("_",W$1)) < YEAR($P33) & TEXT(MONTH($P33),"00")),$O33,"") | X33: =IF(AND(LEFT(X$1,FIND("_",X$1)-1)&RIGHT(X$1,LEN(X$1)-FIND("_",X$1)) >= YEAR($I33) & TEXT(MONTH($I33),"00"),LEFT(X$1,FIND("_",X$1)-1)&RIGHT(X$1,LEN(X$1)-FIND("_",X$1)) < YEAR($P33) & TEXT(MONTH($P33),"00")),$O33,"") | ... BE33: =IF(AND(LEFT(BE$1,FIND("_",BE$1)-1)&RIGHT(BE$1,LEN(BE$1)-FIND("_",BE$1)) >= YEAR($I33) & TEXT(MONTH($I33),"00"),LEFT(BE$1,FIND("_",BE$1)-1)&RIGHT(BE$1,LEN(BE$1)-FIND("_",BE$1)) < YEAR($P33) & TEXT(MONTH($P33),"00")),$O33,"") -> 166666.67 | BF33: =SUM(Q33:U33) -> 0 | BG33: =SUM(V33:AG33) -> 1500000 | BH33: =SUM(AH33:AS33) -> 2000000 | BI33: =SUM(AT33:BE33) -> 2000000 | BJ33: =VLOOKUP(D33,Master!AD:AG,3,FALSE) -> 7611600 | BK33: =VLOOKUP(D33,Master!AD:AG,4,FALSE) -> Depreciation-Tools, furniture & office equipment
A34: 004 | B34: PC for Syauqurrohman | C34: Tools, furniture & office equipment | D34: 2141000 | E34: 10000000 | F34: 60 | G34: Health, Safety & Environment | H34: 1 | I34: 44378 | J34: BIP | K34: Health, Safety & Environment | L34: A | M34: BGT.FY122 | N34: =H34*E34 -> 10000000 | O34: =N34/F34 -> 166666.67 | P34: =DATE(YEAR(I34),MONTH(I34)+F34,DAY(I34)) -> 46204 | Q34: =IF(AND(LEFT(Q$1,FIND("_",Q$1)-1)&RIGHT(Q$1,LEN(Q$1)-FIND("_",Q$1)) >= YEAR($I34) & TEXT(MONTH($I34),"00"),LEFT(Q$1,FIND("_",Q$1)-1)&RIGHT(Q$1,LEN(Q$1)-FIND("_",Q$1)) < YEAR($P34) & TEXT(MONTH($P34),"00")),$O34,"") | R34: =IF(AND(LEFT(R$1,FIND("_",R$1)-1)&RIGHT(R$1,LEN(R$1)-FIND("_",R$1)) >= YEAR($I34) & TEXT(MONTH($I34),"00"),LEFT(R$1,FIND("_",R$1)-1)&RIGHT(R$1,LEN(R$1)-FIND("_",R$1)) < YEAR($P34) & TEXT(MONTH($P34),"00")),$O34,"") | S34: =IF(AND(LEFT(S$1,FIND("_",S$1)-1)&RIGHT(S$1,LEN(S$1)-FIND("_",S$1)) >= YEAR($I34) & TEXT(MONTH($I34),"00"),LEFT(S$1,FIND("_",S$1)-1)&RIGHT(S$1,LEN(S$1)-FIND("_",S$1)) < YEAR($P34) & TEXT(MONTH($P34),"00")),$O34,"") | T34: =IF(AND(LEFT(T$1,FIND("_",T$1)-1)&RIGHT(T$1,LEN(T$1)-FIND("_",T$1)) >= YEAR($I34) & TEXT(MONTH($I34),"00"),LEFT(T$1,FIND("_",T$1)-1)&RIGHT(T$1,LEN(T$1)-FIND("_",T$1)) < YEAR($P34) & TEXT(MONTH($P34),"00")),$O34,"") | U34: =IF(AND(LEFT(U$1,FIND("_",U$1)-1)&RIGHT(U$1,LEN(U$1)-FIND("_",U$1)) >= YEAR($I34) & TEXT(MONTH($I34),"00"),LEFT(U$1,FIND("_",U$1)-1)&RIGHT(U$1,LEN(U$1)-FIND("_",U$1)) < YEAR($P34) & TEXT(MONTH($P34),"00")),$O34,"") | V34: =IF(AND(LEFT(V$1,FIND("_",V$1)-1)&RIGHT(V$1,LEN(V$1)-FIND("_",V$1)) >= YEAR($I34) & TEXT(MONTH($I34),"00"),LEFT(V$1,FIND("_",V$1)-1)&RIGHT(V$1,LEN(V$1)-FIND("_",V$1)) < YEAR($P34) & TEXT(MONTH($P34),"00")),$O34,"") | W34: =IF(AND(LEFT(W$1,FIND("_",W$1)-1)&RIGHT(W$1,LEN(W$1)-FIND("_",W$1)) >= YEAR($I34) & TEXT(MONTH($I34),"00"),LEFT(W$1,FIND("_",W$1)-1)&RIGHT(W$1,LEN(W$1)-FIND("_",W$1)) < YEAR($P34) & TEXT(MONTH($P34),"00")),$O34,"") | X34: =IF(AND(LEFT(X$1,FIND("_",X$1)-1)&RIGHT(X$1,LEN(X$1)-FIND("_",X$1)) >= YEAR($I34) & TEXT(MONTH($I34),"00"),LEFT(X$1,FIND("_",X$1)-1)&RIGHT(X$1,LEN(X$1)-FIND("_",X$1)) < YEAR($P34) & TEXT(MONTH($P34),"00")),$O34,"") | ... BE34: =IF(AND(LEFT(BE$1,FIND("_",BE$1)-1)&RIGHT(BE$1,LEN(BE$1)-FIND("_",BE$1)) >= YEAR($I34) & TEXT(MONTH($I34),"00"),LEFT(BE$1,FIND("_",BE$1)-1)&RIGHT(BE$1,LEN(BE$1)-FIND("_",BE$1)) < YEAR($P34) & TEXT(MONTH($P34),"00")),$O34,"") -> 166666.67 | BF34: =SUM(Q34:U34) -> 0 | BG34: =SUM(V34:AG34) -> 1500000 | BH34: =SUM(AH34:AS34) -> 2000000 | BI34: =SUM(AT34:BE34) -> 2000000 | BJ34: =VLOOKUP(D34,Master!AD:AG,3,FALSE) -> 7611600 | BK34: =VLOOKUP(D34,Master!AD:AG,4,FALSE) -> Depreciation-Tools, furniture & office equipment
A35: 001 | B35: PC Oki Setiawan | C35: Tools, furniture & office equipment | D35: 2141000 | E35: 8000000 | F35: 60 | G35: Maintenance | H35: 1 | I35: 44348 | J35: BIP | K35: Maintenance | L35: B | M35: BGT.FY122 | N35: =H35*E35 -> 8000000 | O35: =N35/F35 -> 133333.33 | P35: =DATE(YEAR(I35),MONTH(I35)+F35,DAY(I35)) -> 46174 | Q35: =IF(AND(LEFT(Q$1,FIND("_",Q$1)-1)&RIGHT(Q$1,LEN(Q$1)-FIND("_",Q$1)) >= YEAR($I35) & TEXT(MONTH($I35),"00"),LEFT(Q$1,FIND("_",Q$1)-1)&RIGHT(Q$1,LEN(Q$1)-FIND("_",Q$1)) < YEAR($P35) & TEXT(MONTH($P35),"00")),$O35,"") | R35: =IF(AND(LEFT(R$1,FIND("_",R$1)-1)&RIGHT(R$1,LEN(R$1)-FIND("_",R$1)) >= YEAR($I35) & TEXT(MONTH($I35),"00"),LEFT(R$1,FIND("_",R$1)-1)&RIGHT(R$1,LEN(R$1)-FIND("_",R$1)) < YEAR($P35) & TEXT(MONTH($P35),"00")),$O35,"") | S35: =IF(AND(LEFT(S$1,FIND("_",S$1)-1)&RIGHT(S$1,LEN(S$1)-FIND("_",S$1)) >= YEAR($I35) & TEXT(MONTH($I35),"00"),LEFT(S$1,FIND("_",S$1)-1)&RIGHT(S$1,LEN(S$1)-FIND("_",S$1)) < YEAR($P35) & TEXT(MONTH($P35),"00")),$O35,"") | T35: =IF(AND(LEFT(T$1,FIND("_",T$1)-1)&RIGHT(T$1,LEN(T$1)-FIND("_",T$1)) >= YEAR($I35) & TEXT(MONTH($I35),"00"),LEFT(T$1,FIND("_",T$1)-1)&RIGHT(T$1,LEN(T$1)-FIND("_",T$1)) < YEAR($P35) & TEXT(MONTH($P35),"00")),$O35,"") | U35: =IF(AND(LEFT(U$1,FIND("_",U$1)-1)&RIGHT(U$1,LEN(U$1)-FIND("_",U$1)) >= YEAR($I35) & TEXT(MONTH($I35),"00"),LEFT(U$1,FIND("_",U$1)-1)&RIGHT(U$1,LEN(U$1)-FIND("_",U$1)) < YEAR($P35) & TEXT(MONTH($P35),"00")),$O35,"") | V35: =IF(AND(LEFT(V$1,FIND("_",V$1)-1)&RIGHT(V$1,LEN(V$1)-FIND("_",V$1)) >= YEAR($I35) & TEXT(MONTH($I35),"00"),LEFT(V$1,FIND("_",V$1)-1)&RIGHT(V$1,LEN(V$1)-FIND("_",V$1)) < YEAR($P35) & TEXT(MONTH($P35),"00")),$O35,"") | W35: =IF(AND(LEFT(W$1,FIND("_",W$1)-1)&RIGHT(W$1,LEN(W$1)-FIND("_",W$1)) >= YEAR($I35) & TEXT(MONTH($I35),"00"),LEFT(W$1,FIND("_",W$1)-1)&RIGHT(W$1,LEN(W$1)-FIND("_",W$1)) < YEAR($P35) & TEXT(MONTH($P35),"00")),$O35,"") | X35: =IF(AND(LEFT(X$1,FIND("_",X$1)-1)&RIGHT(X$1,LEN(X$1)-FIND("_",X$1)) >= YEAR($I35) & TEXT(MONTH($I35),"00"),LEFT(X$1,FIND("_",X$1)-1)&RIGHT(X$1,LEN(X$1)-FIND("_",X$1)) < YEAR($P35) & TEXT(MONTH($P35),"00")),$O35,"") -> 133333.33 | ... BE35: =IF(AND(LEFT(BE$1,FIND("_",BE$1)-1)&RIGHT(BE$1,LEN(BE$1)-FIND("_",BE$1)) >= YEAR($I35) & TEXT(MONTH($I35),"00"),LEFT(BE$1,FIND("_",BE$1)-1)&RIGHT(BE$1,LEN(BE$1)-FIND("_",BE$1)) < YEAR($P35) & TEXT(MONTH($P35),"00")),$O35,"") -> 133333.33 | BF35: =SUM(Q35:U35) -> 0 | BG35: =SUM(V35:AG35) -> 1333333.3 | BH35: =SUM(AH35:AS35) -> 1600000 | BI35: =SUM(AT35:BE35) -> 1600000 | BJ35: =VLOOKUP(D35,Master!AD:AG,3,FALSE) -> 7611600 | BK35: =VLOOKUP(D35,Master!AD:AG,4,FALSE) -> Depreciation-Tools, furniture & office equipment
A36: 002 | B36: Cable and sub distribution panel for Front Office | C36: Building | D36: 2111100 | E36: 80000000 | F36: 120 | G36: General Affair | H36: 1 | I36: 44378 | J36: BIP | K36: Maintenance | L36: B | M36: BGT.FY122 | N36: =H36*E36 -> 80000000 | O36: =N36/F36 -> 666666.67 | P36: =DATE(YEAR(I36),MONTH(I36)+F36,DAY(I36)) -> 48030 | Q36: =IF(AND(LEFT(Q$1,FIND("_",Q$1)-1)&RIGHT(Q$1,LEN(Q$1)-FIND("_",Q$1)) >= YEAR($I36) & TEXT(MONTH($I36),"00"),LEFT(Q$1,FIND("_",Q$1)-1)&RIGHT(Q$1,LEN(Q$1)-FIND("_",Q$1)) < YEAR($P36) & TEXT(MONTH($P36),"00")),$O36,"") | R36: =IF(AND(LEFT(R$1,FIND("_",R$1)-1)&RIGHT(R$1,LEN(R$1)-FIND("_",R$1)) >= YEAR($I36) & TEXT(MONTH($I36),"00"),LEFT(R$1,FIND("_",R$1)-1)&RIGHT(R$1,LEN(R$1)-FIND("_",R$1)) < YEAR($P36) & TEXT(MONTH($P36),"00")),$O36,"") | S36: =IF(AND(LEFT(S$1,FIND("_",S$1)-1)&RIGHT(S$1,LEN(S$1)-FIND("_",S$1)) >= YEAR($I36) & TEXT(MONTH($I36),"00"),LEFT(S$1,FIND("_",S$1)-1)&RIGHT(S$1,LEN(S$1)-FIND("_",S$1)) < YEAR($P36) & TEXT(MONTH($P36),"00")),$O36,"") | T36: =IF(AND(LEFT(T$1,FIND("_",T$1)-1)&RIGHT(T$1,LEN(T$1)-FIND("_",T$1)) >= YEAR($I36) & TEXT(MONTH($I36),"00"),LEFT(T$1,FIND("_",T$1)-1)&RIGHT(T$1,LEN(T$1)-FIND("_",T$1)) < YEAR($P36) & TEXT(MONTH($P36),"00")),$O36,"") | U36: =IF(AND(LEFT(U$1,FIND("_",U$1)-1)&RIGHT(U$1,LEN(U$1)-FIND("_",U$1)) >= YEAR($I36) & TEXT(MONTH($I36),"00"),LEFT(U$1,FIND("_",U$1)-1)&RIGHT(U$1,LEN(U$1)-FIND("_",U$1)) < YEAR($P36) & TEXT(MONTH($P36),"00")),$O36,"") | V36: =IF(AND(LEFT(V$1,FIND("_",V$1)-1)&RIGHT(V$1,LEN(V$1)-FIND("_",V$1)) >= YEAR($I36) & TEXT(MONTH($I36),"00"),LEFT(V$1,FIND("_",V$1)-1)&RIGHT(V$1,LEN(V$1)-FIND("_",V$1)) < YEAR($P36) & TEXT(MONTH($P36),"00")),$O36,"") | W36: =IF(AND(LEFT(W$1,FIND("_",W$1)-1)&RIGHT(W$1,LEN(W$1)-FIND("_",W$1)) >= YEAR($I36) & TEXT(MONTH($I36),"00"),LEFT(W$1,FIND("_",W$1)-1)&RIGHT(W$1,LEN(W$1)-FIND("_",W$1)) < YEAR($P36) & TEXT(MONTH($P36),"00")),$O36,"") | X36: =IF(AND(LEFT(X$1,FIND("_",X$1)-1)&RIGHT(X$1,LEN(X$1)-FIND("_",X$1)) >= YEAR($I36) & TEXT(MONTH($I36),"00"),LEFT(X$1,FIND("_",X$1)-1)&RIGHT(X$1,LEN(X$1)-FIND("_",X$1)) < YEAR($P36) & TEXT(MONTH($P36),"00")),$O36,"") | ... BE36: =IF(AND(LEFT(BE$1,FIND("_",BE$1)-1)&RIGHT(BE$1,LEN(BE$1)-FIND("_",BE$1)) >= YEAR($I36) & TEXT(MONTH($I36),"00"),LEFT(BE$1,FIND("_",BE$1)-1)&RIGHT(BE$1,LEN(BE$1)-FIND("_",BE$1)) < YEAR($P36) & TEXT(MONTH($P36),"00")),$O36,"") -> 666666.67 | BF36: =SUM(Q36:U36) -> 0 | BG36: =SUM(V36:AG36) -> 6000000 | BH36: =SUM(AH36:AS36) -> 8000000 | BI36: =SUM(AT36:BE36) -> 8000000 | BJ36: =VLOOKUP(D36,Master!AD:AG,3,FALSE) -> 7611100 | BK36: =VLOOKUP(D36,Master!AD:AG,4,FALSE) -> Depreciation-Building
A37: 003 | B37: Laptop Agung H | C37: Tools, furniture & office equipment | D37: 2141000 | E37: 15000000 | F37: 60 | G37: Maintenance | H37: 1 | I37: 44378 | J37: BIP | K37: Maintenance | L37: B | M37: BGT.FY122 | N37: =H37*E37 -> 15000000 | O37: =N37/F37 -> 250000 | P37: =DATE(YEAR(I37),MONTH(I37)+F37,DAY(I37)) -> 46204 | Q37: =IF(AND(LEFT(Q$1,FIND("_",Q$1)-1)&RIGHT(Q$1,LEN(Q$1)-FIND("_",Q$1)) >= YEAR($I37) & TEXT(MONTH($I37),"00"),LEFT(Q$1,FIND("_",Q$1)-1)&RIGHT(Q$1,LEN(Q$1)-FIND("_",Q$1)) < YEAR($P37) & TEXT(MONTH($P37),"00")),$O37,"") | R37: =IF(AND(LEFT(R$1,FIND("_",R$1)-1)&RIGHT(R$1,LEN(R$1)-FIND("_",R$1)) >= YEAR($I37) & TEXT(MONTH($I37),"00"),LEFT(R$1,FIND("_",R$1)-1)&RIGHT(R$1,LEN(R$1)-FIND("_",R$1)) < YEAR($P37) & TEXT(MONTH($P37),"00")),$O37,"") | S37: =IF(AND(LEFT(S$1,FIND("_",S$1)-1)&RIGHT(S$1,LEN(S$1)-FIND("_",S$1)) >= YEAR($I37) & TEXT(MONTH($I37),"00"),LEFT(S$1,FIND("_",S$1)-1)&RIGHT(S$1,LEN(S$1)-FIND("_",S$1)) < YEAR($P37) & TEXT(MONTH($P37),"00")),$O37,"") | T37: =IF(AND(LEFT(T$1,FIND("_",T$1)-1)&RIGHT(T$1,LEN(T$1)-FIND("_",T$1)) >= YEAR($I37) & TEXT(MONTH($I37),"00"),LEFT(T$1,FIND("_",T$1)-1)&RIGHT(T$1,LEN(T$1)-FIND("_",T$1)) < YEAR($P37) & TEXT(MONTH($P37),"00")),$O37,"") | U37: =IF(AND(LEFT(U$1,FIND("_",U$1)-1)&RIGHT(U$1,LEN(U$1)-FIND("_",U$1)) >= YEAR($I37) & TEXT(MONTH($I37),"00"),LEFT(U$1,FIND("_",U$1)-1)&RIGHT(U$1,LEN(U$1)-FIND("_",U$1)) < YEAR($P37) & TEXT(MONTH($P37),"00")),$O37,"") | V37: =IF(AND(LEFT(V$1,FIND("_",V$1)-1)&RIGHT(V$1,LEN(V$1)-FIND("_",V$1)) >= YEAR($I37) & TEXT(MONTH($I37),"00"),LEFT(V$1,FIND("_",V$1)-1)&RIGHT(V$1,LEN(V$1)-FIND("_",V$1)) < YEAR($P37) & TEXT(MONTH($P37),"00")),$O37,"") | W37: =IF(AND(LEFT(W$1,FIND("_",W$1)-1)&RIGHT(W$1,LEN(W$1)-FIND("_",W$1)) >= YEAR($I37) & TEXT(MONTH($I37),"00"),LEFT(W$1,FIND("_",W$1)-1)&RIGHT(W$1,LEN(W$1)-FIND("_",W$1)) < YEAR($P37) & TEXT(MONTH($P37),"00")),$O37,"") | X37: =IF(AND(LEFT(X$1,FIND("_",X$1)-1)&RIGHT(X$1,LEN(X$1)-FIND("_",X$1)) >= YEAR($I37) & TEXT(MONTH($I37),"00"),LEFT(X$1,FIND("_",X$1)-1)&RIGHT(X$1,LEN(X$1)-FIND("_",X$1)) < YEAR($P37) & TEXT(MONTH($P37),"00")),$O37,"") | ... BE37: =IF(AND(LEFT(BE$1,FIND("_",BE$1)-1)&RIGHT(BE$1,LEN(BE$1)-FIND("_",BE$1)) >= YEAR($I37) & TEXT(MONTH($I37),"00"),LEFT(BE$1,FIND("_",BE$1)-1)&RIGHT(BE$1,LEN(BE$1)-FIND("_",BE$1)) < YEAR($P37) & TEXT(MONTH($P37),"00")),$O37,"") -> 250000 | BF37: =SUM(Q37:U37) -> 0 | BG37: =SUM(V37:AG37) -> 2250000 | BH37: =SUM(AH37:AS37) -> 3000000 | BI37: =SUM(AT37:BE37) -> 3000000 | BJ37: =VLOOKUP(D37,Master!AD:AG,3,FALSE) -> 7611600 | BK37: =VLOOKUP(D37,Master!AD:AG,4,FALSE) -> Depreciation-Tools, furniture & office equipment
A38: 004 | B38: Relayout Piping & Replacement pressure tank of compressor 4.000 lt | C38: Machinery & Equipment - New | D38: 2121000 | E38: 500000000 | F38: 120 | G38: Maintenance | H38: 1 | I38: 44378 | J38: CIP | K38: Maintenance | L38: B | M38: BGT.FY122 | N38: =H38*E38 -> 500000000 | O38: =N38/F38 -> 4166666.7 | P38: =DATE(YEAR(I38),MONTH(I38)+F38,DAY(I38)) -> 48030 | Q38: =IF(AND(LEFT(Q$1,FIND("_",Q$1)-1)&RIGHT(Q$1,LEN(Q$1)-FIND("_",Q$1)) >= YEAR($I38) & TEXT(MONTH($I38),"00"),LEFT(Q$1,FIND("_",Q$1)-1)&RIGHT(Q$1,LEN(Q$1)-FIND("_",Q$1)) < YEAR($P38) & TEXT(MONTH($P38),"00")),$O38,"") | R38: =IF(AND(LEFT(R$1,FIND("_",R$1)-1)&RIGHT(R$1,LEN(R$1)-FIND("_",R$1)) >= YEAR($I38) & TEXT(MONTH($I38),"00"),LEFT(R$1,FIND("_",R$1)-1)&RIGHT(R$1,LEN(R$1)-FIND("_",R$1)) < YEAR($P38) & TEXT(MONTH($P38),"00")),$O38,"") | S38: =IF(AND(LEFT(S$1,FIND("_",S$1)-1)&RIGHT(S$1,LEN(S$1)-FIND("_",S$1)) >= YEAR($I38) & TEXT(MONTH($I38),"00"),LEFT(S$1,FIND("_",S$1)-1)&RIGHT(S$1,LEN(S$1)-FIND("_",S$1)) < YEAR($P38) & TEXT(MONTH($P38),"00")),$O38,"") | T38: =IF(AND(LEFT(T$1,FIND("_",T$1)-1)&RIGHT(T$1,LEN(T$1)-FIND("_",T$1)) >= YEAR($I38) & TEXT(MONTH($I38),"00"),LEFT(T$1,FIND("_",T$1)-1)&RIGHT(T$1,LEN(T$1)-FIND("_",T$1)) < YEAR($P38) & TEXT(MONTH($P38),"00")),$O38,"") | U38: =IF(AND(LEFT(U$1,FIND("_",U$1)-1)&RIGHT(U$1,LEN(U$1)-FIND("_",U$1)) >= YEAR($I38) & TEXT(MONTH($I38),"00"),LEFT(U$1,FIND("_",U$1)-1)&RIGHT(U$1,LEN(U$1)-FIND("_",U$1)) < YEAR($P38) & TEXT(MONTH($P38),"00")),$O38,"") | V38: =IF(AND(LEFT(V$1,FIND("_",V$1)-1)&RIGHT(V$1,LEN(V$1)-FIND("_",V$1)) >= YEAR($I38) & TEXT(MONTH($I38),"00"),LEFT(V$1,FIND("_",V$1)-1)&RIGHT(V$1,LEN(V$1)-FIND("_",V$1)) < YEAR($P38) & TEXT(MONTH($P38),"00")),$O38,"") | W38: =IF(AND(LEFT(W$1,FIND("_",W$1)-1)&RIGHT(W$1,LEN(W$1)-FIND("_",W$1)) >= YEAR($I38) & TEXT(MONTH($I38),"00"),LEFT(W$1,FIND("_",W$1)-1)&RIGHT(W$1,LEN(W$1)-FIND("_",W$1)) < YEAR($P38) & TEXT(MONTH($P38),"00")),$O38,"") | X38: =IF(AND(LEFT(X$1,FIND("_",X$1)-1)&RIGHT(X$1,LEN(X$1)-FIND("_",X$1)) >= YEAR($I38) & TEXT(MONTH($I38),"00"),LEFT(X$1,FIND("_",X$1)-1)&RIGHT(X$1,LEN(X$1)-FIND("_",X$1)) < YEAR($P38) & TEXT(MONTH($P38),"00")),$O38,"") | ... BE38: =IF(AND(LEFT(BE$1,FIND("_",BE$1)-1)&RIGHT(BE$1,LEN(BE$1)-FIND("_",BE$1)) >= YEAR($I38) & TEXT(MONTH($I38),"00"),LEFT(BE$1,FIND("_",BE$1)-1)&RIGHT(BE$1,LEN(BE$1)-FIND("_",BE$1)) < YEAR($P38) & TEXT(MONTH($P38),"00")),$O38,"") -> 4166666.7 | BF38: =SUM(Q38:U38) -> 0 | BG38: =SUM(V38:AG38) -> 37500000 | BH38: =SUM(AH38:AS38) -> 50000000 | BI38: =SUM(AT38:BE38) -> 50000000 | BJ38: =VLOOKUP(D38,Master!AD:AG,3,FALSE) -> 7611300 | BK38: =VLOOKUP(D38,Master!AD:AG,4,FALSE) -> Depreciation-Machiney & equipment
A39: 005 | B39: Drier Compressor No.5 | C39: Machinery & Equipment - New | D39: 2121000 | E39: 100000000 | F39: 120 | G39: Maintenance | H39: 1 | I39: 44378 | J39: CIP | K39: Maintenance | L39: B | M39: BGT.FY122 | N39: =H39*E39 -> 100000000 | O39: =N39/F39 -> 833333.33 | P39: =DATE(YEAR(I39),MONTH(I39)+F39,DAY(I39)) -> 48030 | Q39: =IF(AND(LEFT(Q$1,FIND("_",Q$1)-1)&RIGHT(Q$1,LEN(Q$1)-FIND("_",Q$1)) >= YEAR($I39) & TEXT(MONTH($I39),"00"),LEFT(Q$1,FIND("_",Q$1)-1)&RIGHT(Q$1,LEN(Q$1)-FIND("_",Q$1)) < YEAR($P39) & TEXT(MONTH($P39),"00")),$O39,"") | R39: =IF(AND(LEFT(R$1,FIND("_",R$1)-1)&RIGHT(R$1,LEN(R$1)-FIND("_",R$1)) >= YEAR($I39) & TEXT(MONTH($I39),"00"),LEFT(R$1,FIND("_",R$1)-1)&RIGHT(R$1,LEN(R$1)-FIND("_",R$1)) < YEAR($P39) & TEXT(MONTH($P39),"00")),$O39,"") | S39: =IF(AND(LEFT(S$1,FIND("_",S$1)-1)&RIGHT(S$1,LEN(S$1)-FIND("_",S$1)) >= YEAR($I39) & TEXT(MONTH($I39),"00"),LEFT(S$1,FIND("_",S$1)-1)&RIGHT(S$1,LEN(S$1)-FIND("_",S$1)) < YEAR($P39) & TEXT(MONTH($P39),"00")),$O39,"") | T39: =IF(AND(LEFT(T$1,FIND("_",T$1)-1)&RIGHT(T$1,LEN(T$1)-FIND("_",T$1)) >= YEAR($I39) & TEXT(MONTH($I39),"00"),LEFT(T$1,FIND("_",T$1)-1)&RIGHT(T$1,LEN(T$1)-FIND("_",T$1)) < YEAR($P39) & TEXT(MONTH($P39),"00")),$O39,"") | U39: =IF(AND(LEFT(U$1,FIND("_",U$1)-1)&RIGHT(U$1,LEN(U$1)-FIND("_",U$1)) >= YEAR($I39) & TEXT(MONTH($I39),"00"),LEFT(U$1,FIND("_",U$1)-1)&RIGHT(U$1,LEN(U$1)-FIND("_",U$1)) < YEAR($P39) & TEXT(MONTH($P39),"00")),$O39,"") | V39: =IF(AND(LEFT(V$1,FIND("_",V$1)-1)&RIGHT(V$1,LEN(V$1)-FIND("_",V$1)) >= YEAR($I39) & TEXT(MONTH($I39),"00"),LEFT(V$1,FIND("_",V$1)-1)&RIGHT(V$1,LEN(V$1)-FIND("_",V$1)) < YEAR($P39) & TEXT(MONTH($P39),"00")),$O39,"") | W39: =IF(AND(LEFT(W$1,FIND("_",W$1)-1)&RIGHT(W$1,LEN(W$1)-FIND("_",W$1)) >= YEAR($I39) & TEXT(MONTH($I39),"00"),LEFT(W$1,FIND("_",W$1)-1)&RIGHT(W$1,LEN(W$1)-FIND("_",W$1)) < YEAR($P39) & TEXT(MONTH($P39),"00")),$O39,"") | X39: =IF(AND(LEFT(X$1,FIND("_",X$1)-1)&RIGHT(X$1,LEN(X$1)-FIND("_",X$1)) >= YEAR($I39) & TEXT(MONTH($I39),"00"),LEFT(X$1,FIND("_",X$1)-1)&RIGHT(X$1,LEN(X$1)-FIND("_",X$1)) < YEAR($P39) & TEXT(MONTH($P39),"00")),$O39,"") | ... BE39: =IF(AND(LEFT(BE$1,FIND("_",BE$1)-1)&RIGHT(BE$1,LEN(BE$1)-FIND("_",BE$1)) >= YEAR($I39) & TEXT(MONTH($I39),"00"),LEFT(BE$1,FIND("_",BE$1)-1)&RIGHT(BE$1,LEN(BE$1)-FIND("_",BE$1)) < YEAR($P39) & TEXT(MONTH($P39),"00")),$O39,"") -> 833333.33 | BF39: =SUM(Q39:U39) -> 0 | BG39: =SUM(V39:AG39) -> 7500000 | BH39: =SUM(AH39:AS39) -> 10000000 | BI39: =SUM(AT39:BE39) -> 10000000 | BJ39: =VLOOKUP(D39,Master!AD:AG,3,FALSE) -> 7611300 | BK39: =VLOOKUP(D39,Master!AD:AG,4,FALSE) -> Depreciation-Machiney & equipment
A40: 006 | B40: Fire Hydrant 1st Step (Diesel engine, Pump, Valve) | C40: Machinery & Equipment - New | D40: 2121000 | E40: 1600000000 | F40: 120 | G40: Health, Safety & Environment | H40: 1 | I40: 44378 | J40: CIP | K40: Maintenance | L40: B | M40: BGT.FY122 | N40: =H40*E40 -> 1600000000 | O40: =N40/F40 -> 13333333 | P40: =DATE(YEAR(I40),MONTH(I40)+F40,DAY(I40)) -> 48030 | Q40: =IF(AND(LEFT(Q$1,FIND("_",Q$1)-1)&RIGHT(Q$1,LEN(Q$1)-FIND("_",Q$1)) >= YEAR($I40) & TEXT(MONTH($I40),"00"),LEFT(Q$1,FIND("_",Q$1)-1)&RIGHT(Q$1,LEN(Q$1)-FIND("_",Q$1)) < YEAR($P40) & TEXT(MONTH($P40),"00")),$O40,"") | R40: =IF(AND(LEFT(R$1,FIND("_",R$1)-1)&RIGHT(R$1,LEN(R$1)-FIND("_",R$1)) >= YEAR($I40) & TEXT(MONTH($I40),"00"),LEFT(R$1,FIND("_",R$1)-1)&RIGHT(R$1,LEN(R$1)-FIND("_",R$1)) < YEAR($P40) & TEXT(MONTH($P40),"00")),$O40,"") | S40: =IF(AND(LEFT(S$1,FIND("_",S$1)-1)&RIGHT(S$1,LEN(S$1)-FIND("_",S$1)) >= YEAR($I40) & TEXT(MONTH($I40),"00"),LEFT(S$1,FIND("_",S$1)-1)&RIGHT(S$1,LEN(S$1)-FIND("_",S$1)) < YEAR($P40) & TEXT(MONTH($P40),"00")),$O40,"") | T40: =IF(AND(LEFT(T$1,FIND("_",T$1)-1)&RIGHT(T$1,LEN(T$1)-FIND("_",T$1)) >= YEAR($I40) & TEXT(MONTH($I40),"00"),LEFT(T$1,FIND("_",T$1)-1)&RIGHT(T$1,LEN(T$1)-FIND("_",T$1)) < YEAR($P40) & TEXT(MONTH($P40),"00")),$O40,"") | U40: =IF(AND(LEFT(U$1,FIND("_",U$1)-1)&RIGHT(U$1,LEN(U$1)-FIND("_",U$1)) >= YEAR($I40) & TEXT(MONTH($I40),"00"),LEFT(U$1,FIND("_",U$1)-1)&RIGHT(U$1,LEN(U$1)-FIND("_",U$1)) < YEAR($P40) & TEXT(MONTH($P40),"00")),$O40,"") | V40: =IF(AND(LEFT(V$1,FIND("_",V$1)-1)&RIGHT(V$1,LEN(V$1)-FIND("_",V$1)) >= YEAR($I40) & TEXT(MONTH($I40),"00"),LEFT(V$1,FIND("_",V$1)-1)&RIGHT(V$1,LEN(V$1)-FIND("_",V$1)) < YEAR($P40) & TEXT(MONTH($P40),"00")),$O40,"") | W40: =IF(AND(LEFT(W$1,FIND("_",W$1)-1)&RIGHT(W$1,LEN(W$1)-FIND("_",W$1)) >= YEAR($I40) & TEXT(MONTH($I40),"00"),LEFT(W$1,FIND("_",W$1)-1)&RIGHT(W$1,LEN(W$1)-FIND("_",W$1)) < YEAR($P40) & TEXT(MONTH($P40),"00")),$O40,"") | X40: =IF(AND(LEFT(X$1,FIND("_",X$1)-1)&RIGHT(X$1,LEN(X$1)-FIND("_",X$1)) >= YEAR($I40) & TEXT(MONTH($I40),"00"),LEFT(X$1,FIND("_",X$1)-1)&RIGHT(X$1,LEN(X$1)-FIND("_",X$1)) < YEAR($P40) & TEXT(MONTH($P40),"00")),$O40,"") | ... BE40: =IF(AND(LEFT(BE$1,FIND("_",BE$1)-1)&RIGHT(BE$1,LEN(BE$1)-FIND("_",BE$1)) >= YEAR($I40) & TEXT(MONTH($I40),"00"),LEFT(BE$1,FIND("_",BE$1)-1)&RIGHT(BE$1,LEN(BE$1)-FIND("_",BE$1)) < YEAR($P40) & TEXT(MONTH($P40),"00")),$O40,"") -> 13333333 | BF40: =SUM(Q40:U40) -> 0 | BG40: =SUM(V40:AG40) -> 1.2e+08 | BH40: =SUM(AH40:AS40) -> 160000000 | BI40: =SUM(AT40:BE40) -> 160000000 | BJ40: =VLOOKUP(D40,Master!AD:AG,3,FALSE) -> 7611300 | BK40: =VLOOKUP(D40,Master!AD:AG,4,FALSE) -> Depreciation-Machiney & equipment
A41: 007 | B41: Fire Hydrant 2nd Step (Water tank, Piping, Sprinkle) | C41: Machinery & Equipment - New | D41: 2121000 | E41: 5300000000 | F41: 120 | G41: Health, Safety & Environment | H41: 1 | I41: 44378 | J41: CIP | K41: Maintenance | L41: B | M41: BGT.FY122 | N41: =H41*E41 -> 5300000000 | O41: =N41/F41 -> 44166667 | P41: =DATE(YEAR(I41),MONTH(I41)+F41,DAY(I41)) -> 48030 | Q41: =IF(AND(LEFT(Q$1,FIND("_",Q$1)-1)&RIGHT(Q$1,LEN(Q$1)-FIND("_",Q$1)) >= YEAR($I41) & TEXT(MONTH($I41),"00"),LEFT(Q$1,FIND("_",Q$1)-1)&RIGHT(Q$1,LEN(Q$1)-FIND("_",Q$1)) < YEAR($P41) & TEXT(MONTH($P41),"00")),$O41,"") | R41: =IF(AND(LEFT(R$1,FIND("_",R$1)-1)&RIGHT(R$1,LEN(R$1)-FIND("_",R$1)) >= YEAR($I41) & TEXT(MONTH($I41),"00"),LEFT(R$1,FIND("_",R$1)-1)&RIGHT(R$1,LEN(R$1)-FIND("_",R$1)) < YEAR($P41) & TEXT(MONTH($P41),"00")),$O41,"") | S41: =IF(AND(LEFT(S$1,FIND("_",S$1)-1)&RIGHT(S$1,LEN(S$1)-FIND("_",S$1)) >= YEAR($I41) & TEXT(MONTH($I41),"00"),LEFT(S$1,FIND("_",S$1)-1)&RIGHT(S$1,LEN(S$1)-FIND("_",S$1)) < YEAR($P41) & TEXT(MONTH($P41),"00")),$O41,"") | T41: =IF(AND(LEFT(T$1,FIND("_",T$1)-1)&RIGHT(T$1,LEN(T$1)-FIND("_",T$1)) >= YEAR($I41) & TEXT(MONTH($I41),"00"),LEFT(T$1,FIND("_",T$1)-1)&RIGHT(T$1,LEN(T$1)-FIND("_",T$1)) < YEAR($P41) & TEXT(MONTH($P41),"00")),$O41,"") | U41: =IF(AND(LEFT(U$1,FIND("_",U$1)-1)&RIGHT(U$1,LEN(U$1)-FIND("_",U$1)) >= YEAR($I41) & TEXT(MONTH($I41),"00"),LEFT(U$1,FIND("_",U$1)-1)&RIGHT(U$1,LEN(U$1)-FIND("_",U$1)) < YEAR($P41) & TEXT(MONTH($P41),"00")),$O41,"") | V41: =IF(AND(LEFT(V$1,FIND("_",V$1)-1)&RIGHT(V$1,LEN(V$1)-FIND("_",V$1)) >= YEAR($I41) & TEXT(MONTH($I41),"00"),LEFT(V$1,FIND("_",V$1)-1)&RIGHT(V$1,LEN(V$1)-FIND("_",V$1)) < YEAR($P41) & TEXT(MONTH($P41),"00")),$O41,"") | W41: =IF(AND(LEFT(W$1,FIND("_",W$1)-1)&RIGHT(W$1,LEN(W$1)-FIND("_",W$1)) >= YEAR($I41) & TEXT(MONTH($I41),"00"),LEFT(W$1,FIND("_",W$1)-1)&RIGHT(W$1,LEN(W$1)-FIND("_",W$1)) < YEAR($P41) & TEXT(MONTH($P41),"00")),$O41,"") | X41: =IF(AND(LEFT(X$1,FIND("_",X$1)-1)&RIGHT(X$1,LEN(X$1)-FIND("_",X$1)) >= YEAR($I41) & TEXT(MONTH($I41),"00"),LEFT(X$1,FIND("_",X$1)-1)&RIGHT(X$1,LEN(X$1)-FIND("_",X$1)) < YEAR($P41) & TEXT(MONTH($P41),"00")),$O41,"") | ... BE41: =IF(AND(LEFT(BE$1,FIND("_",BE$1)-1)&RIGHT(BE$1,LEN(BE$1)-FIND("_",BE$1)) >= YEAR($I41) & TEXT(MONTH($I41),"00"),LEFT(BE$1,FIND("_",BE$1)-1)&RIGHT(BE$1,LEN(BE$1)-FIND("_",BE$1)) < YEAR($P41) & TEXT(MONTH($P41),"00")),$O41,"") -> 44166667 | BF41: =SUM(Q41:U41) -> 0 | BG41: =SUM(V41:AG41) -> 397500000 | BH41: =SUM(AH41:AS41) -> 5.3e+08 | BI41: =SUM(AT41:BE41) -> 5.3e+08 | BJ41: =VLOOKUP(D41,Master!AD:AG,3,FALSE) -> 7611300 | BK41: =VLOOKUP(D41,Master!AD:AG,4,FALSE) -> Depreciation-Machiney & equipment
A42: 008 | B42: Fire Alarm system for fire hydrant | C42: Machinery & Equipment - New | D42: 2121000 | E42: 603300000 | F42: 120 | G42: Health, Safety & Environment | H42: 1 | I42: 44470 | J42: BIP | K42: Maintenance | M42: BGT.FY122 | N42: =H42*E42 -> 603300000 | O42: =N42/F42 -> 5027500 | P42: =DATE(YEAR(I42),MONTH(I42)+F42,DAY(I42)) -> 48122 | Q42: =IF(AND(LEFT(Q$1,FIND("_",Q$1)-1)&RIGHT(Q$1,LEN(Q$1)-FIND("_",Q$1)) >= YEAR($I42) & TEXT(MONTH($I42),"00"),LEFT(Q$1,FIND("_",Q$1)-1)&RIGHT(Q$1,LEN(Q$1)-FIND("_",Q$1)) < YEAR($P42) & TEXT(MONTH($P42),"00")),$O42,"") | R42: =IF(AND(LEFT(R$1,FIND("_",R$1)-1)&RIGHT(R$1,LEN(R$1)-FIND("_",R$1)) >= YEAR($I42) & TEXT(MONTH($I42),"00"),LEFT(R$1,FIND("_",R$1)-1)&RIGHT(R$1,LEN(R$1)-FIND("_",R$1)) < YEAR($P42) & TEXT(MONTH($P42),"00")),$O42,"") | S42: =IF(AND(LEFT(S$1,FIND("_",S$1)-1)&RIGHT(S$1,LEN(S$1)-FIND("_",S$1)) >= YEAR($I42) & TEXT(MONTH($I42),"00"),LEFT(S$1,FIND("_",S$1)-1)&RIGHT(S$1,LEN(S$1)-FIND("_",S$1)) < YEAR($P42) & TEXT(MONTH($P42),"00")),$O42,"") | T42: =IF(AND(LEFT(T$1,FIND("_",T$1)-1)&RIGHT(T$1,LEN(T$1)-FIND("_",T$1)) >= YEAR($I42) & TEXT(MONTH($I42),"00"),LEFT(T$1,FIND("_",T$1)-1)&RIGHT(T$1,LEN(T$1)-FIND("_",T$1)) < YEAR($P42) & TEXT(MONTH($P42),"00")),$O42,"") | U42: =IF(AND(LEFT(U$1,FIND("_",U$1)-1)&RIGHT(U$1,LEN(U$1)-FIND("_",U$1)) >= YEAR($I42) & TEXT(MONTH($I42),"00"),LEFT(U$1,FIND("_",U$1)-1)&RIGHT(U$1,LEN(U$1)-FIND("_",U$1)) < YEAR($P42) & TEXT(MONTH($P42),"00")),$O42,"") | V42: =IF(AND(LEFT(V$1,FIND("_",V$1)-1)&RIGHT(V$1,LEN(V$1)-FIND("_",V$1)) >= YEAR($I42) & TEXT(MONTH($I42),"00"),LEFT(V$1,FIND("_",V$1)-1)&RIGHT(V$1,LEN(V$1)-FIND("_",V$1)) < YEAR($P42) & TEXT(MONTH($P42),"00")),$O42,"") | W42: =IF(AND(LEFT(W$1,FIND("_",W$1)-1)&RIGHT(W$1,LEN(W$1)-FIND("_",W$1)) >= YEAR($I42) & TEXT(MONTH($I42),"00"),LEFT(W$1,FIND("_",W$1)-1)&RIGHT(W$1,LEN(W$1)-FIND("_",W$1)) < YEAR($P42) & TEXT(MONTH($P42),"00")),$O42,"") | X42: =IF(AND(LEFT(X$1,FIND("_",X$1)-1)&RIGHT(X$1,LEN(X$1)-FIND("_",X$1)) >= YEAR($I42) & TEXT(MONTH($I42),"00"),LEFT(X$1,FIND("_",X$1)-1)&RIGHT(X$1,LEN(X$1)-FIND("_",X$1)) < YEAR($P42) & TEXT(MONTH($P42),"00")),$O42,"") | ... BE42: =IF(AND(LEFT(BE$1,FIND("_",BE$1)-1)&RIGHT(BE$1,LEN(BE$1)-FIND("_",BE$1)) >= YEAR($I42) & TEXT(MONTH($I42),"00"),LEFT(BE$1,FIND("_",BE$1)-1)&RIGHT(BE$1,LEN(BE$1)-FIND("_",BE$1)) < YEAR($P42) & TEXT(MONTH($P42),"00")),$O42,"") -> 5027500 | BF42: =SUM(Q42:U42) -> 0 | BG42: =SUM(V42:AG42) -> 30165000 | BH42: =SUM(AH42:AS42) -> 60330000 | BI42: =SUM(AT42:BE42) -> 60330000 | BJ42: =VLOOKUP(D42,Master!AD:AG,3,FALSE) -> 7611300 | BK42: =VLOOKUP(D42,Master!AD:AG,4,FALSE) -> Depreciation-Machiney & equipment
A43: 009 | B43: Renovation Chemical Warehouse | C43: Building | D43: 2111100 | E43: 500000000 | F43: 240 | G43: WH Dept.- KD & RM | H43: 0.5 | I43: 44470 | J43: BIP | K43: Maintenance | L43: B | M43: BGT.FY122 | N43: =H43*E43 -> 250000000 | O43: =N43/F43 -> 1041666.7 | P43: =DATE(YEAR(I43),MONTH(I43)+F43,DAY(I43)) -> 51775 | Q43: =IF(AND(LEFT(Q$1,FIND("_",Q$1)-1)&RIGHT(Q$1,LEN(Q$1)-FIND("_",Q$1)) >= YEAR($I43) & TEXT(MONTH($I43),"00"),LEFT(Q$1,FIND("_",Q$1)-1)&RIGHT(Q$1,LEN(Q$1)-FIND("_",Q$1)) < YEAR($P43) & TEXT(MONTH($P43),"00")),$O43,"") | R43: =IF(AND(LEFT(R$1,FIND("_",R$1)-1)&RIGHT(R$1,LEN(R$1)-FIND("_",R$1)) >= YEAR($I43) & TEXT(MONTH($I43),"00"),LEFT(R$1,FIND("_",R$1)-1)&RIGHT(R$1,LEN(R$1)-FIND("_",R$1)) < YEAR($P43) & TEXT(MONTH($P43),"00")),$O43,"") | S43: =IF(AND(LEFT(S$1,FIND("_",S$1)-1)&RIGHT(S$1,LEN(S$1)-FIND("_",S$1)) >= YEAR($I43) & TEXT(MONTH($I43),"00"),LEFT(S$1,FIND("_",S$1)-1)&RIGHT(S$1,LEN(S$1)-FIND("_",S$1)) < YEAR($P43) & TEXT(MONTH($P43),"00")),$O43,"") | T43: =IF(AND(LEFT(T$1,FIND("_",T$1)-1)&RIGHT(T$1,LEN(T$1)-FIND("_",T$1)) >= YEAR($I43) & TEXT(MONTH($I43),"00"),LEFT(T$1,FIND("_",T$1)-1)&RIGHT(T$1,LEN(T$1)-FIND("_",T$1)) < YEAR($P43) & TEXT(MONTH($P43),"00")),$O43,"") | U43: =IF(AND(LEFT(U$1,FIND("_",U$1)-1)&RIGHT(U$1,LEN(U$1)-FIND("_",U$1)) >= YEAR($I43) & TEXT(MONTH($I43),"00"),LEFT(U$1,FIND("_",U$1)-1)&RIGHT(U$1,LEN(U$1)-FIND("_",U$1)) < YEAR($P43) & TEXT(MONTH($P43),"00")),$O43,"") | V43: =IF(AND(LEFT(V$1,FIND("_",V$1)-1)&RIGHT(V$1,LEN(V$1)-FIND("_",V$1)) >= YEAR($I43) & TEXT(MONTH($I43),"00"),LEFT(V$1,FIND("_",V$1)-1)&RIGHT(V$1,LEN(V$1)-FIND("_",V$1)) < YEAR($P43) & TEXT(MONTH($P43),"00")),$O43,"") | W43: =IF(AND(LEFT(W$1,FIND("_",W$1)-1)&RIGHT(W$1,LEN(W$1)-FIND("_",W$1)) >= YEAR($I43) & TEXT(MONTH($I43),"00"),LEFT(W$1,FIND("_",W$1)-1)&RIGHT(W$1,LEN(W$1)-FIND("_",W$1)) < YEAR($P43) & TEXT(MONTH($P43),"00")),$O43,"") | X43: =IF(AND(LEFT(X$1,FIND("_",X$1)-1)&RIGHT(X$1,LEN(X$1)-FIND("_",X$1)) >= YEAR($I43) & TEXT(MONTH($I43),"00"),LEFT(X$1,FIND("_",X$1)-1)&RIGHT(X$1,LEN(X$1)-FIND("_",X$1)) < YEAR($P43) & TEXT(MONTH($P43),"00")),$O43,"") | ... BE43: =IF(AND(LEFT(BE$1,FIND("_",BE$1)-1)&RIGHT(BE$1,LEN(BE$1)-FIND("_",BE$1)) >= YEAR($I43) & TEXT(MONTH($I43),"00"),LEFT(BE$1,FIND("_",BE$1)-1)&RIGHT(BE$1,LEN(BE$1)-FIND("_",BE$1)) < YEAR($P43) & TEXT(MONTH($P43),"00")),$O43,"") -> 1041666.7 | BF43: =SUM(Q43:U43) -> 0 | BG43: =SUM(V43:AG43) -> 6250000 | BH43: =SUM(AH43:AS43) -> 12500000 | BI43: =SUM(AT43:BE43) -> 12500000 | BJ43: =VLOOKUP(D43,Master!AD:AG,3,FALSE) -> 7611100 | BK43: =VLOOKUP(D43,Master!AD:AG,4,FALSE) -> Depreciation-Building
A44: 009 | B44: Renovation Chemical Warehouse | C44: Building | D44: 2111100 | E44: 500000000 | F44: 240 | G44: SP PD- Plating | H44: 0.5 | I44: 44470 | J44: BIP | K44: Maintenance | L44: B | M44: BGT.FY122 | N44: =H44*E44 -> 250000000 | O44: =N44/F44 -> 1041666.7 | P44: =DATE(YEAR(I44),MONTH(I44)+F44,DAY(I44)) -> 51775 | Q44: =IF(AND(LEFT(Q$1,FIND("_",Q$1)-1)&RIGHT(Q$1,LEN(Q$1)-FIND("_",Q$1)) >= YEAR($I44) & TEXT(MONTH($I44),"00"),LEFT(Q$1,FIND("_",Q$1)-1)&RIGHT(Q$1,LEN(Q$1)-FIND("_",Q$1)) < YEAR($P44) & TEXT(MONTH($P44),"00")),$O44,"") | R44: =IF(AND(LEFT(R$1,FIND("_",R$1)-1)&RIGHT(R$1,LEN(R$1)-FIND("_",R$1)) >= YEAR($I44) & TEXT(MONTH($I44),"00"),LEFT(R$1,FIND("_",R$1)-1)&RIGHT(R$1,LEN(R$1)-FIND("_",R$1)) < YEAR($P44) & TEXT(MONTH($P44),"00")),$O44,"") | S44: =IF(AND(LEFT(S$1,FIND("_",S$1)-1)&RIGHT(S$1,LEN(S$1)-FIND("_",S$1)) >= YEAR($I44) & TEXT(MONTH($I44),"00"),LEFT(S$1,FIND("_",S$1)-1)&RIGHT(S$1,LEN(S$1)-FIND("_",S$1)) < YEAR($P44) & TEXT(MONTH($P44),"00")),$O44,"") | T44: =IF(AND(LEFT(T$1,FIND("_",T$1)-1)&RIGHT(T$1,LEN(T$1)-FIND("_",T$1)) >= YEAR($I44) & TEXT(MONTH($I44),"00"),LEFT(T$1,FIND("_",T$1)-1)&RIGHT(T$1,LEN(T$1)-FIND("_",T$1)) < YEAR($P44) & TEXT(MONTH($P44),"00")),$O44,"") | U44: =IF(AND(LEFT(U$1,FIND("_",U$1)-1)&RIGHT(U$1,LEN(U$1)-FIND("_",U$1)) >= YEAR($I44) & TEXT(MONTH($I44),"00"),LEFT(U$1,FIND("_",U$1)-1)&RIGHT(U$1,LEN(U$1)-FIND("_",U$1)) < YEAR($P44) & TEXT(MONTH($P44),"00")),$O44,"") | V44: =IF(AND(LEFT(V$1,FIND("_",V$1)-1)&RIGHT(V$1,LEN(V$1)-FIND("_",V$1)) >= YEAR($I44) & TEXT(MONTH($I44),"00"),LEFT(V$1,FIND("_",V$1)-1)&RIGHT(V$1,LEN(V$1)-FIND("_",V$1)) < YEAR($P44) & TEXT(MONTH($P44),"00")),$O44,"") | W44: =IF(AND(LEFT(W$1,FIND("_",W$1)-1)&RIGHT(W$1,LEN(W$1)-FIND("_",W$1)) >= YEAR($I44) & TEXT(MONTH($I44),"00"),LEFT(W$1,FIND("_",W$1)-1)&RIGHT(W$1,LEN(W$1)-FIND("_",W$1)) < YEAR($P44) & TEXT(MONTH($P44),"00")),$O44,"") | X44: =IF(AND(LEFT(X$1,FIND("_",X$1)-1)&RIGHT(X$1,LEN(X$1)-FIND("_",X$1)) >= YEAR($I44) & TEXT(MONTH($I44),"00"),LEFT(X$1,FIND("_",X$1)-1)&RIGHT(X$1,LEN(X$1)-FIND("_",X$1)) < YEAR($P44) & TEXT(MONTH($P44),"00")),$O44,"") | ... BE44: =IF(AND(LEFT(BE$1,FIND("_",BE$1)-1)&RIGHT(BE$1,LEN(BE$1)-FIND("_",BE$1)) >= YEAR($I44) & TEXT(MONTH($I44),"00"),LEFT(BE$1,FIND("_",BE$1)-1)&RIGHT(BE$1,LEN(BE$1)-FIND("_",BE$1)) < YEAR($P44) & TEXT(MONTH($P44),"00")),$O44,"") -> 1041666.7 | BF44: =SUM(Q44:U44) -> 0 | BG44: =SUM(V44:AG44) -> 6250000 | BH44: =SUM(AH44:AS44) -> 12500000 | BI44: =SUM(AT44:BE44) -> 12500000 | BJ44: =VLOOKUP(D44,Master!AD:AG,3,FALSE) -> 7611100 | BK44: =VLOOKUP(D44,Master!AD:AG,4,FALSE) -> Depreciation-Building
A45: 010 | B45: Compressor 37kW No .4 | C45: Machinery & Equipment - New | D45: 2121000 | E45: 500000000 | F45: 120 | G45: Maintenance | H45: 1 | I45: 44531 | J45: BIP | K45: Maintenance | L45: B | M45: BGT.FY122 | N45: =H45*E45 -> 500000000 | O45: =N45/F45 -> 4166666.7 | P45: =DATE(YEAR(I45),MONTH(I45)+F45,DAY(I45)) -> 48183 | Q45: =IF(AND(LEFT(Q$1,FIND("_",Q$1)-1)&RIGHT(Q$1,LEN(Q$1)-FIND("_",Q$1)) >= YEAR($I45) & TEXT(MONTH($I45),"00"),LEFT(Q$1,FIND("_",Q$1)-1)&RIGHT(Q$1,LEN(Q$1)-FIND("_",Q$1)) < YEAR($P45) & TEXT(MONTH($P45),"00")),$O45,"") | R45: =IF(AND(LEFT(R$1,FIND("_",R$1)-1)&RIGHT(R$1,LEN(R$1)-FIND("_",R$1)) >= YEAR($I45) & TEXT(MONTH($I45),"00"),LEFT(R$1,FIND("_",R$1)-1)&RIGHT(R$1,LEN(R$1)-FIND("_",R$1)) < YEAR($P45) & TEXT(MONTH($P45),"00")),$O45,"") | S45: =IF(AND(LEFT(S$1,FIND("_",S$1)-1)&RIGHT(S$1,LEN(S$1)-FIND("_",S$1)) >= YEAR($I45) & TEXT(MONTH($I45),"00"),LEFT(S$1,FIND("_",S$1)-1)&RIGHT(S$1,LEN(S$1)-FIND("_",S$1)) < YEAR($P45) & TEXT(MONTH($P45),"00")),$O45,"") | T45: =IF(AND(LEFT(T$1,FIND("_",T$1)-1)&RIGHT(T$1,LEN(T$1)-FIND("_",T$1)) >= YEAR($I45) & TEXT(MONTH($I45),"00"),LEFT(T$1,FIND("_",T$1)-1)&RIGHT(T$1,LEN(T$1)-FIND("_",T$1)) < YEAR($P45) & TEXT(MONTH($P45),"00")),$O45,"") | U45: =IF(AND(LEFT(U$1,FIND("_",U$1)-1)&RIGHT(U$1,LEN(U$1)-FIND("_",U$1)) >= YEAR($I45) & TEXT(MONTH($I45),"00"),LEFT(U$1,FIND("_",U$1)-1)&RIGHT(U$1,LEN(U$1)-FIND("_",U$1)) < YEAR($P45) & TEXT(MONTH($P45),"00")),$O45,"") | V45: =IF(AND(LEFT(V$1,FIND("_",V$1)-1)&RIGHT(V$1,LEN(V$1)-FIND("_",V$1)) >= YEAR($I45) & TEXT(MONTH($I45),"00"),LEFT(V$1,FIND("_",V$1)-1)&RIGHT(V$1,LEN(V$1)-FIND("_",V$1)) < YEAR($P45) & TEXT(MONTH($P45),"00")),$O45,"") | W45: =IF(AND(LEFT(W$1,FIND("_",W$1)-1)&RIGHT(W$1,LEN(W$1)-FIND("_",W$1)) >= YEAR($I45) & TEXT(MONTH($I45),"00"),LEFT(W$1,FIND("_",W$1)-1)&RIGHT(W$1,LEN(W$1)-FIND("_",W$1)) < YEAR($P45) & TEXT(MONTH($P45),"00")),$O45,"") | X45: =IF(AND(LEFT(X$1,FIND("_",X$1)-1)&RIGHT(X$1,LEN(X$1)-FIND("_",X$1)) >= YEAR($I45) & TEXT(MONTH($I45),"00"),LEFT(X$1,FIND("_",X$1)-1)&RIGHT(X$1,LEN(X$1)-FIND("_",X$1)) < YEAR($P45) & TEXT(MONTH($P45),"00")),$O45,"") | ... BE45: =IF(AND(LEFT(BE$1,FIND("_",BE$1)-1)&RIGHT(BE$1,LEN(BE$1)-FIND("_",BE$1)) >= YEAR($I45) & TEXT(MONTH($I45),"00"),LEFT(BE$1,FIND("_",BE$1)-1)&RIGHT(BE$1,LEN(BE$1)-FIND("_",BE$1)) < YEAR($P45) & TEXT(MONTH($P45),"00")),$O45,"") -> 4166666.7 | BF45: =SUM(Q45:U45) -> 0 | BG45: =SUM(V45:AG45) -> 16666667 | BH45: =SUM(AH45:AS45) -> 50000000 | BI45: =SUM(AT45:BE45) -> 50000000 | BJ45: =VLOOKUP(D45,Master!AD:AG,3,FALSE) -> 7611300 | BK45: =VLOOKUP(D45,Master!AD:AG,4,FALSE) -> Depreciation-Machiney & equipment
A46: 011 | B46: Drier Compressor No.4 | C46: Machinery & Equipment - New | D46: 2121000 | E46: 100000000 | F46: 120 | G46: Maintenance | H46: 1 | I46: 44531 | J46: BIP | K46: Maintenance | L46: B | M46: BGT.FY122 | N46: =H46*E46 -> 100000000 | O46: =N46/F46 -> 833333.33 | P46: =DATE(YEAR(I46),MONTH(I46)+F46,DAY(I46)) -> 48183 | Q46: =IF(AND(LEFT(Q$1,FIND("_",Q$1)-1)&RIGHT(Q$1,LEN(Q$1)-FIND("_",Q$1)) >= YEAR($I46) & TEXT(MONTH($I46),"00"),LEFT(Q$1,FIND("_",Q$1)-1)&RIGHT(Q$1,LEN(Q$1)-FIND("_",Q$1)) < YEAR($P46) & TEXT(MONTH($P46),"00")),$O46,"") | R46: =IF(AND(LEFT(R$1,FIND("_",R$1)-1)&RIGHT(R$1,LEN(R$1)-FIND("_",R$1)) >= YEAR($I46) & TEXT(MONTH($I46),"00"),LEFT(R$1,FIND("_",R$1)-1)&RIGHT(R$1,LEN(R$1)-FIND("_",R$1)) < YEAR($P46) & TEXT(MONTH($P46),"00")),$O46,"") | S46: =IF(AND(LEFT(S$1,FIND("_",S$1)-1)&RIGHT(S$1,LEN(S$1)-FIND("_",S$1)) >= YEAR($I46) & TEXT(MONTH($I46),"00"),LEFT(S$1,FIND("_",S$1)-1)&RIGHT(S$1,LEN(S$1)-FIND("_",S$1)) < YEAR($P46) & TEXT(MONTH($P46),"00")),$O46,"") | T46: =IF(AND(LEFT(T$1,FIND("_",T$1)-1)&RIGHT(T$1,LEN(T$1)-FIND("_",T$1)) >= YEAR($I46) & TEXT(MONTH($I46),"00"),LEFT(T$1,FIND("_",T$1)-1)&RIGHT(T$1,LEN(T$1)-FIND("_",T$1)) < YEAR($P46) & TEXT(MONTH($P46),"00")),$O46,"") | U46: =IF(AND(LEFT(U$1,FIND("_",U$1)-1)&RIGHT(U$1,LEN(U$1)-FIND("_",U$1)) >= YEAR($I46) & TEXT(MONTH($I46),"00"),LEFT(U$1,FIND("_",U$1)-1)&RIGHT(U$1,LEN(U$1)-FIND("_",U$1)) < YEAR($P46) & TEXT(MONTH($P46),"00")),$O46,"") | V46: =IF(AND(LEFT(V$1,FIND("_",V$1)-1)&RIGHT(V$1,LEN(V$1)-FIND("_",V$1)) >= YEAR($I46) & TEXT(MONTH($I46),"00"),LEFT(V$1,FIND("_",V$1)-1)&RIGHT(V$1,LEN(V$1)-FIND("_",V$1)) < YEAR($P46) & TEXT(MONTH($P46),"00")),$O46,"") | W46: =IF(AND(LEFT(W$1,FIND("_",W$1)-1)&RIGHT(W$1,LEN(W$1)-FIND("_",W$1)) >= YEAR($I46) & TEXT(MONTH($I46),"00"),LEFT(W$1,FIND("_",W$1)-1)&RIGHT(W$1,LEN(W$1)-FIND("_",W$1)) < YEAR($P46) & TEXT(MONTH($P46),"00")),$O46,"") | X46: =IF(AND(LEFT(X$1,FIND("_",X$1)-1)&RIGHT(X$1,LEN(X$1)-FIND("_",X$1)) >= YEAR($I46) & TEXT(MONTH($I46),"00"),LEFT(X$1,FIND("_",X$1)-1)&RIGHT(X$1,LEN(X$1)-FIND("_",X$1)) < YEAR($P46) & TEXT(MONTH($P46),"00")),$O46,"") | ... BE46: =IF(AND(LEFT(BE$1,FIND("_",BE$1)-1)&RIGHT(BE$1,LEN(BE$1)-FIND("_",BE$1)) >= YEAR($I46) & TEXT(MONTH($I46),"00"),LEFT(BE$1,FIND("_",BE$1)-1)&RIGHT(BE$1,LEN(BE$1)-FIND("_",BE$1)) < YEAR($P46) & TEXT(MONTH($P46),"00")),$O46,"") -> 833333.33 | BF46: =SUM(Q46:U46) -> 0 | BG46: =SUM(V46:AG46) -> 3333333.3 | BH46: =SUM(AH46:AS46) -> 10000000 | BI46: =SUM(AT46:BE46) -> 10000000 | BJ46: =VLOOKUP(D46,Master!AD:AG,3,FALSE) -> 7611300 | BK46: =VLOOKUP(D46,Master!AD:AG,4,FALSE) -> Depreciation-Machiney & equipment
A47: 012 | B47: Rack for Increase Capacity WH Finish Good | C47: Tools, furniture & office equipment | D47: 2141000 | E47: 275000000 | F47: 60 | G47: SCM - FG WH | H47: 1 | I47: 44621 | J47: BIP | K47: Maintenance | L47: B | M47: BGT.FY122 | N47: =H47*E47 -> 275000000 | O47: =N47/F47 -> 4583333.3 | P47: =DATE(YEAR(I47),MONTH(I47)+F47,DAY(I47)) -> 46447 | Q47: =IF(AND(LEFT(Q$1,FIND("_",Q$1)-1)&RIGHT(Q$1,LEN(Q$1)-FIND("_",Q$1)) >= YEAR($I47) & TEXT(MONTH($I47),"00"),LEFT(Q$1,FIND("_",Q$1)-1)&RIGHT(Q$1,LEN(Q$1)-FIND("_",Q$1)) < YEAR($P47) & TEXT(MONTH($P47),"00")),$O47,"") | R47: =IF(AND(LEFT(R$1,FIND("_",R$1)-1)&RIGHT(R$1,LEN(R$1)-FIND("_",R$1)) >= YEAR($I47) & TEXT(MONTH($I47),"00"),LEFT(R$1,FIND("_",R$1)-1)&RIGHT(R$1,LEN(R$1)-FIND("_",R$1)) < YEAR($P47) & TEXT(MONTH($P47),"00")),$O47,"") | S47: =IF(AND(LEFT(S$1,FIND("_",S$1)-1)&RIGHT(S$1,LEN(S$1)-FIND("_",S$1)) >= YEAR($I47) & TEXT(MONTH($I47),"00"),LEFT(S$1,FIND("_",S$1)-1)&RIGHT(S$1,LEN(S$1)-FIND("_",S$1)) < YEAR($P47) & TEXT(MONTH($P47),"00")),$O47,"") | T47: =IF(AND(LEFT(T$1,FIND("_",T$1)-1)&RIGHT(T$1,LEN(T$1)-FIND("_",T$1)) >= YEAR($I47) & TEXT(MONTH($I47),"00"),LEFT(T$1,FIND("_",T$1)-1)&RIGHT(T$1,LEN(T$1)-FIND("_",T$1)) < YEAR($P47) & TEXT(MONTH($P47),"00")),$O47,"") | U47: =IF(AND(LEFT(U$1,FIND("_",U$1)-1)&RIGHT(U$1,LEN(U$1)-FIND("_",U$1)) >= YEAR($I47) & TEXT(MONTH($I47),"00"),LEFT(U$1,FIND("_",U$1)-1)&RIGHT(U$1,LEN(U$1)-FIND("_",U$1)) < YEAR($P47) & TEXT(MONTH($P47),"00")),$O47,"") | V47: =IF(AND(LEFT(V$1,FIND("_",V$1)-1)&RIGHT(V$1,LEN(V$1)-FIND("_",V$1)) >= YEAR($I47) & TEXT(MONTH($I47),"00"),LEFT(V$1,FIND("_",V$1)-1)&RIGHT(V$1,LEN(V$1)-FIND("_",V$1)) < YEAR($P47) & TEXT(MONTH($P47),"00")),$O47,"") | W47: =IF(AND(LEFT(W$1,FIND("_",W$1)-1)&RIGHT(W$1,LEN(W$1)-FIND("_",W$1)) >= YEAR($I47) & TEXT(MONTH($I47),"00"),LEFT(W$1,FIND("_",W$1)-1)&RIGHT(W$1,LEN(W$1)-FIND("_",W$1)) < YEAR($P47) & TEXT(MONTH($P47),"00")),$O47,"") | X47: =IF(AND(LEFT(X$1,FIND("_",X$1)-1)&RIGHT(X$1,LEN(X$1)-FIND("_",X$1)) >= YEAR($I47) & TEXT(MONTH($I47),"00"),LEFT(X$1,FIND("_",X$1)-1)&RIGHT(X$1,LEN(X$1)-FIND("_",X$1)) < YEAR($P47) & TEXT(MONTH($P47),"00")),$O47,"") | ... BE47: =IF(AND(LEFT(BE$1,FIND("_",BE$1)-1)&RIGHT(BE$1,LEN(BE$1)-FIND("_",BE$1)) >= YEAR($I47) & TEXT(MONTH($I47),"00"),LEFT(BE$1,FIND("_",BE$1)-1)&RIGHT(BE$1,LEN(BE$1)-FIND("_",BE$1)) < YEAR($P47) & TEXT(MONTH($P47),"00")),$O47,"") -> 4583333.3 | BF47: =SUM(Q47:U47) -> 0 | BG47: =SUM(V47:AG47) -> 4583333.3 | BH47: =SUM(AH47:AS47) -> 55000000 | BI47: =SUM(AT47:BE47) -> 55000000 | BJ47: =VLOOKUP(D47,Master!AD:AG,3,FALSE) -> 7611600 | BK47: =VLOOKUP(D47,Master!AD:AG,4,FALSE) -> Depreciation-Tools, furniture & office equipment
A48: 013 | B48: Replace AC CFC became AC Non CFC | C48: Tools, furniture & office equipment | D48: 2141000 | E48: 205000000 | F48: 60 | G48: General Affair | H48: 1 | I48: 44621 | J48: BIP | K48: Maintenance | L48: B | M48: BGT.FY122 | N48: =H48*E48 -> 205000000 | O48: =N48/F48 -> 3416666.7 | P48: =DATE(YEAR(I48),MONTH(I48)+F48,DAY(I48)) -> 46447 | Q48: =IF(AND(LEFT(Q$1,FIND("_",Q$1)-1)&RIGHT(Q$1,LEN(Q$1)-FIND("_",Q$1)) >= YEAR($I48) & TEXT(MONTH($I48),"00"),LEFT(Q$1,FIND("_",Q$1)-1)&RIGHT(Q$1,LEN(Q$1)-FIND("_",Q$1)) < YEAR($P48) & TEXT(MONTH($P48),"00")),$O48,"") | R48: =IF(AND(LEFT(R$1,FIND("_",R$1)-1)&RIGHT(R$1,LEN(R$1)-FIND("_",R$1)) >= YEAR($I48) & TEXT(MONTH($I48),"00"),LEFT(R$1,FIND("_",R$1)-1)&RIGHT(R$1,LEN(R$1)-FIND("_",R$1)) < YEAR($P48) & TEXT(MONTH($P48),"00")),$O48,"") | S48: =IF(AND(LEFT(S$1,FIND("_",S$1)-1)&RIGHT(S$1,LEN(S$1)-FIND("_",S$1)) >= YEAR($I48) & TEXT(MONTH($I48),"00"),LEFT(S$1,FIND("_",S$1)-1)&RIGHT(S$1,LEN(S$1)-FIND("_",S$1)) < YEAR($P48) & TEXT(MONTH($P48),"00")),$O48,"") | T48: =IF(AND(LEFT(T$1,FIND("_",T$1)-1)&RIGHT(T$1,LEN(T$1)-FIND("_",T$1)) >= YEAR($I48) & TEXT(MONTH($I48),"00"),LEFT(T$1,FIND("_",T$1)-1)&RIGHT(T$1,LEN(T$1)-FIND("_",T$1)) < YEAR($P48) & TEXT(MONTH($P48),"00")),$O48,"") | U48: =IF(AND(LEFT(U$1,FIND("_",U$1)-1)&RIGHT(U$1,LEN(U$1)-FIND("_",U$1)) >= YEAR($I48) & TEXT(MONTH($I48),"00"),LEFT(U$1,FIND("_",U$1)-1)&RIGHT(U$1,LEN(U$1)-FIND("_",U$1)) < YEAR($P48) & TEXT(MONTH($P48),"00")),$O48,"") | V48: =IF(AND(LEFT(V$1,FIND("_",V$1)-1)&RIGHT(V$1,LEN(V$1)-FIND("_",V$1)) >= YEAR($I48) & TEXT(MONTH($I48),"00"),LEFT(V$1,FIND("_",V$1)-1)&RIGHT(V$1,LEN(V$1)-FIND("_",V$1)) < YEAR($P48) & TEXT(MONTH($P48),"00")),$O48,"") | W48: =IF(AND(LEFT(W$1,FIND("_",W$1)-1)&RIGHT(W$1,LEN(W$1)-FIND("_",W$1)) >= YEAR($I48) & TEXT(MONTH($I48),"00"),LEFT(W$1,FIND("_",W$1)-1)&RIGHT(W$1,LEN(W$1)-FIND("_",W$1)) < YEAR($P48) & TEXT(MONTH($P48),"00")),$O48,"") | X48: =IF(AND(LEFT(X$1,FIND("_",X$1)-1)&RIGHT(X$1,LEN(X$1)-FIND("_",X$1)) >= YEAR($I48) & TEXT(MONTH($I48),"00"),LEFT(X$1,FIND("_",X$1)-1)&RIGHT(X$1,LEN(X$1)-FIND("_",X$1)) < YEAR($P48) & TEXT(MONTH($P48),"00")),$O48,"") | ... BE48: =IF(AND(LEFT(BE$1,FIND("_",BE$1)-1)&RIGHT(BE$1,LEN(BE$1)-FIND("_",BE$1)) >= YEAR($I48) & TEXT(MONTH($I48),"00"),LEFT(BE$1,FIND("_",BE$1)-1)&RIGHT(BE$1,LEN(BE$1)-FIND("_",BE$1)) < YEAR($P48) & TEXT(MONTH($P48),"00")),$O48,"") -> 3416666.7 | BF48: =SUM(Q48:U48) -> 0 | BG48: =SUM(V48:AG48) -> 3416666.7 | BH48: =SUM(AH48:AS48) -> 41000000 | BI48: =SUM(AT48:BE48) -> 41000000 | BJ48: =VLOOKUP(D48,Master!AD:AG,3,FALSE) -> 7611600 | BK48: =VLOOKUP(D48,Master!AD:AG,4,FALSE) -> Depreciation-Tools, furniture & office equipment
A49: 014 | B49: PC Nugroho Budi | C49: Tools, furniture & office equipment | D49: 2141000 | E49: 10000000 | F49: 60 | G49: Maintenance | H49: 1 | I49: 44743 | J49: BIP | K49: Maintenance | L49: B | M49: BGT.FY123 | N49: =H49*E49 -> 10000000 | O49: =N49/F49 -> 166666.67 | P49: =DATE(YEAR(I49),MONTH(I49)+F49,DAY(I49)) -> 46569 | Q49: =IF(AND(LEFT(Q$1,FIND("_",Q$1)-1)&RIGHT(Q$1,LEN(Q$1)-FIND("_",Q$1)) >= YEAR($I49) & TEXT(MONTH($I49),"00"),LEFT(Q$1,FIND("_",Q$1)-1)&RIGHT(Q$1,LEN(Q$1)-FIND("_",Q$1)) < YEAR($P49) & TEXT(MONTH($P49),"00")),$O49,"") | R49: =IF(AND(LEFT(R$1,FIND("_",R$1)-1)&RIGHT(R$1,LEN(R$1)-FIND("_",R$1)) >= YEAR($I49) & TEXT(MONTH($I49),"00"),LEFT(R$1,FIND("_",R$1)-1)&RIGHT(R$1,LEN(R$1)-FIND("_",R$1)) < YEAR($P49) & TEXT(MONTH($P49),"00")),$O49,"") | S49: =IF(AND(LEFT(S$1,FIND("_",S$1)-1)&RIGHT(S$1,LEN(S$1)-FIND("_",S$1)) >= YEAR($I49) & TEXT(MONTH($I49),"00"),LEFT(S$1,FIND("_",S$1)-1)&RIGHT(S$1,LEN(S$1)-FIND("_",S$1)) < YEAR($P49) & TEXT(MONTH($P49),"00")),$O49,"") | T49: =IF(AND(LEFT(T$1,FIND("_",T$1)-1)&RIGHT(T$1,LEN(T$1)-FIND("_",T$1)) >= YEAR($I49) & TEXT(MONTH($I49),"00"),LEFT(T$1,FIND("_",T$1)-1)&RIGHT(T$1,LEN(T$1)-FIND("_",T$1)) < YEAR($P49) & TEXT(MONTH($P49),"00")),$O49,"") | U49: =IF(AND(LEFT(U$1,FIND("_",U$1)-1)&RIGHT(U$1,LEN(U$1)-FIND("_",U$1)) >= YEAR($I49) & TEXT(MONTH($I49),"00"),LEFT(U$1,FIND("_",U$1)-1)&RIGHT(U$1,LEN(U$1)-FIND("_",U$1)) < YEAR($P49) & TEXT(MONTH($P49),"00")),$O49,"") | V49: =IF(AND(LEFT(V$1,FIND("_",V$1)-1)&RIGHT(V$1,LEN(V$1)-FIND("_",V$1)) >= YEAR($I49) & TEXT(MONTH($I49),"00"),LEFT(V$1,FIND("_",V$1)-1)&RIGHT(V$1,LEN(V$1)-FIND("_",V$1)) < YEAR($P49) & TEXT(MONTH($P49),"00")),$O49,"") | W49: =IF(AND(LEFT(W$1,FIND("_",W$1)-1)&RIGHT(W$1,LEN(W$1)-FIND("_",W$1)) >= YEAR($I49) & TEXT(MONTH($I49),"00"),LEFT(W$1,FIND("_",W$1)-1)&RIGHT(W$1,LEN(W$1)-FIND("_",W$1)) < YEAR($P49) & TEXT(MONTH($P49),"00")),$O49,"") | X49: =IF(AND(LEFT(X$1,FIND("_",X$1)-1)&RIGHT(X$1,LEN(X$1)-FIND("_",X$1)) >= YEAR($I49) & TEXT(MONTH($I49),"00"),LEFT(X$1,FIND("_",X$1)-1)&RIGHT(X$1,LEN(X$1)-FIND("_",X$1)) < YEAR($P49) & TEXT(MONTH($P49),"00")),$O49,"") | ... BE49: =IF(AND(LEFT(BE$1,FIND("_",BE$1)-1)&RIGHT(BE$1,LEN(BE$1)-FIND("_",BE$1)) >= YEAR($I49) & TEXT(MONTH($I49),"00"),LEFT(BE$1,FIND("_",BE$1)-1)&RIGHT(BE$1,LEN(BE$1)-FIND("_",BE$1)) < YEAR($P49) & TEXT(MONTH($P49),"00")),$O49,"") -> 166666.67 | BF49: =SUM(Q49:U49) -> 0 | BG49: =SUM(V49:AG49) -> 0 | BH49: =SUM(AH49:AS49) -> 1500000 | BI49: =SUM(AT49:BE49) -> 2000000 | BJ49: =VLOOKUP(D49,Master!AD:AG,3,FALSE) -> 7611600 | BK49: =VLOOKUP(D49,Master!AD:AG,4,FALSE) -> Depreciation-Tools, furniture & office equipment
A50: 015 | B50: PC Nugraha Agus | C50: Tools, furniture & office equipment | D50: 2141000 | E50: 8000000 | F50: 60 | G50: Maintenance | H50: 1 | I50: 44774 | J50: BIP | K50: Maintenance | L50: B | M50: BGT.FY123 | N50: =H50*E50 -> 8000000 | O50: =N50/F50 -> 133333.33 | P50: =DATE(YEAR(I50),MONTH(I50)+F50,DAY(I50)) -> 46600 | Q50: =IF(AND(LEFT(Q$1,FIND("_",Q$1)-1)&RIGHT(Q$1,LEN(Q$1)-FIND("_",Q$1)) >= YEAR($I50) & TEXT(MONTH($I50),"00"),LEFT(Q$1,FIND("_",Q$1)-1)&RIGHT(Q$1,LEN(Q$1)-FIND("_",Q$1)) < YEAR($P50) & TEXT(MONTH($P50),"00")),$O50,"") | R50: =IF(AND(LEFT(R$1,FIND("_",R$1)-1)&RIGHT(R$1,LEN(R$1)-FIND("_",R$1)) >= YEAR($I50) & TEXT(MONTH($I50),"00"),LEFT(R$1,FIND("_",R$1)-1)&RIGHT(R$1,LEN(R$1)-FIND("_",R$1)) < YEAR($P50) & TEXT(MONTH($P50),"00")),$O50,"") | S50: =IF(AND(LEFT(S$1,FIND("_",S$1)-1)&RIGHT(S$1,LEN(S$1)-FIND("_",S$1)) >= YEAR($I50) & TEXT(MONTH($I50),"00"),LEFT(S$1,FIND("_",S$1)-1)&RIGHT(S$1,LEN(S$1)-FIND("_",S$1)) < YEAR($P50) & TEXT(MONTH($P50),"00")),$O50,"") | T50: =IF(AND(LEFT(T$1,FIND("_",T$1)-1)&RIGHT(T$1,LEN(T$1)-FIND("_",T$1)) >= YEAR($I50) & TEXT(MONTH($I50),"00"),LEFT(T$1,FIND("_",T$1)-1)&RIGHT(T$1,LEN(T$1)-FIND("_",T$1)) < YEAR($P50) & TEXT(MONTH($P50),"00")),$O50,"") | U50: =IF(AND(LEFT(U$1,FIND("_",U$1)-1)&RIGHT(U$1,LEN(U$1)-FIND("_",U$1)) >= YEAR($I50) & TEXT(MONTH($I50),"00"),LEFT(U$1,FIND("_",U$1)-1)&RIGHT(U$1,LEN(U$1)-FIND("_",U$1)) < YEAR($P50) & TEXT(MONTH($P50),"00")),$O50,"") | V50: =IF(AND(LEFT(V$1,FIND("_",V$1)-1)&RIGHT(V$1,LEN(V$1)-FIND("_",V$1)) >= YEAR($I50) & TEXT(MONTH($I50),"00"),LEFT(V$1,FIND("_",V$1)-1)&RIGHT(V$1,LEN(V$1)-FIND("_",V$1)) < YEAR($P50) & TEXT(MONTH($P50),"00")),$O50,"") | W50: =IF(AND(LEFT(W$1,FIND("_",W$1)-1)&RIGHT(W$1,LEN(W$1)-FIND("_",W$1)) >= YEAR($I50) & TEXT(MONTH($I50),"00"),LEFT(W$1,FIND("_",W$1)-1)&RIGHT(W$1,LEN(W$1)-FIND("_",W$1)) < YEAR($P50) & TEXT(MONTH($P50),"00")),$O50,"") | X50: =IF(AND(LEFT(X$1,FIND("_",X$1)-1)&RIGHT(X$1,LEN(X$1)-FIND("_",X$1)) >= YEAR($I50) & TEXT(MONTH($I50),"00"),LEFT(X$1,FIND("_",X$1)-1)&RIGHT(X$1,LEN(X$1)-FIND("_",X$1)) < YEAR($P50) & TEXT(MONTH($P50),"00")),$O50,"") | ... BE50: =IF(AND(LEFT(BE$1,FIND("_",BE$1)-1)&RIGHT(BE$1,LEN(BE$1)-FIND("_",BE$1)) >= YEAR($I50) & TEXT(MONTH($I50),"00"),LEFT(BE$1,FIND("_",BE$1)-1)&RIGHT(BE$1,LEN(BE$1)-FIND("_",BE$1)) < YEAR($P50) & TEXT(MONTH($P50),"00")),$O50,"") -> 133333.33 | BF50: =SUM(Q50:U50) -> 0 | BG50: =SUM(V50:AG50) -> 0 | BH50: =SUM(AH50:AS50) -> 1066666.7 | BI50: =SUM(AT50:BE50) -> 1600000 | BJ50: =VLOOKUP(D50,Master!AD:AG,3,FALSE) -> 7611600 | BK50: =VLOOKUP(D50,Master!AD:AG,4,FALSE) -> Depreciation-Tools, furniture & office equipment
A51: 016 | B51: Emergency Exit Access | C51: Building | D51: 2111100 | E51: 100000000 | F51: 240 | G51: Health, Safety & Environment | H51: 1 | I51: 44774 | J51: BIP | K51: Maintenance | L51: C | M51: BGT.FY123 | N51: =H51*E51 -> 100000000 | O51: =N51/F51 -> 416666.67 | P51: =DATE(YEAR(I51),MONTH(I51)+F51,DAY(I51)) -> 52079 | Q51: =IF(AND(LEFT(Q$1,FIND("_",Q$1)-1)&RIGHT(Q$1,LEN(Q$1)-FIND("_",Q$1)) >= YEAR($I51) & TEXT(MONTH($I51),"00"),LEFT(Q$1,FIND("_",Q$1)-1)&RIGHT(Q$1,LEN(Q$1)-FIND("_",Q$1)) < YEAR($P51) & TEXT(MONTH($P51),"00")),$O51,"") | R51: =IF(AND(LEFT(R$1,FIND("_",R$1)-1)&RIGHT(R$1,LEN(R$1)-FIND("_",R$1)) >= YEAR($I51) & TEXT(MONTH($I51),"00"),LEFT(R$1,FIND("_",R$1)-1)&RIGHT(R$1,LEN(R$1)-FIND("_",R$1)) < YEAR($P51) & TEXT(MONTH($P51),"00")),$O51,"") | S51: =IF(AND(LEFT(S$1,FIND("_",S$1)-1)&RIGHT(S$1,LEN(S$1)-FIND("_",S$1)) >= YEAR($I51) & TEXT(MONTH($I51),"00"),LEFT(S$1,FIND("_",S$1)-1)&RIGHT(S$1,LEN(S$1)-FIND("_",S$1)) < YEAR($P51) & TEXT(MONTH($P51),"00")),$O51,"") | T51: =IF(AND(LEFT(T$1,FIND("_",T$1)-1)&RIGHT(T$1,LEN(T$1)-FIND("_",T$1)) >= YEAR($I51) & TEXT(MONTH($I51),"00"),LEFT(T$1,FIND("_",T$1)-1)&RIGHT(T$1,LEN(T$1)-FIND("_",T$1)) < YEAR($P51) & TEXT(MONTH($P51),"00")),$O51,"") | U51: =IF(AND(LEFT(U$1,FIND("_",U$1)-1)&RIGHT(U$1,LEN(U$1)-FIND("_",U$1)) >= YEAR($I51) & TEXT(MONTH($I51),"00"),LEFT(U$1,FIND("_",U$1)-1)&RIGHT(U$1,LEN(U$1)-FIND("_",U$1)) < YEAR($P51) & TEXT(MONTH($P51),"00")),$O51,"") | V51: =IF(AND(LEFT(V$1,FIND("_",V$1)-1)&RIGHT(V$1,LEN(V$1)-FIND("_",V$1)) >= YEAR($I51) & TEXT(MONTH($I51),"00"),LEFT(V$1,FIND("_",V$1)-1)&RIGHT(V$1,LEN(V$1)-FIND("_",V$1)) < YEAR($P51) & TEXT(MONTH($P51),"00")),$O51,"") | W51: =IF(AND(LEFT(W$1,FIND("_",W$1)-1)&RIGHT(W$1,LEN(W$1)-FIND("_",W$1)) >= YEAR($I51) & TEXT(MONTH($I51),"00"),LEFT(W$1,FIND("_",W$1)-1)&RIGHT(W$1,LEN(W$1)-FIND("_",W$1)) < YEAR($P51) & TEXT(MONTH($P51),"00")),$O51,"") | X51: =IF(AND(LEFT(X$1,FIND("_",X$1)-1)&RIGHT(X$1,LEN(X$1)-FIND("_",X$1)) >= YEAR($I51) & TEXT(MONTH($I51),"00"),LEFT(X$1,FIND("_",X$1)-1)&RIGHT(X$1,LEN(X$1)-FIND("_",X$1)) < YEAR($P51) & TEXT(MONTH($P51),"00")),$O51,"") | ... BE51: =IF(AND(LEFT(BE$1,FIND("_",BE$1)-1)&RIGHT(BE$1,LEN(BE$1)-FIND("_",BE$1)) >= YEAR($I51) & TEXT(MONTH($I51),"00"),LEFT(BE$1,FIND("_",BE$1)-1)&RIGHT(BE$1,LEN(BE$1)-FIND("_",BE$1)) < YEAR($P51) & TEXT(MONTH($P51),"00")),$O51,"") -> 416666.67 | BF51: =SUM(Q51:U51) -> 0 | BG51: =SUM(V51:AG51) -> 0 | BH51: =SUM(AH51:AS51) -> 3333333.3 | BI51: =SUM(AT51:BE51) -> 5000000 | BJ51: =VLOOKUP(D51,Master!AD:AG,3,FALSE) -> 7611100 | BK51: =VLOOKUP(D51,Master!AD:AG,4,FALSE) -> Depreciation-Building
A52: 017 | B52: Asphalt Replacement & Gutter renovation Front Office Area | C52: Building | D52: 2111100 | E52: 600000000 | F52: 240 | G52: General Affair | H52: 1 | I52: 44896 | J52: BIP | K52: Maintenance | L52: C | M52: BGT.FY123 | N52: =H52*E52 -> 600000000 | O52: =N52/F52 -> 2500000 | P52: =DATE(YEAR(I52),MONTH(I52)+F52,DAY(I52)) -> 52201 | Q52: =IF(AND(LEFT(Q$1,FIND("_",Q$1)-1)&RIGHT(Q$1,LEN(Q$1)-FIND("_",Q$1)) >= YEAR($I52) & TEXT(MONTH($I52),"00"),LEFT(Q$1,FIND("_",Q$1)-1)&RIGHT(Q$1,LEN(Q$1)-FIND("_",Q$1)) < YEAR($P52) & TEXT(MONTH($P52),"00")),$O52,"") | R52: =IF(AND(LEFT(R$1,FIND("_",R$1)-1)&RIGHT(R$1,LEN(R$1)-FIND("_",R$1)) >= YEAR($I52) & TEXT(MONTH($I52),"00"),LEFT(R$1,FIND("_",R$1)-1)&RIGHT(R$1,LEN(R$1)-FIND("_",R$1)) < YEAR($P52) & TEXT(MONTH($P52),"00")),$O52,"") | S52: =IF(AND(LEFT(S$1,FIND("_",S$1)-1)&RIGHT(S$1,LEN(S$1)-FIND("_",S$1)) >= YEAR($I52) & TEXT(MONTH($I52),"00"),LEFT(S$1,FIND("_",S$1)-1)&RIGHT(S$1,LEN(S$1)-FIND("_",S$1)) < YEAR($P52) & TEXT(MONTH($P52),"00")),$O52,"") | T52: =IF(AND(LEFT(T$1,FIND("_",T$1)-1)&RIGHT(T$1,LEN(T$1)-FIND("_",T$1)) >= YEAR($I52) & TEXT(MONTH($I52),"00"),LEFT(T$1,FIND("_",T$1)-1)&RIGHT(T$1,LEN(T$1)-FIND("_",T$1)) < YEAR($P52) & TEXT(MONTH($P52),"00")),$O52,"") | U52: =IF(AND(LEFT(U$1,FIND("_",U$1)-1)&RIGHT(U$1,LEN(U$1)-FIND("_",U$1)) >= YEAR($I52) & TEXT(MONTH($I52),"00"),LEFT(U$1,FIND("_",U$1)-1)&RIGHT(U$1,LEN(U$1)-FIND("_",U$1)) < YEAR($P52) & TEXT(MONTH($P52),"00")),$O52,"") | V52: =IF(AND(LEFT(V$1,FIND("_",V$1)-1)&RIGHT(V$1,LEN(V$1)-FIND("_",V$1)) >= YEAR($I52) & TEXT(MONTH($I52),"00"),LEFT(V$1,FIND("_",V$1)-1)&RIGHT(V$1,LEN(V$1)-FIND("_",V$1)) < YEAR($P52) & TEXT(MONTH($P52),"00")),$O52,"") | W52: =IF(AND(LEFT(W$1,FIND("_",W$1)-1)&RIGHT(W$1,LEN(W$1)-FIND("_",W$1)) >= YEAR($I52) & TEXT(MONTH($I52),"00"),LEFT(W$1,FIND("_",W$1)-1)&RIGHT(W$1,LEN(W$1)-FIND("_",W$1)) < YEAR($P52) & TEXT(MONTH($P52),"00")),$O52,"") | X52: =IF(AND(LEFT(X$1,FIND("_",X$1)-1)&RIGHT(X$1,LEN(X$1)-FIND("_",X$1)) >= YEAR($I52) & TEXT(MONTH($I52),"00"),LEFT(X$1,FIND("_",X$1)-1)&RIGHT(X$1,LEN(X$1)-FIND("_",X$1)) < YEAR($P52) & TEXT(MONTH($P52),"00")),$O52,"") | ... BE52: =IF(AND(LEFT(BE$1,FIND("_",BE$1)-1)&RIGHT(BE$1,LEN(BE$1)-FIND("_",BE$1)) >= YEAR($I52) & TEXT(MONTH($I52),"00"),LEFT(BE$1,FIND("_",BE$1)-1)&RIGHT(BE$1,LEN(BE$1)-FIND("_",BE$1)) < YEAR($P52) & TEXT(MONTH($P52),"00")),$O52,"") -> 2500000 | BF52: =SUM(Q52:U52) -> 0 | BG52: =SUM(V52:AG52) -> 0 | BH52: =SUM(AH52:AS52) -> 10000000 | BI52: =SUM(AT52:BE52) -> 30000000 | BJ52: =VLOOKUP(D52,Master!AD:AG,3,FALSE) -> 7611100 | BK52: =VLOOKUP(D52,Master!AD:AG,4,FALSE) -> Depreciation-Building
A53: 018 | B53: Renovation fence to full fill regulation from government regarding social facility 1st step | C53: Building | D53: 2111100 | E53: 723000000 | F53: 240 | G53: General Affair | H53: 1 | I53: 44986 | J53: BIP | K53: Maintenance | L53: B | M53: BGT.FY123 | N53: =H53*E53 -> 723000000 | O53: =N53/F53 -> 3012500 | P53: =DATE(YEAR(I53),MONTH(I53)+F53,DAY(I53)) -> 52291 | Q53: =IF(AND(LEFT(Q$1,FIND("_",Q$1)-1)&RIGHT(Q$1,LEN(Q$1)-FIND("_",Q$1)) >= YEAR($I53) & TEXT(MONTH($I53),"00"),LEFT(Q$1,FIND("_",Q$1)-1)&RIGHT(Q$1,LEN(Q$1)-FIND("_",Q$1)) < YEAR($P53) & TEXT(MONTH($P53),"00")),$O53,"") | R53: =IF(AND(LEFT(R$1,FIND("_",R$1)-1)&RIGHT(R$1,LEN(R$1)-FIND("_",R$1)) >= YEAR($I53) & TEXT(MONTH($I53),"00"),LEFT(R$1,FIND("_",R$1)-1)&RIGHT(R$1,LEN(R$1)-FIND("_",R$1)) < YEAR($P53) & TEXT(MONTH($P53),"00")),$O53,"") | S53: =IF(AND(LEFT(S$1,FIND("_",S$1)-1)&RIGHT(S$1,LEN(S$1)-FIND("_",S$1)) >= YEAR($I53) & TEXT(MONTH($I53),"00"),LEFT(S$1,FIND("_",S$1)-1)&RIGHT(S$1,LEN(S$1)-FIND("_",S$1)) < YEAR($P53) & TEXT(MONTH($P53),"00")),$O53,"") | T53: =IF(AND(LEFT(T$1,FIND("_",T$1)-1)&RIGHT(T$1,LEN(T$1)-FIND("_",T$1)) >= YEAR($I53) & TEXT(MONTH($I53),"00"),LEFT(T$1,FIND("_",T$1)-1)&RIGHT(T$1,LEN(T$1)-FIND("_",T$1)) < YEAR($P53) & TEXT(MONTH($P53),"00")),$O53,"") | U53: =IF(AND(LEFT(U$1,FIND("_",U$1)-1)&RIGHT(U$1,LEN(U$1)-FIND("_",U$1)) >= YEAR($I53) & TEXT(MONTH($I53),"00"),LEFT(U$1,FIND("_",U$1)-1)&RIGHT(U$1,LEN(U$1)-FIND("_",U$1)) < YEAR($P53) & TEXT(MONTH($P53),"00")),$O53,"") | V53: =IF(AND(LEFT(V$1,FIND("_",V$1)-1)&RIGHT(V$1,LEN(V$1)-FIND("_",V$1)) >= YEAR($I53) & TEXT(MONTH($I53),"00"),LEFT(V$1,FIND("_",V$1)-1)&RIGHT(V$1,LEN(V$1)-FIND("_",V$1)) < YEAR($P53) & TEXT(MONTH($P53),"00")),$O53,"") | W53: =IF(AND(LEFT(W$1,FIND("_",W$1)-1)&RIGHT(W$1,LEN(W$1)-FIND("_",W$1)) >= YEAR($I53) & TEXT(MONTH($I53),"00"),LEFT(W$1,FIND("_",W$1)-1)&RIGHT(W$1,LEN(W$1)-FIND("_",W$1)) < YEAR($P53) & TEXT(MONTH($P53),"00")),$O53,"") | X53: =IF(AND(LEFT(X$1,FIND("_",X$1)-1)&RIGHT(X$1,LEN(X$1)-FIND("_",X$1)) >= YEAR($I53) & TEXT(MONTH($I53),"00"),LEFT(X$1,FIND("_",X$1)-1)&RIGHT(X$1,LEN(X$1)-FIND("_",X$1)) < YEAR($P53) & TEXT(MONTH($P53),"00")),$O53,"") | ... BE53: =IF(AND(LEFT(BE$1,FIND("_",BE$1)-1)&RIGHT(BE$1,LEN(BE$1)-FIND("_",BE$1)) >= YEAR($I53) & TEXT(MONTH($I53),"00"),LEFT(BE$1,FIND("_",BE$1)-1)&RIGHT(BE$1,LEN(BE$1)-FIND("_",BE$1)) < YEAR($P53) & TEXT(MONTH($P53),"00")),$O53,"") -> 3012500 | BF53: =SUM(Q53:U53) -> 0 | BG53: =SUM(V53:AG53) -> 0 | BH53: =SUM(AH53:AS53) -> 3012500 | BI53: =SUM(AT53:BE53) -> 36150000 | BJ53: =VLOOKUP(D53,Master!AD:AG,3,FALSE) -> 7611100 | BK53: =VLOOKUP(D53,Master!AD:AG,4,FALSE) -> Depreciation-Building
A54: 019 | B54: Mini Crusher for composting | C54: Tools, furniture & office equipment | D54: 2141000 | E54: 30000000 | F54: 60 | G54: Health, Safety & Environment | H54: 1 | I54: 45231 | J54: BIP | K54: Maintenance | L54: C | M54: BGT.FY124 | N54: =H54*E54 -> 30000000 | O54: =N54/F54 -> 500000 | P54: =DATE(YEAR(I54),MONTH(I54)+F54,DAY(I54)) -> 47058 | Q54: =IF(AND(LEFT(Q$1,FIND("_",Q$1)-1)&RIGHT(Q$1,LEN(Q$1)-FIND("_",Q$1)) >= YEAR($I54) & TEXT(MONTH($I54),"00"),LEFT(Q$1,FIND("_",Q$1)-1)&RIGHT(Q$1,LEN(Q$1)-FIND("_",Q$1)) < YEAR($P54) & TEXT(MONTH($P54),"00")),$O54,"") | R54: =IF(AND(LEFT(R$1,FIND("_",R$1)-1)&RIGHT(R$1,LEN(R$1)-FIND("_",R$1)) >= YEAR($I54) & TEXT(MONTH($I54),"00"),LEFT(R$1,FIND("_",R$1)-1)&RIGHT(R$1,LEN(R$1)-FIND("_",R$1)) < YEAR($P54) & TEXT(MONTH($P54),"00")),$O54,"") | S54: =IF(AND(LEFT(S$1,FIND("_",S$1)-1)&RIGHT(S$1,LEN(S$1)-FIND("_",S$1)) >= YEAR($I54) & TEXT(MONTH($I54),"00"),LEFT(S$1,FIND("_",S$1)-1)&RIGHT(S$1,LEN(S$1)-FIND("_",S$1)) < YEAR($P54) & TEXT(MONTH($P54),"00")),$O54,"") | T54: =IF(AND(LEFT(T$1,FIND("_",T$1)-1)&RIGHT(T$1,LEN(T$1)-FIND("_",T$1)) >= YEAR($I54) & TEXT(MONTH($I54),"00"),LEFT(T$1,FIND("_",T$1)-1)&RIGHT(T$1,LEN(T$1)-FIND("_",T$1)) < YEAR($P54) & TEXT(MONTH($P54),"00")),$O54,"") | U54: =IF(AND(LEFT(U$1,FIND("_",U$1)-1)&RIGHT(U$1,LEN(U$1)-FIND("_",U$1)) >= YEAR($I54) & TEXT(MONTH($I54),"00"),LEFT(U$1,FIND("_",U$1)-1)&RIGHT(U$1,LEN(U$1)-FIND("_",U$1)) < YEAR($P54) & TEXT(MONTH($P54),"00")),$O54,"") | V54: =IF(AND(LEFT(V$1,FIND("_",V$1)-1)&RIGHT(V$1,LEN(V$1)-FIND("_",V$1)) >= YEAR($I54) & TEXT(MONTH($I54),"00"),LEFT(V$1,FIND("_",V$1)-1)&RIGHT(V$1,LEN(V$1)-FIND("_",V$1)) < YEAR($P54) & TEXT(MONTH($P54),"00")),$O54,"") | W54: =IF(AND(LEFT(W$1,FIND("_",W$1)-1)&RIGHT(W$1,LEN(W$1)-FIND("_",W$1)) >= YEAR($I54) & TEXT(MONTH($I54),"00"),LEFT(W$1,FIND("_",W$1)-1)&RIGHT(W$1,LEN(W$1)-FIND("_",W$1)) < YEAR($P54) & TEXT(MONTH($P54),"00")),$O54,"") | X54: =IF(AND(LEFT(X$1,FIND("_",X$1)-1)&RIGHT(X$1,LEN(X$1)-FIND("_",X$1)) >= YEAR($I54) & TEXT(MONTH($I54),"00"),LEFT(X$1,FIND("_",X$1)-1)&RIGHT(X$1,LEN(X$1)-FIND("_",X$1)) < YEAR($P54) & TEXT(MONTH($P54),"00")),$O54,"") | ... BE54: =IF(AND(LEFT(BE$1,FIND("_",BE$1)-1)&RIGHT(BE$1,LEN(BE$1)-FIND("_",BE$1)) >= YEAR($I54) & TEXT(MONTH($I54),"00"),LEFT(BE$1,FIND("_",BE$1)-1)&RIGHT(BE$1,LEN(BE$1)-FIND("_",BE$1)) < YEAR($P54) & TEXT(MONTH($P54),"00")),$O54,"") -> 500000 | BF54: =SUM(Q54:U54) -> 0 | BG54: =SUM(V54:AG54) -> 0 | BH54: =SUM(AH54:AS54) -> 0 | BI54: =SUM(AT54:BE54) -> 2500000 | BJ54: =VLOOKUP(D54,Master!AD:AG,3,FALSE) -> 7611600 | BK54: =VLOOKUP(D54,Master!AD:AG,4,FALSE) -> Depreciation-Tools, furniture & office equipment
... A78: 001 | B78: Replacement Computer Desktop (Foreman) | C78: Tools, furniture & office equipment | D78: 2141000 | E78: 8000000 | F78: 60 | G78: SP PD- Plating | H78: 1 | I78: 44287 | J78: BIP | K78: SP PD- Plating | L78: B | M78: BGT.FY122 | N78: =H78*E78 -> 8000000 | O78: =N78/F78 -> 133333.33 | P78: =DATE(YEAR(I78),MONTH(I78)+F78,DAY(I78)) -> 46113 | Q78: =IF(AND(LEFT(Q$1,FIND("_",Q$1)-1)&RIGHT(Q$1,LEN(Q$1)-FIND("_",Q$1)) >= YEAR($I78) & TEXT(MONTH($I78),"00"),LEFT(Q$1,FIND("_",Q$1)-1)&RIGHT(Q$1,LEN(Q$1)-FIND("_",Q$1)) < YEAR($P78) & TEXT(MONTH($P78),"00")),$O78,"") | R78: =IF(AND(LEFT(R$1,FIND("_",R$1)-1)&RIGHT(R$1,LEN(R$1)-FIND("_",R$1)) >= YEAR($I78) & TEXT(MONTH($I78),"00"),LEFT(R$1,FIND("_",R$1)-1)&RIGHT(R$1,LEN(R$1)-FIND("_",R$1)) < YEAR($P78) & TEXT(MONTH($P78),"00")),$O78,"") | S78: =IF(AND(LEFT(S$1,FIND("_",S$1)-1)&RIGHT(S$1,LEN(S$1)-FIND("_",S$1)) >= YEAR($I78) & TEXT(MONTH($I78),"00"),LEFT(S$1,FIND("_",S$1)-1)&RIGHT(S$1,LEN(S$1)-FIND("_",S$1)) < YEAR($P78) & TEXT(MONTH($P78),"00")),$O78,"") | T78: =IF(AND(LEFT(T$1,FIND("_",T$1)-1)&RIGHT(T$1,LEN(T$1)-FIND("_",T$1)) >= YEAR($I78) & TEXT(MONTH($I78),"00"),LEFT(T$1,FIND("_",T$1)-1)&RIGHT(T$1,LEN(T$1)-FIND("_",T$1)) < YEAR($P78) & TEXT(MONTH($P78),"00")),$O78,"") | U78: =IF(AND(LEFT(U$1,FIND("_",U$1)-1)&RIGHT(U$1,LEN(U$1)-FIND("_",U$1)) >= YEAR($I78) & TEXT(MONTH($I78),"00"),LEFT(U$1,FIND("_",U$1)-1)&RIGHT(U$1,LEN(U$1)-FIND("_",U$1)) < YEAR($P78) & TEXT(MONTH($P78),"00")),$O78,"") | V78: =IF(AND(LEFT(V$1,FIND("_",V$1)-1)&RIGHT(V$1,LEN(V$1)-FIND("_",V$1)) >= YEAR($I78) & TEXT(MONTH($I78),"00"),LEFT(V$1,FIND("_",V$1)-1)&RIGHT(V$1,LEN(V$1)-FIND("_",V$1)) < YEAR($P78) & TEXT(MONTH($P78),"00")),$O78,"") -> 133333.33 | W78: =IF(AND(LEFT(W$1,FIND("_",W$1)-1)&RIGHT(W$1,LEN(W$1)-FIND("_",W$1)) >= YEAR($I78) & TEXT(MONTH($I78),"00"),LEFT(W$1,FIND("_",W$1)-1)&RIGHT(W$1,LEN(W$1)-FIND("_",W$1)) < YEAR($P78) & TEXT(MONTH($P78),"00")),$O78,"") -> 133333.33 | X78: =IF(AND(LEFT(X$1,FIND("_",X$1)-1)&RIGHT(X$1,LEN(X$1)-FIND("_",X$1)) >= YEAR($I78) & TEXT(MONTH($I78),"00"),LEFT(X$1,FIND("_",X$1)-1)&RIGHT(X$1,LEN(X$1)-FIND("_",X$1)) < YEAR($P78) & TEXT(MONTH($P78),"00")),$O78,"") -> 133333.33 | ... BE78: =IF(AND(LEFT(BE$1,FIND("_",BE$1)-1)&RIGHT(BE$1,LEN(BE$1)-FIND("_",BE$1)) >= YEAR($I78) & TEXT(MONTH($I78),"00"),LEFT(BE$1,FIND("_",BE$1)-1)&RIGHT(BE$1,LEN(BE$1)-FIND("_",BE$1)) < YEAR($P78) & TEXT(MONTH($P78),"00")),$O78,"") -> 133333.33 | BF78: =SUM(Q78:U78) -> 0 | BG78: =SUM(V78:AG78) -> 1600000 | BH78: =SUM(AH78:AS78) -> 1600000 | BI78: =SUM(AT78:BE78) -> 1600000 | BJ78: =VLOOKUP(D78,Master!AD:AG,3,FALSE) -> 7611600 | BK78: =VLOOKUP(D78,Master!AD:AG,4,FALSE) -> Depreciation-Tools, furniture & office equipment
A79: 002 | B79: Vaccum Cleaner | C79: Tools, furniture & office equipment | D79: 2141000 | E79: 13000000 | F79: 60 | G79: SP PD- Plating | H79: 1 | I79: 44228 | J79: BIP | K79: SP PD- Plating | M79: BGT.FY121 | N79: =H79*E79 -> 13000000 | O79: =N79/F79 -> 216666.67 | P79: =DATE(YEAR(I79),MONTH(I79)+F79,DAY(I79)) -> 46054 | Q79: =IF(AND(LEFT(Q$1,FIND("_",Q$1)-1)&RIGHT(Q$1,LEN(Q$1)-FIND("_",Q$1)) >= YEAR($I79) & TEXT(MONTH($I79),"00"),LEFT(Q$1,FIND("_",Q$1)-1)&RIGHT(Q$1,LEN(Q$1)-FIND("_",Q$1)) < YEAR($P79) & TEXT(MONTH($P79),"00")),$O79,"") | R79: =IF(AND(LEFT(R$1,FIND("_",R$1)-1)&RIGHT(R$1,LEN(R$1)-FIND("_",R$1)) >= YEAR($I79) & TEXT(MONTH($I79),"00"),LEFT(R$1,FIND("_",R$1)-1)&RIGHT(R$1,LEN(R$1)-FIND("_",R$1)) < YEAR($P79) & TEXT(MONTH($P79),"00")),$O79,"") | S79: =IF(AND(LEFT(S$1,FIND("_",S$1)-1)&RIGHT(S$1,LEN(S$1)-FIND("_",S$1)) >= YEAR($I79) & TEXT(MONTH($I79),"00"),LEFT(S$1,FIND("_",S$1)-1)&RIGHT(S$1,LEN(S$1)-FIND("_",S$1)) < YEAR($P79) & TEXT(MONTH($P79),"00")),$O79,"") | T79: =IF(AND(LEFT(T$1,FIND("_",T$1)-1)&RIGHT(T$1,LEN(T$1)-FIND("_",T$1)) >= YEAR($I79) & TEXT(MONTH($I79),"00"),LEFT(T$1,FIND("_",T$1)-1)&RIGHT(T$1,LEN(T$1)-FIND("_",T$1)) < YEAR($P79) & TEXT(MONTH($P79),"00")),$O79,"") -> 216666.67 | U79: =IF(AND(LEFT(U$1,FIND("_",U$1)-1)&RIGHT(U$1,LEN(U$1)-FIND("_",U$1)) >= YEAR($I79) & TEXT(MONTH($I79),"00"),LEFT(U$1,FIND("_",U$1)-1)&RIGHT(U$1,LEN(U$1)-FIND("_",U$1)) < YEAR($P79) & TEXT(MONTH($P79),"00")),$O79,"") -> 216666.67 | V79: =IF(AND(LEFT(V$1,FIND("_",V$1)-1)&RIGHT(V$1,LEN(V$1)-FIND("_",V$1)) >= YEAR($I79) & TEXT(MONTH($I79),"00"),LEFT(V$1,FIND("_",V$1)-1)&RIGHT(V$1,LEN(V$1)-FIND("_",V$1)) < YEAR($P79) & TEXT(MONTH($P79),"00")),$O79,"") -> 216666.67 | W79: =IF(AND(LEFT(W$1,FIND("_",W$1)-1)&RIGHT(W$1,LEN(W$1)-FIND("_",W$1)) >= YEAR($I79) & TEXT(MONTH($I79),"00"),LEFT(W$1,FIND("_",W$1)-1)&RIGHT(W$1,LEN(W$1)-FIND("_",W$1)) < YEAR($P79) & TEXT(MONTH($P79),"00")),$O79,"") -> 216666.67 | X79: =IF(AND(LEFT(X$1,FIND("_",X$1)-1)&RIGHT(X$1,LEN(X$1)-FIND("_",X$1)) >= YEAR($I79) & TEXT(MONTH($I79),"00"),LEFT(X$1,FIND("_",X$1)-1)&RIGHT(X$1,LEN(X$1)-FIND("_",X$1)) < YEAR($P79) & TEXT(MONTH($P79),"00")),$O79,"") -> 216666.67 | ... BE79: =IF(AND(LEFT(BE$1,FIND("_",BE$1)-1)&RIGHT(BE$1,LEN(BE$1)-FIND("_",BE$1)) >= YEAR($I79) & TEXT(MONTH($I79),"00"),LEFT(BE$1,FIND("_",BE$1)-1)&RIGHT(BE$1,LEN(BE$1)-FIND("_",BE$1)) < YEAR($P79) & TEXT(MONTH($P79),"00")),$O79,"") -> 216666.67 | BF79: =SUM(Q79:U79) -> 433333.33 | BG79: =SUM(V79:AG79) -> 2600000 | BH79: =SUM(AH79:AS79) -> 2600000 | BI79: =SUM(AT79:BE79) -> 2600000 | BJ79: =VLOOKUP(D79,Master!AD:AG,3,FALSE) -> 7611600 | BK79: =VLOOKUP(D79,Master!AD:AG,4,FALSE) -> Depreciation-Tools, furniture & office equipment
A80: 003 | B80: Drump Pump | C80: Tools, furniture & office equipment | D80: 2141000 | E80: 16000000 | F80: 60 | G80: SP PD- Plating | H80: 1 | I80: 44256 | J80: BIP | K80: SP PD- Plating | M80: BGT.FY121 | N80: =H80*E80 -> 16000000 | O80: =N80/F80 -> 266666.67 | P80: =DATE(YEAR(I80),MONTH(I80)+F80,DAY(I80)) -> 46082 | Q80: =IF(AND(LEFT(Q$1,FIND("_",Q$1)-1)&RIGHT(Q$1,LEN(Q$1)-FIND("_",Q$1)) >= YEAR($I80) & TEXT(MONTH($I80),"00"),LEFT(Q$1,FIND("_",Q$1)-1)&RIGHT(Q$1,LEN(Q$1)-FIND("_",Q$1)) < YEAR($P80) & TEXT(MONTH($P80),"00")),$O80,"") | R80: =IF(AND(LEFT(R$1,FIND("_",R$1)-1)&RIGHT(R$1,LEN(R$1)-FIND("_",R$1)) >= YEAR($I80) & TEXT(MONTH($I80),"00"),LEFT(R$1,FIND("_",R$1)-1)&RIGHT(R$1,LEN(R$1)-FIND("_",R$1)) < YEAR($P80) & TEXT(MONTH($P80),"00")),$O80,"") | S80: =IF(AND(LEFT(S$1,FIND("_",S$1)-1)&RIGHT(S$1,LEN(S$1)-FIND("_",S$1)) >= YEAR($I80) & TEXT(MONTH($I80),"00"),LEFT(S$1,FIND("_",S$1)-1)&RIGHT(S$1,LEN(S$1)-FIND("_",S$1)) < YEAR($P80) & TEXT(MONTH($P80),"00")),$O80,"") | T80: =IF(AND(LEFT(T$1,FIND("_",T$1)-1)&RIGHT(T$1,LEN(T$1)-FIND("_",T$1)) >= YEAR($I80) & TEXT(MONTH($I80),"00"),LEFT(T$1,FIND("_",T$1)-1)&RIGHT(T$1,LEN(T$1)-FIND("_",T$1)) < YEAR($P80) & TEXT(MONTH($P80),"00")),$O80,"") | U80: =IF(AND(LEFT(U$1,FIND("_",U$1)-1)&RIGHT(U$1,LEN(U$1)-FIND("_",U$1)) >= YEAR($I80) & TEXT(MONTH($I80),"00"),LEFT(U$1,FIND("_",U$1)-1)&RIGHT(U$1,LEN(U$1)-FIND("_",U$1)) < YEAR($P80) & TEXT(MONTH($P80),"00")),$O80,"") -> 266666.67 | V80: =IF(AND(LEFT(V$1,FIND("_",V$1)-1)&RIGHT(V$1,LEN(V$1)-FIND("_",V$1)) >= YEAR($I80) & TEXT(MONTH($I80),"00"),LEFT(V$1,FIND("_",V$1)-1)&RIGHT(V$1,LEN(V$1)-FIND("_",V$1)) < YEAR($P80) & TEXT(MONTH($P80),"00")),$O80,"") -> 266666.67 | W80: =IF(AND(LEFT(W$1,FIND("_",W$1)-1)&RIGHT(W$1,LEN(W$1)-FIND("_",W$1)) >= YEAR($I80) & TEXT(MONTH($I80),"00"),LEFT(W$1,FIND("_",W$1)-1)&RIGHT(W$1,LEN(W$1)-FIND("_",W$1)) < YEAR($P80) & TEXT(MONTH($P80),"00")),$O80,"") -> 266666.67 | X80: =IF(AND(LEFT(X$1,FIND("_",X$1)-1)&RIGHT(X$1,LEN(X$1)-FIND("_",X$1)) >= YEAR($I80) & TEXT(MONTH($I80),"00"),LEFT(X$1,FIND("_",X$1)-1)&RIGHT(X$1,LEN(X$1)-FIND("_",X$1)) < YEAR($P80) & TEXT(MONTH($P80),"00")),$O80,"") -> 266666.67 | ... BE80: =IF(AND(LEFT(BE$1,FIND("_",BE$1)-1)&RIGHT(BE$1,LEN(BE$1)-FIND("_",BE$1)) >= YEAR($I80) & TEXT(MONTH($I80),"00"),LEFT(BE$1,FIND("_",BE$1)-1)&RIGHT(BE$1,LEN(BE$1)-FIND("_",BE$1)) < YEAR($P80) & TEXT(MONTH($P80),"00")),$O80,"") -> 266666.67 | BF80: =SUM(Q80:U80) -> 266666.67 | BG80: =SUM(V80:AG80) -> 3200000 | BH80: =SUM(AH80:AS80) -> 3200000 | BI80: =SUM(AT80:BE80) -> 3200000 | BJ80: =VLOOKUP(D80,Master!AD:AG,3,FALSE) -> 7611600 | BK80: =VLOOKUP(D80,Master!AD:AG,4,FALSE) -> Depreciation-Tools, furniture & office equipment
A81: 001 | B81: PERSONAL COMPUTER | C81: Tools, furniture & office equipment | D81: 2141000 | E81: 10000000 | F81: 60 | G81: PC PD- Injection | H81: 1 | I81: 44256 | J81: BIP | K81: PC PD- Injection | M81: BGT.FY121 | N81: =H81*E81 -> 10000000 | O81: =N81/F81 -> 166666.67 | P81: =DATE(YEAR(I81),MONTH(I81)+F81,DAY(I81)) -> 46082 | Q81: =IF(AND(LEFT(Q$1,FIND("_",Q$1)-1)&RIGHT(Q$1,LEN(Q$1)-FIND("_",Q$1)) >= YEAR($I81) & TEXT(MONTH($I81),"00"),LEFT(Q$1,FIND("_",Q$1)-1)&RIGHT(Q$1,LEN(Q$1)-FIND("_",Q$1)) < YEAR($P81) & TEXT(MONTH($P81),"00")),$O81,"") | R81: =IF(AND(LEFT(R$1,FIND("_",R$1)-1)&RIGHT(R$1,LEN(R$1)-FIND("_",R$1)) >= YEAR($I81) & TEXT(MONTH($I81),"00"),LEFT(R$1,FIND("_",R$1)-1)&RIGHT(R$1,LEN(R$1)-FIND("_",R$1)) < YEAR($P81) & TEXT(MONTH($P81),"00")),$O81,"") | S81: =IF(AND(LEFT(S$1,FIND("_",S$1)-1)&RIGHT(S$1,LEN(S$1)-FIND("_",S$1)) >= YEAR($I81) & TEXT(MONTH($I81),"00"),LEFT(S$1,FIND("_",S$1)-1)&RIGHT(S$1,LEN(S$1)-FIND("_",S$1)) < YEAR($P81) & TEXT(MONTH($P81),"00")),$O81,"") | T81: =IF(AND(LEFT(T$1,FIND("_",T$1)-1)&RIGHT(T$1,LEN(T$1)-FIND("_",T$1)) >= YEAR($I81) & TEXT(MONTH($I81),"00"),LEFT(T$1,FIND("_",T$1)-1)&RIGHT(T$1,LEN(T$1)-FIND("_",T$1)) < YEAR($P81) & TEXT(MONTH($P81),"00")),$O81,"") | U81: =IF(AND(LEFT(U$1,FIND("_",U$1)-1)&RIGHT(U$1,LEN(U$1)-FIND("_",U$1)) >= YEAR($I81) & TEXT(MONTH($I81),"00"),LEFT(U$1,FIND("_",U$1)-1)&RIGHT(U$1,LEN(U$1)-FIND("_",U$1)) < YEAR($P81) & TEXT(MONTH($P81),"00")),$O81,"") -> 166666.67 | V81: =IF(AND(LEFT(V$1,FIND("_",V$1)-1)&RIGHT(V$1,LEN(V$1)-FIND("_",V$1)) >= YEAR($I81) & TEXT(MONTH($I81),"00"),LEFT(V$1,FIND("_",V$1)-1)&RIGHT(V$1,LEN(V$1)-FIND("_",V$1)) < YEAR($P81) & TEXT(MONTH($P81),"00")),$O81,"") -> 166666.67 | W81: =IF(AND(LEFT(W$1,FIND("_",W$1)-1)&RIGHT(W$1,LEN(W$1)-FIND("_",W$1)) >= YEAR($I81) & TEXT(MONTH($I81),"00"),LEFT(W$1,FIND("_",W$1)-1)&RIGHT(W$1,LEN(W$1)-FIND("_",W$1)) < YEAR($P81) & TEXT(MONTH($P81),"00")),$O81,"") -> 166666.67 | X81: =IF(AND(LEFT(X$1,FIND("_",X$1)-1)&RIGHT(X$1,LEN(X$1)-FIND("_",X$1)) >= YEAR($I81) & TEXT(MONTH($I81),"00"),LEFT(X$1,FIND("_",X$1)-1)&RIGHT(X$1,LEN(X$1)-FIND("_",X$1)) < YEAR($P81) & TEXT(MONTH($P81),"00")),$O81,"") -> 166666.67 | ... BE81: =IF(AND(LEFT(BE$1,FIND("_",BE$1)-1)&RIGHT(BE$1,LEN(BE$1)-FIND("_",BE$1)) >= YEAR($I81) & TEXT(MONTH($I81),"00"),LEFT(BE$1,FIND("_",BE$1)-1)&RIGHT(BE$1,LEN(BE$1)-FIND("_",BE$1)) < YEAR($P81) & TEXT(MONTH($P81),"00")),$O81,"") -> 166666.67 | BF81: =SUM(Q81:U81) -> 166666.67 | BG81: =SUM(V81:AG81) -> 2000000 | BH81: =SUM(AH81:AS81) -> 2000000 | BI81: =SUM(AT81:BE81) -> 2000000 | BJ81: =VLOOKUP(D81,Master!AD:AG,3,FALSE) -> 7611600 | BK81: =VLOOKUP(D81,Master!AD:AG,4,FALSE) -> Depreciation-Tools, furniture & office equipment
A82: 001 | B82: WEIGHING SCALE | C82: Machinery & Equipment - New | D82: 2121000 | E82: 10000000 | F82: 120 | G82: PC PD- Assy | H82: 1 | I82: 44287 | J82: BIP | K82: PC PD- Assy | L82: B | M82: BGT.FY122 | N82: =H82*E82 -> 10000000 | O82: =N82/F82 -> 83333.333 | P82: =DATE(YEAR(I82),MONTH(I82)+F82,DAY(I82)) -> 47939 | Q82: =IF(AND(LEFT(Q$1,FIND("_",Q$1)-1)&RIGHT(Q$1,LEN(Q$1)-FIND("_",Q$1)) >= YEAR($I82) & TEXT(MONTH($I82),"00"),LEFT(Q$1,FIND("_",Q$1)-1)&RIGHT(Q$1,LEN(Q$1)-FIND("_",Q$1)) < YEAR($P82) & TEXT(MONTH($P82),"00")),$O82,"") | R82: =IF(AND(LEFT(R$1,FIND("_",R$1)-1)&RIGHT(R$1,LEN(R$1)-FIND("_",R$1)) >= YEAR($I82) & TEXT(MONTH($I82),"00"),LEFT(R$1,FIND("_",R$1)-1)&RIGHT(R$1,LEN(R$1)-FIND("_",R$1)) < YEAR($P82) & TEXT(MONTH($P82),"00")),$O82,"") | S82: =IF(AND(LEFT(S$1,FIND("_",S$1)-1)&RIGHT(S$1,LEN(S$1)-FIND("_",S$1)) >= YEAR($I82) & TEXT(MONTH($I82),"00"),LEFT(S$1,FIND("_",S$1)-1)&RIGHT(S$1,LEN(S$1)-FIND("_",S$1)) < YEAR($P82) & TEXT(MONTH($P82),"00")),$O82,"") | T82: =IF(AND(LEFT(T$1,FIND("_",T$1)-1)&RIGHT(T$1,LEN(T$1)-FIND("_",T$1)) >= YEAR($I82) & TEXT(MONTH($I82),"00"),LEFT(T$1,FIND("_",T$1)-1)&RIGHT(T$1,LEN(T$1)-FIND("_",T$1)) < YEAR($P82) & TEXT(MONTH($P82),"00")),$O82,"") | U82: =IF(AND(LEFT(U$1,FIND("_",U$1)-1)&RIGHT(U$1,LEN(U$1)-FIND("_",U$1)) >= YEAR($I82) & TEXT(MONTH($I82),"00"),LEFT(U$1,FIND("_",U$1)-1)&RIGHT(U$1,LEN(U$1)-FIND("_",U$1)) < YEAR($P82) & TEXT(MONTH($P82),"00")),$O82,"") | V82: =IF(AND(LEFT(V$1,FIND("_",V$1)-1)&RIGHT(V$1,LEN(V$1)-FIND("_",V$1)) >= YEAR($I82) & TEXT(MONTH($I82),"00"),LEFT(V$1,FIND("_",V$1)-1)&RIGHT(V$1,LEN(V$1)-FIND("_",V$1)) < YEAR($P82) & TEXT(MONTH($P82),"00")),$O82,"") -> 83333.333 | W82: =IF(AND(LEFT(W$1,FIND("_",W$1)-1)&RIGHT(W$1,LEN(W$1)-FIND("_",W$1)) >= YEAR($I82) & TEXT(MONTH($I82),"00"),LEFT(W$1,FIND("_",W$1)-1)&RIGHT(W$1,LEN(W$1)-FIND("_",W$1)) < YEAR($P82) & TEXT(MONTH($P82),"00")),$O82,"") -> 83333.333 | X82: =IF(AND(LEFT(X$1,FIND("_",X$1)-1)&RIGHT(X$1,LEN(X$1)-FIND("_",X$1)) >= YEAR($I82) & TEXT(MONTH($I82),"00"),LEFT(X$1,FIND("_",X$1)-1)&RIGHT(X$1,LEN(X$1)-FIND("_",X$1)) < YEAR($P82) & TEXT(MONTH($P82),"00")),$O82,"") -> 83333.333 | ... BE82: =IF(AND(LEFT(BE$1,FIND("_",BE$1)-1)&RIGHT(BE$1,LEN(BE$1)-FIND("_",BE$1)) >= YEAR($I82) & TEXT(MONTH($I82),"00"),LEFT(BE$1,FIND("_",BE$1)-1)&RIGHT(BE$1,LEN(BE$1)-FIND("_",BE$1)) < YEAR($P82) & TEXT(MONTH($P82),"00")),$O82,"") -> 83333.333 | BF82: =SUM(Q82:U82) -> 0 | BG82: =SUM(V82:AG82) -> 1000000 | BH82: =SUM(AH82:AS82) -> 1000000 | BI82: =SUM(AT82:BE82) -> 1000000 | BJ82: =VLOOKUP(D82,Master!AD:AG,3,FALSE) -> 7611300 | BK82: =VLOOKUP(D82,Master!AD:AG,4,FALSE) -> Depreciation-Machiney & equipment
A83: 002 | B83: PERSONAL COMPUTER | C83: Tools, furniture & office equipment | D83: 2141000 | E83: 10000000 | F83: 60 | G83: PC PD- Assy | H83: 1 | I83: 44256 | J83: BIP | K83: PC PD- Assy | M83: BGT.FY121 | N83: =H83*E83 -> 10000000 | O83: =N83/F83 -> 166666.67 | P83: =DATE(YEAR(I83),MONTH(I83)+F83,DAY(I83)) -> 46082 | Q83: =IF(AND(LEFT(Q$1,FIND("_",Q$1)-1)&RIGHT(Q$1,LEN(Q$1)-FIND("_",Q$1)) >= YEAR($I83) & TEXT(MONTH($I83),"00"),LEFT(Q$1,FIND("_",Q$1)-1)&RIGHT(Q$1,LEN(Q$1)-FIND("_",Q$1)) < YEAR($P83) & TEXT(MONTH($P83),"00")),$O83,"") | R83: =IF(AND(LEFT(R$1,FIND("_",R$1)-1)&RIGHT(R$1,LEN(R$1)-FIND("_",R$1)) >= YEAR($I83) & TEXT(MONTH($I83),"00"),LEFT(R$1,FIND("_",R$1)-1)&RIGHT(R$1,LEN(R$1)-FIND("_",R$1)) < YEAR($P83) & TEXT(MONTH($P83),"00")),$O83,"") | S83: =IF(AND(LEFT(S$1,FIND("_",S$1)-1)&RIGHT(S$1,LEN(S$1)-FIND("_",S$1)) >= YEAR($I83) & TEXT(MONTH($I83),"00"),LEFT(S$1,FIND("_",S$1)-1)&RIGHT(S$1,LEN(S$1)-FIND("_",S$1)) < YEAR($P83) & TEXT(MONTH($P83),"00")),$O83,"") | T83: =IF(AND(LEFT(T$1,FIND("_",T$1)-1)&RIGHT(T$1,LEN(T$1)-FIND("_",T$1)) >= YEAR($I83) & TEXT(MONTH($I83),"00"),LEFT(T$1,FIND("_",T$1)-1)&RIGHT(T$1,LEN(T$1)-FIND("_",T$1)) < YEAR($P83) & TEXT(MONTH($P83),"00")),$O83,"") | U83: =IF(AND(LEFT(U$1,FIND("_",U$1)-1)&RIGHT(U$1,LEN(U$1)-FIND("_",U$1)) >= YEAR($I83) & TEXT(MONTH($I83),"00"),LEFT(U$1,FIND("_",U$1)-1)&RIGHT(U$1,LEN(U$1)-FIND("_",U$1)) < YEAR($P83) & TEXT(MONTH($P83),"00")),$O83,"") -> 166666.67 | V83: =IF(AND(LEFT(V$1,FIND("_",V$1)-1)&RIGHT(V$1,LEN(V$1)-FIND("_",V$1)) >= YEAR($I83) & TEXT(MONTH($I83),"00"),LEFT(V$1,FIND("_",V$1)-1)&RIGHT(V$1,LEN(V$1)-FIND("_",V$1)) < YEAR($P83) & TEXT(MONTH($P83),"00")),$O83,"") -> 166666.67 | W83: =IF(AND(LEFT(W$1,FIND("_",W$1)-1)&RIGHT(W$1,LEN(W$1)-FIND("_",W$1)) >= YEAR($I83) & TEXT(MONTH($I83),"00"),LEFT(W$1,FIND("_",W$1)-1)&RIGHT(W$1,LEN(W$1)-FIND("_",W$1)) < YEAR($P83) & TEXT(MONTH($P83),"00")),$O83,"") -> 166666.67 | X83: =IF(AND(LEFT(X$1,FIND("_",X$1)-1)&RIGHT(X$1,LEN(X$1)-FIND("_",X$1)) >= YEAR($I83) & TEXT(MONTH($I83),"00"),LEFT(X$1,FIND("_",X$1)-1)&RIGHT(X$1,LEN(X$1)-FIND("_",X$1)) < YEAR($P83) & TEXT(MONTH($P83),"00")),$O83,"") -> 166666.67 | ... BE83: =IF(AND(LEFT(BE$1,FIND("_",BE$1)-1)&RIGHT(BE$1,LEN(BE$1)-FIND("_",BE$1)) >= YEAR($I83) & TEXT(MONTH($I83),"00"),LEFT(BE$1,FIND("_",BE$1)-1)&RIGHT(BE$1,LEN(BE$1)-FIND("_",BE$1)) < YEAR($P83) & TEXT(MONTH($P83),"00")),$O83,"") -> 166666.67 | BF83: =SUM(Q83:U83) -> 166666.67 | BG83: =SUM(V83:AG83) -> 2000000 | BH83: =SUM(AH83:AS83) -> 2000000 | BI83: =SUM(AT83:BE83) -> 2000000 | BJ83: =VLOOKUP(D83,Master!AD:AG,3,FALSE) -> 7611600 | BK83: =VLOOKUP(D83,Master!AD:AG,4,FALSE) -> Depreciation-Tools, furniture & office equipment
A84: 001 | B84: ELECTRIC LABEL DISPENCER | C84: Machinery & Equipment - New | D84: 2121000 | E84: 12000000 | F84: 120 | G84: PC PD- QC | H84: 1 | I84: 44287 | J84: BIP | K84: PC PD- QC | L84: B | M84: BGT.FY122 | N84: =H84*E84 -> 12000000 | O84: =N84/F84 -> 100000 | P84: =DATE(YEAR(I84),MONTH(I84)+F84,DAY(I84)) -> 47939 | Q84: =IF(AND(LEFT(Q$1,FIND("_",Q$1)-1)&RIGHT(Q$1,LEN(Q$1)-FIND("_",Q$1)) >= YEAR($I84) & TEXT(MONTH($I84),"00"),LEFT(Q$1,FIND("_",Q$1)-1)&RIGHT(Q$1,LEN(Q$1)-FIND("_",Q$1)) < YEAR($P84) & TEXT(MONTH($P84),"00")),$O84,"") | R84: =IF(AND(LEFT(R$1,FIND("_",R$1)-1)&RIGHT(R$1,LEN(R$1)-FIND("_",R$1)) >= YEAR($I84) & TEXT(MONTH($I84),"00"),LEFT(R$1,FIND("_",R$1)-1)&RIGHT(R$1,LEN(R$1)-FIND("_",R$1)) < YEAR($P84) & TEXT(MONTH($P84),"00")),$O84,"") | S84: =IF(AND(LEFT(S$1,FIND("_",S$1)-1)&RIGHT(S$1,LEN(S$1)-FIND("_",S$1)) >= YEAR($I84) & TEXT(MONTH($I84),"00"),LEFT(S$1,FIND("_",S$1)-1)&RIGHT(S$1,LEN(S$1)-FIND("_",S$1)) < YEAR($P84) & TEXT(MONTH($P84),"00")),$O84,"") | T84: =IF(AND(LEFT(T$1,FIND("_",T$1)-1)&RIGHT(T$1,LEN(T$1)-FIND("_",T$1)) >= YEAR($I84) & TEXT(MONTH($I84),"00"),LEFT(T$1,FIND("_",T$1)-1)&RIGHT(T$1,LEN(T$1)-FIND("_",T$1)) < YEAR($P84) & TEXT(MONTH($P84),"00")),$O84,"") | U84: =IF(AND(LEFT(U$1,FIND("_",U$1)-1)&RIGHT(U$1,LEN(U$1)-FIND("_",U$1)) >= YEAR($I84) & TEXT(MONTH($I84),"00"),LEFT(U$1,FIND("_",U$1)-1)&RIGHT(U$1,LEN(U$1)-FIND("_",U$1)) < YEAR($P84) & TEXT(MONTH($P84),"00")),$O84,"") | V84: =IF(AND(LEFT(V$1,FIND("_",V$1)-1)&RIGHT(V$1,LEN(V$1)-FIND("_",V$1)) >= YEAR($I84) & TEXT(MONTH($I84),"00"),LEFT(V$1,FIND("_",V$1)-1)&RIGHT(V$1,LEN(V$1)-FIND("_",V$1)) < YEAR($P84) & TEXT(MONTH($P84),"00")),$O84,"") -> 100000 | W84: =IF(AND(LEFT(W$1,FIND("_",W$1)-1)&RIGHT(W$1,LEN(W$1)-FIND("_",W$1)) >= YEAR($I84) & TEXT(MONTH($I84),"00"),LEFT(W$1,FIND("_",W$1)-1)&RIGHT(W$1,LEN(W$1)-FIND("_",W$1)) < YEAR($P84) & TEXT(MONTH($P84),"00")),$O84,"") -> 100000 | X84: =IF(AND(LEFT(X$1,FIND("_",X$1)-1)&RIGHT(X$1,LEN(X$1)-FIND("_",X$1)) >= YEAR($I84) & TEXT(MONTH($I84),"00"),LEFT(X$1,FIND("_",X$1)-1)&RIGHT(X$1,LEN(X$1)-FIND("_",X$1)) < YEAR($P84) & TEXT(MONTH($P84),"00")),$O84,"") -> 100000 | ... BE84: =IF(AND(LEFT(BE$1,FIND("_",BE$1)-1)&RIGHT(BE$1,LEN(BE$1)-FIND("_",BE$1)) >= YEAR($I84) & TEXT(MONTH($I84),"00"),LEFT(BE$1,FIND("_",BE$1)-1)&RIGHT(BE$1,LEN(BE$1)-FIND("_",BE$1)) < YEAR($P84) & TEXT(MONTH($P84),"00")),$O84,"") -> 100000 | BF84: =SUM(Q84:U84) -> 0 | BG84: =SUM(V84:AG84) -> 1200000 | BH84: =SUM(AH84:AS84) -> 1200000 | BI84: =SUM(AT84:BE84) -> 1200000 | BJ84: =VLOOKUP(D84,Master!AD:AG,3,FALSE) -> 7611300 | BK84: =VLOOKUP(D84,Master!AD:AG,4,FALSE) -> Depreciation-Machiney & equipment
A85: 001 | B85: Desktop PC for Edi Pujianto Foreman Assy - replacement | C85: Tools, furniture & office equipment | D85: 2141000 | E85: 8000000 | F85: 60 | G85: SP PD- Assy | H85: 1 | I85: 44317 | J85: BIP | K85: SP PD- Assy | L85: B | M85: BGT.FY122 | N85: =H85*E85 -> 8000000 | O85: =N85/F85 -> 133333.33 | P85: =DATE(YEAR(I85),MONTH(I85)+F85,DAY(I85)) -> 46143 | Q85: =IF(AND(LEFT(Q$1,FIND("_",Q$1)-1)&RIGHT(Q$1,LEN(Q$1)-FIND("_",Q$1)) >= YEAR($I85) & TEXT(MONTH($I85),"00"),LEFT(Q$1,FIND("_",Q$1)-1)&RIGHT(Q$1,LEN(Q$1)-FIND("_",Q$1)) < YEAR($P85) & TEXT(MONTH($P85),"00")),$O85,"") | R85: =IF(AND(LEFT(R$1,FIND("_",R$1)-1)&RIGHT(R$1,LEN(R$1)-FIND("_",R$1)) >= YEAR($I85) & TEXT(MONTH($I85),"00"),LEFT(R$1,FIND("_",R$1)-1)&RIGHT(R$1,LEN(R$1)-FIND("_",R$1)) < YEAR($P85) & TEXT(MONTH($P85),"00")),$O85,"") | S85: =IF(AND(LEFT(S$1,FIND("_",S$1)-1)&RIGHT(S$1,LEN(S$1)-FIND("_",S$1)) >= YEAR($I85) & TEXT(MONTH($I85),"00"),LEFT(S$1,FIND("_",S$1)-1)&RIGHT(S$1,LEN(S$1)-FIND("_",S$1)) < YEAR($P85) & TEXT(MONTH($P85),"00")),$O85,"") | T85: =IF(AND(LEFT(T$1,FIND("_",T$1)-1)&RIGHT(T$1,LEN(T$1)-FIND("_",T$1)) >= YEAR($I85) & TEXT(MONTH($I85),"00"),LEFT(T$1,FIND("_",T$1)-1)&RIGHT(T$1,LEN(T$1)-FIND("_",T$1)) < YEAR($P85) & TEXT(MONTH($P85),"00")),$O85,"") | U85: =IF(AND(LEFT(U$1,FIND("_",U$1)-1)&RIGHT(U$1,LEN(U$1)-FIND("_",U$1)) >= YEAR($I85) & TEXT(MONTH($I85),"00"),LEFT(U$1,FIND("_",U$1)-1)&RIGHT(U$1,LEN(U$1)-FIND("_",U$1)) < YEAR($P85) & TEXT(MONTH($P85),"00")),$O85,"") | V85: =IF(AND(LEFT(V$1,FIND("_",V$1)-1)&RIGHT(V$1,LEN(V$1)-FIND("_",V$1)) >= YEAR($I85) & TEXT(MONTH($I85),"00"),LEFT(V$1,FIND("_",V$1)-1)&RIGHT(V$1,LEN(V$1)-FIND("_",V$1)) < YEAR($P85) & TEXT(MONTH($P85),"00")),$O85,"") | W85: =IF(AND(LEFT(W$1,FIND("_",W$1)-1)&RIGHT(W$1,LEN(W$1)-FIND("_",W$1)) >= YEAR($I85) & TEXT(MONTH($I85),"00"),LEFT(W$1,FIND("_",W$1)-1)&RIGHT(W$1,LEN(W$1)-FIND("_",W$1)) < YEAR($P85) & TEXT(MONTH($P85),"00")),$O85,"") -> 133333.33 | X85: =IF(AND(LEFT(X$1,FIND("_",X$1)-1)&RIGHT(X$1,LEN(X$1)-FIND("_",X$1)) >= YEAR($I85) & TEXT(MONTH($I85),"00"),LEFT(X$1,FIND("_",X$1)-1)&RIGHT(X$1,LEN(X$1)-FIND("_",X$1)) < YEAR($P85) & TEXT(MONTH($P85),"00")),$O85,"") -> 133333.33 | ... BE85: =IF(AND(LEFT(BE$1,FIND("_",BE$1)-1)&RIGHT(BE$1,LEN(BE$1)-FIND("_",BE$1)) >= YEAR($I85) & TEXT(MONTH($I85),"00"),LEFT(BE$1,FIND("_",BE$1)-1)&RIGHT(BE$1,LEN(BE$1)-FIND("_",BE$1)) < YEAR($P85) & TEXT(MONTH($P85),"00")),$O85,"") -> 133333.33 | BF85: =SUM(Q85:U85) -> 0 | BG85: =SUM(V85:AG85) -> 1466666.7 | BH85: =SUM(AH85:AS85) -> 1600000 | BI85: =SUM(AT85:BE85) -> 1600000 | BJ85: =VLOOKUP(D85,Master!AD:AG,3,FALSE) -> 7611600 | BK85: =VLOOKUP(D85,Master!AD:AG,4,FALSE) -> Depreciation-Tools, furniture & office equipment
A86: 002 | B86: Desktop PC for Septian Nugraha Admin Assy-replacement | C86: Tools, furniture & office equipment | D86: 2141000 | E86: 8000000 | F86: 60 | G86: SP PD- Assy | H86: 1 | I86: 44378 | J86: BIP | K86: SP PD- Assy | L86: B | M86: BGT.FY122 | N86: =H86*E86 -> 8000000 | O86: =N86/F86 -> 133333.33 | P86: =DATE(YEAR(I86),MONTH(I86)+F86,DAY(I86)) -> 46204 | Q86: =IF(AND(LEFT(Q$1,FIND("_",Q$1)-1)&RIGHT(Q$1,LEN(Q$1)-FIND("_",Q$1)) >= YEAR($I86) & TEXT(MONTH($I86),"00"),LEFT(Q$1,FIND("_",Q$1)-1)&RIGHT(Q$1,LEN(Q$1)-FIND("_",Q$1)) < YEAR($P86) & TEXT(MONTH($P86),"00")),$O86,"") | R86: =IF(AND(LEFT(R$1,FIND("_",R$1)-1)&RIGHT(R$1,LEN(R$1)-FIND("_",R$1)) >= YEAR($I86) & TEXT(MONTH($I86),"00"),LEFT(R$1,FIND("_",R$1)-1)&RIGHT(R$1,LEN(R$1)-FIND("_",R$1)) < YEAR($P86) & TEXT(MONTH($P86),"00")),$O86,"") | S86: =IF(AND(LEFT(S$1,FIND("_",S$1)-1)&RIGHT(S$1,LEN(S$1)-FIND("_",S$1)) >= YEAR($I86) & TEXT(MONTH($I86),"00"),LEFT(S$1,FIND("_",S$1)-1)&RIGHT(S$1,LEN(S$1)-FIND("_",S$1)) < YEAR($P86) & TEXT(MONTH($P86),"00")),$O86,"") | T86: =IF(AND(LEFT(T$1,FIND("_",T$1)-1)&RIGHT(T$1,LEN(T$1)-FIND("_",T$1)) >= YEAR($I86) & TEXT(MONTH($I86),"00"),LEFT(T$1,FIND("_",T$1)-1)&RIGHT(T$1,LEN(T$1)-FIND("_",T$1)) < YEAR($P86) & TEXT(MONTH($P86),"00")),$O86,"") | U86: =IF(AND(LEFT(U$1,FIND("_",U$1)-1)&RIGHT(U$1,LEN(U$1)-FIND("_",U$1)) >= YEAR($I86) & TEXT(MONTH($I86),"00"),LEFT(U$1,FIND("_",U$1)-1)&RIGHT(U$1,LEN(U$1)-FIND("_",U$1)) < YEAR($P86) & TEXT(MONTH($P86),"00")),$O86,"") | V86: =IF(AND(LEFT(V$1,FIND("_",V$1)-1)&RIGHT(V$1,LEN(V$1)-FIND("_",V$1)) >= YEAR($I86) & TEXT(MONTH($I86),"00"),LEFT(V$1,FIND("_",V$1)-1)&RIGHT(V$1,LEN(V$1)-FIND("_",V$1)) < YEAR($P86) & TEXT(MONTH($P86),"00")),$O86,"") | W86: =IF(AND(LEFT(W$1,FIND("_",W$1)-1)&RIGHT(W$1,LEN(W$1)-FIND("_",W$1)) >= YEAR($I86) & TEXT(MONTH($I86),"00"),LEFT(W$1,FIND("_",W$1)-1)&RIGHT(W$1,LEN(W$1)-FIND("_",W$1)) < YEAR($P86) & TEXT(MONTH($P86),"00")),$O86,"") | X86: =IF(AND(LEFT(X$1,FIND("_",X$1)-1)&RIGHT(X$1,LEN(X$1)-FIND("_",X$1)) >= YEAR($I86) & TEXT(MONTH($I86),"00"),LEFT(X$1,FIND("_",X$1)-1)&RIGHT(X$1,LEN(X$1)-FIND("_",X$1)) < YEAR($P86) & TEXT(MONTH($P86),"00")),$O86,"") | ... BE86: =IF(AND(LEFT(BE$1,FIND("_",BE$1)-1)&RIGHT(BE$1,LEN(BE$1)-FIND("_",BE$1)) >= YEAR($I86) & TEXT(MONTH($I86),"00"),LEFT(BE$1,FIND("_",BE$1)-1)&RIGHT(BE$1,LEN(BE$1)-FIND("_",BE$1)) < YEAR($P86) & TEXT(MONTH($P86),"00")),$O86,"") -> 133333.33 | BF86: =SUM(Q86:U86) -> 0 | BG86: =SUM(V86:AG86) -> 1200000 | BH86: =SUM(AH86:AS86) -> 1600000 | BI86: =SUM(AT86:BE86) -> 1600000 | BJ86: =VLOOKUP(D86,Master!AD:AG,3,FALSE) -> 7611600 | BK86: =VLOOKUP(D86,Master!AD:AG,4,FALSE) -> Depreciation-Tools, furniture & office equipment
A87: 003 | B87: Handlift OPK maks 2500 kg | C87: Tools, furniture & office equipment | D87: 2141000 | E87: 15000000 | F87: 60 | G87: SP PD- Assy | H87: 1 | I87: 43862 | J87: BIP | K87: SP PD- Assy | M87: BGT.FY121 | N87: =H87*E87 -> 15000000 | O87: =N87/F87 -> 250000 | P87: =DATE(YEAR(I87),MONTH(I87)+F87,DAY(I87)) -> 45689 | Q87: =IF(AND(LEFT(Q$1,FIND("_",Q$1)-1)&RIGHT(Q$1,LEN(Q$1)-FIND("_",Q$1)) >= YEAR($I87) & TEXT(MONTH($I87),"00"),LEFT(Q$1,FIND("_",Q$1)-1)&RIGHT(Q$1,LEN(Q$1)-FIND("_",Q$1)) < YEAR($P87) & TEXT(MONTH($P87),"00")),$O87,"") -> 250000 | R87: =IF(AND(LEFT(R$1,FIND("_",R$1)-1)&RIGHT(R$1,LEN(R$1)-FIND("_",R$1)) >= YEAR($I87) & TEXT(MONTH($I87),"00"),LEFT(R$1,FIND("_",R$1)-1)&RIGHT(R$1,LEN(R$1)-FIND("_",R$1)) < YEAR($P87) & TEXT(MONTH($P87),"00")),$O87,"") -> 250000 | S87: =IF(AND(LEFT(S$1,FIND("_",S$1)-1)&RIGHT(S$1,LEN(S$1)-FIND("_",S$1)) >= YEAR($I87) & TEXT(MONTH($I87),"00"),LEFT(S$1,FIND("_",S$1)-1)&RIGHT(S$1,LEN(S$1)-FIND("_",S$1)) < YEAR($P87) & TEXT(MONTH($P87),"00")),$O87,"") -> 250000 | T87: =IF(AND(LEFT(T$1,FIND("_",T$1)-1)&RIGHT(T$1,LEN(T$1)-FIND("_",T$1)) >= YEAR($I87) & TEXT(MONTH($I87),"00"),LEFT(T$1,FIND("_",T$1)-1)&RIGHT(T$1,LEN(T$1)-FIND("_",T$1)) < YEAR($P87) & TEXT(MONTH($P87),"00")),$O87,"") -> 250000 | U87: =IF(AND(LEFT(U$1,FIND("_",U$1)-1)&RIGHT(U$1,LEN(U$1)-FIND("_",U$1)) >= YEAR($I87) & TEXT(MONTH($I87),"00"),LEFT(U$1,FIND("_",U$1)-1)&RIGHT(U$1,LEN(U$1)-FIND("_",U$1)) < YEAR($P87) & TEXT(MONTH($P87),"00")),$O87,"") -> 250000 | V87: =IF(AND(LEFT(V$1,FIND("_",V$1)-1)&RIGHT(V$1,LEN(V$1)-FIND("_",V$1)) >= YEAR($I87) & TEXT(MONTH($I87),"00"),LEFT(V$1,FIND("_",V$1)-1)&RIGHT(V$1,LEN(V$1)-FIND("_",V$1)) < YEAR($P87) & TEXT(MONTH($P87),"00")),$O87,"") -> 250000 | W87: =IF(AND(LEFT(W$1,FIND("_",W$1)-1)&RIGHT(W$1,LEN(W$1)-FIND("_",W$1)) >= YEAR($I87) & TEXT(MONTH($I87),"00"),LEFT(W$1,FIND("_",W$1)-1)&RIGHT(W$1,LEN(W$1)-FIND("_",W$1)) < YEAR($P87) & TEXT(MONTH($P87),"00")),$O87,"") -> 250000 | X87: =IF(AND(LEFT(X$1,FIND("_",X$1)-1)&RIGHT(X$1,LEN(X$1)-FIND("_",X$1)) >= YEAR($I87) & TEXT(MONTH($I87),"00"),LEFT(X$1,FIND("_",X$1)-1)&RIGHT(X$1,LEN(X$1)-FIND("_",X$1)) < YEAR($P87) & TEXT(MONTH($P87),"00")),$O87,"") -> 250000 | ... BE87: =IF(AND(LEFT(BE$1,FIND("_",BE$1)-1)&RIGHT(BE$1,LEN(BE$1)-FIND("_",BE$1)) >= YEAR($I87) & TEXT(MONTH($I87),"00"),LEFT(BE$1,FIND("_",BE$1)-1)&RIGHT(BE$1,LEN(BE$1)-FIND("_",BE$1)) < YEAR($P87) & TEXT(MONTH($P87),"00")),$O87,"") -> 250000 | BF87: =SUM(Q87:U87) -> 1250000 | BG87: =SUM(V87:AG87) -> 3000000 | BH87: =SUM(AH87:AS87) -> 3000000 | BI87: =SUM(AT87:BE87) -> 3000000 | BJ87: =VLOOKUP(D87,Master!AD:AG,3,FALSE) -> 7611600 | BK87: =VLOOKUP(D87,Master!AD:AG,4,FALSE) -> Depreciation-Tools, furniture & office equipment
A88: 001 | B88: Desktop PC for Pepen Ependi Admin FI - replacement | C88: Tools, furniture & office equipment | D88: 2141000 | E88: 8000000 | F88: 60 | G88: SP PD- Final Inspection | H88: 1 | I88: 44409 | J88: BIP | K88: SP PD- Final Inspection | L88: B | M88: BGT.FY122 | N88: =H88*E88 -> 8000000 | O88: =N88/F88 -> 133333.33 | P88: =DATE(YEAR(I88),MONTH(I88)+F88,DAY(I88)) -> 46235 | Q88: =IF(AND(LEFT(Q$1,FIND("_",Q$1)-1)&RIGHT(Q$1,LEN(Q$1)-FIND("_",Q$1)) >= YEAR($I88) & TEXT(MONTH($I88),"00"),LEFT(Q$1,FIND("_",Q$1)-1)&RIGHT(Q$1,LEN(Q$1)-FIND("_",Q$1)) < YEAR($P88) & TEXT(MONTH($P88),"00")),$O88,"") | R88: =IF(AND(LEFT(R$1,FIND("_",R$1)-1)&RIGHT(R$1,LEN(R$1)-FIND("_",R$1)) >= YEAR($I88) & TEXT(MONTH($I88),"00"),LEFT(R$1,FIND("_",R$1)-1)&RIGHT(R$1,LEN(R$1)-FIND("_",R$1)) < YEAR($P88) & TEXT(MONTH($P88),"00")),$O88,"") | S88: =IF(AND(LEFT(S$1,FIND("_",S$1)-1)&RIGHT(S$1,LEN(S$1)-FIND("_",S$1)) >= YEAR($I88) & TEXT(MONTH($I88),"00"),LEFT(S$1,FIND("_",S$1)-1)&RIGHT(S$1,LEN(S$1)-FIND("_",S$1)) < YEAR($P88) & TEXT(MONTH($P88),"00")),$O88,"") | T88: =IF(AND(LEFT(T$1,FIND("_",T$1)-1)&RIGHT(T$1,LEN(T$1)-FIND("_",T$1)) >= YEAR($I88) & TEXT(MONTH($I88),"00"),LEFT(T$1,FIND("_",T$1)-1)&RIGHT(T$1,LEN(T$1)-FIND("_",T$1)) < YEAR($P88) & TEXT(MONTH($P88),"00")),$O88,"") | U88: =IF(AND(LEFT(U$1,FIND("_",U$1)-1)&RIGHT(U$1,LEN(U$1)-FIND("_",U$1)) >= YEAR($I88) & TEXT(MONTH($I88),"00"),LEFT(U$1,FIND("_",U$1)-1)&RIGHT(U$1,LEN(U$1)-FIND("_",U$1)) < YEAR($P88) & TEXT(MONTH($P88),"00")),$O88,"") | V88: =IF(AND(LEFT(V$1,FIND("_",V$1)-1)&RIGHT(V$1,LEN(V$1)-FIND("_",V$1)) >= YEAR($I88) & TEXT(MONTH($I88),"00"),LEFT(V$1,FIND("_",V$1)-1)&RIGHT(V$1,LEN(V$1)-FIND("_",V$1)) < YEAR($P88) & TEXT(MONTH($P88),"00")),$O88,"") | W88: =IF(AND(LEFT(W$1,FIND("_",W$1)-1)&RIGHT(W$1,LEN(W$1)-FIND("_",W$1)) >= YEAR($I88) & TEXT(MONTH($I88),"00"),LEFT(W$1,FIND("_",W$1)-1)&RIGHT(W$1,LEN(W$1)-FIND("_",W$1)) < YEAR($P88) & TEXT(MONTH($P88),"00")),$O88,"") | X88: =IF(AND(LEFT(X$1,FIND("_",X$1)-1)&RIGHT(X$1,LEN(X$1)-FIND("_",X$1)) >= YEAR($I88) & TEXT(MONTH($I88),"00"),LEFT(X$1,FIND("_",X$1)-1)&RIGHT(X$1,LEN(X$1)-FIND("_",X$1)) < YEAR($P88) & TEXT(MONTH($P88),"00")),$O88,"") | ... BE88: =IF(AND(LEFT(BE$1,FIND("_",BE$1)-1)&RIGHT(BE$1,LEN(BE$1)-FIND("_",BE$1)) >= YEAR($I88) & TEXT(MONTH($I88),"00"),LEFT(BE$1,FIND("_",BE$1)-1)&RIGHT(BE$1,LEN(BE$1)-FIND("_",BE$1)) < YEAR($P88) & TEXT(MONTH($P88),"00")),$O88,"") -> 133333.33 | BF88: =SUM(Q88:U88) -> 0 | BG88: =SUM(V88:AG88) -> 1066666.7 | BH88: =SUM(AH88:AS88) -> 1600000 | BI88: =SUM(AT88:BE88) -> 1600000 | BJ88: =VLOOKUP(D88,Master!AD:AG,3,FALSE) -> 7611600 | BK88: =VLOOKUP(D88,Master!AD:AG,4,FALSE) -> Depreciation-Tools, furniture & office equipment
A89: 002 | B89: Handlift OPK maks 2500 kg For Final Inspection | C89: Tools, furniture & office equipment | D89: 2141000 | E89: 15000000 | F89: 60 | G89: SP PD- Final Inspection | H89: 1 | I89: 44410 | J89: BIP | K89: SP PD- Final Inspection | L89: B | M89: BGT.FY122 | N89: =H89*E89 -> 15000000 | O89: =N89/F89 -> 250000 | P89: =DATE(YEAR(I89),MONTH(I89)+F89,DAY(I89)) -> 46236 | Q89: =IF(AND(LEFT(Q$1,FIND("_",Q$1)-1)&RIGHT(Q$1,LEN(Q$1)-FIND("_",Q$1)) >= YEAR($I89) & TEXT(MONTH($I89),"00"),LEFT(Q$1,FIND("_",Q$1)-1)&RIGHT(Q$1,LEN(Q$1)-FIND("_",Q$1)) < YEAR($P89) & TEXT(MONTH($P89),"00")),$O89,"") | R89: =IF(AND(LEFT(R$1,FIND("_",R$1)-1)&RIGHT(R$1,LEN(R$1)-FIND("_",R$1)) >= YEAR($I89) & TEXT(MONTH($I89),"00"),LEFT(R$1,FIND("_",R$1)-1)&RIGHT(R$1,LEN(R$1)-FIND("_",R$1)) < YEAR($P89) & TEXT(MONTH($P89),"00")),$O89,"") | S89: =IF(AND(LEFT(S$1,FIND("_",S$1)-1)&RIGHT(S$1,LEN(S$1)-FIND("_",S$1)) >= YEAR($I89) & TEXT(MONTH($I89),"00"),LEFT(S$1,FIND("_",S$1)-1)&RIGHT(S$1,LEN(S$1)-FIND("_",S$1)) < YEAR($P89) & TEXT(MONTH($P89),"00")),$O89,"") | T89: =IF(AND(LEFT(T$1,FIND("_",T$1)-1)&RIGHT(T$1,LEN(T$1)-FIND("_",T$1)) >= YEAR($I89) & TEXT(MONTH($I89),"00"),LEFT(T$1,FIND("_",T$1)-1)&RIGHT(T$1,LEN(T$1)-FIND("_",T$1)) < YEAR($P89) & TEXT(MONTH($P89),"00")),$O89,"") | U89: =IF(AND(LEFT(U$1,FIND("_",U$1)-1)&RIGHT(U$1,LEN(U$1)-FIND("_",U$1)) >= YEAR($I89) & TEXT(MONTH($I89),"00"),LEFT(U$1,FIND("_",U$1)-1)&RIGHT(U$1,LEN(U$1)-FIND("_",U$1)) < YEAR($P89) & TEXT(MONTH($P89),"00")),$O89,"") | V89: =IF(AND(LEFT(V$1,FIND("_",V$1)-1)&RIGHT(V$1,LEN(V$1)-FIND("_",V$1)) >= YEAR($I89) & TEXT(MONTH($I89),"00"),LEFT(V$1,FIND("_",V$1)-1)&RIGHT(V$1,LEN(V$1)-FIND("_",V$1)) < YEAR($P89) & TEXT(MONTH($P89),"00")),$O89,"") | W89: =IF(AND(LEFT(W$1,FIND("_",W$1)-1)&RIGHT(W$1,LEN(W$1)-FIND("_",W$1)) >= YEAR($I89) & TEXT(MONTH($I89),"00"),LEFT(W$1,FIND("_",W$1)-1)&RIGHT(W$1,LEN(W$1)-FIND("_",W$1)) < YEAR($P89) & TEXT(MONTH($P89),"00")),$O89,"") | X89: =IF(AND(LEFT(X$1,FIND("_",X$1)-1)&RIGHT(X$1,LEN(X$1)-FIND("_",X$1)) >= YEAR($I89) & TEXT(MONTH($I89),"00"),LEFT(X$1,FIND("_",X$1)-1)&RIGHT(X$1,LEN(X$1)-FIND("_",X$1)) < YEAR($P89) & TEXT(MONTH($P89),"00")),$O89,"") | ... BE89: =IF(AND(LEFT(BE$1,FIND("_",BE$1)-1)&RIGHT(BE$1,LEN(BE$1)-FIND("_",BE$1)) >= YEAR($I89) & TEXT(MONTH($I89),"00"),LEFT(BE$1,FIND("_",BE$1)-1)&RIGHT(BE$1,LEN(BE$1)-FIND("_",BE$1)) < YEAR($P89) & TEXT(MONTH($P89),"00")),$O89,"") -> 250000 | BF89: =SUM(Q89:U89) -> 0 | BG89: =SUM(V89:AG89) -> 2000000 | BH89: =SUM(AH89:AS89) -> 3000000 | BI89: =SUM(AT89:BE89) -> 3000000 | BJ89: =VLOOKUP(D89,Master!AD:AG,3,FALSE) -> 7611600 | BK89: =VLOOKUP(D89,Master!AD:AG,4,FALSE) -> Depreciation-Tools, furniture & office equipment
A90: 003 | B90: Desktop PC | C90: Tools, furniture & office equipment | D90: 2141000 | E90: 10000000 | F90: 60 | G90: SP PD- Final Inspection | H90: 1 | I90: 44228 | J90: BIP | K90: SP PD- Final Inspection | M90: BGT.FY121 | N90: =H90*E90 -> 10000000 | O90: =N90/F90 -> 166666.67 | P90: =DATE(YEAR(I90),MONTH(I90)+F90,DAY(I90)) -> 46054 | Q90: =IF(AND(LEFT(Q$1,FIND("_",Q$1)-1)&RIGHT(Q$1,LEN(Q$1)-FIND("_",Q$1)) >= YEAR($I90) & TEXT(MONTH($I90),"00"),LEFT(Q$1,FIND("_",Q$1)-1)&RIGHT(Q$1,LEN(Q$1)-FIND("_",Q$1)) < YEAR($P90) & TEXT(MONTH($P90),"00")),$O90,"") | R90: =IF(AND(LEFT(R$1,FIND("_",R$1)-1)&RIGHT(R$1,LEN(R$1)-FIND("_",R$1)) >= YEAR($I90) & TEXT(MONTH($I90),"00"),LEFT(R$1,FIND("_",R$1)-1)&RIGHT(R$1,LEN(R$1)-FIND("_",R$1)) < YEAR($P90) & TEXT(MONTH($P90),"00")),$O90,"") | S90: =IF(AND(LEFT(S$1,FIND("_",S$1)-1)&RIGHT(S$1,LEN(S$1)-FIND("_",S$1)) >= YEAR($I90) & TEXT(MONTH($I90),"00"),LEFT(S$1,FIND("_",S$1)-1)&RIGHT(S$1,LEN(S$1)-FIND("_",S$1)) < YEAR($P90) & TEXT(MONTH($P90),"00")),$O90,"") | T90: =IF(AND(LEFT(T$1,FIND("_",T$1)-1)&RIGHT(T$1,LEN(T$1)-FIND("_",T$1)) >= YEAR($I90) & TEXT(MONTH($I90),"00"),LEFT(T$1,FIND("_",T$1)-1)&RIGHT(T$1,LEN(T$1)-FIND("_",T$1)) < YEAR($P90) & TEXT(MONTH($P90),"00")),$O90,"") -> 166666.67 | U90: =IF(AND(LEFT(U$1,FIND("_",U$1)-1)&RIGHT(U$1,LEN(U$1)-FIND("_",U$1)) >= YEAR($I90) & TEXT(MONTH($I90),"00"),LEFT(U$1,FIND("_",U$1)-1)&RIGHT(U$1,LEN(U$1)-FIND("_",U$1)) < YEAR($P90) & TEXT(MONTH($P90),"00")),$O90,"") -> 166666.67 | V90: =IF(AND(LEFT(V$1,FIND("_",V$1)-1)&RIGHT(V$1,LEN(V$1)-FIND("_",V$1)) >= YEAR($I90) & TEXT(MONTH($I90),"00"),LEFT(V$1,FIND("_",V$1)-1)&RIGHT(V$1,LEN(V$1)-FIND("_",V$1)) < YEAR($P90) & TEXT(MONTH($P90),"00")),$O90,"") -> 166666.67 | W90: =IF(AND(LEFT(W$1,FIND("_",W$1)-1)&RIGHT(W$1,LEN(W$1)-FIND("_",W$1)) >= YEAR($I90) & TEXT(MONTH($I90),"00"),LEFT(W$1,FIND("_",W$1)-1)&RIGHT(W$1,LEN(W$1)-FIND("_",W$1)) < YEAR($P90) & TEXT(MONTH($P90),"00")),$O90,"") -> 166666.67 | X90: =IF(AND(LEFT(X$1,FIND("_",X$1)-1)&RIGHT(X$1,LEN(X$1)-FIND("_",X$1)) >= YEAR($I90) & TEXT(MONTH($I90),"00"),LEFT(X$1,FIND("_",X$1)-1)&RIGHT(X$1,LEN(X$1)-FIND("_",X$1)) < YEAR($P90) & TEXT(MONTH($P90),"00")),$O90,"") -> 166666.67 | ... BE90: =IF(AND(LEFT(BE$1,FIND("_",BE$1)-1)&RIGHT(BE$1,LEN(BE$1)-FIND("_",BE$1)) >= YEAR($I90) & TEXT(MONTH($I90),"00"),LEFT(BE$1,FIND("_",BE$1)-1)&RIGHT(BE$1,LEN(BE$1)-FIND("_",BE$1)) < YEAR($P90) & TEXT(MONTH($P90),"00")),$O90,"") -> 166666.67 | BF90: =SUM(Q90:U90) -> 333333.33 | BG90: =SUM(V90:AG90) -> 2000000 | BH90: =SUM(AH90:AS90) -> 2000000 | BI90: =SUM(AT90:BE90) -> 2000000 | BJ90: =VLOOKUP(D90,Master!AD:AG,3,FALSE) -> 7611600 | BK90: =VLOOKUP(D90,Master!AD:AG,4,FALSE) -> Depreciation-Tools, furniture & office equipment
